Workbook

Sheet ASWXL.Storage
A1: ASWXL Storage Version 40.0.0.10 | B1: C:\Program Files\AspenTech\Aspen Simulation Workbook V14.0
A2: UEsDBBQAAAAIALt1wlq3H+Sh4O8AAL3rCAAYAEIAQXNwZW5UZWNoLkFTV1hMLldvcmtib29rTlU2AE5VQ1gYAEEAcwBwAGUAbgBUAGUAYwBoAC4AQQBTAFcAWABMAC4AVwBvAHIAawBiAG8AbwBrAAoABAAAAAAA7L3ZeyPJdidWvdXtrnu71fde7StU7vFIoyaYEblT7NKAJKoINUFSBKure66uoSwwyYIKBCgs1c3rsT/vM57xeDyjkWfVzMjjfV/G8vruP8FPfvCD3/zi7/OnB7/IEbkhAZwEIpmRESAyq78GkcjIiBMnIn7nROQvTjx468GDB39K/tG/9N933iYff6E2unH7527nVbXWevHlUbV2cdHtf1r5wh2OuoP+Z5pSpf8h5dPK/qQ3ngzdz/ruZDx0ep9WTicve93O5+7t+eC12/9McTodXe0oln2JFevi8j1a0E/P5/9iMHz9cjB4/X1y8532m8532qPu9aTnjElpo++2nc64+8ZtRT99p30zdC/dodvvuKPvtLv97rjr9Lo/ci8+al87o7E7PHDGTssd/+TsZTWowE/Eft4f9MfDQa/nDj9sD53+ldt0+s6VO/xO+2o4mNzUOqSI0ffbzmQ8uCaFd86dq+c3F87Y/YX2gdtzx+6587Lnvnjl9r3Lbv/qjObyZ9oTL1X9m47bezrpd7yq0GQnpOphfX+2PXLeuEfd/mv3glTvhOTh1ZU8+PPerfr1S/fiYuHmL7UvB8OO+3TS6525l0N39Oqkfzbp7w+ub6hIF1RlVO6nrkNbp+nc/GR7TOXc6zn91/uDHq212x+PfrbtjL72alDzJDx1+m69T68v3iX/HpD/yKf37913Hjyeb7cvnGGXJt6nCvQyoN1Hn082vT3yf5k25eyTv7zQ8VoN+v80PU31yXyq06g3zGb31i/Op6Qt7n+l32ia939leZpp/6Cpf34+8Vmsy9AEPzef4Nm0F3kief8qC/Wcay6a9I/fad2SXno9o75nbt8ddjvVg673gzO8/R38gx8ECVvjIel/n1auR53BsNd9GRux3oBlGK8vTdPRO7qBbFVzyaj94ac/SCtFoz9WcU5CnLz8XSID38x/yDm7t2jjffAO/aBD54P36MdD2vYffIt+0sv36ccH5OO9PyHgu6zT0OTfeuP0Jm67/eB9mjXNmfQjktEH36bZfIdevkd/ZRyfD9vOcOjcPmx3BpP++N3FPtsIn/vBD70h4lXow8BCvPdupiE+X/gvLBQ+fTJe/EeB6t57jwknqjRp+2rSvXivfexcu98haD3qDLs39OZ322+6oy4FvXFr7AzHk5vvtntd0sH654Mm0TkZzKPvtd03BCGPBlctYliOutfd8bsEQ69IysGVB5/fjP3x9m0/ZY1W6yfbL5zueH8yHA2GFOwJKPdJkp9tP+1NRq+m4gWlkNy/3SYy7lNduMOP2kfELrUGvTfueffa/V67FuB9JOeHbZJjdPV+m+S474zcnw6szcGECnRw23euux2ScvRT7Qv/wrdZT4fu700ITt5+f/b358SCjj7yPls3bufUGb9Sfiy6/IL2PmX2Npq7jWZv47nbePa2Ondbnb2tzd3WZm/rc7f12dvG3G1j9rY5d9ucvW3N3bZmb9tzt2PXnlqUj+f0oswlQPMJ0FwCPJ8gpjuvn7zz1lseAIR2OTQq4L8H3w6Q8xnpZm+99f7WsoFbp/046Jped/Yt1vsfvvXWArTQERcb46QTeokfeqP13f+HoFq8ZApUb7edt9sv32533m5fvN12325fvt2+erv96u129+32777dfv1g+u/9b33r7eDfX/onrz79sd96tveHf+H/+oM/+u6fPHz4Mbmvnd4So3w76o7avznou6O2bqL2193xq8Fk/HQ46Nc7g/6AdO9R+2j/5MoZDXrdvvvwu17eb/2/RH8Pv0dBxavUKRmaD6nn+QnuGJajWuaWjpTLLQ1r5pZ9oTtbrm7rDkLo0lCMD37c08n//qsPHvx/xo/e+T//6P/4yySjnwjQyfv3AS3n4U+RD3w+uKk6NzfNwYXbqxIPdHJDjbTrXG+dEvvpElt5MxlXT88a+/WqioxntdbDn6YQ/8l27+HPkC8vZjPo/ogM74rTv6jsD0bU16zWv3E7E887nlxfEztcbRx/UW+dN+vH5zvV88HY6VVOhwNqNCv7zk2XXtNHH/4sLeV56+Dhz6UWExut2tOHPx+K+QvkSyuTmASZu0P3onJGkKgyuKycEQGG/Ye/SDL+8NQlfm5/vP1nv3Kd4cNfIj+d8lHJxYSopOX03NHDCu1wRBfbXhm/TK7UVWUcEIE7Y3rlFUKHwMPHoUr/mcUcVqhUNQ4a9dbDT0Kd/hny5bc41JPMNYYOTew3+j87U9E/S65+M1Mhj0+rJ9UKaaLu4OLxw1+hA9/LmYyNB885iH/mfF1pkk5BnJHeyK/Cn5upwq+RK3umoDN3RBy2USXM9Pm42+uOb7fIdfVkMqY6Pz85f36+f9I6f/gplfiT7VfDh1sUU1ZJHAyg2Vavhq2+zanNfIm7blBhJV5h6oO995B1CkS9zUdHA+fiKZk3DobfCnzb9+k00Rm6w48PndGrfSIqGQ5vuhfu8H36A3V33iXu7eihZ35GpHrvEK/r2+//PDARaIR5fQLdXMif2ob/+7es36BD+9EjCpMfIPqBab2ouCsmbNTJ/alwMn/mXg+oUoNqffDlda/VeeVeO98m3w66l5fPhs41MZYfBaIF6TxvUqUIrZGP/+3339n9jW+ue5U3geP/GFWVxxWiyMEFyfuzx5Px5RYyHv/Gkw8f7X4z2hl5JVS6F589jqR6XCHu2JU7pn7m6MbpuJ89fjUe3+xsb5Nib4hLVh0Mr7ZpypE7RtVvRhePK6TI/mjnejTuj1hTM+f6zTTp119/Xf1a9VJiRUHbXzaPfB1NJSD+n0OqOewHdRttEbs5HIwGl+OtzuB6h6Tb8lNNn7kZDm5WP0NTPa44Y+Ilv5wQ53MwvD5wLx0yPj97/HsTp9e97LpEaLfnXhOIT7hN9F6pUM0HySrEbXVnlO8Lt9MYBR3js8fj4cSNfn8+cok/PvR8+Q7B++C2l6+fc8dbNvnm/PbGDX4Nfn81IEhdue72Tzod4tJ/9pj0jGvnm/Bq0n9J/LGLUMjpg7OinjtX4XyKCkW1shPrbTj+dLJA07sj34efvwUV3TiI1HDmOhcn/d7tnHZqk/Gg0e8MvafCe2NS8GePSW7d/jhKmb6PbzNISPOLFTjyZlQ5lxmbCfIserafsAjiAWxMhIvBJOgkwkTwphZytfBbdKyPb+UK4a24yBXBW0oU2Ba720lg4t2BQci7FcjNgHrnSainFBr11gaBvD4nVwTiJB6SVnKHZ4OvY5K8HAx6rkPUcxH6BJdkEiAWHIlosZZaP/loN6ZukzOW24R7gyFpv9qQekPcxtHd1PGiezF+tWbN5IFga3zbkzzSzrvjtZCDDndS5hpI0uj33aHfeyX226ZLyqj1L/Zd+hIA6rwChWmNnfEE8kKiAXTy+f13SY66o3GOHohXBnVDBPoU+6+6vQvBZRKTeHJ5SZ4RNHpy7x+1cLGi0O7pVAtS0Xl/0Jtc9yUCc2CoJNuoq/5g6F6so0/DEW3uYqhm3QfR5e+RpwW7MPnCn/fSolypTJKQ90pl+h63NqsG8+uWEkQI1i2DTtp0bg+dN+6JpxuSyflQtnxHg69nXHkZKrq5kS3CGqyqUmiSKwFl9ciVYMrTWYPVRslvG7yBud9zrm+iYvcdDzeCe5Xg5lq5W95YTpDau7eWUu8P+hfR2515senNLv3qXlTW4hUQFSiwbMtkXQPjF3pIS5t7xnkSMrK6dGtBoCjJC9LOqDv1Dk6H3cGQdK/PHm9hpJmapRqaFd2duptPwwHi/R45E62x079whhcBOWH0aSX4dti9uHAl19QnxPtGbr7X+vcq4c1UujgPes+9U4XvpieoIry56aoIZ3GwMsK7eapD8prJAUrsA8G9DawzXlJnvKF1VpfUWS3CUG8caEtUoBVDBfoSFejFUIGxRAVGEVRw5Lx0e0WoKN185nT7dG1nAyE9ql0bdmqj+3n6tZKXa4JX8BtYtUCKIgzTg+7opufcwi54cLMwE5LJ4Lo98CUFFrD63THd99V0ndFk6FZOpgk3XS/7Tr9dp6yfduMCwDqnX/HuVvzXYxu/muFxWNreLldAG/RmJbq58co46JKLkbeWVoDaUhBoexRbEB6COxuvhqn7s++M3avBEF45D1ygeJqNV423qNs+SbIi3u072477qJDIeCyxHIVQxKEzanvWYej2F3VB7lbidzdeHY1Rz3UuFxXRGFWOghsbrwPfk2hcLAEM359oHGwuaOROlw3f25a8sPx2sObbiPVviJHoO738WzJvPa3ooptAUA8ZmuWuSlDCteFHlrsqV4i21rsqn/a6N8GWvbmtUOsgXbnns9zzWe75LPd8lns+07tM5a7Pctcn3EPKfZ/lvs9y32e577OI+z7PnSvsgSC0olDsPZ9+xIiYnNHiMblTiXjUUsdD86KXIKPXqGsiJdEXzIShiuS9NHgnJcLi+TqUL6B/KMeifMFhHeu1E8gbNuBGKn/YSI966I0ZUMBwzEjf40XPmQn3OC/qcA3CNhIdJgjo63ANRCz3H+YjabC5Hd4+6x2VITmoqb/zHd4ouwbyrd6D7Anp7+mFwX2t9h6vk7Q08LcfCF1uGyfEHYiM8ozXLfbNlGRUJjVvehxwqc3jXC2sYckRg74Lk2zJaTcUK4agGW25rFcu65XLeuWyXqGX9Uq2EChhyRYq2UIlH6fk45R8nJKPU/JxYuII9EpKQk5JyEmYCQhxTWX7oD7sSV6PezroS/ZdjifXL93hOnhRL4bOzbn7zViyAWhQI9QdDPcHvYHkEL60dwgWI1948cdcgUDmqNtfB4/zhdu9eiV5eHsdudG/cL/ZlN7sL6oWqDeX1qq0Vst7x0ZZq9Ph4LLbc2d3fpbLtuWy7fov23oEsLWUbK0XlIl8Z+cL70rXQbLjwckl0ddI4jLdeffa9czNG6cnmblBJFkDimP5+qF8/VC+fihfP5SvH1K70yU5LKYRqdyfkqA2g4olQa0kqBWAoNbquH1n2B2UaxrlmsbM9LdxsudQr2wt5+blgssdJKPYtU/+p1mtpYBrvSK03gHJ1mBVqFwEKRdBykWQchGEq7vvvHH3BzfLz1gVP4akrs2ALqM7IsWMj6l5XzfTdOZ2iUvUdXrdH7lrJlrT6QwHe+4lmWq33HGjfzMZj2qdcfcNFJOCpq34iSskdcVPXgnTL6mY8NAfsXqdTfpMNSLp1rcqtUsCRStr4qVa74rM9TVaIntP81MvwZx+rfUinM+354qS2P8Yakkb7S7VI8/J643L6jXti+mqFeYt3MoeDTrOODjmaLZC9G5lelsq6Suwb/MiHlfmDZ/nNUU6RrlJKWZxrnxJEteG1AVo//UEVbdkykH5tmZ93taIfS+SM+a4N87QGQ+Go0b/cpAj4DwbDiY3pDS5TXfgdrrXTk+oHPwa0E//atCN8knIgVZ80u+SIoN6e9EqP3enIdlOh0QPw1vyUwDt00I8aXtuh3SKyjc3zvjVZ4+r29vXo3F/tOMH5+z60Q22Z5657Lq9i/ABPzUdI9txSX2ZkoSMZU61vz/ok5Zx6NjKQzjfU0shXtjmRGeYjx7P89Ej8TC/PKLSEqn09AJ5G0RXCxWh4MqU0fbMuykbcVB2zH7mqW0tq6gh5zynERaXlYdaoxiOOUABzZuOUYpaOQiUevjHdWdm1d38EWA5y2vw6pcCEMu6i0hrgVkzo0vhovIccSuKCkAEi80G7w4GYWjF3ASlyuArrAj1en2Or9g5jcLFOBGpsHc+xoTs4ei94+Oi+OBtIW99x3ZFcxEzvsuau7CxTa9chI1vouUuLLSDrw0bxOks45i/2QR3EuZa2wjR2gnWaFl9sxstmOvNvcYzNEYZDTvLo8ytfpJbc3FBmkdNX7u3Q/cSakmgPJLSHS5v8PzqsmCfvAr58idVaGYGl1yh2VljflWIr6KnqEXMlMx19UD+BduVz7iZZXfdtRkSUClDU9wV52I7P1JUBjIjy+vEYADzrehdhk7MJVheuwVfJN+6zDkp6YYP7AJkG0V3dCvuPJhmnXvI1Q/qA016RM4f0tVldTVyrwE8r2HuXPMzwmzdKvX8kneHWhzpHDqUQNRaUpE7QtadapEer2JvTmILOYHo0bsj/itB07Pe7mraF8W9izlPI/P07Lc7yOx1MAY/hNU8i+7hfHu3gJ69qPjZJeOsus+6AJ22v7NVgbXf36UKGU0WV0dIpAcUvKpZeHMDqB/l9hYIesXFjO+elhYH78x7bWa8FGtWeRpUEaY09GvAkXo3hQtAmlk3AJQ9vTMgFl5miBWZ3WGx0DLDXwFgxcyFB7MST+aoSD6dqfPKvXaePNQfPHjwT//WT+1edC8vr4Y7/h/nuvLNdY9k7a8+fvZ4MuwHT4y2rrud4WA0uBxvdQbXOyTdlp/qcfCMn8WqZ8KCtt4QrN2NlOTnsZqx9WR3xqhWAvG7F3PWdsqRGA6+PqEN7DG8guSvnNH+K+9wt88ed/sjdzh2adaNgyfK7jb53KVrsk8ax1/UW+fN+vH5TvV8MHZ6FTJ9v5h0xpWW03NHu9teql3viEnSBrvejmL6xeNznblOb3fb+7p7Slrtyfngpurc3HhiVlvdH3X7VxWnf1HZH4zG5Hu1/o3bmdD9EK3JNV3zra4s38t2t9W9nvQ80veT09vhoHc76o7avznou6O2bqL2193xq8Fk/HQ46Nc7g/6ANMmofbR/cuWMBr1u393djmWw6x9594TK9Mt75u52cL07PYTxibf9Z3c79svu9NDD8G7sl93YwaJPjgdjulVidzv+4250mCfVXshqDrOKrnePuv3X0eGeT54NBhdEjJnfdk9e/i4ZWp7WQZXF7gdp55s6TBM27pTWBuc4k4J0ITSbGf2B/IqfzDcvvYXpLfXJYmegN1V6U6MaaRzo/h+D/jlyXro9WBb/1u5Bd3TTc26TZY4n2N13+u063UNIO//0YvfQGbU9TB+6fXpr5nq3Meq5zqU3Xvxvu9szA5B1oGJgoCKGgYpiA/WkWjmlMVUvHgsdk49Pq/GS8x6NSLnXw3GqqIQxeLJk5E0fXhxuJ7FB9vg0NqzmxqE/nsBxqHljLGEc6nMjL9bq4Iibub9GI00FRhpmGGk4wSQeuKPu0L2onDljtzK4rJy5Y2L6hY7AJBHyHor2vR6JSVrLZBuTMpVkHpPEAcZrUtI1GroaMHRVhqGrLvVmT0hPdKg6PbVKcGfnBch72Or3etjCOuPg0M5nKdWjnRcm0aWdT7hGw1UHhqvGMFy1pcP1+bhLelfXHckarvMC5D1crQ0YrvM64zBc57OUOlznhUkcrvMJ12i4GsBw1RmGq75qrYg2Y2XfuenSa0mDFhYj76GrbcDQhTXHZwEJyFj2OhIg0rLlJCD5Gg1pExjSBsOQNmJDGhhvB2Si0BnTK0/5tOPwHtJgEbkvLeF7PV5BnSUMVGiMJE9qoYwXByo87vzx6g841f+TPF2FCoLmqlA6fuMOZR13FjDuTIZxZy41pWfO15WmQ4/NIv1EliGFhMh7XBr3elgm642DEYWylWpCIYESDSiUeI3Mpw0MY4thGFvLzWfgLuRqP+Eycjeg6F6PVFhpPCwonHMeJhQuCRiBcMI1MqKx7V/T4WczDD87PvzcMdXiqOpGXdnxoi3ODDgqrP/FH270tLArd7hkxCVnm98Y884w84tpvXLd8S/X8E4jB5fVHybwcKOaml5wG3mLakwadYHil4y1xbyAcRZlk250LeYNjKzFRLOjio6U9v5g0h974yp2KWpkQbQgxMILQgo4tgbOZDwYOfxGVSzD3MaT16r3eMjEdJRhsMRy4ThMYrlCAyR2e92GBkjEYWLixKk4p1+dnTSOq/UvT89wOCZix0VQxVZuBt3+uDIYVvx4bZU3njtzSX5o3bidivvNzdAdjUjqasXbJe30x5/S5E8Hw/HQ6ccSVLr9CjEN1yP63vZpb/D1iJoHkuGQ/NKvHLiXZAhUtqMnvdujauWMHq6+1el1O68r40HF52NWIh1RwuunlfErt1+ZjIjKhs7VFvFMti6GgxuavjO4uaWFeKlHNHwpKeYiVmJQDmnkWNUDbLBVq2poGNmaaSq6MYsU9HzqZJiIakhdpRMv15HHgbjqb1HVVQPte5GEwzYQaZbNnUYOnMGlGLOgzhwQJ6biRMjxVb8EcILmWMAaH0MY8SXIJIAWIu3YIa0zjEqf/jK92fbrUG81nh1vtU7r+7Fk/r1dP07+E1rB7mXXJcoIfplBr6Bw2FNuNy5mnGV6vRTWpjLsk4nw1WB4myRjdD/mlyMZfjnEoEIsFCoU51Cdb6lIqR63zmvP6hBEHk+uX7pDimgE+khmnxKU6/QmNHoqQZ7+hUuz9mZKQ/floNtzhzDQqEqELd64o0Qu/4s/9p7Y5F8w6lgdlb3eoPN6VPWr4MNMWBGROGPtNOCXwzRERiLM+DfvhDJUlzkAi6/OREzx1LwEUkLVZ8OUMJcFUAmKT8aUs9rB07NaOjzxQ317fc/vf+EvM1ATypQf1uwdnex/vpYoA5G9EAvbC6kLKPO0Xj9oJyLNU5d4LR7IVPoe6MBAguaBBM0BiYqyw8hU0ir5cQuJBRR7pwFzOvMCFLSWgBLvLouToqBd0s2IgofEgEsMLYJyiwggEP0MsfDPkLYAIHu1VqPVPjuD4OPMvexNvqlQFt6g8ivTK5dqfdzt9Sihll7/auXrV93OKzJxo34MmTFdDl238jV9/+FN+5xer9KhB0PQFO7NmCQnUy8yNLoXldNX9MZnXzg3g+HWUff3Jt2Lrafk8Rf06Vr/tkXhC8YtrYo0XdUNFZnqPILVt5A+h2JIif7NwtnydxAAlk2VJhLDkLLTSNgjkheKzWqYF57tOUQ/T5onRwSF/O8cIW7aNtm8pmk+Qv0mVP81VU9wmqYiSUE9r6nawbLEk2at1XpE2/BR6/zgi5OjR0FbRglkoyTE+kMstD+kz6IkFjGZQ0aekzksczKHEMEt+P1pbt5XPutEq6EJy53O4XI6JxxnICoiYuEiImMBZ/hM59AslHikCw838N3ncRiax2HBy88IEySB3wvnhiT5vOPKiCQr5nEYp57FYWjVORdEic/hcK7LzeuLGRCNErHwKJG5gBn3eQaHqopt6siwsYZEzOCw5BmcSvBLFYtfMxpelxncUnATM4PLzVUqZ3C8UBJiqSIWmiqyZlFSFTKDs/KcwalSZ3AawS14y1duuGVJ8rtUuTM4tZzBicYZDNFxEQsfF9kLOMNlBmfmMIFToQkc7W1CgUQnQAJHacgLSMx1xJEV8zdVST1/o4+IwZP4/I3mXkTEgGjGmIVmjJUFxLjP8zelauqqZSPbsjUhr+BUyRM4g+AXvGkvL/yaU/G6zOCWwpuYGVxurlI5g+OFkxDnHLNwznGcc+6HFrndak2uq+cn58/P909a53MbMmzLqGJFM3GEQt4+wyefbL8i7pH/nQVqztwRafNRJdwnHC/7ZDKm0BMTIedthwHe/PoiEKnEkVJzCHe1fE4WU3IOPtWc6hPRJ9Yky3YRT1spGwjFMlpAoefnjaOt1vNms3b21VJydu28lohE+06vQ5s/ycuKCTCDOZPBdXsQDPRPti+c20e0s5OP626ffJLx1CF/BqSht25dh97wf/nadV+TP95vr/0HX3tPvo6nfh2kaDb9JPTv9C69ol92t+NSZIDBg+6126dbPp7Qmm6d1c69yWj4ozea22eDr58gOumKrkCW+ZyyIa9RxrZPDAboZIrQGaeXq9ho1Z5WW+dnzfbz09NZHFSqSDd1ZNk6nt14smKf9XjoOtejapB3AHRhEdUvjoh9eXpWbTa+rB9Q/KsdVWtnza2a4E2hdFeo6G2hMxrNAfUC1Seind8kS4Bu2hEWZ5JBw8VCI3hNGIuH4DVmLHpu0KxhyNwFNAzuLyBhKGYyBjbJkD5r0MLuiINB0fn5XUST9VpzLaED4oxjFs44VpmhQwBg7AkGDJUABvy+LUfAKApM7K2AiT15MLFXUJiAmOGYhRmONXYPQ1GxiRXVMMycEaNxfFA7bgmGDI1ARg7RDVf4GHGdbj56hA2bCB9hAhn4EZZdSACBSNOYhTSNdVYAUauKRTq6pqv1LUXPH0Lqx3XRGKITDBG9ODOv1kKgiN+2y2DETyEJR/zCCwkkECsas7CiscEKJFpVVxC2dNMkPT5vX+S4dnp4fki7g1AkMQiS5BAkcsWmr1m9bj6STBs3EUqmSWRgybT0QoIJRJfGLHRpbLKCCapixUSmamv1LWTkDCanh/Xj2vH5oWAwMQmYiA7fM6/XzQeTaeMmgsk0iQwwmZZeSDCBWMWYhVWMrRRrJIpi27ql6YaFBIDJyZHoKY5FsCSH81tWLZPMqLUYWOK17VIo8VLIQhKv8CICiQrRhjELbRjb7F6JiVVTVU3sk+nyBZKTo6+2amdNwUhiEyTJ4bzFFV7JrF4LgCRR4yZDSZRECpZEpRcSTCBGscrCKFYVVjCxqtiwdRvReT3O+23v6Vdn4hdeVWWnocIRcvLDknm1FgBLwrZNhpIwhRQkCQsvJJBAlFuVhXKrIuaFV7Wq27at6Poc2bb5m9uvr9KwbVcAy9HhF80WMdBxZBGKKE2881w04SyuXV5YErD9a60WxPbPFV7CNmTHlyVEXFnrr0HRifTbvfFku/fyUcfpbV9dP3pG/76+ekRHw6PXwcVr76oZpGz6V9FlM0zWbJ52vJ/8Pznwa2kv2Kof0+XkU5hiqykrGLZrDH8Qx1Zl4diqKTi2pqUgC2kaz3Xi1rOtM3k4p+48F86Ti6vxvjlNtLU2DtGK4iJBZFqVhUyrMpNpcVXDKunals154Yai99Ozljyk0Haei6bHzSvzvoFF0GYlXtxTvIBYtSoLq1ZlZtWiuZnU/uwsqjYcOrd3xowDy9hCeUZ6uOcHTuU6+EPlpzwvOHiK61CfOWg4KCBxSrP/6Omjzx+d3XkCghInIOf15mn9rHb+/Cxhix/d45Xv/APldbCqChFoVRYCrQoQaH3DQTexc96oE2YcuBEvaJfJ0414OvzRqZxTHTkuyOa8iDJtbMCDCP2FwH8IGiz0H1aASZBahtsQFF1ItwGiwKosFFgVoMCKgoLDXEP6Bjig7jTu8a68NcKBQ8wMAodQgF8BCHCYa4jfNR7+EGlVZSGtqgBpVdTwPxEx/LWdhvAddhs5/E/Yh/+JpOF/UtThD9FMVRaaqQrQTEUN/2MRw1/faYjeHLeZw/+YffgfSxr+xwUd/hpEDlVZyKEqQA4VNfxrIhYBjJ2G6B1tmzn8a+wrADVJ0/9aQef+GkTn1FjonBpA5xQ1/PdPBAx/CUfIb+bwp63FOPxpUhnDn5ZbyOEPkTA1FhKmBpAwxQ1/Ed5/4tHu5fhPO/7Z3f99WdP//aLO/zWIiKixEBE1gIgoCgKa9fPD2nGup8sEMJB4IHsJA+lgIGoyRiiI0suAg6jwQkICxDvUWHiHGsA7FAUJwhBhyfHmJSakw4SUkCATEQoNCBCxUGMhFmoAsVAUIJyenZwKQoTkg8NLREiHCFGjMUJClF7KBs6w8EKCAsQg1FgYhJpEBuHx1t7zc0GokHwIeIkKKV8gRq3G+hoxekDKy8So9EICA8Qn1Fj4hJpEPiHx7+piYCH5bO0SFlJPH+rppg91idOHemEBAWIYaiwMQ00iw5A6d4IQIfnU6hIR0k8f0kBClF7W9KG4oADxDjUW3qEmkXeIqGcnCBWSj6AuUSEdKkxbjREWpg/IwIVp6UUEBh1iJGosjERNIiOxJYSTsORY5xIT0mFCKwUroSWLldAqKitBh3iJOgsvUZfISzwWAwImAYGSmshlXTEFCBzLAoHjwoIAxE7UWdiJOjM7Ua0iSzWQrmh8Dvma36iw3zjINbZsiAkWwQTRdMV53W0gQATtx7p7wU8tZQODX3QhYQJiMOosDEadmcGIqraGTd2w6lt0pY43Shwd1A+/OhCyqmAToBAfxX5Ge5uIE1ELskJF9IAUtIhKLyRgQPxGnYXfqDPzG7WqYiqqqRkoF7/i8/r5Sc5R68NQSMpOA4tmO85rbwMRI2pBRsCI0svAi6jwQsIFxH7UWdiPOjP70ajaqqIaikojh3I4iGvBwdg/Ocz57K0QLxDBC9FcyHn1bSBeTJuQ2cMIH5DjYYSlFxIyIG6kzsKN1Jm5kUbVMolbjQ16NBTmDhnPntcatf2TXIM2h5BBwy2KJkrOq28DIWPahIyQMX1ABmRMSy8kZECsSZ2FNakzsyaNqmEamolNMhHH/CclrefPjpovRACGSgBDNIVyXnkbCBhhA7K+Fg2SS3kzGpRdSKiA+JQ6C59Sl8inJC12KAYdNIIOJZ2SEyAcpgOEQ4mAcFhYQIC4lDoLl1Jn5lKqVUXVFNNSVWL+LP7bL748JxfnIuBBJ/Agmlc5r70NxIqoBVl3Y4TppWzHCAsvIlwYEMNSZ2FY6swMS1S1LctSLWzXt1T+zsRRg7p/WzUReGEQvBDNuZxX3wbixbQJGQFj+oAMxJiWXkjIgPiYBgsf02DmY6pVzdA1rGCtvkU3SOYDGXsiIMMkkCGaoTmvvs2FjL20kLEnFTL2CgoZEHvTYGFvGhJjS5I2OxTlWFgEJcoQk5yA4TCtL3Eo1Zc4LLAvAfE1DRa+piEx4mTQZkLcB5sAQxl0kiMwpPIYDqV6DIcF9hggXqbBwss02ONOVhUFkRSaqppGDtGl9k+apyIOplN2GqrwGJSzuttAuAjbjznKlJ9cTowpv+xCAgXEyDRYGJkGMyMTVVUbG6apGrls+WgJQwpEkEI0H3NeeRsIFa10UNGSCBWtIkMFxMQ0WJiYhsQolSKI2iomwFCGp+SCBewwIAkBCjr4IU6lwcKpNCRGotwXMfjpydZlEEoux9uwH24j6Wibgg5+iCVpsLAkDYksyVrrUMTw18jwLymSXPZl0QZj3ZJF00rZjUULLiQIQMxIg4UZaUiMMtmqHR+IQAGdoEAZYZLLDMBrMdZJgJdYyjzAK7mIQGBCnEeDhfNopOA8GqpmY0VXc4sltdU4FsGRVg2CDOI5j7Pq20CYmDZhiohS/gOygkr5pRcSMiDOo8nCeTSZOY+oahqqZXgL5Qr/95H7Z3vHoiDDJJAhmvM4r74NhIxpE7KuMkQPSFlsiEovJGRAnEeThfNoyuQ8PjtsikIJi6BEyXnkQm2KWo2V2hQ9IIXaFJVeSGCAOI8mC+fRlMh5bD2jLSaEDK3aBBhKziOXtYio1VjXI6IHpKxJRKUXEhggzqPJwnk0JZ61HbSZCDK0puw0NOFMx00GBnYy9PQBicBQUDK0CXEcTRaOo8nMcdRoSCMTY82sb6EcUGJ/67R2RntJ/iiBCEqIZjnOq28TISNqQlbIiB6QAhlR6YWEDIjraLJwHU12rmNVwZauIt1S+AeBaQoEDEwAQzj7cUZ5GwgXzbRw0ZQKF81iwwXEjjRZ2JEmMzsSVW3bVpCeUxj8xtbp2VMh6xOaSvBCNGFyXnsbiBhRCzICRpReBl5EhRcSLiA+pcnCpzTZ+ZRVpJo2ti07L6wQsmShEawQzq6Mq25jgYJ97SJKLw8oirpyAXEuTRbOpcnOuawqKjKwopoK/9My9r/a18U4FToBCuEEzBnVbSBShM3HypcIkkthSwRlFxEmLIiRabIwMk32c76rCGkIW2oOB2R4bSfEnTAISgg/9DuuuU0FCXZvIkwuDSQK6ktYEAfTYuFgWswcTL2qq5ama8gis2wzD5wwxHgTJsEJ0QzMeeVtJlQY6fwJQ6I/YRTWn4C4lxYL99Ji515WFdMydMPAZi7TDkOMQ2ERoBBOwpxR3abCRCqPwpDoURiF9SggJqbFwsS0mJmYatW2dNuwNTuXtx57DdKARycigsRoNoEK0bTMefVtIFhMm5ARLqYPyACMaemFhAyIo2mxcDStNHEpNVUzVduw+AebI41nnh49FwEYurLT0CUEpowpbwPhYtqA7N5F8IAk/yIovZBwATE3LRbmpsXM3FSqyLQ0pGoq/4MyamdNIesVOiJQIZqzOaO4DUSKoPFYt5f7qaXsLfeLLiRAQDxNi4WnaUmMSUkbTMTqhI4JLJRxKXmBAfuKRJBaFhgUdT0CYmFaLCxMKwUL01SQaZoaPRqKf5SJ08P6ce34XETgOl0l4CCehjmrvg1EimkTMoLF9AEZeDEtvZCQATExLRYmpsXMxERVbGBDV23a523+kPHVWf24LmRBQiOIIZqMOa+9TUSMsAVZASNMLwUvwsILCRcQH9Ni4WNazHxMvWqrhqEhHeeyk/SgcSrqvAxdJ3ghmpM5r74NxItpEzICxvQBGYgxLb2IkGFD3EyLhZtppeBmKpqCbWSZOn8uReP4oHYsxL0wCFyIJ2fGVbeBYBE2H+tejyC5lK0eQdmFhAmInWmzsDNtZnamRvdMY023rXx2kB4fiJqImAQpRNMz57W3mViRaiISpZeEFsWdiNgQQ9NmYWjazAxNrYoUXbc1U83l2D6Eta3j2qmQpU6L4IVolua8+jYQL6ZNyAgY0wdkIMa09EJCBsTWtFnYmjYzW1OvWghh3TZy2f5B2+78kHaA/BHDJoghmqw5p70NBIxpC7IeCxw9IOVg4Kj0QgIGxNW0WbiaNjNXE1c1rJuqqdDTbflPSU5Pjr7aqp01BSCGoew0DNFszXn1bSBkTJuQ9e1I9ICU1yNR6YWEDIivabPwNe0UfE1FIZ4cslVF5b8Vnb4OPzkSsYhhIAIY4jmbM8rbRLwIGzAF+8JLL4t84RVeSLCAuJs2C3fTlnme+POjp7VnxyIAAhOAKNmbXGLvho3GGno3TC8l8m5YeCFBAeJw2iwcTlviOeOn9ePz2nFdBCioBBTK08a5eApho7F6CmF6KZ5CWHghQQFiadosLE1b4vnjh1jINEIjgFCeP84DELwGYwQDL60MIPAKLiQIQNxLm4V7aTNzL42qbRi6bli4vqXyp1IdPTsSdTqgoRNYEM29nFffBmLEtAmZjwoMH5BzVGBYehEhAykQ+dJmIV/azORLXMWaZllIQfUtzB8z6l+en4nCDINghmgC5rz6NhAzpk3IiBnTB2RgxrT0YmIGxMT0kGQlaJBUqYLUIFXBVj7xdI2tw/3PRWCGSTBDNBVzVnkbiBjTBkwTAs97QFoQPK/0YiIGRMb0cIQBMVIEzEQ20kwV5zAxOaatJyRSjWERvBAfMDOmug2Ei6j5WFlVYXoppKqw8GJiBcTC9BCEASvYzy+n3GOsIcPkH6LCbz8R4WsMm2CF8IPM46rbWKxgD2UTpZeHFQUNZ4MUiIDpIQgDVjBQMPkF0T3xu3buiGAqOw0zB5Ll8WBcabnjOVDINOTlhcMNGoM5Gm6QPo/xTfXaWRkQNxCgmGMcYkx6I59hjDNwJrktKRzWzkQMcEQGeA6kyA0a4H5LsK4LeIllDW2/9GKOa4jc6I12hnEdpzfqSPHH4lHzy7mXlYauVU1DNaZ7M5/3u+PRk97L7VdDMha8izQIQMuKD39SZDXofvmN/P3BiAx8TCw7Vn69QRvJ6Yy7b9zWK9clN1Rzp6GKXmCMq3Y95gA6jWWzHD+8DrISP3yIWHmYuP/QAnDoQUidvBz+oNwZyJgMrtuDG6rE0ZNnV9fbF87tI/r31fBRcBVdXHf79M/I7Tx6feXdIn/ILfJJb5E/A9Ibtm5dx/stSOdfjgf9vhu/7//gfT/aIhcjL8Pg66voR5oxGXH0njfw6Gfw2zQzckELI3+8y2YgeNOXvBlkNU0f/uJfBNk3/fybMzk3ozyBXGazifIJM5rLKZbVQkaxbObvTW/5GqNF+N9ehT9NU8eUGqk0VGikzrkSogJ2t+N9IYMtOeheu/0RHZZ05Gw9PTp5QTtd+KOHo+2zwddPaHePLu6bCYKotJ5hYjBBcTItVpTqF0et84N5C2Rhu6ooBCb1OQvUmVyO72iDaGGBDQrKFGaCiO+JEWSCLGKCRK9Zx3XL1wR9cXL0vFm/ixHCyjIjFHWRnG2QJ4VEG1Tbf9p89PJlz8Mu+pdAl9fh6XXQ8/2/FMu8LxT7O5PrIMW1n+A6uH8dgzp6FSb2frhyvPzpH8+CheW+DrN7HeT3OnzUv+895T/T835uhk82A5GbkczNUOhmJHUzzL4ZZN8Ms28GEjVDkZrTnKOsY3lPM4+eDB/NAc79vr0M0PE9BnSIBu3BPAOgx4nQmqJViaYWpxTI0HVkV03EEdBpYSGg+2UKA3RMAB1DgG4TQBf9YiGu23UBdI0uISUDethFcgZ0T4oS0EtALxygQ5R2D+YZAD1Oajcw/jJhlUjTDE3HVURJF3xWibzCZC0TqQTSVQDSNWWnoYkOvxHX7XosE9G2WYd1Il+OcqGoXCgqF4rW3gwhaJeEZ5wYzFB8nwTWdXheYWPVqKpYjwVsyb5QRAqTNK/QiBHSICOEiBESHdIlrtt1mVdgGvZf+rzCk6KcV5TziqLNKxC4hQUxbWFB8S0sGCkwoFs6wlVNs+z5WUUWQJ++fRYN6DoBdB0CdEwAXXQInrhu1wbQl75+Fgbokt8+l4BeArocQAd3GCGmHUYovsMImxgGdA1rtl5VFcQRz0lZkvDcIHhuQHiuEjwXHT0pptq1gXMTrwOcm7iE8xLOCwjn4CYwxLQJDAGbwEBEx9io6qqFdZMfpM9SxIWhOvAGlyC8KjxURUyj64LkK6nlosBcwG6wEs9LPF9PPAc36iGmjXoovlGv5Y7H3f7VqOpMxoO2+4YADKnjHEdndkcvxcYrd7gEuxPyFArXBK1F0234YXQMeud0mADKocqXwPJcRovgPM0jHT7PZRzgdBwz51LMbs9ZMphFDSZwRxxi2hGH4jvizrYQUqr7J/WnKBxBB+6oM+ze+N19MOrSLloZjQfdzqvu4NodD7udSmfgXl52O123P65cDoaVkdsjTeheVG6Gg4tJZ0wSXN+QAdIfV4nyYhnGIvsgTVexOiXRef2b6sz/wuJy7fUGndejql+JRp/6W15Vqqha228ctGR4XZpJps8ygv1E+sxhSPuKThzLXgMsGchB/1ocwCi2Z89rsemmvannpd7J1wpkSna1zlrnJ439REerdeN2upfdGT/LvXQmvfETVP81qufwcqX/NeMLoIz7+faOTmgQoeUWHkmx8OB2PsS0nQ/p6wFKiq5rpp4bKBE4OTw5koNLFsEl8UGFYiq9r7gUNFoJTfcYmsBtXohpmxcy1gKaTGQqimXhnKDp8/r5yXFdDjLZBJnEhzCKafSeIlPQZiUw3WNgArcrIabtSshcC2DCtqpZlmrk5jMd1A+/OqjLQCZd2WnoognzMyq9p8gUNloJTfcYmsCNN4hp4w2y1gKakK2puidMLtD07HmtUds/OZICTYhAk4STMacqvafQFDZaCU33F5owuBkDMW3GQPZaQBNWdWsmKAhfaGo9f3bUfCEFmDABJuEncsYVek+ByW+yEpbuMSyBWwow05YCrKwFLBmqahg2QvnB0qEkWFIJLAk/EzSu0PsLS4clLN1rWAKJ8ZiJGI/RWsAStrGCtLyWmI4a1PJu1aTgkkZwSfjRpDGN3lNYCtusBKZ7DEwgxRszUbwxXgtgUiwN2Ro9gCNPZNqTgkw6QSbRp6POqPR+Q9NeCU33GJpAtjJmYitjdT2gyVBNy7bycproCZi1/XMpyGQQZBK9sWVGo/cUmYI2K4HpHgMTyPzGTMxvvB7Mb6TRhVrLzM9nOpQ2mzMJMkkgf09Vek+RKWy0EpruMTSB/G/MxP/G68H/VlSkmt65cHlCk5zpnEWgSQL/e6rS+w1N5XTuPkMTyP/GTPxvvB78bzKQTAUbeU3njrf2T5qnUoDJJsAkgf49Veg9BSa/yUpYusewBLK/MRP7G68B+9uqGrah2PUtJTcekzRYMpSdhiGa+z2j0HsKS60Slu47LIHMb8zE/MazzG+M9So+PN9q1hrH1ebJUb39VaN+dACB1Fddt0eQxx1WJv3uuHLtjEaVwWVlPBg7vcqlS1CJXEWANKqMXznjijN0K/3BuNLrjihuOaNKg6hyPILxCleTt8954/UJUqJ/wRBOh2C0vgdEceEvUd19WJtqoHp6WD+WtBXY0Ai0wZyD8XCSjGz+zbuFhapK2mYX74DLDn2Idc1FeAvaKgZyEaYxnTCcDG2z4i3BuEC29BinlPg2j28qSB/HTPRxbK8xvilrhm5ICrrpBN1g3kJe6Kbce2xDJbZtCLaBHHSViYOurrPvtj7Ytv/Vvr5Vk4NtNsE2eK2sxLZFbAtaqsS2DcE2kMiuMhHZ1dJvY8Q2QxK2mWinYcI7mktsA7HNKLFtc7AN5MKrTFx4TSmxjRnbsBRswwTb4E3RJbYlYRsusW1DsA0k06tMZHoNldjGjG2qFGxTCbbBO6tLbEvCNrXEtg3BNpCPrzLx8TVcYhsDttXOmrKmpDqBtvJVAiu0+Q1VItuGIBtI51eZ6PyaWiIbK7LJmZAaBNngLZQlsiUgWzkf3RRkA3cDqEy7ATStRDZGZNuT47NZBNngfU4lssHItlf6bJuCbOCGApVpQ4GmrzGyoWrynkwp2CbHa7MJtomlf3iKv9/oVvptm4Ju4L4ElWlfgmasMbqtj9/ms0GlgJtBpqRGOSVNx9stsW1DsE0D9ySoTHsSNLPENmZsk/KO1DAJtsFxgUpsS8K28h3ppmAbuCdBY9qToK3zngRUTT5aSM6uBCngZhFwE7vi5in+3sKb31Qlum0IuoG7EjSmXQnaOu9KwFVtndDNkINuprLTMOE4IPltltfuN7oZJbptDLqB+xI0pn0J+jrvS1CryTGLpPBApICbRsBNbCQQT+/3Fty8liqxbUOwDdyXoDHtS9DLfQnM70qlIJtJkK1ccUv1orTEtQ3BNXBPgsa0J0GP70lQVeOgUW9Vm7VW6+lZbT+Es3mUYcCO1njoOtejapjlyWTsQUWQsw8R1Re18/pZnkBx0HVHT3vO6NUv1/BOQ/gxtfwQYs8h2nhC1be77X+Pg0ag7UTUCFphGVxETb4IFhE4BGARtBojWASpF8AikikZJZr00UbtKBEn9p1ehzb5DFDEECAoOxkUlIyg0Do/q9eaq1BBkYIKIJ9fY+Lz66pMVDjEgiBB3WkIPyJ2MyHhEDPjAU0qBQxowcVEApD/rjHx33VNJhKciEICbach/FDWzUSCE3YkOJGFBCeFRQKQL64x8cV1XSYSHItCAnoKaokEPJDgmB0JjmUhwXFhkQDkVmtM3GrdkIkENVELBpSfXCIBDySosa8W1GQtFdSKuk6gg0xkjYmJrJsykWD/RBAS0HcLJRLwQALaZIxIQJNKQQJacDGRAOTt6ky8Xd2SiwSipgfWTkP4oZqbCgXs84N9aUsF+4VdK9BBnqvOxHPVbZlo0KyfH9aO64IQwd5pCD/NcjMRIWo3VhpCmF4KMkSlFxMdQJ6ozsQTNRSZ6CAUHJCy00Awm7yEh5TwkBIdpIJDsbEB5FnqTDxLA8nEhtOzk1OB4IAIOMAnYJTgkBIcopZjRIcovRR4iEovJj6AfEWdia9oSOUrHm/tPT8XCBCYAERJWuTzNjJqOtZ3ktEDct5MRsUXEyNA9qLOxF40pLIXietXF4cQKkGIksPIa35RTze/qMucX9SLiw0gn1Fn4jMaUvmM1O8TCA4aAYeS1shtfpEGHaL00uYXBcYHkOWoM7EcDaksR0SdPoEAoROAKNmOXABi2nSMCDF9QApETIsvJkaA/Eedif9oSOU/toRxHZBB4KGkQHKBh1YKtkNLGtuhVVi2gwGyIHUmFqQhlQV5LA4PTIIHJRGSz3JkCjw4loYHx8XFA5ALaTBxIQ12LqRdNbCuq4qi1bcUK4fNEvuNg5YoeLAIPIgmR84rcBOxImhE1h0Ufmo5myj8souJGCBf0mDiSxrsfEmzalq2gpCWF2IcHdQPvzoQtgRhE9AQzZ+c1+FGgkbUjqy4ET0gBzqi4ouJHiCf0mDiU5rsfEqrammqYhg6qm+hHCYjn9fPT47rojwOrOw0sGh25bwKNxE8omZkxI4ovRToiEovJnKAbEuDiW1psrMt1aqtY9tEGiY208zD79g/OTw5EgYdiECHaO7lvA43ETqm7cjsd4QPSPI7wuKLiR4gF9Ng4mKa7FxMVMW2oWPPaCo6f/R49rzWqO2fHIlCDxpMUjQxc16Hm4ge03ZkRI/pA1LQY1p8MdEDZGkaTCxNk52lqVcVzTAs2zKJy50DerSePztqvhCFHSrBDtGUzXkNbiJ2hK3I+pY1SC7nRWtQeDFRA+RvGkz8TVMqf5M026E4oNAIUJT0TV7YcJgOGw5lYsNhcbEB5G4aTNxNk527aVWRrquaYmjEHqo5bAL58pxcnItCCp0ghWge57wKNxE2omZk3RMSppezKSQsvZjIATI6DSZGp8nO6MRVA6m2ZSErn7nIUYN6hvTQKTHQYRDoEM3xnNfhJkLHtB0ZsWP6gBTwmBZfSPQwQf6nwcT/NNn5n0ZVMTXTVrGez1uUoBX3RKGHSdBDNCN0XocbjB57adFjTy567BUVPUC2qMnEFjWlRs4kDXco0t2wCGCUATR5YcRhWg/jUK6HcVhkDwPkh5pM/FBTajzNoOGEORU2wYgypCZPjEjlRxzK9SMOi+xHgCxQk4kFarGzQHEVq0jVVVPNh41xvLV/0jwVdYifstNQRZNA5zW4idgRtiJzvCw/uaRoWX7hxUQNkAFqMjFALXYGKKYcAk2xbTrvNnJ4uSoUNRBBDdH8z3kNbiJqtNKhRksmarQKjRog89NkYn5aUqNwiuKIq5hgRBl+kw8ssCOCLDAoKg6AHE6TicNpSY20uS8KB+g54WWQTT6n/rCf+SPrxJ+i4gDIyjSZWJmWVFZmrXUoCgk0ggQlJZPPRjHaaqx7xGhaOdvDaMnFxAOQiWkyMTEtqVE0W7XjA1GAoBNAKCNo8pkieM3GOkvwEsuZKHhFFxMTQI6lycSxtNg5lqhqmYqiaxbKLyrWVuNYFD1bNQhIiOZYzutwExFj2o4pYmP5D0gLj+UXX0j0sECOpcnEsbTYOZZm1TSRqqo26fh2DqsOZ3vHIsHDJOAhmmI5p8JNxI5pM7KuR0QPyFmWiIovJnaADEuLiWFpyWVYPjtsisQLi+BFybDkw56Kmo6VPRU9IIc9FRVfTIwAGZYWE8PSksqwbD2jzSaMha3aBCNKhiWfVYuo6VhXLqIH5KxeRMUXEyNAhqXFxLC02RmW+WGEKBa2puw0NNG0ys3GCHYW9vQBmRhRVBa2BfIpLSY+pS31/PLW/tZp7az2VBRGIIIR5QHmfDAiajpWjIgekIMRUfHFxAiQPWkxsSftFOzJKkaKadsWyuE1SFMwWmCCFsLplHEFbiJuNNPiRlMubjQLjhsg29JiYlva7GxLtWogXTe8t38I8YeOxtbp2VNh6xWaSpBDNAFzXoWbCB5RMzJiR5ReCnREpRcTOUB+psXEz7RT8DOriqLoWFU1xQtskw9yCFvF0AhyCCdszqlwc5GDfUUjSi8ROQq7ngEyOS0mJqfNzuRUqzYysalgK5/YVvtf7eviXA6dAIdoYue8BjcROMJWZGVdBMnlcC6CwouJGiDX02LietrsXE+zqiPVVG3FzmdXudeGwtwNg6CGaKbnvAY3FjXYvY0wuTzUKKqvYYMcT4uJ42mzczytqmJibCAb5RO/m7ShIc7XMAlqiKZ4zmtwQ1HDSOdrGDJ9DaOwvoYNsjttJnannYLdSSbmhqpg27RyYYbTJhTmalgENITzPGcVuLGYkcrTMGR6GkZxPQ2Q7WkzsT3tFGzPKtKIc62qVg6B8vYapAmPTkQFtNFsghnCeZ9xBW4iYkwbkREzpg9IQY1p8cXEDZABarMwQLGSggFaVQwNkSdQHsBBWtA8PXouCjh0ZaehCyeDzmhwE5Fj2ors3kbwgCx/Iyi+mMgB8kJtFl4oVlLwQunrQ6TZhq3YSg5rG7WzprClDR0R4BDOEJ1T4CZCR9CIrPve/dRyNr37ZRcTMUCWqM3CEsWK1BibtNVELWXomIBEGWeTGy6wr14EqaXhQmHXLkAWqM3CAsUKOwvUrlqGpdkqNvN5t3p6WD+uHZ+Lir6nqwQnRNNA53W4iaAxbUdG3Jg+IAU6psUXEz1AJqjNwgTFCjsT1CSj3zQ108wnCNfpV2f147qwFQyNYIdoIuicBjcSOsJWZEWOML0c4AhLLyZugDxQm4UHipUUET2rCkKWQpfucnjJetA4FXlOiK4T3BAe4HNGg5sIG9NWZMSN6QNSgGNafDGRA+SC2ixcUKywc0Hpwh1SdUMxFIRz2HpyfFA7FuZwGAQ4RFNB5xS4icgRNiLrvpMguZxtJ0HhRcQMrIBMUJuFCYoVdiYo6fK6ZSNDy2F9g7SfyCmKSRBDNA00rr4NhYtU85MovSzAKO78BCsQC9TDEQbESMcCRYqODdXScqBmIKxtHddOhS2KWgQ1ZPBAYyrcROCYNiMjckwfkAId0+KLiR0QG9RDFAbsSMUGJX3eUDScAzGDNt/5Ie0DYpDDJsghgQ06VeAm4sa0EVnPTY4ekHNyclR8MXEDYoN6aLIaNxA7G1SrWpZtYAvnc+D66cnRV1u1s6Yg5DCUnYYhmg46p8JNxI5pM7K+TYkekPM6JSq+mNgB8UE9RGHAjjR8UIxU27ANNQ/kOKwfnxyJWuIwEAEO8XTQmP42EjbCNkzB3vDSSyNveKUXEzMgRqiHJAyYIffU9edHT2vPjkUhBSZIUXJC+YQWDluONbJwmF5OYOGw9GLiA8QM9VCDAR/YmaE54MNp/fi8dlwXhQ8qwQfRXNANxYeo5Vj9hzC9HP8hLL2Y+ABxPz3UYMAHqae0H2JhswyNYEN5SjsXbPBajREXvLRSMMEruZh4AHE6PZRgwAN2Tieq2lhRTYSM+hbKIbbn0bMjkYckGjpBCNGsznkdbiJcTNuR+cTE8AFJJyaGxRcTPSBep4cpDOiR5jx3pCq2rdo4n60k9S/Pz0Sih0HQQ/x57rM63ET0mLYjI3pMH5CCHtPiC4keCGJ4epjCgB7sDE+9inQN24qVX1xxY+tw/3NR6GES9BBN85zX4Saix7Qd08Tu8x6QF73PK76Y6AGyPRET2xOlY3vSPRGagmw9B474MW1CYfF0DIuAhwy2Z1yFmwgeUTOysrbC9HJIW2HpxUQOkOuJmLieiJ3rqVcVA2HD0PMJnuG3oagYO4ZNgEM02XNOg5uLG+wRd6L0EnGjoFF3MAK5noiJ64lTRP7Mi6WFBGGFqew0TOHRPjcTH6KWS8XNQlK5Waio+ADyORETnxNLPffdbzcsCh8QwYfy2HeO+IBT4gOWig+4qPgAcjcRE3cTS+Vu+u2misIHTPCh5G5yxAc1JT6oUvFBLSo+gNxNxMTdxFK5m/5Bl8LmFyrBh5K7yfE4Vfb5RZRe4oGqhZ1fgNxNxMTdxFK5m/7hdMLwQSP4UPI3OR6BmAofDKn4YBQYH0AuJ2LicuIU8Tnzwgdh6w86wQfhMTk3GR/Y1x+i9BLxobDrDyBbEzGxNXGKKJx54YOw9QeD4IPw0JubjA/s6w9Reon4UNT1BwzyMRETHxOniLiZ05FkwqYXJoEH4XE2NxMewoZLcw6ZrMlFWHgxsQFkW2ImtiVOwbbMCRuETS0sgg3C+ZUbjA3sM4swuTxsKOq8AoN8SszEp8QpYmfmdEqhML/BJtggPF7m5mLDXjq/YU+m37BXWL8B5ExiJs6kmoIzWUXI1hUdGTlsD/UaUJQHYSk7DUs4eTKuvo3Fi3S+xJ5MX2KvsL4EyKHETBxKlYVDyQ0V9honft8WAwuIwEIOnMnjwbjScsdzyJBp3Esb5FGLMI7yKH0uw5xqtrNiqEcSFHOsg3xIzMSHVFn4kPzePxzWzkQNdEwGeg7kx00a6H5zsL5R8BJLG+J+8cUc3yCfETPxGdUZPiM2WrWnSzZoa6pmaYZu3O28UD93Wb7/0+GPTsf5jfuVO7NjulsTz99rj3Vz/AOhSr8/J6wAuY2YiduoasxYkQ8+5LqCGOJDThOAe7J6yB0TeCweCsKEwq4dgnxGzMRnVHW5mJDvG8cQE6SsFW4sJnB52SgGE4r7rhHkMGImDqNqSMYEEX5Cwd8ycscEHuQkQZhQVD9BBXmLmIm3qJryMEEAqzkEhWLTkniCAkdCc/6wUGw+swpyFlUmzqJqycYFEROIglOZ+eMCl41QonChqHMIFeQrqkx8RdWWjQtCJhHF3gHFHxe4bKAWhQuFnUeAXEWViauoKVJxIe/oKyEuFHvnNGdc4BV4RQguFDjuigpyElUmTqKG5OGCgKhtIS4UO+IKT1zgGLAtf1wodrw2FeQvqkz8RQ3LxgUh6wvFjtTGHxe4BHoVhQuFXV8AeY8qE+9RY+c95oQLQuYRxY7wyh8XuASIF4ULhZ1HgBxHlYnjqM1wHJHxrNaqkqo2289PT2dxwcBVS1VU1ZzuhHze745J45Bx431JBRh+UQFghCVWDyxjCykBbpyfnNM+IWJ7xAneeSEaN+IK5QUgadDCa4ElaDHtBoto4bdTDC4i+PDB4knQdvTrMtQIki1iRiBcjpgRFD2DGJPBdXtwQ1VJnn/09NHnj852t+M/ZsCUg+612x/RVjqvN0/rZ7Xz52d1Wn74szec2meDr5/QoOzRxX0DI5BcqTKRKzWdFYxsXDU0zdBtPWcwsmWAkbrzQvTkJq7Q+whGdglGJRgtghHI6lSZWJ0aFJkSRiOsoqpJLLlmc0Gj2S2j8uFI23kheg02rlEZcLRyW6lUPBIQLKIEpFwASQMppSoTpVQzF72jL06Onh41v5yFI6QrVQsjWzXm4KgzuRxvvxpmd5GCYqtBx84NhbyxIAJv4irju5hDVPW8Wb/Tcs4qnyhq/JWrOT60rFrCCR6S4f8ERSfCTW3/afPRy5e97Qvn1vv7avjI6830OujW/t/rbt//MnI75Mt1kOLaT3Ad3L/eHpBesnXrOv6vYWLvhyvHy5/+oalfh+W+DrN7HeT3OnzUv+895T/T835uhk82A5GbkczNUOhmJHUzzL4ZZN8Ms28GEjVDkZrTnKOsY3lPM4+eDB/NAbD9Hr719OjkBQzY6D4DNsj11Zi4vhoUnxRGbAVXkanzxOtZJ3LzADvS2NrA9UqfURheC/APS8AuAXs9ARskYWtMJGzNBjzso9b5wQJea3oVq9i01dw8bL/Y3AH7SYO2jtMZd9+4rVeuKytiTFyja4PoKx3wsG+UDniJ5yWe54PnIHleYyLP6wB5HsRzjFDVwKpJI/5ww/MZSoxMPFcJnot+nxTX6Nrg+Sp+jDA8z58RU+J5iefriefgpgeNadODDgViBgHd1gj+mhq2eAL63JKKRETXCKKLfiUXV+naIPrqNRdRkF6uuZSYXlhMBzesaEwbVvT4hhV/vG+dDrsdt3p61tivh7B+4I46w+6Nj6z0dmVwWRm/cisj75EqUWosRRTC1zLn8P+T7V4q7HfHk5vqjFiNPkV/T7hqODEXCv46AX/he2U9TfKFfQLMZFSAsE+1ngj68dZYgvxB91nE/bDR0gF/+NQC8vvjcisoLhn+D2rntUTob924ne5ldwb53Utn0vMwJfw6Yw1CgRLNwSfbBPUefbLd6dAPAnbeHwKM9M+193l7Qf4Q0COfr/3Er/1br+l3+n/T/7kZPN/0bzf9Z669W2GSKE1wt9n0P59/HlyHX7y/yzAWZcLYoCUgkNX1FSA730hTiPV6afskkJfupHjUPDmqP/J78SP6f9CVo0QxWEZSYBncL6Qx7RfS1RxhOV9MDibXQjHZIJh87+OaSAPkoMVSAnLw1PoAciBQCcglICcAMrhRS2PaqKVrefrJ9jxzmTMmh7NjoaBsElAWHoTOU+WG4HLYaimBOXxsfZA5lKiE5sJB87lzFQzTOC5Pf4X4fYqPufG3h/7w9DvO9vTp1flDdBTk5x9fzd5z4Ozr3xAt9J0eUMbcLbgiKyzLQt1iZSuzkmzPlZdGNlgJLLLF9BITBq0SLewE50kG2btxJ5VNO0bMklL08+zMk/3BaPzLe9rOHgopNF4fPiSw7w7pUArswMxvNEUst9lkczd2n/a6N574AfwFKed/3q1NxoOng+G1M37yTc+TZPrL8YCa0ViK3b0BrX9tSIDCW+ScufbyetG9IMY7KG36w25Q6C1RNNHCeXccu6JV7PavoutGnyCFn7XX/WOXu013SETsX+y73sgfDyeknLkfQyNw8vkU/bdn2pS17e/UJaeDFmz7BR/kk9onaOeTxicq3BX8Kq51T8AieoIqtSeABBMWlzxNT6gZOw1k3NtuoInoBrrUbgC9l2Z5K62uMgY1pN/rtjdEtL0pte2h91csb6+0VBCA0U5DVe5tP7BE9ANbaj+AFsxZlsv1NP2giXaea/e2FyAxvqFc5xBap2NZpTOW9AM/RFnoEVoJs4P70AOE+IRIrlMIRbFhiWFjrvYG7J0Gvr/eABLiCiK5viAUNoQlaIiVcnKoahQLtPs7PURCnEMk1ztEUNAGlpANdsruoBm0Oxj310VEQnxEJNdJRNCyIWJZN0TLFg6hDmGotENExy7evw6BhXiLWK63iMC1RKbFxGWridMITBvgNGIhTiOW6zQiaCkRsawlomWLibGOcEI7wotP7u/0EQtxH7Fc9xFBa4mIZTERLVtNhCyE5QODeX87hBAPEgvxII+6o3Fip6A37/TC0Xvaf+sYfvVf8vsLT+HXXdJiJ5eXI9d77T+9mBOZipFW7Du9K1smtgqKjTiLfacXO8vENkGxMWex7/QiYpnYCii2ylnsO62hLxNbA8XWOIt9pyXfZWJjUGyds9h3WqFcJjYCxTY4i32nZbVlYlug2CZnse+0HrRMbAMU2+Is9t0WLkJhESC3LQS47zjDDqXFUPeG+zd3ye82FVwqOQwovK3OHecuSyWHzTxvw3NHb3up5GJsD4JsJmI2mqDksEfI2/wgyGwiZrsJSg5jIm8LhCDLiZhNJyg57BfyNkIIMp6I2XqCksPmk7sdguwnYjagoOSwJbJ5z3wgC4qYTSgkOYbdccR90gZGLmU2oiokuhgjisEQfsxGVIMkh40od8nBKSezEQUlh40ob/OP4bNoM0kOG1He5h/DwQcySQ4bUd7mH4P7c5mNKCg5bER5m38MbmRjNqKg5LAR5W3+MXg8EbMRBSUXMwfF4FkmzEYUlBw2orzNvwoeesBsRCHJVdiI8jb/KmRDVWYbqkOSi7GhKmRDVWYbCkouZiKqQjZUZbahoORiJqLgee6rj3MPxTUgyWFLxL23QDZ09YHTSyWHLRH33gLZ0NVH4i6VHLZE3HsLZENXH9q5VHLYEvH2W8Aj/laf8LdUctgS8fZbwPPAVh8HtkxyDbZEvP0W8OCg1ecGLZUctkS8/RbwBI3VB2gslRy2RLz9FjCU/OpI8kslhy0Rb78FDJq8OmbyUsnh2Rz3ZQswPujq8KBLRU8worytKBgGb3UUvKWiw1YUcX/nDJnR1ZGilooOm1HE246CQVVWx1RZKjpsRxFvQ6pBhlTLZEi1hDd0vC2pBllSLZMl1RMWRnmbUh0ypVomU6onTOp421IdsqV6JluqJ6yM8jamOmRM9UzGVE+gEfG2pjpkTfVM1lSHrSnmbU11yJrqmaypDltTzNua6pA11TNZUz1hTsrbmuogqSiTNdUTuGfcWVyQNdUzWVMdtqaYtzXVIWuqZ7KmOmxNMW9rqkPWVM9kTQ3YmmLe1tSArKmeyZoasDXFvK2pAVlTI5M1NRLWSHlbUwOypkYma2okvGjkbU0NyJoamaypkfCmkbc1NSBramSypgZsTVXe1tSArKmRyZoasDVVeVtTA7KmRiZraiQs8fK2pgZI081kTQ3YmqrcedGQNTUyWVMDtqYqb2tqQNbUyGRNzQQOPW9rakLW1MhkTU3Ymqq8rakJWVMzkzU1YWuq8ramJmRNzUzW1Ex45cjbmpqQNTUzWVMzgfzK25qakDU1M1lTM4G4w9uampA1NTNZUxO2phpva2pC1tTMZE1N2JpqvK2pCVlTM5M1NRPemPK2pia48SWTNTVha6px32kEWVMzkzW1YGuqcd9tBFlTM5M1tWBrqvG2phZkTa1M1tSCranG25pakDW1MllTC7amGm9rakHW1MpkTS3Ymuq8rakFWVMrkzW1EvaS8LamFmRNrUzW1ErgwfK2phZkTa1M1tSCranO25pakDW1MllTC7amOm9rakHW1MpkTa0EAhJva2qBW0kzWVMbtqY6b2tqQ9bUymRNbdia6tz370LW1M5kTe2Efd68rakNWVM7kzW1YWuq87amNmRN7UzW1IatqcHbmtqQNbUzWVMbtqYGb2tqQ9bUzmRN7YStmbytqQ1ZUzuTNbUTtpXwtqY2ZE3tTNbUhq2pwdua2pA1tTNZUxu2pgZva2pD1tTOZE2RkkDo5b4RWQGjM2Syp0hJCOPBfS+yAodoyGRSkQLbVIN/XAwwTIOSyaoiBTarBm+zSgoCpc9kWJECW1aTt2UlBYHSM9tWE5RezD4ZUg4oPLN1hYUXs1WGlAMKz2xfYeHF7JYh5YDCM1tYWHgxG2ZIOaDwzDYWFl7MnhlSDig8s5UFhUdits0gMASSV6UswovZOYPgOEjsgZAsUHhB8YQSQiEx21hQ+ASc5442cDQk9nBIsPAJr/i4Cw9aWPaISLDwCcuS3IUHLSx7UCRY+ISpFHfhQQvLHhcJFh7Gef5oA1pY9tBIMNrAOM/do4eDI7FHR4KFh3Geu0MPx0diD5AECS8oVg+CIySxh0iCogyihMhx3G0UGCMJsQdJskHhE3ZKchceNLDscZJg4RN2d3AXHg43yGxgYeETGKnchQcNLHu0JFj4BBYNd+FBA8seMAkWPuHNH3fhQQPLHjMJFj5htZK78KCBZQ+bBAqfEE6Ou3cABk5C7JGTYOFhI8XdOwBjJyH24Emw8PBEirt3AIZPQuzxk2DhE/ZOcl/uA0MoIfYYSrD0CSaWu40Fwygh9jhKsPQJi5X8Q/qCRpY9lhIsfUJIAu5WFgynhNjjKcHSJ0Ql4G5mwZBKiD2mEgKDtCfEmuPf70E7yx5XKUH6hO2U3KUHDS17bCVY+oRYHPz7PWhp2eMrJUgvyL0EQywh9hhLsPQJka24u2hgmCXEHmcpQXoxcRYRGGoJscdaSug5YmItIjDcEmKPt5QgfcI6CHdHB4y5hNiDLiWInxCegztmgnGXEHvgpQTxE9xM/mcAwKH0M5rbpKBX3Oe1YPwlxB6AKUH8BEeTP2yCBpc9CFOC+IIWFcAwTIg9DlOC9IKW7cFITIg9FBMsfVIwJu6eJhiNCbGHY0oQPwH1+Z/gAZpc9pBMCFz/TgrKxF160OSyR2VKkF7Q6j0YlwmxB2ZKkF5M2HoEhmZC7LGZEqQXE7oegdGZEHt4pgTpxYSvR2CAJsQeoSlBejEh7BEYowmxB2lKkF5MGHsEhmlC7HGaEqQXNMUCIzUh9lBNsPQJwZq4T7HAYE2IPVpTgvSiplhgwCbEHrEpQfwEY8vd2oJBmxB71KYE8ROmWNzNLRi4CbFHbkoQP2GKxd3egsGbEHv0pgTxE6ZY3A0uGMAJsUdwShA/YTGf/3lxoMVlj+KUIH7Caj53kwsGckLskZwSxE9Yzeduc8FgTog9mlOC+AmxhrkbXTCgE2KP6ASLnxDTiXv4WAQGdULsUZ0SxE+Iksjd6oKBnRB7ZKcE8RNoyNytLhjcCbFHd0oQP2GOy93qggGeEHuEpwTxE+IPc7e6YJAnxB7lKUH8BJYad6sLBnpC7JGeEsRP2PDD3eqCwZ4Qe7SnBPETYhHzP6oVtLrsEZ8SxE+IR8zd6oJBnxB71KcE8RNeonO3umDgJ8Qe+QkWPyH2E/cwswgM/oTYoz8liJ8QTZG71QUDQCH2CFAJ4idEVORudcEgUIg9ClSC+AlRFblbXTAQFGKPBJUgfsLSMnerCwaDQuzRoBLET9h8xd3qggGhEHtEqATxE/g73K0uGBQKsUeFShA/YaMtd6sLBoZC7JGhEsRPiFvM/5R00OqyR4dKED8hdjF3qwsGiELsEaJg8RNiRHEPR4vAIFGIPUpUgvgJURe5W10wUBRijxSVIH5C5EXuVhcMFoXYo0UliJ8QfZG71QUDRiH2iFEJ4ifEM+ZudcGgUYg9alSC+AlvdLlbXTBwFGKPHJUgfsKmZ+5WFwwehdijRyWIn0Cb5W51wQBSiD2CVIL4CQEuuFtdMIgUYo8ilSB+Qoxj7lYXDCSF2CNJgeLjhFBS3MPWYjCUFGKPJZUgfkJ0Rt5WF4PBpDB7MKkE8RMiNPK2uhiMJoXZo0kliJ8QpZG31cVgOCnMHk4qQfyEuMe8rS4G40lh9nhSCeInxD7mbXUxGFEKs0eUShA/gUjF2+piMKYUZo8plSB+QrAR3lYXg1GlMHtUqQTxE4jLvK0uBuNKYfa4UgniJwSW4m11MRhZCrNHloLFTwg5wj28LQZjS2H22FIJ4ieEcORudcHoUpg9ulSC+AkxHLlbXTC+FGaPL5UgfkIQR+5W
A3: F4wwhdkjTCWInxAfmbvVBWNMYfYYUwniJ8RI5m51wShTmD3KVIL4CXGSuVtdMM4UZo8zlSB+An+Zu9UFI01h9khTCeIn7BHlbnXBWFOYPdZUgvgJUUi4W10w2hRmjzYFi58Qh4R79FsMBpzCKQJOweInhHTkbnXBkFOYPeRUgviw1TW5W10w6BRmDzqVID5sdU3uVhcMO4XZw04liJ8QO5m71QUDT2H2wFMJ4sNW1+RudcHQU5g99FSC+LDVNblbXTD4FGYPPpUgPmx1Te5WFww/hdnDTyWIn7BtiLvVBQNQYfYAVAniJ+zS5W51wRBUmD0EFSy+mhD9i7vVBYNQYfYgVAniJ8T/4m51wShUmD0KVYL4sNW1uFtdMAwVZg9DBUX8xypsdHOQHjS67GGoYOlhm5tD1wFtLnsYKlj6BJPLf9yCJpc9DBUsfYLF5Q6aYBgqzB6GCpY+weByt1hgGCrMHoYKlj7B3nJ3F8AwVJg9DBUsfYK55e6rgWGoMHsYKlD6hEhI/B1lMAwVZg9DBUufMMXlPksBw1Bh9jBUsPQJM1zuU0QwDBVmD0MFS58wweVua8EoVDhFFCoMii8mpDUGg1DhFEGoYOnFxLTGYAwqnCIGFSy9mLCDGAxBhVOEoFJB6RP2iHKXHrS1KSJQgdInREHi33NAW5siAhUsfcJeFe7Sg7Y2RQQqWPoE0ixv6cEAVDhFACpY+gT2DnfpQVubIv4ULH3Ca0Q26Wvj8bD7cjJ2F0SP7kBSr5SZCEPGIxUpyufJF05v4u5uT3/Y3R/0Jtd9mjL4tnvoOhfd/lWYNrzcbVz1B0P34sml0xuR38PLSDfxyGKt8W3Ppb/4X4LKx4plrTnI0GaoOZqv+bFzzVpxPylzvdFCvVH2eoN+CUO9MXOLo+wtvlhznL3mkE+z0qMhEqjzNX/e745HUM3xYs2DtBlqrmavOeQPrfSGiATafM1bY2c8AauuLlY9TJyh7lr2ukPe1EpfikigL/b3YZdKlzTeNajb+49UMg98PbsiIMdspVvmz6NmFdE4QFD99cX6n7z8XbczrngPZKi8kb3ykF+30qtreMcOzlceQ5U3llQeZ6q8mb3ykFu40ilseMdZzVZ+f9AfO92+O4RUYC6qIJY+gwas7BoAGYIrPcuGd3ZBggra57c3IA5YS/QQPJRBGTYHZcBHRrP4PgtuX37OD150fjh4fQmHYbLUfcHxy9MBAmrPwfeDT9Nk8f7QgvuXpxME1J6D/wcfx8niAaIFFzBfRwioPwcvED7Rk8UPRAuOoEBnCFAGB7cQPiGUxTFEC55hzg4RoAAO7iB8yiiLQ4gAjzBXpwhQAAeXED6plMUpRAteoQjHCNACB98QPvKUxTtEye7hnXyjSkrfCNAHB08RPkaVxVVEC75ifs6Rulh3Do4hTIllcQwx+3ogB+dosfaYx4IgvI+FpfYLrmGezhFQew6uYQIhl6X2C65hvs4RUH8OziHM6GVxDvGCcyjQOQKUwcFThPnBLJ4iXvAUc3aOAAVw8A5hhjGLd4gB7zBX5whQAAfvEOYos3iHeME7FOEcAVrg4CLCVGcWFxEnu4hCnCNAHxycRZg7zeIs4gVnMT/nSFusOwfHECZesziGeMExzNM5AmrPwTUEeduradu0Jy64hnk6R4u1Vzm4hiDtezXrm9Z+wTXM1zkC6s/jnTHkHK7mjdP6A6+NhTlHgDI4eIogD301DZ0qY8FTzNk5AhTAwTsEqeyrmexUAYB3mKtzBCiAg3cIsuFXk+GpAha8QxHOEaAFDi4iyKpfTaqnWkh2EYU4R4A+ODiLIE9/NU2f6mPBWczPOdIX687BMQRZ/qtJ/rTuC45hns4RUHsOriG4S2D1JgFa+wXXME/nCKg9B9cQ3GWwepMBHYcLrmG+ztFi/TUOziG4T2H1NgVaf+CVsjDnCFAGB08R3PawetcDVcaCp5izcwQogAfJEPIOV2+coAoAvMNcnSNAARy8Q3Dzxeq9F1QBC96hCOcI0AIHFxHcxLF6DwfVQrKLKMQ5AvTBwVkEt4Ws3hVC9bHgLObnHBmLdefgGIKbSlbvKaF1X3AM83SOgNpzcA3BTSmr96TQ2i+4hnk6R0DtObiG4KaW1XtaaO0XXMN8nSOg/hycQ3BbzOpdMRSHgFfKwpyjRWXoHDxF8JT31Ye8U2UseIo5O0eAAjh4h+BB8avPiacKALzDXJ0jQAEcvEPwrPnVR81TBSx4hyKcI0ALPLajQC7i6iPrqRaSXUQhzhGgDw7Oog7uUWHapLLgLObnHJmLdefgGOqQY6izOIb6gmOYp3ME1J6Da6hDrqHO4hrqC65hns4RUHsOrqEOuYY6i2uoL7iG+TpHQP05OIcG5BzqLM6hDrxSFuYcAcrg4CkakKdosHiKxoKnmLNztKgAg4N3aEDeocHiHRqAd5ircwQogIN3aEDeocHiHRoL3qEI5wjQAgcX0YBcRIPFRTSSXUQhzhGgDw7OogE5iwaLs2gsOIv5OUfWYt157F2GHEODxTE0gO3L+TlHQO05uIYGuGOZacvygmuYp3ME1J6Da2hArqHB4hoaC65hvs4RUH8OzqEBOYcGi3NoAK+UhTlHgDI4eIom5CkaLJ6iseAp5uwcAQrg4B2akHdosniHJuAd5uocLSrA5OAdmpB3aLJ4h+aCdyjCOQK0wMFFNCEX0WRxEc1kF1GIcwTog4OzaELOosniLJoLzmJ+zpG9WHcOjqEJOYYmi2NoAtuZ83OOgNpzcA1NyDU0WVxDc8E1zNM5AmrPI5YN5BqaLK6hueAa5uscAfXn4ByaYDwbpoA2wCtlYc4RoAwOnqIJeYomi6doLniKOTtHgAI4eIcW5B2aLN6hCXiHuTpHgAI4eIcW5B1aLN6hteAdinCOFrVgcXARLchFtFhcRCvZRRTiHAH64OAsWpCzaLE4i9aCs5hjkMfF6JYWB8/QgjxDi8UztID9zDlGegSqz8E5tCDn0GJxDq0F5zDXcI9A9Tl4hxbkHVos3qG14B3mHPMRUAAHB9GCHESLxUG0gNfK4gI/AtrgEf0QchctFnfRAgIg5hv9EdAABx/RAmMgMgVBBHzEfENAAhrg4CTakJNosTiJVnIQxDzjQAJq4OAq2pCraLO4inayqyjESQIUYnPwGm3Ia7RZvEZbZChsIBImBxfRhlxEm8VFtMXGwwaqz8FJtCEn0WZxEm2xQbGB6nNwEm3ISbRZnERbdGRsQAEc3EQbchNtFjfRlhoeG9AGB5/RhnxGm8VntIXHyAY0wMFPtCE/0WbxE23hgbIBDfAIlQ35iTaLn2jLiZYNqIFLvGwwYDZTxGzOIbNTu0mARngEzVbgqNlsYbMFxs2eObzKr7VXfnYFgKGzFabY2YrQ4NmgCniEz1bA+NkKUwBtRWgEbVAFPGJoK2AQbYUpirYiOIw2qAQegbQVMJK2whRKW5EZSxvUCI9o2goYTlthiqetiA6oDWqBR0htBYyprTAF1VZER9UGtcAjrrYCBtZWmCJrK1JCa4Oq4BFcWwGjaytM4bUVyfG1QaXw8C3Bw1g8VTEoRWCQ7Zkj+UIFcDl/BXQl2U5gWTyCJVdPClABl2NYEs5hYTuIRWi4bVAFPJxJ+DAWttNYFo9jydmTgpTAw52Ez2RhO5Rl8VQWkZ4UpBEeviV8SgvbMS2L57Tk7UlBWuDhT8LHs7CdzwId0JKvJwVpgYc/CZ/RwnZIy+IpLUI8KUgVPJxK+LQWtuNalpzXIsaTgpSyxL3cG9DqeXfjGon9nPHY3iNSC7/wb3rR9+NBnwg/vbX7wu1evRqTJE33oju53t0OfqAqGgwb/Qv3G3JzelGbjAfXzrjb8VQXptjdjsnNUreMB/Oudd0yHr671nXLeLzuWtct4wG6a123jAfkrnXdMp55u9Z1y3ik7VrXLeOJtWtdt6xn0a535TKfLbve1ct8fOx6Vy/z+bDrXb3MB8Cud/Uyn++63tXLfGLrelcv83ms6129zKetrnf1Mh+jutbVy34q6npXL/PBp+tdvcwnm6539TIfXbre1ct8Mul6Vy/zWaPrXb3MJ4mud/UynxO63tXLfACoxOr57y8Wqhf7OeNrhO1YVizFZVzZT1tcxsX2tMVlXP9OW1zGJem0xWVcJU5bXMaF27TFZVxLTVtcxuXNtMVlXXFMXV7mRcDUJWZel0tdYualstQlZl69Sl1i5gWl1CVmXuNJXWLmZZfUJWZeCUldYubFidSWPvN6QeoSM0/hU5eYeVadusTME93UJWaee6YuMfN0MHWJmWdoqUvMPGlKXWLmeUzqEiHMwSyYg++IOSqEOZgFc/AdMUeFMEdlwRz1jpiT/SD61CVmPvo9dYmZz1dPXWLmA81Tl5j5BPHUJWY+rTt1iZnPw05dYuZTqFPP+TOf/Jy6xMynLacuMfP5xqlLzHyIcOoSM5/am7rEzMfkpi4x85G0qUvMfOhr6hIzH7WausTMx5umXvjLfKRo6hIzH+KZusTMJ2WmLjHz0ZSpS8x8FmTqEjOfu5i6xMwnG6YuMfN5gqlLzHyGX+oSM5+bl3r1P/NJdalLzHwcXOoSM5+/lrrEzAeepS4x8+FiqUvMfHxX6hIzH5qVusTMB1WlLjHz4VCpS8x8HFPqV4CZzzxKXWLmQ4ZSl5j5VJ/UJWY+QSd1iZnPqEldYuaTYVKXmPk0ltQlZj4BJXWJmc8cSV1i5oM9UvMAMp+kkbrEzEdXpC4x8zERqUvMfBBD6hIzn36QusTMBw6kLjFzjP/UJWYOqp+6xMyB61OXmDlQfGoyUObA7KlLzBwDPXWJmYOMpy4xc2Tv1CVmDqadusTM8atTl5g5YHTqEjMHZU5dYuYgyKlLzBx0OD0jMHN83/RFcgigm75QDkFr0xfKIUxs+kI5BGZNXyiHQKjpC+UQazR9oRxCe6YvlEMkzfSFcohZmZ4xzCEmZPpCOcRhTF8oh8iH6QvlEGswfaEcYvulL5RD+Lz0hXKIVpe+UA7B4dIXyiEM22yhLffGGTrjwXDU6F8O4uXO3rnTXqVnw8HkhuTz5NPd7ej77oHb6V47Pfq9ursdu9rdni2T/FBrvfjy6IAUS74HZfl/nOsn773/4MGDX6mNbtz+udt5VfXSVmniavQYDRo3HPR67vA7JPHD9uDrvjv86bYX8u0LZ+iFhZum+XH/xlF3NJ7+OE3dnU39S+3T4eCy23MTcvuFdqvj9sljg9Z4cnE7d/cn2+fO1eJDPxH8PCtDmLg7Ly/5GXvFx+WNfpzN5GemN+YKfTf276fnFfpiMHz9cjB4/TZR4KegthPq/3Zi8wDCrc69u5i7Cj6wvFXocwh8bllr0af+HPgU2Io0+a8uSb5Y92WZAzWH9Qr0hmS9JvQS+sDW8geAytL/P3iLfpj0w6IfNv3YoR+/Tj926cdn9OMJ/fgN+vHn6UeNfLz3Afn4+flizyikNJ2+c+WXEozfD9qjV647bjo3K7rrL8zfbNHnglxvZuXep1J8m3xU5h+qdTruaPTUdcaTIX1OJYm+V+uMu2+csdvqXk96zrg76H9Yu7iYvSIKI8lvuv2r4Oq3Jk6vO779ln81+g75Gzbv6HvRplJy6/kNgVr3uz6m1vtvusNB/9rtjz/0fzmb9GlDfOxfTQv9sf3Bza3fRANagHdNv5wPvF8/OnB77tgNVfRx/ZubwXA8ff7jxvXsD4/8H2gW3294uB4OEq8PfOT/Rm57l9+NLsMRESQIL79PpOhe3s7k8RP+b1Nd+Q9Gv8Yvw3y+2xy8cWdy+T79ZS6P7wS/TS/C53/s1JmMYnr7+Mzt9ruxen//zL2eL+Lj4Lf4U9czpU5/CBr6UfTD6KPoq1+D6DKSyf8l6g8fRdfe7Q9Jm8d6V+sVtcJXTr/7I3f4Eb2a3vyoNR7cTC9/5ouu+7XXXeM9iQ7679I7ZBxfdq8mQy/t+/SXowHpOfRL0M1o0u/R62me9KeP6U+ebMEI9dKE8vuD5vvxnwItvZv+38/ND0nPmfCLoCO4vF/eL++X98v75f273Kf/v/W//umf/umfkP/foRf/S3Dh3fmf4xf/U/zif4xf/A/xiz+O5/bfxy/+afziv4tf/Lfxi/8mfvFfx7P+r+IX/2X84r+IX/zn8Yv/LH7xn8Yv/pP4xX8cv/iP4hf/YfziP4hf/Pvxi38Sv/j34hd/FL/4x/HK/aP4xT+MJ/vD+MU/iF/8/fjF34tf/N34xd+JX/zt+MW/G7/4g7gEfyt+8fvxi78Zv/gb8Yt/J57bX4/f+bfjF38tfvFvxZ/5q/GLvxK7eJeuW/zxO63b0di9ru7TCVeHemCj6jOXTIW6nepB1/vBGd7+Dv7BD4KErfGQuFqfVq5HncGw1335aeULdzgiyT7Tqgr979PK/qRHJzSf9d3JeOj0Pq2cTl72up3P3dvzwWu3/9lL03T0jm4gW9VcxbJ/+OkP0krR6I9VnJMQ/lERfDP/IefsaDt/K8jn/f3B9Y0zdIfvHzqjVy3itz9458H7f/OtJToN/tZ/z59NhBn8Dsq1mX9Il9UefPD1A//ftz6kn3SK/DHtjj8zD6WN0L2nvfXDj7/1UZj8Xfr/AvI2ppMIb+79Hn3qne/ckj+f9wZXWt8dTyuBSRWQxlILw7Bd5eLiUnn5EjkOdt778QfAMkZcyfU3ZBbUJAaATF1qw6FzSxvrYduhXx+2O4NJf/xBuzMZHrlv3N67D979xfnM4hn84Ie0Mu9/L6gBKWjoVr0nbwPz8sGPyMev0C//PPl47yfIx+OFhYZWozpVz74zch+RZN9tnwy7V92+03va7bmnzvjVo3b9+qV7QRN82Kaf4Y2f8K7o9J70ioPukNR1MLz9qB3o8+TGmx6Gl37n+bE2nWiOyTf/9ofR9SmZ+X83ujocjMZ959p9RAs7cvtX41dvPXiL/iP1e+v9D7z1mb9IPv65g53frpOOe3VL10epiaV/6WD97cNbMs/+ba/av316Oxz0bkfdUfs3B3131NZN1P66O341mIyfkjlqvTPoD667nVH7aP/kyhkNet2+W335+ubBB7SQh/8C+dBXlkSURov47fA2Xcd6+C+SRx/V+reBGj74Ls3vX6JN0+gHCWkffhQMgAcfI5qA/v8v06vmFyfVlkv7kXtx1O2/fvivPACW754OhtcjcO3y4b9KRWdPX/Xm2PTMKPfhv0Ye/Y2ExTmS6Ny9viGdx92bdHsX7nB2Yba6PxkOSZd9+K+TTGp3zSS8O3r4b2SR5cC9dMiQ/hiHqv1L5OMnfY/sL3pJK9FKyAd/mbbNv0mb5IO/Qj/fpStwHwUQGLTiu97obTq/OxiSP90+/eMV/QHpwW+6NAlty/fJv7eDdv3T4N97dMky9cr2t9pjT7pgTfKdd38eQHIK9V4y5tcU0aLkX6UfFIrfo4upzOvobz2IlknfTV+oV569Uh3AgvSj9puwvfLSyF+LJKSLyndd+8+73f56JCVd9b7bm4a8ZfwbkYy7EHYtf6+Rt3C/HwlHXxawv0Xh0POfrNDGXL/nUOJvJI5t4F0Oh/L+fOLYTngdxKHMGuSKrXyjlHc3+4NIPvrmZ/mborc8gOv2iRy0xHeWiuLl/rep80td6HV08Knx+9aPQj+dOurvLrx6i3u3Xo3+Dv34u/Tj79GPv08//gH9+EP68Q/pxz+iH/+Yfvz/7J11QBRr+/5ZyQEDuxWxA6QFA1kapEHKWBdYQpeQBQH12N3did2B3d3H7u6uY7e/uZ6dB9mZJVzO1/f3x+F9vc7ecz1zf+6Z2ZjZ2Zl7PiQbsgCyELIIshiyBLIUsgyyHLICshKyCrIasgayFrIOsh6SA9kA2QjZBNkM2QLZCtkG2Q7ZAdkJ2QXZjd2Gy+x+vi72wdXsrOMQoGSiRI7HpFerERegO2U57rFrgoLdscnCJHb/1wA7+E7sitDbg1Xp5efuz+CRLnZaBKcSPVITYsienK8MJ2GS9QFkk7E7veyWlkkTDYKSM1xw7FGS7mKyExSlZZkp0qQYWQz53kphFJKcwk4md50t5Z4cna5gDwbIjzqMuYh1PdkZ5DJtLX0wKtEDcn9zlsweE3A0A7o/xOxlBeuH2QfZzwq2lwn7D5tHF3tfbdTvszqzhxxYLu411pS8ln24Zfq1qKCUZT+eU2SpaVkYH5YQwx6x5J0Syu6mReGFwO6niTD+Dp6euiMKeM/Ks6P56wVGDkVUjuR0tOoVnoA7iCOr44CWcr9UB7thBb7csXoNfZKlMe5SHG0JDveNMdKFfZNjl7RHQkye438d9iWq0CPPM/aAQ1tbS1fXyEAdy4vmqqfOFOR/HmjfFsc0hob1sSgHIYfwYscOFJYHA0qJMGANq8xhDDiCAWPzDNAiGfCKYI5CjmHAePUDjkNOYMBE9QP+hpzEgMnqB5yCnMaAqXkG6JIBWMPMGchZPB3wRlTo25WeRIYpBpJE5TQdUVXVl3tyHHtIHUdmyz1EPwfBmhPhfY684V3InTSDTrqE9JdZaWjm+Oto3SRaKo/mHitMotkNhjPtMSbm5uaimXTWK5j16u/MOovOei23kNl00o3cSXPopFu5k+bSSXdyJ82jk+7lTppPJz3InZRNJz1CsY9ZaWli0qRJExOTMGlqErvOGikam2TIUmUmCQpFOltmTDo+oky8klLS00xCUqVJCm6x2JlEC2i2J8j2tJjZFtJsz5DtOSutuWwu8bLobiZp8TKToPQkE2WDZZMgmYL9bFSYxCanmrBvejIT/KgsNfFXvkU03wvke1nsfItpvle5q3MJnfRP7qSldNLb3EnL6KT3uZOW00kfUdsnVmxNVP9IocHpiYnS1CyT5FiTPM8ot9TU5FQFGSJaQRN9RqIvmidaSRN9zS1yFZ30PXfSajrpJ3DYw6huIvwLiM9SJLDPe9EaOlzEjtQrUdjwtXS4NobriMgWEw7nPlRyJyjfN3Oj3OUTraP5dJFPr9j51tN8+shnwIq9iUmILDUR39/lrk38WfAYgliUQ3PhB0p6hsXKtYHmMkKukspcbOXsuyT7PP6dXJaijTQXPkP0Shcr1yaaqwxyGdNc3N/v5LITbaa5yiJXuWLl2kJzlUeuCiq5uHeuIuWytLQRbaW5KiJXpWLl2kZzVRbRF9x2Oqlq7qQddFJ1EGuwUsXMkRxsSPFVrkkq90aGT5iddGxNjK1V4NhddGztXNRuOqkOnaSDXcl8djjxnaq+JCo9NlaWqi9JJt9rM5KUZEUCXj367A42vldmJNHSFGk0uyNoJFHu+WJHi5FkpCaQXS5DTE1WkL0vSYLCn90VqOkrTVXES+XOWUGyWOWpoaYSCbs7lJSGH9xpcX8lSmCHF19aM3VFWrl/e5tpaVk4aZGvsw3LYA8YpgHegsvs58YY6GOfkBhkx1Dw7b1wh5LsVNTDeqkPaQBpCGkEacyKMXbOcMbEwKAU0ZJEjYgaEmWIGhDVJ6pHVJeoDlFtomTv1YBUTk7hGB/ikjNNwGsKaQYxg5hDmkMsIJYQK4g1xAZiC7GDtECt2E/8SLL/IPqd6DeiX4l+IfqZ6CeiyvEfiL4n+o7oW6JviP5D9DXRV0RfEn1B9DnRZ0SfEn1C9DHRR0QfEn1A9D7Re0TvEr1D9DbRW0RvEr1B9DrRa0SvEr1C9DLRS0QvEr1A9DzRc0TPEj1D9DTRU0RPEv2b6Amix4keI3qU6BGih4keInqQ6AGi+4nuI7qX6B6iu4nuIrqT6A6i24luI7qV6Baim4luIrqR6AaiOUTXE11HdC3RNURXE11FdCXRFUSXE11GdCnRJUQXE11EdCHRBUSzic4nOo/oXKJziM4mOovoTKIziE4nOo3oVKJTiE4mOonoRKITiI4nOo7oWKJjiI4mOoroSKIjiPYn2o9oX6J9iP5FtDfRXkR7Es0imkk0g2gPoulE04gqiKYS7U40hWgy0SSiiUTlRLsR7Uo0gWg80TiisURlRGOIRhONIiol2oWohGhnop2IdiTagWgk0Qii4UTDiIYSbU80hGgw0SCigUQDiPoT9SPqS9SHaDui3kS9iHoS9SDqTtSNqCtRF6LORMVEnYi2JepItA3R1kRbEW1J1IGoPdEWRO2I2hK1IWpN1IqoJVELos2JmhM1I9qMaFOiTYg2JtqIaEOiDYjWJ1qPaF2ipkTrEDUhWptoLaI1idYgWp1oNaJViVYhWploJaIViVYgWp5oOaJliRoTLUP0/+wTAm9CeItm7PEu7wBpCWkFaQ1pA3GEtIU4QcQQZ4gLxBXiBnGHeEA8IV4Qb0g7iA/EF+IH8YcEQAIhQZBgSAikPSQUEgYJh0RAIiEdIB0hnSCdIRJIF4gUEgWJhsRAZJBYSBwkHpIA6QrpBpFDEiFJkGQIvvplukPwTTijgKRB0iE9IBmQTEgWpCekF6Q35C9IH0hfSD9If8gAyEDIIMhgyBDIUMgwyHDICMhIyCjIaMgYyFjIOMh4yATIRMgkyGTIFMhUyDTIdMgMyEzILMhsyBzIXMg8yHxINmQBZCFkEWQxZAlkKWQZZDlkBWQlZBVkNYR8t7QWsg6yHpID2QDZCNkE2QzZAtkK2QbZDtkB2QnZBdkN2QPZC9kH2Q85ADkIOQQ5DDkCOQo5BjkOOQH5G3IScgpyGnIGchZyDnIecgFyEXIJchlyBXIVcg1yHXIDchNyC3IbcgdyF3IPch/yAPIQ8gjyGPIE8hTyDPIc8gLyEvIK8hryD+QN5C3kHeQ95APkI+QT5DPkC+Qr5BvkO+QH5CcEX3Qx+G6VKQHRhuhAdCF6EH0I3ioY/KaDMYQYQUpCSkFKQ8pAjCFlIeUg5SEVIBUhlSCVIVUgVSHVINUhNSA1IbUgtSEmkDoQU0hdSD1IfUgDSENII0hjSBNIU0gziBnEnBVj7GaRN7lj9MFx+uAEffA3fXCSPjhFH5ymD7B7hzdRpjlSW0AsIVaAnKWmNSbZQGwhdqzoYicx/68d8RZuiAmyVJxL0CVnIPS57zANQ+LZ46UYGExIQiJ+/pGYUtInOZp8zYDvnQzaK5QzlnHLjJaRn+4oTxYZct9WJMgUeq7JidKEJAMv7jhIpCMSabH/2P/n81OlUvx6fwFh16Fu+7QEufkv0K9f/2EU/um1YNdAKXFwnt97kV8+KX9t0xLrKDQ4RCzxZesbdGuzwf35N4YxrdjJeq2xXj0j3Lz8zNwC3HyUP+UhszGO8Nuy0sqlJX7Tg8tATfB7JEXH3KMx5aO832HRy51MQvFbso7K41bszJPve1Hnr8oYVJZbjxt47vnX44l525bg5hVdEuTU8y1R9C97CVuht0XJ9gc7IH92kCr7inB5wFbNGYGckfnn7Kia81oB6yg3ZzRyxuSfM1Y1542i5ExEzqT8c6ao5rxVlJwZyJmZf86eqjnvFCVnf+QckH/OQao57xWQs6sZl3Mkco7KP+cY1ZwPipJzMnJOyT/nNNWcj4TP49klivXNvWo5c1HOvPzLyVYt54lwEWeX4C/iMuRcnn/Olao5nwkXcV2JYn79r1pQDgrakH9Bm1QLeiFcyHV0IWNCuJw7kXNX/jn3qOZ8VcBzIzfnYeQ8kn/OY6o5/ylKzjPIeTb/nOdVc74tSs5ryHk9/5w3VXO+L0rOB8j5MP+cj1VzfhQ+aV6U0PR0imolr1DJ6/wreaNayWfh0r2gz5bgXlzOz8j5Jf+c31Rzfi1gjeXm1NbGaRftfHPqaavk/F6UnKWQs3T+OY1Vc/4UboWK2gWfNlLlVQavSv68aqo8dpeJvwzgqeasg5ym+eesp5pTW5BTr7F2Mc89kYI8s7mCmqKgZvkXZK5akK5wIRvThczNaYucdvnntFfNqS9cyDbaxTiJpVpMWxTjlH8xzqrFMMIFbCNYQC/k9M4/p49qTiPhAgZqF+NsmGoxwSgmJP9iQlWLKSVcwEDBAuKKFL3O+efsopqzjHABZdrFOK1GinE8yhUTh2Li8y+mq2oxZYULKKMLmJuzO3Km5p8zTTVneeECZmkX4/ycajG9UEzv/Ivpo1pMReECZtEFtLrG5RyMnEPyzzlMNWdlYc7cN+Bq7mJDknMsco7LP+cE1ZxVC8hpnMjlnI6cM/LPOUs1Z3XhhpivXcCpSFXYAsAW5g9brAqrKVyA+dr8BViFnKvzz7lWNWftoqyUzci5Jf+c21Rz1ilKzr3IuS//nAdUcpbBaU+c6izxavvu1uFpqdJgWWqCVI7bSJj04H5aamppbmFqIk1JkScoD//bmOI+DqaOpQxNTFqn0A8kXA3UxrSu8qd+3M/eTE2aqx2l/HmiwpQ9WOgmy2pjmpaaLjM16YHfvpGeVGQm4Wxe7CedJWZKSpfL6Vx5U3DzCecMTk5Nw0+LTR1d0hVpyYmtm9MB+c6i/PmhjPys0tTRouhzmDqiliKMJz95NHW0QsfLQgfjux1TRzxWrjzBLMIJatae1Z9ae9yyod1EERctRqaITk0g31wVZwmt/zfPD8v/u+dHi6I895TrkLyCirP2bP43a8/q/27t4RbyRVx76UkJaYrirD3b/83aK8oSarj2bIu+9hTka5HirD67P/zmRO6BWNSl+3UhbjGWsMUfXkKborwtKRcwDtcSFGfZ7DVaNlpo0T8n2ImJKWnFqdThT2+Fory9KRdOnpwhSy3OsuF+uf+/PsXSU1KKuXB/bOePWzh0Wy7iwqVlpRTrk9fyj+2aKeuNTpZ7uWpY6h/bx8otFbcz0LDYP7ZLk1ssuU5QoWG5f2wfIrdcH/KeI5cmpmhY8h/73M4tuT15JylGyX/sgzi3ZJfkpBjuPpAa1qzZB2xxayYXpGlY8R/7oP310pNJY/yT5BquYqs/9uH568WXkNQNq5n84l3Dqv/Yp2Ju1c5SRYKGb3BWf/5zTnkBQAj7Aa1hyX/+805ZMkINS/4fHcjb/B8ciuauFHrLhWKslv/REbrt/+Vq8XIV7oIXbW38sQ9u1bVRlJ3qYqwN4dFW0dbGn98n8HIVfr1StFr//L6Al6vwtV20Wv/8XoCXq/AFV7Qvj//8DoCXq/DlULRa//zHvo80SibXsNo/9rGv+l5TlG/4NH6vwT0upAlJslQN18n/6FxFUb5rK/46kWi+w2X954/ZuTvQaVjvnz9oz3PbGQ1r/vNH7enJiZJkcoJPw2MH6//BYbs0SeKWlMY+nb1iNCz6f3DcHp8gj5GQGwdpWPOf/8x2TUiUJSk0Pgi2+fOf3O2TEtIkQckZGhb85z++f701u0jTZHHJqRp+TWLz5w/hyRcOEv/ivHnY/Pmj+Nw3Dw0r/vMfg55ShYS8e6TKNH0h/vnPQi+FXCaN1bDcP/8xqHx39oop8vOZH/ISK5v5uCfI2Sea8povU8cOKt8rdjJpY9LQWRrT8DcyuSXhq5YYtTuA/Pm45SC/Cit8bfLnVp41Q78r7qxbrFSuECALrsA3qL2ybIWpYx/8jq0u7kNnZyMWu4nFYtfm+BMHiumfrziOVfc0t8jwSHeZp3NWZLhfTx95vEV0ortndKK8m09ShLVPV1+Fl3ukPDrJLyXKysbBL8ump0/X6HRfl4y4QOtQRYxnaFZkiGV6ZHgo5lP4uDgHxoR5K6Rhfj6R4fL2UVZp8qiuFrYRXd2sfcN8bSMTA638PILifcMCM50DUZfYKsgj1CooPD4jOjG0Z3SWbUSMp3d8kLV3SqSLbZg0LNSaneYSEe4n9+lmGRwaGpkSGR7jIQ3LtIgM93aNsspURIb5WUjDHNLJsjn7qUwLTHTvGRmcppCG+1mIMzNDZOx/I8Ms0gOtHBRRHqFdYzzkPaKSfNMDw72zIsLlvmQc1ou4myvUmV1N7F90e2t5zxiP0DSfbn49ojwy5RHWQez6sO3p0809i11u2xAP1leO9Qi3krMMy57OoQ49peEpchd3Byu21p6ox5mt0UUc5+1MNoEXJAriptwwZIW4BLbHf7ydSR0WLq7iaFQSzltPbhHhQfH/99uI1JJS5G0kz7t9vFzICvGI9GfXFbaLZVSYbe62Y59j+G9KRFD+24xd/93VLne3yJQozyA5myM9Msv2V672Dhnsf+NjPByynDOw2n5nmyd7k4LFbh5k2wdy05SbhmwscQZ5brQjjwOVLyMMdfn12NslI3dTuiofJefZtsT0E2eKfZTPL5LPjwwO9PV1RR3O8YW9Jt1JYle//McptwP7/PSOj7Zqnx6aKJfHWLDPXc/QtCi67rqx6y7RniyyM50WF8ltJxs3cXBm/vm7cbmwHtn1GhNmmR6UKFewr5Gs4DDbxKgMG6T1Vy6zPXkakBXg7NyVze8rDbNNZedLj/SQc69di9wV6BJERnoTFbcPgPq4BcljuoXaRHt6y6OtfdPDPIOyItrHZEnDAnP57HOD/xzzjkqM7KHcjkHtZeHOcme3tJSoxECfIPb1Gu2RGS8LDZLLPAN9ae3trYPYnLZJzqGR8ezyyckmCvRin8g2vzYXyRcRonwbjSAvEHfLNMEyhQeLHbxcYlwiwgKTXOLcgsgm+/XccFYuq/I9w51s95go9n0kXYrtlBiUQp6ncou4gGBxEvua6Oadkeyj8hHQurnqr5Vxz5D//v77++/vv7///v77++/vv7///v77++/vv7///v77++/vv7///v77++/v3/nTxY3Mi3DTc9wNUVeCkzRovkJa/+hKcK2UvkSRnJ4aLRPp6Ojk19UtT548bYPqqB/NDcSvjjCqboGjggkb4/BP77C2llYtnKAzI5c7mJFLSxRmOMOvMFPe74s5gk5RLb79/Fk4n101WvrkWmyJRCu3waSuHTtzUcoSzo4pItw1Hmtd7zhu75CnWlImc4KdKrJmEagRPJEV+wBMMncDOvcpdlxl/tx0IU8jSfO8SczzJmlIk5xjx9XIJ4kZLtZiziNT07yZmuTN1IhmuoTVSpIw6MUlaph3lgZ5Z2lMZ7nGjjPKu+jXMWPdvDOa5plRF/e7V9/hNJ/GkE1VpoelSnG5kbKlKOk+V1bZjI5c56X8pb6RJDp37lJKF4Cg5Az26a1VhQ+n96DEtq3IN0laOL/dhFTZrArLzNzGfT5we2zcJlrUlJ1G7vpPvHvUw82jRc1UvIfUw/1IRWYq3hPqGZInhor3nHq4/bSouYr3inq4y7TIQsV7Qz3cqlpkqeK9p54eeTareJ+oh9tai6xVvK/UwyYT2ah4P6hHmq7bqngiHc4jLzk7FU+HeuSp2ELF06ceeZXj3tnq24vR6xfyPKFKB+BGKQp6vxTa3VCSEKOnbDDILoOOwW+3XzUQFIBm0uw/F2l0vCxvi2767sLgtupo5MAYsnWJcO9vLEiuRTr6lITVkm+h5QNTGlYrvkVaAxnDas230ByCKQerDd/C7eyYCrAc+RbaSDCVYLXlW+TG5VVgOfEtNJxgqsES8y3SYakGLGe+hdYUTC1YLnyLtGoygeXKt9DEgjGF5ca3SM+nerDc+RbaXTANYHnwLdI8qhEsT76FxhhME1hefAs3kGSawfLmW2ihwZjDase3cB9MxgKWD99Csw3GCpYv38IdORkbWH58C205GDtY/nwLtxVl7GEF8C008GBawgrkW6QzWWtYQXwLrT4YR1jBfIu0OHOCFcK37uKBM6z2fOsOHrjCCuVbt/HAHVYY3yJN1zxhhfMtNBphvGFF8C3Svc0HViTfQksSxg9WB75F2sAFwOrIt9C8hAmC1Ylv4ebATAisznwLbU6YUFgSvoXbGTPhsLrwLTREYSJhSfkW6ZjXEVYU30LrFKYzrGi+RW5z1QVWDN/CLbaZKFgyvoVbczMxsGL5Fm7fzcTCiuNbpNdgPKx4voXbgDNdYSXwLdLCUA6rK9/C7cQZdCAXdeNbpDNiCiw538JtyRl8JogS+RZpuJgGK4lvoWMD0wNWMt8ifRwzYaXwLTSYYXrC6s63SHvI3rBS+RZa0TB9YCn4FvrTMP1gpfGtfXgwAFY639qLB4Ng9eBbe/BgCKwMvkXakg6Dlcm3SFvXEbCy+BZp+zoKVk++RdrCjoHVi2+RtrHjYPXmW6St7ARYf/Et0nZ2Eqw+fIu0pZ0Cqy/fIm1rp8Hqx7dIW9sZsPrzLdL2dhasAXyLtMWdA2sg3yJtc+fBGsS3SFvdbFiD+RY6AzELYQ3hW6Qt72JYQ/kWadu7FNYwvkXa+i6HNZxvkba/K2GN4FukLfBqWCP5FmkbvBbWKL5F2gqvhzWab5G2wxtgjeFbpC3xJlhj+RZpW7wF1ji+Rdoab4M1nm+Rtsc7YE3gW6Qt8i5YE/kWaZu8B9YkvpWNB/tgTeZb8/HgAKwpfGseHhyCNZVvkbbNR2BN41ukrfMxWNP5Fmn7fALWDL5F2kKfhDWTb5G20adhzeJbpK30WViz+RZpO30e1hy+RXrPXYQ1l2+hdxRzGdY8voWGUsxVWPP5FukLfh1WNt9C6ynmJqwFfIs0rb8NayHfQpMq5i6sRXwLnauY+7AW8y20s2IewlrCt9DjinkMaynfQuMr5imsZXwL3bCY57CW8y20yGJewlrBt9A3i3kNayXfQjMt5g2sVXyrPx68g7Wab/XDgw+w1vAt9OJiPsFay7fQoIv5Amsd30LXLuYbrPV8C628mB+wcvgWuZkmDiVFG/gWmn4xJWBt5FtZeKADaxPfQnswRg/WZr6FnmEMujGJtvAtNBJjDGFt5VvoLsaUhLWNb6HlGFMa1na+hT5kjDGsHXwLzcmYcrB28i10LGMqwNrFt9DGjKkEazffQm8zpgqsPXwLDc+YarD28i10QWNqwNrHt9AajakFaz/fQr80xgTWAb6FJmqMKayDfAud1Zh6sA7xLbRbYxrAOsy30IONaQTrCN9CYzamCayjfAvd2phmsI7xrRg8MId1nG+hrxtjAesE34rCAytYf/MtKR7YwDrJt7rggR2sU3wLveIYe1in+RYayDEtYZ3hW+gqx7SGdZZvodUc4wjrHN9C/znGCdZ5voWmdIwzrAt8KwIPXGFd5FtoX8e4w7rEt9DTjvGEdZlvodEd4w3rCt9C9zvGB9ZVvoWWeIwfrGt8C33ymABY1/kWmucxQbBu8C101GNCYN3kW2izx4TCusW30HuPCYd1m2+hIR8TCesO30KXPqYjrLt8C637mM6w7vEt9PNjusC6z7fQ5I+JgvWAb6HzHxMD6yHfQjtAJhbWI76FHoFMPKzHfAuNA5musJ7wLXQTZOSwnvItVzxIgvWMb6HvIJMC6znfcsaDVFgv+JYYD9JgveRbTnjQA9YrvoVehkwmrNd8Cz9WZnrC+odvoesh0xvWG76FVohMH1hv+Rb6IzL9YL3jW2iayAyA9Z5v4R8zCNYHvoX2iswQWB/5FvmSdxisT3wLjRiZEbA+8y10Z2RGwfrCt9CykRkD6yvfQh9HZhysb3wLzR2ZCbC+8y10fGQmwfrBt9AGkpkC6yffQm9IZhosfCmqYqFhJDMDlohvoYskMwtWCb6F1pLMHFjafAv9Jpl5sHT4FppQMtmwdPkWOlMyC2Hp8S20q2QWw9LnW+hhySyFZcC30NiSWQ6L4VvodsmshGXIt+rhwWpYRnwLfTGZtbBK8i1TPFgPqxTfqoMHG2CV5lsmeLAJVhm+hV6bzBZYxnwLDTiZbbDK8i105WR2wCrHt9Cqk9kFqzzfQv9OZg+sCnwLTT2ZfbAq8q2qeHAAViW+hfafzCFYlfkWeoIyR2BV4VtoFMocg1WVb6F7KHMCVjW+hZaizElY1fkW+owyp2HV4FtoPsqchVWTbymb9sCqxbfQppS5CKs230LvUuYyLBO+RbpSX4VVh2/h9BVzHZYp38LZK+YmrLp8CyevmNuw6vEtnLti7sKqz7dw6oq5D6sB38KZK+YhrIZ8CyeumMewGvEtnLdinsJqzLdw2op5DqsJ39LBg5ewmvItnLRiXsNqxrfIqb83sMz4FnnwDpY538If84G1dNHOsKq685SKeJkMfTLoyU/l2XxDSa6nIxIVeIIz96Sk3ieA3FN7BqQxeChC90TSRpG4X9hJOi7JijQGj0SWKuY3dpKxF66llpKLVINBZjBVZKUy8Ac7iXFNkCnc5VJFPINQF90YBWfE2iclJCeRc60uOG9GOhaSHwNIpKmp0iw9STTun6CjVVnt+dkOnX6dcP2pq1yjIjR8JJ0fseWVJxjpFJEed/rTjk4poadcNbpoc5h/n0U8h4wSJdHs0ihwwt0wURKboLwHWslEiTwhSeaXnhglS2WDRFlafHIMHZQul2P+UokSRZo0upt7KjtdgZb2Ip2aKrTgXBsXRHfohMNa/NPTZtmitgz+wxNDXfReLLz9I4qvxI2SZFpYWIsltE+ltp+rC6PcloqERN4gT/ZZgEG8ybRxpUEG9/QiiyMix+HoE8mQ9zO8B+npo8p49L0wk6XI5Mo+kww7sUZAVmqyPAu3E/BOTpIpJLZ29hJ2w5pnyhWZIrR4xPZQt9DKJRehyyOWnnFXITIgKntsACPyLzxTEM0UUGCmiMIzdaSZIgvMFF14pliaKabATImFZ0qhmZIKzJRReKaeNFNmgZn6F55pEM00oMBMIwvPNIZmGlVgpsmFZ5pGM00pMNPcwjNl00zzCsy0rPBMK2mm5QVmyik80yaaaUOBmXYWnmkPzbSrwEyHC890jGY6UmCmM4VnOk8znS0w07XCM92kma4XmOlB4Zke00wPC8z0qvBMb2im1wVm+lx4pm8005cCM6GdYCGZ0FGQZELXwfwzlSo8kzHNVLrATJULz1SNZqpSYKY6hWeqRzOZFpipaeGZzGmmZgVmsi08kz3NZFdgpraFZ3KmmZwKzORVeCYfmsm7wEzBhWcKpZlCCszUqfBMXWimzgVmiis8U1eaKb7ATN0Lz5RGM6UWmKlX4Zn60Ey9C8w0uPBMw2imIQVmGlt4pgk007gCM00vPNMsmmlGgZkWFJ5pMc20sMBMqwrPtJZmWl1gps2FZ9pGM20pMNPewjMdoJn2FZRJFz+VLvpvuvG9i7EkVp6QQlzlj4hLSuKlipCENLksKDlDXxIvk8bgl7XsRE/ykJ1KhpAfALNBeQS4548L+4/76W0ZTPPyd5bih5R0hqAQ5f2GGElSsn8sO1VRSpKWwB774Niyh1RuSCKS1kgiTUtLTYhKT5MpDCVSeoOikhL/1AS2cHKIZiTBjYvcSeNnQ4kPezgWnJYll5WSOCensmWGyRLi4tOMJCwzOZXcfrOMxAvl5I4sp4zzDjdWTvo1DyPx7yFLTU2IkRkpf1tM5mQfY/1wPKyhhKQ4ElVgDwVT42TipBgXGRaLrEdGksIujiw1SVFWokiPUrAzp2MJQqWpCuXxK/5EOlo69A+9brW1lcdYIgM9M/4W/XXcrDB3TkgCXvlraJ8ERVoJJDPhz0K2cJ7Vh1EWvgnRqcmK5Ng0c//Y2IRomTnZFskp5m6Z0TK5ebiyocav9YyZmhQ6U+4axnCzQofn3QCYo2mhc/zaPv9fFqT+SgP6RFLesotspL7KFsIqm5O02UyINseW7GLZoQM3RHl7sWYmiYro5FR5QlQzE+6Hy21szC3wv2YmLunytPRUWZskWXpaqlTezCQgPUqeEN1OlhWS3E2W1CaqRQupbbStnaWDtY3Mwt6hU6floiIUoHZhglWfxuRHzc0EzzlxDPvMzFMpKdTcsgi1Wkijo22to9kqY60s7GNiO5EvfbREetX1tbQq5GnkTeEK+jLK/VO+K9Zkx4t07376+bPQVwQyCC/+0L3DzvvbLxRhrkOvfv7Uvc3m+o2nqzDLWWS5xWb5vWexMNFFJLrJJvqdJ7cwzUc2jegGmwZLhuJE19kHKBAA0TX2ASAYpnv1U34X4ai+NISUX5szV0RMI3bLMo2xeXH9zRHypZ9ek/yeHvxnB5eqGeYXnWMrw1OEfJV4ln2AbY4NJjqTd9FO5120U3kWTXQy77C/8w47kXfYcfYB1oLa5WmB5bFHPad/LY/Dby5PK7I8B/Iuz/68y7Mvb6F78xa6J2+hu/MO25V32M68w3YUtDzuWB4P1HP+1/J4/ubL15ssz8a8y7Mh7/Lk5C10fd5C1+UtdG3eYWvyDludd9iqgpanPZYnFPVcpsujtPLZFOHkupoleUtfzJVOyliUt6aFeWtakLem7LzD5ucdNi/vsLkFlR6N0mNQ+vXc0vVkv7kp4simmJZ3eabm3RRT8hY6OW+hk/IWOjHvsAl5h43PO2xcQcuTiuVRsKKLi63UX8aFhTSQSGNiUmUKBXcCxUiSSi4cw2ORjk6B506Kf9kasuCfXhpbaRX+GZQ6YnvLll72LZQXMuGSJhGuDsMC6WWwM5TJPZNSx9+yZZiNchwuJxM9pON6suOMf40TI6GVciCuLRM9oQP/Ul+BnXVLrxYOyhlwwZnoOZ2hn/oZbOxaetlZKGfAVWiiV3SGgepnsLZp6WVjrZwBl6aJ3tAZhrAzlMQ5J7Zsh5ZeVnbKQbhGTfSeDhqOQeS0lcrC4WI10Sc6aBQ7qJIA7WvZsj230nD9mugrHT5WfaVWbH5rbtFwUZvoB51hQp5KbVt6WXKV4uo2ES5cI4Mms4Mqq1nDv8bjijeRDh0/TW3RWEhubeEiOJE+HT6THW5EanC2aelsya0HXAyni6vGinTRmZ7yFaFIYo9G2EOpaHL7XJw7Yo/D2NmjE6Ry7PMpcs82xqUnxOhIWMGVwtrCiyLz7jUq909/nX/CE9+yKFU1Dc6DxlyCi3y5uX69VWGUEbfn6sGWpzwXSH4BMRdvCl3Y943fZ6vsdpShL14Gp4tFndmM//z8+dNjm27iQ6fqzoMjfa2jfpZrdboxa+LaPGwEhvxWYSHeJjuw41HFrwwRXIaWNt8cGhi+cR52beeWkwOHLjiFDKVpBvILhGXIECrIEMJlqL7/xpKduo4+m5dvOBlb6q8uJ5HBmMugt4qd2TKE3Xtj34LImxK2jEyaqDC3trZz9XILNvdPT0tJTzMP9QkOcfUNN/f1CndzZVaDGShg+nPMKhOOh7bd/91znMgqu7xNkHNvMMtR5np2Zgv1TCu7YLG7emQOkD4CpDeHrJqxY4l+bwevNT6uJ7t8/OKVAWQFitycP9LSzkOcz1JuAdJDgHTjkGk3Pjo+8kzxXlmn66Myow9JXjdizUoUuaPIa9bfx90nl7kTTGcB04lj2g9Zu2KH0XCXxV5vHksf3HjyCswqlLm3qIupgtwHZBsBshWHNMvRnjf4mpnrym+j3aaMfLE6HshqFHmInbltURYzOCTIV9I+IMDc1d7OzMFCyTYP8Q8R+zCHUYG9oAI7roK2P5vYR29Y7zr8yeawGfZ2aZYNWLMGreA4O7NjERa6oAJOoABrQQGWXAETH86YLyqR4jnlcMOAAyX1pzdCAbVoAac1KcBStYAzKMBcUEAzrgBvg0k3K33Y7TVrrVXcUwOj1g1RgAkt4AI7s0MRXlC+4uBg9yCxC0cO8HTz8/exZC6C3Zhja+WyG9LtP8Xy9hGfWLeRnv4pu2tXPDGjPmuaUvbV4rCtmGtg1xOwTTl25JiW9fs99Wm3YmHcnpzBiROmg12Psm8Vh23N3Aa7toBdk2MPDbqUcEevmcecEc9sPRb+bTwN7AaUfV8ztkuEi62Z2JJ5AHY1AbsKx55ru91gwJVe3rvaV063trSdPBXsRpT9RGO2HdhPwa4oYJfn2DLDnakXNmd75pj7n+h7IP34FLCbUPbL4rCtmFdgGwvYpTm2T9lvss/7jnst+Rz/aXX5ba0ng92Mst8Wh23NvAPbSMBmOHaJLQ2bZQ3b5TTy7rKK2572Hj4JbHPK/sTObP/7bHGQL1b5Z6D1BGgdDi0+uvDmqoi1Tiu6H9qYk1Svx0SgLSj6ezHQVswPchwmQP/8qER3aTpzouOVZKc5M15IFp8vZTsBaCuKLmGgMdrZktFm5xZ9+8hHf+HQEVeGHL0+MsBp4tvdzeL2dK87HmgbitYvBtqKMQD6owD9nkNnN7i0rn+QrufuJtoLrrVf6TcOaDuKLsnO3KIon2n8J5qnOIgpBfIbAfk1Rz7qPUw26nPpdhPqP3g74/Xmefvr4aOPksuyM7fUgOzs5Y8pTDnAXwjgzzi4xaCLr1+dmOO+9PHn0ocbnZi/D/CWFF7JIN+XV4FwbpVXBvuxgP2QY1d+Xibu5dTuzhNHGI32VPjF7QW7NWVXLw7bkqkB9j0B+w7HNtj9KTZz3iHxks0W20cPeR+zB2xHyjYpBpt9gdUB+6aAfZ1jaw/teX3U0Raeu3c8e9tvzbGXu8F2ouz6xWFbMg3AviJgX+LYNUoYDv+78w3x/HKbL5TLmaK9C2xnym6i4ZONvp82Bfy8AH6Wgx87ErD585oVHusm/eM6ukRSv52Au1J482LBrRgLwE8J4H9z8E4fPD50/lneY4S08tIaD6tO2gG4O4XbFAtuydgCfkwAP8LBd4SVPH797Gm/XVUzY+5HbHi9HXBPCnfQHE52HVoCflAA38/BR43YWOvBhdpuy364iOrtl33YBrg3hTtqCKf7TG0B3yOA7+Lg43zmjtpx9pTvwKtHuix7+bn0VsB9KNylWHArxhXw7QL4Vg5+5Ot9yxePhzrtqhm6OyDsQ+IWwP0o3LNYcEvGC/BNAvgGDh52qfXLh726+UwxSmzpZDBv/2bAAyjcV0O4n5mnSzszZ8YP8HUC+BoO7rnIyjbFx7Ddwv5WnZ/rmLXYBHgQhQcVCy5mggFfKYAv5+BaT+432t7wtd+iz/KBrex1S24EPITCw9iZW2n6UmP5TDjoSwT0RRy9/tel0gqV7DyX9g5raNv6Sr8NoIdSekcN6W7hIUFmXn4hTCfQswX0eRy9sb24p+K5druxNRbWb/54W8cc0MMpXaoh3cfDx5fQo0CfLaDP5OgZoxuufZw003W9ffSpVrEbxOtBj6T0WHZmOw3onlbBTBzA0wTgKRzYfFrttlYXp7bbWKXrwKXaAZbrAO5Iwd00faW5+YWI/dwYOeATBfDxHHzOSrcFijnnnfsbG/U65nDwwlrAO1N4iobw4PY+7mIPP6Y74GME8FEcvNvRY5er/1XXa42vT0BY9wdd1wDehcLTi/UeE8z0AHy4AD6Ug58c4rWr/ffdntO0v09WWFy5shrwKArvqeGzLcDfJ8KM3Z9geoE+SEAfwNGXHrza743da/GaratktfdPr7UK9BhK76sh3U8c4BniKfZh+oHeV0D/i6MPPZbc9PL0NNfBvUx2XXUdc2Yl6LGUPkhDuqWVjRkqYAaD3lNAz+TorZffq/jDZJ/zBr2x4w5Na8CsAD2e0odruNm9/Fzd/NyCmRGApwvgCg7+Znpbg6Yr6/vvfHms2pqQ+7OXA96VwsdouAfJwsV+wcxYsFME7CSOfcPEItN5/DLfWYMisx5ccnJfBracsidquNpdvQLMXPx9A5hJoHcT0BM4+tnkqLe9shzcl8ifzfypCGm3FPQkSp+m6astIois9umAxwrgMRx8gW/JK/dvDHafULPHPL9OR/svATyFwmdr+mpjX+pivxBPZg7oUgFdwtH1Hp68HDIozGX1mWHPrsovTFsMeiqlZ+d/cFz44RKzAOiOAnQkh568YKCf8+45fnMe6Gnv379YfxHQaRS9pBhoMbMU6DABuj2HfqZrW7Zjx5mu64yXDe2VfO/iQqB7UPRKzfclWgT4tA9mVoEeJKAHcPTFB0eevKezwWlRYn3FMscQvQWgZ1L6Og3pzl4s38c/mFkPuq+A3o6jr7lxpPnKgdH+K23CNx070ntnNug9KX2Thi9zsh/lzGwG21PAdufYI96YpTnN2Om6+/Df53qvu9RhPti9KXt7cdhiZgfYLgK2mGP7bo1vEXOunkdO7SpLRIGybfPA7kPZezRn27LLvRdsRwG7NcdesvhEUMspy1w3JI4wKjWoY/pcsPtR9sHisMXMIbAdBOwW9M3N6l5lh47ObhtnzZvh+POswRywB1D2MU0/U8wCgtzZBT8OuI0AbsXBXQM6NHAcU9tnqlmziFRF6TezAR9E4aeKBRczpwFvLoCbcfAp0weta/p0qfPC9Zve1VJs2zoL8CEUfl7D15mvi1mAOEjszlwAvYmA3oijd5zr7nTytLtTTl/zs2v1pveaCfowSr+iIT2Y0q+CXl9Ar8vRj6+K9ms761q7iXc36rz5PL/hDNBHUPpNTekeOF5gN/st0E0E9Foc3Wzwk0qzchyd+x2cad7xdPSX6aCPovR7xaOLmfugVxfQq3L0uqdqPBwYv9Bzp/WA0y0PRoyZBvoYSn+s8dGSp/Jo6QnolQT0Chw9Oad2aJdvkz2W7k3Suuaw+8dU0MdR+gtNP1uCnP0I/SXoZQX0Mhy9qmvdKZOSNnoO3ru9gnjwxEZTQJ9A6W80pItdvFwJ/S3oJQV0Q/qKEz85blOvn+fKb5FG/ZrElZgM+iRK/6jh993BYj9X5hPI+gKyLke2Wxn35N3p3q7rfT2Tt1jvlkwCeQolf9PwGFUc7Ml8B7iEAKzFgScudbxa580uryl+VcudywgbOBHgaRQsYrS0bDTZ3EwJdk7R9w987NcPSuz7vrcbrCizpN2k9x/GVsiIc58A7AyK1dMQG8zoA/tJgP3AYWdNiVg7pVcb790lryTWNp45YzywsyjWiNHsgyxYuZdeEuy3AvY/HLvahXflmmw65zL4seXXHuvruI8Dew5lG2vI9lOyy4L9UsB+zrG/1rowwGd4pXYLPN68/RraqsdYsOdRdkVGw7cUL/Y9JYx9O60E+hMB/RFHn1M5/t3Sbld9lyQ/evtystbIMaBnU3q14tHFTHXQ7wvodzl6xxrTqqbUr+u2/oT5vTY7blmMBn0hpdfWnO5Dlt0E9FsC+g2OHtS84s3MDrs9h935kNWnzbOwUaAvpvR6xaOLmfqgXxXQL3P0qOdN0rTGm3ls+Bm4p9O6jpVHgr6U0hszmu2/4Gs/sUsI0wTwCwL4OQ6+adYDcWDHGa45b4d22Lrr2u4RgC+ncHNNX2ztsdmZ5mCfFrBPcuyPnlalHy666D9lf9MLU11PHRkO9krKttacza52xgbs4wL2UY59u+WLcqsedxYPqH39Xo/at2cOA3s1ZdtruMk92ou9xC7+PowD6IcE9AMcPfvzkrmhFUb5j5psM2Fou1oTh4K+ltLbaEgX+7j4e+K7N0fQ9wrouzm617fJlzp7nvGfbP131PO2xveHgL6e0p01fMK1cwvxx1cRLoDvEMC3cfCqN+aMuj2gnsuQy9nOcU3KGQ0GfAOFe2i86K5unhGubown6JsF9I0cPbhW6+Mvf9b2ntUtyK7PyKffB4G+idJ9GA2/D2B3XYIZX6DXC9BrObRTwu5yvmvLeW2ukh6cmtzBdCDQWyg6kNFs78HP34oJAniVALyCA889Jw7oZJzotdxw9+ip6VezBgC8jYJDNQQHs+AwgJcKwIs58NOK3+9vvtDea/KH/cPLmy+b1R/gHRTcQcNNbWnm3D7Ezc+N6Qj6AgF9Pkfv7dXtSNTZbM+JN0SVRfr+8f1A30XpXTR8lgcE+QcALgV8jgA+i4PvrnMtx7eczGfz7DKPPbdsWtQX8D0ULtPwrc0txBPsWLCnC9hTOXb6hp0rGj8e7rQofcaHCU3NO/cBex9ld9VwtfthteOURjfQJwnoEzj6/D06foEeh3yWh9k0bJspbvIX6AcoPbkYqx3wFMDHCuCjOfiAHoPOXfa+4Ls84tv4k95PtvUG/BCFp2m+2sFOB3uEgD2M7r5ZNui8W/7ddUW5mu9ONdN92QvsI5SdpeGC+3LwnoAPFsAHcvB1g1Neee8Z7bXm9bz+6w6+dewJ+DEK76Pha9yFfY33BbifANyHA4+cOXbZh86T3KeldPHdO7aFSRbAJyh4IDuzrUZgZhC4vQTcLI6bttRtwI9Gd13nrduwx2jxX98ywT1JucM05IqDmOHg9hBw0ziuIrjE1eZWKV7z+4ZP3NvBs3cGuKcpd7SGXD8rZgy43QXcZI47PvhIjeFrH3pMPHDU+qRp36o9wD1LuRM05LLbdyK4cgG3K8c9LJveLaxaa6e5BpPXt0zZWyEd3POUO1VDrqcVMw3cOAFXxnEjvzbJSXn9xGdgRkrM486lO6WBe5FyZ2n4QR0mDnELYmYDHSVAd+HQgyrN3i962s1pmpbNHcdnsc8UQF+m6PnszO1U0M7y5OhuCvMgMysrW+WlUtwUK88QM1+xl5+5VxKpxd/HTRLh5ebDnbvgfrKejWo6CarpwFUjevvUrNfwxk6TN5o3sTp8J2ehKQ4maDWL/61qxFw1S1BNuKCaUK4ac3ml3t7PMny2DO77OavvmyoLUM11Ws0Kdmaf4laj/KadK2clygkWlBPIldPYxD785sWXngMj53Q5o2s5NBvl3KTlrP2XyrHNLWcdyvETlOPDlTP5coPvfp8M3TfMWTM79kzVCfNRzm1azkZ2Zt/ilsP9eImrZxPq8RLU48HVI017Vy7y4Gvx0OtlrjsrholnoZ67tJ5t/149Vlw921GPq6AeZ64ecfvqGUPMnJ1XzR5/8AbjUmIm6rlP69n9b2wu5Q84uXL2oJy2gnLacOXMdBswJOPcXr/17un6V7Lils9AOQ9pOQf+tXIsuXIOopyWgnLsuXIM2y6t1FYvxnlZ7yfudgmVV01HOY9pOUf/rXLEdO0cQzm2gnKs6ZciG+tMOdfsq9+09Yke/Rva9JiGcp7Sck7+a+XQtXMK5VgIyjHnyimV8iPgQYVFfkP63Ewv06+85VSU85yWc+7feC5zPwbl6jmPepoK6mnM1fP6zJZmXuIs56mVV5QcWPpMzhTU85LWc/nfq4duriuop4GgnnpcPVN09D7J/La6zLvfYfDlg/PeTUY9r2k9N/69euj2uol66gjqqU33SKOdYu91uSCeZzWvclSF0PGTUM8bWs/df6ke21/13EM9NQT1VOPqqVxJ71WJuJHe02sExV90WLZsIup5R+t59O+9F9J6HqOeyoJ6KtLP9R3vD3wZHuCxaYnJ9s3ZTT971WLND7Se5/9ePcFcPS9QTzlBPcZcPZtTPOOkd7c4bdsXf77160eDPVHPJ1rPP4Iv+3PrsbS04NAu/m7uluaW3FftHPYNsKUEWCMO2+L550ta20q5jBlQpvMsm07DDlZlzS8U++F3sH55sR+BNRBg9TisW2/XmUHnbdxXbDQ4sfTo11UHgP1GsV8Fx0sFYOkX7Bz4G8DaArCIA4+VVu4dc1DcbvqD9POWVypb7Qf4BwXjRtG/C6b7JiJDZHrPB397z1142CyzTuDJ0k6zzoiGJA0YemsfwLgjNAHrGvJ35AsAc18tc1w9cD8LuB85rkfLgw5V5CNcNty8eG7k6n2994JbgnINf3OBffKsaSOA3wnAbzhwxefJ1V1vpvrPXdohMm3Zmxd7ANah4DIagOmaNgb4lQD8ggO/XL9+wfL4ROdBGWV8Ax+e7rwbYD0KrmD4O68k8j06h60I7FMB9jGH3b/u64M24hD/uUZi8YgNV9/uAtaAYqv+JtYnF1sN2AcC7D0O+9Qya+2G+Lmuu8tM/T6rn6XLTmANKbbW76xm+u05B64N8G0B+CYH3uf7qU2r85/dZy1KCljk3PvKDoBLUnDd3wHTb485cD2ArwnAVziwQ0bntiH/xHmMzSx1uURsr07bAS5NwY1+55XEfWfOcRuDe1HAPc9xr9lnHDr3Wu61brNiys3BjrJt4BpTrtnvLbDyTAEHNgf4jAB8igPPCKp5qL/bTafFPd1O13rfYO1WgMtRsBU7s3WRwfimnKNag3pCQD3GUbs823Kt7uRpPguqf9l6ZGvi3i2gVqDUFuzMdVW/AZClpSUkxSnMcc88iQy3M5CmyRh7UA6/51+NfJCj3NKxm1113WX/pU8OR8+/fzT1dmXWrEQprQ2LeHm/ykXobYDcJ0Du4ZCNNh8Z2co31m/x9Ka+2xpUvnQLyCoUKWZnNlOLtGphpZ7nDN5OAW87x5ue7Ng3fPVsz1Gfw8PKPV9Q8yp41SjPPX8eu/XU8jzA2yLgbeJ4OTsky/av3uc67FFXaWRJJ4dg8GpQXrv8eba26nk+4OUIeOs4XquE1RUX7ooVD526o9syo0PWJyqxZi3KC2Bnbq6WZ2dlFa7yPdEvYiCIqwXElRxx6+O2S05t3+2+etyLBVfDg+a4gWhCie3zXUIbCxv1SxgK3jIBbwnHMzP2ta16r4HToAXfLKtYno3bVZE1TSkvMv81avFrC6rcDaIDeAsFvGyONy9Fy/Z5S4l4VcVOJbS/RLRsAV49ypOwM5ur5dn+esbwVmgXAOcKgLM5YHqtejYTT370HDLncQWt016T11bAsQ4Fxgje2op2rTQuYZUBPEPwJjONA3+vUNKl3NLJLhssK1ndHlnCtDHAjSg4wVCji7TpFaxdwZ4sYE/k2KObxD/bYx8lHneh3P5Rw/bIG4HdhLKTNGPTq6ySwR4nYI/h2DHTzpV2rW/isWJW15zO9w4faQh2M8pWFIctZtLAHilgD+fY96rMn+u47ZbrjrPVWreKmrilAdjmlJ1pmO+JkkIvjMc1VlmADxHAB9Hd0YD+DatsLe81fU47jwqPfavWB9yCwv/SDJ57iVUfwPsL4H05eIuov10efuzgmt3N6aDLfQfzeoBbUfgAzeC5V1gNBLy3AN6Tg7+5WefEgiatnDZ20T/GpJZ4VxdwGwofKthtKRIcF1gNAzdDwE3nuOJQRWDii02e246VMe7VeHmiKbh2lDtKs6cavb5qNNipAnYKx9a6V+FYlCzaafL6tsYGIyfE1AHbnrLHa8aml1dNADtRwO7GsXWnjTawjqjdblJKWYeAa0EWJmC3pOwpGi43d3XVVLDjBexYjr1zQelEo631nLfse9Sqw/7mE2uD3ZqyZ2r2RMu9uGoW4NECuJSDn/vbuu3k1mYeMw7d7hg+1+x6LcAdKXyeZvDca6vmA95ZAO/Iwa/Mad1kxskwnxybjEl9fV3v1ATcicIXaQbPvbRqMeARAngYB1/f++LPM5tfu446dnnigMUN02sA7kzhyzXb5PTKqhVghwjYQRw7+Gv2FlkdH49+c1xnme+6/6462K6UvcZQoztQcBdWrQXaX4D25dBJrZt277Vjvu/c5Dtl9XausaoGtDtFb9BsnedeV7URcG8B3JODDzjxbfqd+6s8x9U4tbTTD8mZqoB7UvhWDV9m3GVV28B2E7BdOHbXDlorrKxKuAxbel1L3+eBQRWwvSl7l4YvM3pV1W7AnQRwRw5+zLZnjG/Dn74r282b9mrkxn2VAfeh8P2G+f4OutBbjjAHQG4lIDtw5PgdHT8P/8vGfUK/BtvbtWy+vBLIfpR8RHOymDkKsp2AbMORDy0zTUjt3NNr5/c15Z9Vr9+zIsgBlPy3xrsOykuqTgJuKYA35+BjJ/98u3i8pfPCuCoT5EdOdawAeBCFn9UMnntF1TnAmwngTeiXDjOHdZz8bqLn5hq94hyqltUrD3gIhV/S7OXNXVB1GeiGAnR9Dm3rHuTt7vDaKafy8UG7Fw+oXg7oUIq+Xgy0mLkBtKkAbcKhPcsO8vQq881752b7EO1yS16VBTqcou9ojMblVHeBrilAV+fQdSdGxh/+Yui+uNfwsndHVxxjDHQkRT8sBlrMPAK6igBdiUObWIfsHf5phtv4dRu7Xqpx/ksZoDtS9DMNP0a4i6meg11ewC7LsSO6HDTcHmjvPXVa+ZJmtkampcHuTNmvi8MWM/+AXVrALsmxm2S1O7b4022PofOT9kdINi4uBXYXyn6v2Qss91KqD4AzArg+Bx/mUb7FqbZ1ncZLhvQxG689pCTgURT+RTN47pVUXwHXEcBLcPBF5lfKZt476tbvuF+/a8y1BUaAx1D4Tw3h9EIqdKYU/XzHh39/x+05rKniOCpos9PuQVsMm9qkhxgCHkvhOkbFgYsZXcC/COCfOLjX5tenV00z8R8QGWxW5ofhAAbweApnNIPnXkZlCPh7AfwtB7ed0fzZmeij7fqb3LZY+8bZ3gDwrhReWjN47lVUZQB/LYC/5OB/3TP4a2D1G65j5fM2DTx5U6IPuJzCy2sGz72IqgLgzwTwJxx8oE5zSd31nZ1Ge9+f5L4pZaAe4EkUXsVIoy9cyDVUVQF+KADf58D99n3qfMx1lP/WKF+zzQvbZegCnELBNY00OgrFJVS1wL0j4N7iuBdTlx+aVS3bZe29+Ue1W1WdpgNuKuWaGvG/wy7apmbqgnpdQL3KUZe2eN29y8geHsPL3Gx8MNV1rzaoaZTaUDNqMNMI1EsC6gWOOmrIA7u1Gc3dJ8nu17wxwbNOCVB7UGozI40+urjrp8yAPitAn+bQbzPOrO+7cofPrG2Bs4bWP64tAjqToi01Q3OXT1kB/bcAfZxDD55ar0lp18ru8726JlxatJVBC2JRT4q20/CdhF491QLwIwL4IQ7ebsS7ZzPLB3osunMtPmDYzh8/y+O7GApvVSy4mGkN+H4BfC8HX1viunTMu3HOs89sbt37WfbeH4D3oXAnjeHKa6fEgO8SwHdw8CrjfkyY2eqT88wMrY9pR2X1vwPej8LdigUXM+6AbxXAN3NwT6dGt5I+DPeYK72rlyp27vYN8AEU7m2k0d4KvXKqHdgbBOz1HHvYhxl7J22t0m6VSddBm25dNvwK9iDK9tfwVaa8cCoA6DUC9CoOPfPyoSqD9Ve754zYElvWoKLoC9BDKDpEYzSum2oP9HIBeimHNsxsm5RQZZHn9HCdQ/0v3dj2
A4: GehhFB2h2ebOvWwqEvBFAvgCDi5pcctWcWWB35TVsrFfbNM+fwJ8BIV31vAjk141JQF8ngA+h4NPM93lM6BTH/+laxL/epY+1vIj4KMoPFqz5xq9aCoG7JkC9nSO3fSu+f2H/0h9dnxuc7PyyBFzPoA9hrLjNV1w7pqpBMCnCOCTOLhH/XMuR0ZcES8NOKw3J+lFxHvAx1F4opFmh/vkkqkkkMcLyGM58oZP31xmeE/yzTHQYfo1yVn8DuQJlJyq2c4CrphSgDtKwB3BcSvtuT9+X1qY2xz9WFEpw6j+b8GdRLkZmnFxwVQmuEMF3MEct4HZ4H0H0hjXgfpptQ9/1b3+BtwplNtbs82ce73UX4APEMD7cfDux5pPUty/47kgOWrj/Cq7rP4BfBqF99fs+U0vlxoA9l8Cdi+Ondq/y9qgjC2uI0Mv3nYMOT/sNdgzKHuIZm9o3NVSQ4HOFKB7cGgf32o/O/1c6TXz5bivzk9ujn4F9CyKHqnZOs+9WGoU4AoBvDsH73UwI7xBQnenHY16jT++8KHNS8DnUPg4zdc52OPBThKw5Ry7tlPNmjVFMp/Rq59N/fjIf+sLsOdR9mSN1znQU4BOEKDjOLSiS+qHcU3fuK78fmHgmsEXWj4HOpuiZ2i22PRKqZlgxwjYURy7mnyzxVermy47y6c07z/n/rxnYC+k7LmavbZxodQ8cCUCbieO2/yvyK2RAXpegzq5ms26pffwKbiLKXehUb43UyiYyywCNlKADeewD6Y8/dF+hbfzlNJ9z9XaVeHmE2CXUuwyzbDiIGY5sO0F2GAOG+5h936HXj23bb3mRg8KeHbrMbDLKXa1Zlg/K2YNsAECrB+Hnb3Q5l3wuEriQWYlkoc//6vcI2BXUmyOZlh2224Atp0A68Vhr9/rHji5ZUP/oav6xA4Z1MD3IbCrKXaLZlhPK2YrsO4CrCuHLT1msn4TR0vvNQs7X3k+uar1A2DXUuxOzT6YlZdI7QJZLCC35chNfvacEXRykU/2y7el7p3VyrgP8npK3sfObFUEMq+JBLMf0Nbv+D8SafmOXk58xyzLfqjHxKSHrYbsDeswHdANFHrYKN/mHeqhyuXmfozGta44ggpaCBbblqvAzOzvtf2StrtkW5YRd9sae28qKthEKzjBztz6dyoI9jALUsH/DbyVAG/B4Rf3DNk+eaOD84j4lafr3uxUaxLwWyj+DDuz0+/gfTxDfYPNLG1VSjiLEswE26ApV8LBVSW3SQdauO6YXP1Uj9aZi8ajhG20hIvszB6/UwL5VZK7ykrIPfd2CZU0EqyMBlwlWv3dyzaM8fZZlP6p6Ym40h3HoJIdtJJr7Myexa6EnvC+jlLqCkqpQ3cXfe+mPPnHxn32tfL/rA1NOz0apeyipdz+V1YKd97/DiqpJaikBldJ36s15vxtGus6ZYXvg64XrpYZhUr20Eoe/CsrhZ6efIhSqgpKqUz3ZY9eM5q+o4TnnCyHR+e+rnk3EqXso6U8/TdKyf1NwDOUUkFQSjmulJcbEjYF3RH5LRu4qn0Lrcc/R6CUA7SUV//G9qEn6V+jkjKCSkpxlbhlL2ix2qu1d86MQ6k6Xk8HD0clh2gl79iZ3f+FSnDK/j0KMRQUYsAVcu3ENMtblVu4DXma3dDNPydnGAo5Qgv5zM7sVtxClKeSv6AOXUEd2vRL8CuD54vv9PRed8ZMv12f+NtDUccxWsePf6sOMfMTdWgJ6vjxVlnHEc93n++ffOI38+sESfdgG6chqOMEVwfTFON1SrKTvr7lvzN+5jLUXTyx5d0hq/yGnOpX5uSorM/65VjzJF0SA3bmRup+JB1iZm1NfyTtjFZvkqAghgHqw1t+se841NN+3a/WdIl2yV5Rhbk460fJ9WVZ8zRFlSrJ/3mmGpS7m5urJDhE7OFmzk5kSgP4jwD4igPGLmx8zkv7nniHa2xrj8r9aq8D8CwFlmNnblAY0I/AmPIAPReAnnKggKrdq0n7VPPYfuXaibO16qSuAeg8BVUuYCVaCVZiFaAeCVAP6Bav+PW046wr7qNyAvfpuLUpuw7DL1JUjQJWopW6lWhlxdREhrsC4G0OeKZen+Wj40e2G91aWqHMjVnn12L4ZQqsU8BKtOKtRFPMeUMAusaBDG/N3/Wk7Uavsd+/t/k88XrMagy/SkENCliJloKV2JAUKUBd5FDV38Xorx8Y77r15akBsd+Pd1lLGq1SVNOS/F/Pq0HlXYmWFmaWTDMgzwmQZzikm/Mbq0pbHzrlZA4+v1gcv2ENkDcp0qKA1WjJW42WAJ0UgE5woB+9j87Us6rsNPpR54OdO2YYor2g6DYF2Zbk7225y5MzFGhlmZAUZ6Js56wwd5UpEuKSzNBsETs2/rmX6bmFBwRZMXYo4aighMNcCe7eX5fVyF7jteTEp4pDo+ruWFMCzzBaQkt2ZhP1l0DIknERhELaQ8a0AuKA4G1rH4eI/Npoe8uodNch+qIGzXqIr8Wi9+Z9imgrWJ2/ENHJScmJCdEKibKLJ+ME0G4BaCcHatDE5uWWmBSfqeu9tpx4mnpaRtq50ndYM4x3Q4ZtgrWxhcswYmzmtpJnq/oMjWgz+0n5fg0ZmI9phsYY740MGwUZcrgMO8cltnqaedR/6wLbz0FlDQ7rkPcemqEOxvsjw1pBhtVchj4tDnd8fbi639SRNypumr0bl7Cw72c0Q1WMD0GGFYIMy7gM4dfL2Dl8G+Y0c+iJrctbt6pBmq2/pBmaY3wEMiwWZFjIZfj8McxtjqPIbUt2372NvJ5WRHNT0WuaoT7Gd0aG+YIMc7kM5xfd+fZT8tBteuXzXUMdGj8iDarf0Aw1MT4aGWYJMszgMrww7VzaYeJel5V2O0f3812+ljR8fkczNMT4eGSYKsgwmcuw+aLdkfUNHPwHLWn1pm7UsDIGMD/QDLUxPhEZJggyjOMyzP/UP5vZd91zgXFs9xBRJr5L0dL/SYaw/4zZfzrq+yOTJyca7ZYqo6+lV8Tx6EfLoDEugz6+pUrpi4o6JxrlMujBy6BvL4O+wQya4TJoOcygUTGDRrelDPRLFDUl2iAz6JlcqrRuTXbdmxXUn9Y5ISmGfcn6R3Vlp6DfK+nMLJGmpkqz9CTRyelJabrKZvNM35JaZIXooMN8X67PbN5cHrIkWWpCtDnSdLHs0IEbEkxa4DYzSVREJ6fKE6KamYTKUhXsHG1szC3wv2YmLunytPRUWZskWXpaqlTezCQgPUqeEN1OlhWS3E2W1CaqRQupbbStnaWDtY3Mwt6hUydtUmYCm1+hK1Ek9JQZSHoos7IlGhgw/Upq5f7pNGYLXi4qQsVqe1sHp0cp0hLS0jEL7ZDbzETQRzeGXY95Fo0smbllERbOQhodbWsdzS5WrJWFfUxsQQvHPjOaFrnIDp2w3diV0T/PyhA1Y1cGnhbMAHYqeXG3YCNsU5WVJrJnp2DFqc7dis49mJ1K3iLd1c7toXZubzr3MHYqeTG2Vzt3qNq5w+ncI0sqXwmiaLVzx6idO47OPaaksoWxKFXt3Ap1c+uigfJvNXpGfYaShCT2CeYpVcRr11Dz9IORhi1FXl/jsVRokwwWMwHRMhpNRLSaRpMQ5dBoMqItNJqCaCeNpiLaR6NpiA7TaDqiEzSagegMjWaSHV4azUJ0jUazEd2m0RxED2g0F9FTGs1D9IpG8xG9o1E2os80WoDoB40WIkJTRRItQmRAo8WIStFoCaJyNFqKqDKNliGqQaPliOrQaAWiBjRaiagpjVYhsqAR2UG2pdEaRC1pRPbS29KIHCS40mg9Ii8a5SDyo9EGRME02ogonEabEHWi0WZEUTTagiiORlsRyWm0DVF3Gm1H1INGOxD1otFORP1otAvRYBrtRjSCRnsQjaXRXkSTaLQP0XQa7Uc0h0YHEC2g0UFES2l0CNEqGh1GtJ5GRxBtptFRRDtodAzRXhodR3SIRicQHafR34hO0+gkogs0OkUOd2h0GtEtGp1BdJ9GZxE9odE5RC9pdB7RWxpdQPSJRhcRfafRJUS4kzaJLiPSp9EVRCVpdBVRWRpdQ1SJRtcRVafRDUQmNLqJqD6NbiFqQqPbiJrT6A4iGxrdReRAo3uIHGl0H5ELjR4g8qTRQ0S+NHqEKIhGjxGF0egJoo40eopISqNniGJp9BxRNxq9QJRCo5eI0mn0ClFPGr1G1JdG/yAaRKM3iIbT6C2iMTR6h2gijd4jmkajD4hm0+gjomwafUK0hEafEa2k0RdE62j0FdEmGn1DtJ1G3xHtodEPRAdp9BPRMRpplWKjUzQSITpPoxKIrtBIG9FNGukgukcjXUSPaaSH6AWN9BG9oZEBoo80YhB9o5EhItxGhERGiPRoVBKREY1KITKmUWlEFWlUBlE1Ghkjqk2jsojq0agcosY0Ko/InEYVEFnTqCIiexpVQtSGRpUROdOoCiIPGlVF5EOjaogCaVQdUSiNaiDqQKOaiLrQqBYiGY1qI+pKIxNEyTSqgyiNRqaIsmhUF1EfGtVDNJBG9RENo1EDRKNp1BDRBBo1QjSVRo0RzaJRE0TzadQU0WIaNUO0gkZmiNbSyBzRRho1R7SNRhaIdtPIEtEBGlkhOkoja0QnaWSD6ByNbBFdppEdohs0aoHoLo3sET2ikQOi5zRqiegfGrVC9IFGrRF9pVEbRPjZO4kcEenSqC0iQxo5ISpDIzGiCjRyRlSVRi6IatHIFVFdGrkhakQjd0RmNPJAZEUjT0QtaOSFqDWNvBGJadQOkTuNfBC1o5EvogAa+SFqTyN/RJE0CkAkoVEgohgaBSFKoFEwoiQahSBS0Kg9okwahSL6i0ZhiAbQKBzRUBpFIBpFo0hE42nUAdEUGnVENJNGnRDNo1FnRItoJEG0nEZdEK2hkRTRBhpFIdpKo2hEu2gUg2g/jWSIjtAoFtHfNIpDdJZG8Ygu0SgB0XUadUV0h0bdED2kkRzRMxolInpNoyRE72mUjOgLjVIQ/aRRd0Q4EUGiVEQMjRSIStMoDVF5GqUjqkKjHohq0igDkSmNMhE1pFEWomY06onIkka9ENnRqDeiVjT6C5ETjfogcqNRX0TeNOqHyJ9G/RGF0GgAoggaDUTUmUaDEEXTaDCieBoNQZRIo6FsZIwvNvClCjOMjZjhkBGQkZBRkNGslDIsS48T9cmhoSj364UiH5HjOM94AMWNQeqxkHHIX8p4MHXGY+IEyETIJNgljYdRezImToFMhUyDTMcYI+ORdMwMxGWMx9B4JgbNwsTSIhxpjmQnPg+0b1sWx6mG5IvB2Rgyh3yiqB8wFwPmYcBE9QPmY0A2BkxSP2ABBizEgMnqByzCgMXk1a9+wBIMWEo+6NQPWIYByzFgmvoBKzBgJQZMVz9gFQasxoAZ6geswYC15E1J/YB1GLAeA2apH5CDARswYLb6ARsxYBMGzFE/YDMGbMGAueoHbMWAbeS9Uv2A7RiwAwPmqx+wEwN2YUC2+gG7MWAPBixQP2AvBuzDgIXqB+zHgAPkLVz9gIMYcAgDFqsfcBgDjmDAEvUDjmLAMQxYqn7AcQw4gQHL1A/4GwNOkk8W9QNOYcBpDFihfsAZDDiLASvVDziHAecxYJX6ARcw4CIGrFY/4BIGXCYfeOoHXMGAqxiwVv2AaxhwHQPWqR9wAwNuYsB69QNuYcBtDMhRP+AOBtzFgA3qB9zDgPsYsFH9gAcY8BADNqkf8AgDHmPAZvUDnmDAUwzYon7AMwx4jgFb1Q94gQEvMWCb+gGvMOA1BmxXP+AfDHiDATvUD3iLAe8wYKf6Ae8x4AMG7FI/4CMGfMKA3eoHfMaALxiwR/2ArxjwDQP2qh/wHQN+YMA+9QN+YoBWaexMqR8gYj2mBAYcUD9AGwN0MOCg+gH/j7X7AI+qaBs+Th2yoQ2hppEKiBgkgdAFlyRAICQhBbBADLBAIBAgQQi9iV2kiWJXRHqxi9KL2AXpRRRFVHoVBeQ795a573N2zjwv3zXPdb2+u5v/vZnf7EkgYfdsRQgYBDvlQSUIAiD4Qh44IAiEYJc8qAxBFQi+lAdVIagGwVfyoDoEHIKv5UENCIIg+EYe1ISgFgTfyoPaENSB4Dt5UBeCehB8Lw+CIQiB4Ad5EApBGAS75UE4BPUh2CMPIiCIhOBHeRAFQTQEe+VBDASxEOyTBw0gaAjBfnnQCIK7IDggDxpDcDcEB+VBEwjugeCQPIiDoCkEh+XBvRA0g+CIPIiHIAGCo/KgOQQtIDgmDxIhaAnBT/KgFQStITguD9pA0BaCn+VBOwjaQ/CLPLgPgg4QnJAHHSG4H4Jf5YETgk4Q/CYPkiBIhuCkPEiBoDMEv8uDLhB0heCUPEiFoBsEf8iD7hCkQfCnPOgBQToEf8mDDAgyITgtD3pCkAXBGXmQDUEOBGflQS4EvSA4Jw96Q9AHgvPy4AEIHoTggjx4CIKHIbgoD/pC0A+CS/IgD4JHILgsD/Ih6A/BFXkwAIKBEFyVBy4IBkFwTR4MhmAIBH/LgwIIhkJwXR4Mg6AQgn/kwXAIRkDwrzwogmAkBDfkwSgIRkNwUx4UQ1ACwS15MAaCRyH4Tx6MhWAcBLflQSkE4yGAX1NLggkQTISgrDyYBMFkCMrJgykQTIWgvDyYBsF0CCrIgxkQzISgojx4DIJZEDB58DgET0BQSR48CcFTEATIg6cheAYChzx4FoLnIAiUB7MheB6CyvJgDgRzIagiD+ZBMB+CqvJgAQQvQFBNHiyE4EUIqsuDlyBYBAGXBy9D8AoENeTBqxC8BkGQPHgdgjcgqCkP3oTgLQhqyYO3IVgMQW158A4ESyCoIw/ehWApBHXlwTIIlkNQTx6sgGAlBMHyYBUEqyEIkQdrIFgLQag8WAfBexCEyYP3IfgAgnB58CEEH0FQXx58DMEnEETIg08hWA9BpDz4DILPIYiSBxsg2AhBtDzYBMFmCGLkwRYItkIQKw+2QbAdggbyYAcEOyFoKA++gGAXBI3kwZcQfAXBXfLgawi+gaCxPPgWgu8guFsefA/BDxA0kQe7IdgDwT3y4EcI9kIQJw/2QbAfgqby4AAEByG4Vx4cguAwBM3kwREIjkIQLw+OQfATBAny4DgEP0PQXB78AsEJCFrIg18h+A2CRHlwEoLfIWgpD05B8AcEreTBnxD8BUFreXAagjMQtJEHZyE4B0FbeXAeggsQtJMHFyG4BEF7eXAZgisQ3CcPrkJwDYIO8uBvCK5D0FEe/APBvxDcLw9uQHATAqc8uAXBfxB0kge3IShT3QiS5EFZ42OOchAky4PyEFSAIEUeVISAQdBZHlSCIACCLvLAAUEgBF3lQWUIqkCQKg+qQlANgm7yoDoEHILu8qAGBEEQpMmDmhDUgqCHPKgNQR0I0uVBXQjqQZAhD4IhCIEgUx6EQhAGQU95EA5BfQiy5EEEBJEQZMuDKAiiIciRBzEQxEKQKw8aQNAQgl7yoBEEd0HQWx40huBuCPrIgyYQ3APBA/IgDoKmEDwoD+6FoBkED8mDeAgSIHhYHjSHoAUEfeVBIgQtIegnD1pB0BqCPHnQBoK2EDwiD9pB0B6CfHlwHwQdIOgvDzpCcD8EA+SBE4JOEAyUB0kQJEPgkgcpEHSGYJA86AJBVwgGy4NUCLpBMEQedIcgDYICedADgnQIhsqDDAgyIRgmD3pCkAVBoTzIhiAHguHyIBeCXhCMkAe9IegDQZE8eACCByEYKQ8eguBhCEbJg74Q9INgtDzIg+ARCIrlQT4E/SEoIUFNDAZAMBCCMfJ7cEEwCIJH5cFgCIZAMFb+KQogGArBOPk9DIOgEIJSeTAcghEQjJcHRRCMhGCCPBgFwWgIJsqDYghKIJgkD8ZA8CgEk+XBWAjGQTBFHpRCMB6CqTa/f4BgIgTTbH7/AMFkCKbb/P4BgqkQzLD5/QME0yGYafP7BwhmQvCYze8fIJgFwSyb3z9A8AQEj9v8/gGCp4z/VISnLzSUPhehU36xy1lSMrqg/5gSV2qJazi8jqNSXtGgQcWukoC8Ia58eBFIYF6+rwnIG5DvfpUayysuKS10wf/LL3GVKWv8r0JA4v/tkzQR17JhGJ78AP8H/2NPGwuukJ4/3MWeEZee9V1yAK/iqAu3b///fSZ4ZkYleI8fV16e58Ur7lcLwDM7YI/gCnsedqwXNGwOXpwrLrrXULbQWAOswz3/lHfe/RKZBUZZOa1orGt0ZFJh/vCR7AXjhkD3DZ7rCy2B5w4H0zt82nuH7td7LII+d+RIcYcvwx26b/Bcf8USeO6wP73DZ7x3CC/MYK+DJXdEQUkxewMvvikueub70vlnvfMVYX6xUTLYzzHF7B1yeQle9txFH3oXz3nvwv0oLxOP7XJxaYXpUS6bTYdn00doNT4sa/DiWssjlE7nn6eP0PuI/gAvfmjxp9L5OXTxn4glfyourTcvPpkOz6WL34Ar3ogXN1kW35HOz6OL34or3oYXt1sW35bOz6dH0xfkAdtFLn9pffAS6V0soP5vhPpbcek7s78ZHX6B+ncjeg9e/NHib0LnF1L/fkQfwIsHLf6GdP5F6j9CzEfJ5WNWfxS9i5fo18/PYM3MLxnCfhGXTvgueYbD6PAiunknEf07Xjxl8del8y/T+b9w6DRePGOZD6Lzr9D9P4+bdgEvXrTsX1Uyz+HpX9Vg9opRlU9Nbs6uwnecQvgWlldYMLyghF0TB8LfxqWALOPPjYwRhaXsOoRj4FuTN/wHvnd5XlSYUzrSxf7F6+7xG55PkcBuei7Es1vGhSq+58m5m/88H2rJbnsuJDJ4JptxoQUra1yoMrCgeGRhfmneCCPmr3kX73Y5ynM4ObXxnyDPOSHiMkcXDHA1zcxKTUoJKOv9ODP+UzHbVTJmJKsE90dT990wh3FzJe+bxrNAyN334Pkc4j+sCsn4676FwC46YAcdsGsO2DAH7JMD9sYBG+KAXXDADjhA7wCwA7AOgDoAyd/wd4X/D1cEuiLlrmjIPGfJYDG2rAZY8Tf1qt7yV7X8H6rWqGojV7Vzrze+ZRdnNmtvq+qAFX9br2oxVQWydOO26t7DwvcWawYnkGXA8eI9WQnLJAePZ4VZsHb3SUpYNnzQO2qF5IqMv6PXscTscBm3VfOeU4UyBlHGYDxYPMsrQMVQhaIQFe/qVSw1Kya6Fe7H3aSYRBWT8eDwLG8qKqYpFDNQsUyvYrlZMc90THneJtDNmE8ZC/yOqYXoeNHt8IxaHYvQsUKvY6XZsZw+GoSxgjJWWh+N1ahYo1CsQ8UqvYrVvj8iN8OncJ9CKJBtgY/4HhPf2Ybcmq1Us43+YbIdJTtACSe5a9OM7TQuB/juwsraJT4nX6OXtdbHOkBYB92HmuchMqkOUdVh8k33CKKOEtQxFeo4otbpRb3nQ50jqPN2qAsUdZGgLiHqsg8V34xdUaGuIep9vagPzF9GrAZwPN+afadqdHMq1SCcgBr4xz0MVvK+Fz0LrCFslY2LAb67sHqqkiH+oV7RR2ZRuJ2oPhVFEFEkLi6BRaEoWiWKJUP8Y72iT8yiFnaiRCpqSUStcHHNWWsUtVGJ2pEh/qle0XqzqLudKI2KehBROnzA8/5G8SwDRZkqURYZ4p/pFX1uFvW3Ew2gooFE5PIuriWIBqFosEpUQIb4Br2ijWZRqZ1oPBVNIKKJuLgENglFk1WiqWSIb9Ir2mwWPW8nmkNFc4loHi6uOZuPogUq0UIyxLfoFW01i961Ey2lomVEtBwuu89ZGM9WIGilCrQaZ/g2vZ7tZs9GO88m6tlMPFvE2hLYVvRsU3l24Azfodez0+zZZ+fZTz0HiOegb22d4tkh9BxWeY7iDP9Cr2eX2XPGznOWes4Rz3mxtgR2AT0XVZ7LOMO/1Ov5yuwpH0T+4m0CVQgioIpB5C/ezLhSAd78m8E5OL2egCCFJ9A3wb/Wq/nGrAmx1YRSTRjVhMMV7zuKs/oIilCBosgQ/1av6TuzKd7WlEBNzampRRAec4lIaqkitcYZ/r1e0Q9mUVdbUSoVdaOi7kH4XSENRT1Uogyc4bv1ivaYRXm2okeoKJ+K+gfh9+0BKBqoEg3CGf6jXtFes+hRW9FYKhpHRaVB+CfreBRNUIkm4Qzfp1e03yx61lb0HBXNpqLng8jffuYgaa6KNJ8M8QN6TQfNpsW2pneoaQk1vRtE/o66FE3LVKYVZIgf0ms6bDZ9Zmv6nJo2UNNGXF4824SmzSrTVjLEj+g1HTWb9tiafqSmvdS0L4j8vLcfTQdUpkNkiB/Ta/rJbPrT1vQXNZ2mpjNB5Kfys2g6pzJdIEP8uF7Tz2ZTmZp2prI1ialcTWIqX5P87qRCTWGqWFNhqkSG+C96TSfMprq2pnrUFExNIbi8eBaKpjCVqT4Z4r/qNf1mNjW1Nd1LTc2oKR6upMd1Teoe14kloKm5ypRIhvhJvabfzaYUW1NnaupCTV1xeU6WiqZuKlMaGeKn9Jr+MJsetjX1paZ+1JQHa3d/WzZWyB5BVL4KNYBO8T/1qv4yq4ptVSVUNYaqHoX1wRtfwpsHs7GoGqdSjadT/LRe1Rmz6ilb1dNU9QxVwRuxBKR1SXO/GTR7DlWzVao5dIqf1as6Z1a9aat6i6repqrFxpXyXROy2TsIWqICLfUO8PN6LRfMlk9sLZ9Sy3pq+cz9TTklHd4sj32Ong0qzyYyxC/qNV0ym763Nf1ATbupaY/7I7lpnZ1d0tmPaNqrMu0nQ/yyXtMVs+l3W9MpavqDmv7EPzyz2V9oOq0ynSVD/Kpe0zWz6Zat6T9quk1N8AbRAb73eGLwTtVeFLxfti2qAp3if+tVXTeratWyU9WuRVR1ahFVXVif752RWD1UBatUoXSK/6NX9a9Z1cRWdQ9VxVFVU1hffEKLOFgjuxdVzVSqBDrFb+hV3TSrOtmqkqgqmapS4Ir3raNYZ0R1UaFSyRC/pdf0n9n0gK3pQWp6iJoergVrdL8JFeuLpH4q0iM4w2/rFcF9EdFIW9EoKhpNRcWw9OTUTPe70LMSNI1RmcbSKV62mlZVObPqcVvVE1T1JFU9BVe877XHnkbUMyrUc2SIl9drqmA2vWZrep2a3qCmN93fm71vUMfeQtTbKtQ7dIpX1KtiZtWHtqqPqOpjqvoEHO7fE7NPkbReRfpcjPBKej0BZs83tp5vqec76vnetzgn+wE9u1WeH8UId+j1BJo9v9p6fqOek9Tzey3Pz3atMtNys9kpJP2hIv1Fp3hlvaoqZtW/tqobVHWTqm7B+jqlGitMy8hm/6HqtkpVtjaZ4lX1qqqZVTVq26mCahNVzdpEVcu4wtw/h3ditWsLU53aClM9nOHV9Yq4WXSXragxFd1NRU3E6pzsHhTFqUT34gyvoVcUZBZ1tBXdT0VOKurkXV2i8RgloShZJeqMM7ymXlEts6iXrag3FfWhogfE6pzsQRQ9pBL1xRleW6+ojlk03FY0goqKqGgkXEmNy8zqbDxIo5A0WkUqIUO8rl5TPbNppq3pMWqaRU2P4/Kc7Ak0PakyPU2GeLBeU4jZ9LKt6RVqepWaXnOvPSku05nl7MxeR9QbKtRbdIqH6lWFmVXv2arep6oPqOpDWF+2T/URqj5WqT6lUzxcr6q+WfWlreorqvqaqr5xr68L/NbR+KL6FlXfqVQ/0CkeoVcVaVb9bKv6hapOUNWvZH1O9huqTqpUp+gUj9Krijar/rZVXaeqf6jq39ru3xF39fxm+QaqbqpU/9EpHqNXFWtWVatjp6peh6h4HaKqUQf+TprVKd2tCqojVDXrKFS16RRvoFfV0KxqYKtqSFWNqOouWJ8zKTXZrWqMqrtVqnvoFG+kV3WXWdXeVnUfVXWgqo7GlQrZzvRkdj+KnCpRkm+CN9arudusybbV5FBNLtX0Mq6Ud2Z3Zb0R00eFedA7wJvotdxjtgy1tQyjlkJqGV4HzkbFRqCkSCUZ5c55nF5HU7Njmq1jOnXMoI6ZsLBs9hg6ZqkcT7hzfq9eRzOz40Vbx0vUsYg6XjausGzPb+9eQcyrKszrOMPj9YoSzKI1tqK1VLSOit6D1aV7RO+j6AOV6COc4c31ilqYRTttRV9Q0S4q+hKWnpZq/NHY2/i7z1do+lpl+pZO8US9qpZm1TFb1U9UdZyqfibrc7JfUHVCpfqNTvFWelWtzaortqqrVHWNqv72ri/N/VhdR9U/KtUNOsXb6FW1Nasq17VTValLVFXrElW1urg+J6teV6h4XYUqiE7xdnpV7c2qaFtVDFXFUlUDuALP0HAm5bCGiGqkQjUmQ/w+vaYOZlMbW1NbampHTe3rwvfmXPj6YPchqYOKdD/O8I56RfebRZm2op5UlEVF2d7VGUcRy0FRrkrUG2e4U6+ok1k02FY0hIoKqGgoLL1LrjPVmZSRxoahqVBlGkGneJJeVbJZNdlWNYWqplLVNFifMy0poys8DWI6qmaoVI/RKZ6iV9XZrFpgq3qBqhZS1YtwpXtKTgb8S+BLiFqkQr1ChngXvaauZtNKW9MqalpNTWs8e56c0vWB5BS2FlHrVKj36RRP1avqZlZts1Vtp6odVLUTHPAzaTb7Akm7VKSvxAjvrteTZvYctvUcoZ6j1HPMuFI+PSOB/YSa4yrNL94B3kOvJd1suWhruUQtl6nlCiwt27BcRcs1leW6d4Bn6LVkmi0B9ewsjnrEEliPWCrXg+fNxHXKzUlJT2FV6glQ1XoKUHU6xXvqVWWZVRG2qkiqiqKqaLiSmZWRCagYRMWqUA3JEM/Wa8oxm1ramlpRU2tqamNcYSk5XYHUFkntVKT7cIbn6hX1Mot62IrSqSiDijJh6elwFMFTQnuiKUtlyqFTvLdeVR+zaqCtykVVg6hqsO8wAtQQRBWoUMPIEH9Ar+lBs2mCrWkiNU2ipsne4whIU5A0VUWajjP8Ib2ih82iubaieVQ0n4oWwJUeXtILSFqoIr1EhnhfvaZ+ZtMyW9NyalpBTSuNK+WTjD+XVqFntcqz1jvA8/RaHjFbNttatlDLVmrZZlwpl5TBtiNlh4ryhafn+Xol/c2SA7aSg1RyiEoOw8qcWewISo6qJD95ej5Ar2SgWXLOVnKeSi5QyUVYWXoCu4SSyyrJVU/PXXolg8ySisF2EhZMJJWCiSTAuFLO+EJxBAtJYLBCUsXT88F6JUPMkjBbSTiV1KeSCFhZ1wQWiZIolSTG0/MCvZKhZklzW0kLKkmkkpYg6O3MSclirRDTWoVpK0b4ML2eQuoJgPNru//HuhmfMTgrLiEhsWlC15y4Hs7U9KY9MtJS8h5ITUlLNoTuNjLvjXKdWHejZZ0KiwYMK2ZpxuVq5jnWA5XpweJ5nxnGxUC8Syu5pxjiw/WSR9iQ8++A3J+QB0jIA5Hs8pGdbJCaPATJRXrJI23I4+6AXErI4yXkCUieGIzP35ukNk9B8yi95tE25tl3YH6emOdIzHPRPC8Ynw83X21+Ac3Fes0lNuYld2B+l5iXSszL0Lwcvq35Xlu+Qo1ehegxetGP2qA33AF6I0FvkqA3I3oLohPYVjV6O6LH6kWPs0HvvQP0PoLeL0EfQPTB4DLi7DaH1OYjaC7Vax5vYz59B+YzxHxWYj6H5vPCHM8uqM2X0DxBr3mijblcyP/dXD4EzRVC/M0VQ4SZhZQRZ8ipFKI0O8QUn6TXPNnGHHwH5hBiDpWYw9AcLszxrL7aHInmKXrNU23Mze7AHE/MCRJzczS3MC6Ks+wkqtGtED1NL3q6DbrLHaC7EnSqBN0N0d0RncDS1Oh0RM/Qi55pg+53B+g8gn5Egs5HdH9Ex7MBarQL0Y/pRc+yQY+5A/SjBD1Wgh6H6FIv2n0in/Fq9EREP+5dJZsUYnkHickhvneQmBJifkuIqcZ1fEeJaSGWd5SYjrn7HSVmhHjfpGJmiPetJB4L8b6VxKwQ61tJPB7ifSuJJ0K8byXxZIj3rSSeCrG+lcQT3sWT3X1aubvsGf9NNO/4s7jjnr2ajVv8fEgZPF/NHPUWz8MtftJ3IMAWO2BbHbCjDthGB+yeA3bMAdvkgC1ywPY4YGscsBsO2AkH7IIDdoA/5Y9+S41++3+hF1vRSxD9LqKz2VI1ejmin/YdVyt8j/5K6wG2Shxgq00H1BrrAbXWckCtsxyP7/mOq/d9x9UHfsfVh77j6iPfcfWx77j6xO+4esa3+E8FiOz2elhfVlx8fLOmSRkpnePFG198Tr5aN8CkO2IbQ/CJi5uMy2Xj2Wb4qHvYuoVbcQuf9R03sIUO2D4HbJkDdssBm+SAjXHAbjhgCxzAdwDdAVoHSB2gdICQP+dD7Zah9tih9hLUPkTtD8HnLh7woA7aog4jarZe1PM+1J8y1F92qDMEdRZR50Lo0xfPe1gXbFmXkDVHL2uuj1U2VMIqF2rDqhCKrIqhgsVC6fMXK4W6WQGhdqxA8Tn5PL2s+T5WsIwVYscKI6xwZNUPJU+Ki/CoIm1V0ahaoFf1gk8VL1Ml2KlaEFUiqlqG0qdltvKwWtuy2iJroV7Wiz5WqozVzY6VRlg9kJVOWE6W4WFl2rKykPWSXtYiHytfxupvxxpIWC5kDQoVT0hkgz2oIbaooYh6WS/qFR+qVIYab4eaSFCTEDXZi4LnMU7xoKbaoqYj6lW9qNd8qDky1Fw71HyCWoCoF0LpUxkXelgv2rIWIet1vaw3fKxlMtZyO9ZKwlqFrNWh9Blyazystbas95D1pl7WWz7WFhlrqx1rO2HtQNbOUPJkxi88ql22qq9Q9bZe1WKf6pBMddhOdZSojqHqp1D6xNPjHtbPtqwTyHpHL2uJj3VRxrpkx7pCWFeRdS1UPJ/xb4/puq3pXzS961vEjVDLTwY3Q30/GdwKNf9V/79Q+pPC7VDLTwplwsw/KZQN8/7wUS7M+yNC+TDvjwgVwqw/IlQM8/6IwMK8PyJUCvP+iBAQZv0RYal38YHMYXysTrarpKRgxODipvljSoryXPCOtvklLhYYBq9/9X7M/W+klY1bqpoisjlVac6qKVJPz/0Kvsx3oMCmsqAw30bWDDNtpAM20gH7x+pY9qyub8/q+fYs2LdnIX57FurbszDfnoV798wBe8aXi22KMK6K96bzvBsYizRu876BgXtzosLwH5Dpv2uH4ZP8oLB5M7GGIuMr6C44YBccsAGodoDaAVQHMB1AdADPASIHaBwg8ShWCkWicbVyQqsEQWgJXOMGzxP85Otvg+tvq1h/e1z/Kr3rXy3W3929fuML27f+NPf645u5199Dvv4MXH+mYv1ZuP41ete/Vqw/373+xESx/v7u9Scmet4DSL5+F65/kGL9Q3D96/Su/z2x/rHwFdsyIaGP55kTIBgHX6Nwk5tQKidMQMLEMN+zJiSGyWh4X6/hA2F4Fh6DFs1aiMfgOXgMjBvcgNlywBwEzFU8BvNx/R/qXf9HYv1vu4+hZs18by7JFruPoWaer4F35Ot/F9e/1L1++dtLLsf1f6x3/Z+I9X8K34UTja9hcQitB0Ci94v4MzlgAwI2qo6gzSj4VK9gvRB8H+b/9jbshzDzHwa7rQ72Y5jvHWH2ImZfmOJJRAd8E/wzvZbPheV3meWUxfKHn+UvuMX3fjCnkXNGxTlHhvgGvaKNQnRLJvrPIrrtJyobXgbPfF4uXIjKhytEFckQ36RXtFmIaoVLRLXDzaI64VZRPVyckwWjKEQlCiNDfIte0VYhaiIT3WMRxfmJ7g0vQ8563gxJ8SpSczrFt+k1bRemTjJTksWU7GfqDKsT5zzvgqauKlM3OsV36DXtFKYHZKYHLaaH/Ex9w8uQM573Q1OeypRPp/gXek27hGmkzDTKYhrtZyoJ957vfAxyHlVxxnkH+Jd6JV8JyeMyyRMWyZN+kqfhFt/Zzp9BzbMqzWwyxL/WK/pGiF6TiV63iN7wE73lvsV7rvO3UbRYJVpChvi3ekXfCdGHMtFHFtHHfqJPw8k/W65H0Wcq0QYyxL/XK/pBiL6Rib61iL7zE/0AKxfnOd+NpD0q0l46xXfrNe0Rpl9lpt8sppN+plOwOnGW8z/Q9KfKdJpO8R/1mvYK078y0w2L6aaf6T9YnTjH+W00lamvMJWrT6b4Pr2m/cJUo77EFFTfbKpZ32qqDbf4znBep74g1VWRgskQP6BXdFCI7pKJGltEd/uJ7oHCe37zOAQ1VYGa4Qw/pNdzWHg6yjz3WzxOP08SLFyc3TwZRSkqURc6xY/oNR0Vpl4yU2+LqY+f6UG4xXdu84eQ9LCK1I8M8WN6RT8J0XCZaIRFVOQnGgUrF2c2H42kYhVpDJ3ix/WafhammTLTYxbTLD/TE/XF61ueRNBTKtAzYoT/oldzQmhelmlesWhe9dO87luak72BmjdVmrfFCP9Vr+Y3oXlPpnnfovnAT/NR/TLknOYfI+gTFWg9neIn9Zp+F6YvZaavLKav/UzfwurEGc2/Q9P3KtNuOsVP6TX9IUw/y0y/WEwn/Ey/QeE9n/lJFP2uEv2BM/xPvZ6/hOdvmee6xfOPn+eGWJuT3UTPLZXnNs7w03o9Z4SnWoTEUz3C7OERVk9QRBlxLvOaEcJTK0LhqYMz/KxezznhaSDzNLR4Gvl5Gou1Odnd6Gmi8sThDD+v13NBeNrLPPdZPB38PPfDLb7zmDsR1EkFSiZD/KJe0SUhypaJciyiXD9Rb1yck/VB0QMq0UNkiF/WK7oiRENlomEWUaGfaIR75b6zfRchaaSKNJpO8at6TdeEaZrMNN1imuFnegxWJ85gPgtNj6tMT9Ip/rde03VhelFmesliWuRnesW9Ot/5y19F02sq0xt0iv+j1/SvMK2RmdZaTOv8TO+T1TnZB2j6UGX6mE7xG3pNN4Vpp8z0hcW0y8/0VUQZcu7yr9H0jcr0HZ3it/Sa/hOmYzLTTxbTcT/TL7A6cebyE2j6VWU6Saf4bb2mMtV9pisy01WL6Zqf6TqsTpy3/B80/asy3aRTvGx1raZywlQ5UmKqEmk2VY20mqpH+s5aziOFp0akwlPTN8HL67VUEJZomSXGYon1szSM9J6zvBFS7lJR7vYO8Ip6JUxI2sgkbS2Sdn6S+yLdZyzvgI6OKofTnfNKehUBQpEpU/S0KLL8FDmR7vOV56Kil0rRx51zh15FoFAMlimGWBQFfophUHhf9FOIlOEqShHO8Mp6PVWEZ7LMM8XimernmQ6F9/U+M9AzU+WZhTO8ql5PNeFZIPO8YPEs9PO8FElf6rMIRS+rRK/SKV5dr4kL00qZaZXFtNrPtJaszsnWoek9lekDOsVr6DUFCdM2mWm7xbTDz/RFJH05zC40fakyfU2neE29plrCdFhmOmIxHfUz/URW52TH0fSzynSCTvHaek11hOmizHTJYrrsZ7oaSV6MdQ1Jf6tI/5AhXlevqJ4QBURJRI4osygwyiqqAoX3pT1VowSoWpQCxHGGB+v1hAhPhMwTafFE+XlivGuDV/XEoqeBytMIZ3ioXk+Y8LSUeVpZPK39PG2j6At62qGovUrUgU7xcL2m+sLUQ2ZKt5gy/Ew9o+gLRLLQlK0y5dIpHqHXFClMA2Uml8U0yM80JIq8lKcASUNVpEIyxKP0iqKFaIJMNNEimuQnmhJFX3M1FUnTVKQZdIrH6DXFCtNcmWmexTTfz/RClHgNz0IEvagCLRIjvIFeTUOhWSbTLLdoVvhpVkV5z0i+Gi1rVJZ13gHeSK/kLiHZLJNssUi2+km2R3nPR74DJTtVkl3eAd5Yr+RuITkgkxy0SA75SY7AqsXZyI8i55iKc5xO8SZ6TfcI0zmZ6bzFdMHPdAlu8Z2L/DKSrqhI18gQj9MraipEFaMlIhZtFlWKtoocUHjPRB4YLUCVoxWgqjjD79XraSY8YTJPuMVT388TCQsX5yGPQlG0ShRLp3i8XlOCMDWXmVpYTIl+plbRZfAs5K2R1EZFakeGeHO9ohZC1E0m6m4RpfmJ0r1HEIAyEJSpAmXhDE/U62kpPPkyT3+LZ4CfxwW3+M5APghBg1WgAjLEW+kVtRaicTJRqUU03k80Mdp7/vFJqJms0kz1DvA2eiVthWS2TPK8RTLHTzIv2nP28fkIWaCCLPT0vJ1eR3vhWCJzvGtxLPVzLI/2nHt8BTpWqhyrPT2/T6+jg3BskDk2Whyb/Bxboj1nHt+Kjm0qxw5PzzvqddwvHHtljn0Wx34/x8Foz3nHD6HjsMpx1NNzp15HJ+E4LXOcsTjO+jnOR3vOOn4BHRdVjsuenifpdSQLR7kYiaN8jNlRIcbqYMYt3nOOV4oRlIAYBSVQjPAUvZrOQhNMNNk5WT3ycjMzWYhFE2rVeNYXDlly65ZxcPYjgPjuwAqJxJB30SvpKiT3yiTNLJJ4ImEJsL85GTnONNYcH5IWkHgekmyWqGK1EvM8Va+qm1B1lqm6WFRdqSoVVd1Q1T0G/sGzS1wWS1OR0pHUXS8pTZD6ykj9LKQ8SnoESflI6g+QtK69emTHxSeyASqWC1k99LLSBatExhpjYT1KWWORNQ5ZpTG+13N3zmLj5So2MYY8F30SucIz9Poyhe8Zme9Zi+856puNvufRN4f65tr45sfQVxctoNd4T73CLCFcLBO+YxEuocJ3UbgUhcuocLmNcGUMeUXYKnKFZ+v15Qjf5zLfBotvI/VtQt9m9G2hvq02vu0x9LUFO+g1nqtX2Av/riQT7rMI91PhARQeROEhKjxsIzwaQ18tdoxe4731CvsI4RmZ8KxFeI4Kz6PwAgovUuElG+GVGPI6q6vkCn9Ar+9B4asQK/FVjDX7WCzxVYoVvoBY4XPEEl9grNxXBe7X+6qrqniZP6RX9zD+1kimC7fo6lNdBOoiURdFddE2uthY8UqYBuIi76vX1k/YWshsiRZbS2prhbbWaGtDbW1tbO19ICe7T1zkeXptjwhbmvE5aueWFBQWlJTGZY8Z3tRYdW5OUkZ2DuthfKgy+ZCbmQ57keUqHlNYUhxp3Dg8f3Sp9e8kmUbjEPfj9+sk00d5vl5Zf+/dBbA6vU69tqb8nvYs3/iE1XLimjdv1rSTMzs1Oy8ri/V3P0Bwm/kEzQPgUSUnaKZ/04IHzHcH1g8Oph/kA/SaBvruzv2pxsbCH31uTueUlOS87BxnlxQ2zgQKqA1lqQzDJhi3ljc6NtG4EIh3YSVN9nbcpVczyPcIBZSDT/Os8WmqeDjpHspzZkr1RkY12/5xmQMfSpcS5uGH+GC9iiH+x9lb3uMsgRxnb3stCZbjbLG9Z4nqOFtqOs4K9JqGmo6zT7zHWYLpOPvUBPIcZ+ulx9nn7uMnIYFtUB9nm7wdH6ZXU2g+zr7zHmcJ4jj73kxxH2c/2D8ue+yPs73kOBuuVzHC/zj71XucxZPj7DevJd5ynJ2095xSHWd/mo6zIr2mkeKRKQuf67r3QIs3HWj/mEQBEVD+Kz3QbkJpdHHx7Jb6ULstSj5KL2m0+WCr1sBzsMWLg616AxPHfbDxBrYPTlAD24OtFn6IF+tVlPjuzn0S0lhAGD98Z6SmN03pk5mVwBrAp/bcIk5V2si4rXKyq7hg8Ii47JGuAdblNga4e9z6kSbiI3yMyQFnJXXACUmJA0446oCzjDrgDKMOOLuoA84s6oCTiTrgRKKOSsLxqPjrTVvjc9QU5wx1FcE5PIvzH3Wxdg3KWE4Y2t64JRALstAOtGUd7TpP7DR/mI/VSxuHz/o2PlEw0gYUjSgaXjCgOC9/QEmBAezpB8wybuHWjqw8x8TMVdeekd6yiJfqJY8X5EHGp2uUXTDeWGBk/oiBkUlFxbDYpkn5IwtK8gvhqvuvpCUFRSPYYCMO8o/dWzHE+Fgt2RSxDZXPs2H/e9ZzB8PtQj5B7wZNFBs00fiUsanpvVKyc3qkpOe0bZpTZHzyyKz8sZE98ktcowvyC4vdEDYJvmxJ6d6WycaN9WxHpthsyFQ4CFLGuQaMgUff+zMBm2b5BGy66s6tezdTFfNJevdvsti/ecanbSg5wJILRrsGlJiPr/mK42sBfNuRDBHhQpvdfPF/jnrmF9l0fIrezZmKTxGDzfE/uDJHF8EpjSO9R7rnWFkuO7xWGDeGKIZW2mzJKukBttp6gK1R3711A9epcz5N7z5OxyeoGZ840n8fPT9pF7i8X21bZDu4Fb6lSPNtNnu3Xbp3O6x7t9Pujq27tssu5DP07tdMfBqcfL8yRrpG54PRswEHZft1CFdryQ/b7NcR6X4dte7XMbs7tu7XcbuQP6Z3v2bhU+yMTxlN9wv+djbaNdD4TlriiiwaFJnlKhkzegQ7L9uxC8aNdWwGLtrs2SXpnl227tkV+7u27to1+5Q/rnffnsAn8jWE87M3jcw0/qgpGhjNmHG9bIbn6XvGxQDxgYCGFpnDuKFcdCYLdE+wyrT2gKo2lG9dtYayrasOnyCzqVgLf1Kv+Slhrm98pgjp9/SBY4xviNn5ha5iFtFQcqBEGjfWlNVRNtRoKTXGupexNvdrPUQa2nQV4KeSiOzS4hLX8Ka5IwpKSrPdf3UoGO/+47FrUeFA1+jyxj1USM4vyXe4CzgdfxVncbFreP/CUjjdftkyZQMCy/k+V+X/BwAA//8DAFBLAQItABQAAAAIALt1wlq3H+Sh4O8AAL3rCAAYAGAAAAAAAAAAAAAAAAAAAABBc3BlblRlY2guQVNXWEwuV29ya2Jvb2tOVTgATlVDWBgAAABBAHMAcABlAG4AVABlAGMAaAAuAEEAUwBXAFgATAAuAFcAbwByAGsAYgBvAG8AawAKACAAAAAAAAEAGABRAhObgdPbAVECE5uB09sB87kQm4HT2wFQSwUGAAAAAAEAAQCmAAAAWPAAAB8AQVNXWEwgU3RvcmFnZSBWZXJzaW9uIDQwLjAuMC4xMA==

Sheet 20250529_175057
A1: PYROTEMP | B1: GAS.N | C1: GAS.F | D1: GAS.RR | E1: SAF.N | F1: SAF.F | G1: SAF.RR | H1: DSL.N | I1: DSL.F | J1: DSL.RR | K1: TCC | L1: TOC | M1: TRC | N1: TPS | O1: TUC | P1: SAF | Q1: MJSP | R1: LHV | S1: SG | T1: SLF | U1: ARM | V1: MBP | W1: MFP | X1: ERRSIM | Y1: ERR_0 | Z1: ERR_1 | AA1: ERR_2 | AB1: ERR_3 | AC1: ERR_4 | AD1: ERR_5 | AE1: ERR_6 | AF1: ERR_7
A2: 930 | B2: 30 | C2: 15 | D2: 2.95 | E2: 20 | F2: 12 | G2: 0.56748 | H2: 20 | I2: 11 | J2: 0.7 | K2: 6.1086586e+08 | L2: 49299900 | M2: 79696321 | N2: 73520700 | O2: 17282674 | P2: 227.47242 | Q2: 1.3530016 | R2: 43.783614 | S2: 782.84949 | T2: 1.260035e-16 | U2: 23.545149 | V2: 91.85 | W2: -238.42529 | X2: 0 | Y2: 0 | Z2: 0 | AA2: 0 | AB2: 0 | AC2: 0 | AD2: 0 | AE2: 0 | AF2: 0
A3: 910 | B3: 30 | C3: 15 | D3: 2.95 | E3: 20 | F3: 12 | G3: 0.56748 | H3: 20 | I3: 12 | J3: 0.7 | K3: 6.1075516e+08 | L3: 49392500 | M3: 79675748 | N3: 73048600 | O3: 17286537 | P3: 226.18491 | Q3: 1.3713921 | R3: 43.784049 | S3: 782.81451 | T3: 1.2661919e-16 | U3: 23.538142 | V3: 91.85 | W3: -238.42529 | X3: 0 | Y3: 0 | Z3: 0 | AA3: 0 | AB3: 0 | AC3: 0 | AD3: 0 | AE3: 0 | AF3: 0
A4: 915 | B4: 30 | C4: 15 | D4: 2.95 | E4: 20 | F4: 12 | G4: 0.56748 | H4: 20 | I4: 12 | J4: 0.7 | K4: 6.1091723e+08 | L4: 49398800 | M4: 79681640 | N4: 73184500 | O4: 17288108 | P4: 226.55227 | Q4: 1.3671287 | R4: 43.783925 | S4: 782.82451 | T4: 1.2643968e-16 | U4: 23.540099 | V4: 91.85 | W4: -238.42529 | X4: 0 | Y4: 0 | Z4: 0 | AA4: 0 | AB4: 0 | AC4: 0 | AD4: 0 | AE4: 0 | AF4: 0
A5: 920 | B5: 30 | C5: 15 | D5: 2.95 | E5: 20 | F5: 12 | G5: 0.56748 | H5: 20 | I5: 12 | J5: 0.7 | K5: 6.1086875e+08 | L5: 49502300 | M5: 79687532 | N5: 73323100 | O5: 17289931 | P5: 226.92685 | Q5: 1.3640442 | R5: 43.783798 | S5: 782.83474 | T5: 1.2625702e-16 | U5: 23.542082 | V5: 91.85 | W5: -238.42529 | X5: 0 | Y5: 0 | Z5: 0 | AA5: 0 | AB5: 0 | AC5: 0 | AD5: 0 | AE5: 0 | AF5: 0
A6: 925 | B6: 30 | C6: 15 | D6: 2.95 | E6: 20 | F6: 12 | G6: 0.56748 | H6: 20 | I6: 12 | J6: 0.7 | K6: 6.1054553e+08 | L6: 49505100 | M6: 79690229 | N6: 73384000 | O6: 17280331 | P6: 227.09144 | Q6: 1.36096 | R6: 43.783745 | S6: 782.83899 | T6: 1.2618193e-16 | U6: 23.542925 | V6: 91.85 | W6: -238.42529 | X6: 0 | Y6: 0 | Z6: 0 | AA6: 0 | AB6: 0 | AC6: 0 | AD6: 0 | AE6: 0 | AF6: 0
A7: 930 | B7: 30 | C7: 15 | D7: 2.95 | E7: 20 | F7: 12 | G7: 0.56748 | H7: 20 | I7: 12 | J7: 0.7 | K7: 6.1086537e+08 | L7: 49299900 | M7: 79696321 | N7: 73525800 | O7: 17282674 | P7: 227.47462 | Q7: 1.3528881 | R7: 43.783614 | S7: 782.84949 | T7: 1.2599722e-16 | U7: 23.544939 | V7: 91.85 | W7: -238.42529 | X7: 0 | Y7: 0 | Z7: 0 | AA7: 0 | AB7: 0 | AC7: 0 | AD7: 0 | AE7: 0 | AF7: 0
A8: 935 | B8: 30 | C8: 15 | D8: 2.95 | E8: 20 | F8: 12 | G8: 0.56748 | H8: 20 | I8: 12 | J8: 0.7 | K8: 6.1092798e+08 | L8: 49306600 | M8: 79702513 | N8: 73670400 | O8: 17285331 | P8: 227.86654 | Q8: 1.3480763 | R8: 43.783481 | S8: 782.86023 | T8: 1.2580144e-16 | U8: 23.546895 | V8: 91.85 | W8: -238.42529 | X8: 0 | Y8: 0 | Z8: 0 | AA8: 0 | AB8: 0 | AC8: 0 | AD8: 0 | AE8: 0 | AF8: 0
A9: 940 | B9: 30 | C9: 15 | D9: 2.95 | E9: 20 | F9: 12 | G9: 0.56748 | H9: 20 | I9: 12 | J9: 0.7 | K9: 6.1100248e+08 | L9: 49325000 | M9: 79708904 | N9: 73818200 | O9: 17288288 | P9: 228.26525 | Q9: 1.3434407 | R9: 43.783342 | S9: 782.87128 | T9: 1.2561418e-16 | U9: 23.549006 | V9: 91.85 | W9: -238.42529 | X9: 0 | Y9: 0 | Z9: 0 | AA9: 0 | AB9: 0 | AC9: 0 | AD9: 0 | AE9: 0 | AF9: 0
A10: 945 | B10: 30 | C10: 15 | D10: 2.95 | E10: 20 | F10: 12 | G10: 0.56748 | H10: 20 | I10: 12 | J10: 0.7 | K10: 6.0919398e+08 | L10: 49395800 | M10: 79715296 | N10: 73969000 | O10: 17291504 | P10: 228.67315 | Q10: 1.3341312 | R10: 43.7832 | S10: 782.88259 | T10: 1.2541619e-16 | U10: 23.551065 | V10: 91.85 | W10: -238.42529 | X10: 0 | Y10: 0 | Z10: 0 | AA10: 0 | AB10: 0 | AC10: 0 | AD10: 0 | AE10: 0 | AF10: 0
A11: 950 | B11: 30 | C11: 15 | D11: 2.95 | E11: 20 | F11: 12 | G11: 0.56748 | H11: 20 | I11: 12 | J11: 0.7 | K11: 6.0933653e+08 | L11: 49402900 | M11: 79721987 | N11: 74123000 | O11: 17294441 | P11: 229.08966 | Q11: 1.3292974 | R11: 43.783055 | S11: 782.8942 | T11: 1.2521347e-16 | U11: 23.553137 | V11: 91.85 | W11: -238.42529 | X11: 0 | Y11: 0 | Z11: 0 | AA11: 0 | AB11: 0 | AC11: 0 | AD11: 0 | AE11: 0 | AF11: 0
A12: 955 | B12: 30 | C12: 15 | D12: 2.95 | E12: 20 | F12: 12 | G12: 0.56748 | H12: 20 | I12: 12 | J12: 0.7 | K12: 6.0953488e+08 | L12: 49411300 | M12: 79729779 | N12: 74287900 | O12: 17281592 | P12: 229.53629 | Q12: 1.3242877 | R12: 43.782976 | S12: 782.9005 | T12: 1.2514662e-16 | U12: 23.554624 | V12: 91.85 | W12: -238.42529 | X12: 0 | Y12: 0 | Z12: 0 | AA12: 0 | AB12: 0 | AC12: 0 | AD12: 0 | AE12: 0 | AF12: 0
A13: 960 | B13: 30 | C13: 15 | D13: 2.95 | E13: 20 | F13: 12 | G13: 0.56748 | H13: 20 | I13: 12 | J13: 0.7 | K13: 6.0411395e+08 | L13: 49411300 | M13: 79729904 | N13: 74287900 | O13: 17763051 | P13: 220.91558 | Q13: 1.3593069 | R13: 43.782976 | S13: 782.90161 | T13: 1.2359892e-16 | U13: 23.53953 | V13: 91.85 | W13: -238.42529 | X13: 100 | Y13: 0 | Z13: 0 | AA13: 0 | AB13: 0 | AC13: 0 | AD13: 0 | AE13: 0 | AF13: 0
... A125: 930 | B125: 30 | C125: 15 | D125: 2.95 | E125: 20 | F125: 12 | G125: 0.56748 | H125: 20 | I125: 12 | J125: 1.4 | K125: 6.1110137e+08 | L125: 49299400 | M125: 79696221 | N125: 73515900 | O125: 17282680 | P125: 227.47685 | Q125: 1.3537616 | R125: 43.783582 | S125: 782.84903 | T125: 1.2599053e-16 | U125: 23.544727 | V125: 91.85 | W125: -238.42529 | X125: 0 | Y125: 0 | Z125: 0 | AA125: 0 | AB125: 0 | AC125: 0 | AD125: 0 | AE125: 0 | AF125: 0

Sheet 20250531_220044_OilComponent
A1: PHENOLS | B1: PHENOL1 | C1: PHENOL2 | D1: PHENOL3 | E1: CYC-5A | F1: CYC-5A1 | G1: CYC-6A | H1: CYC-6A1 | I1: CYC-6A2 | J1: CYC-6A3 | K1: ARM-A | L1: ARM-A1 | M1: ARM-A2 | N1: ARM-B | O1: ARM-B1 | P1: ARM-B2 | Q1: TCC | R1: TOC | S1: TRC | T1: TPS | U1: TUC | V1: SAF | W1: MJSP | X1: LHV | Y1: SG | Z1: SLF | AA1: ARM | AB1: MBP | AC1: MFP | AD1: GT10 | AE1: GT90 | AF1: DFP | AG1: DT90 | AH1: ERRSIM | AI1: ERR_0 | AJ1: ERR_1 | AK1: ERR_2 | AL1: ERR_3 | AM1: ERR_4 | AN1: ERR_5 | AO1: ERR_6 | AP1: ERR_7 | AQ1: ERR_8 | AR1: ERR_9 | AS1: ERR_10 | AT1: ERR_11
A2: 2.2 | B2: 0 | C2: 0 | D2: 0 | E2: 1.8 | F2: 0 | G2: 2.4 | H2: 0 | I2: 0 | J2: 0 | K2: 3.5 | L2: 0 | M2: 0 | N2: 1.5 | O2: 0 | P2: 0 | Q2: 6.1109186e+08 | R2: 49299400 | S2: 79696219 | T2: 73515900 | U2: 17281811 | V2: 227.47874 | W2: 1.353722 | X2: 43.783633 | Y2: 782.84833 | Z2: 1.2598471e-16 | AA2: 23.544546 | AB2: 91.85 | AC2: -239.5006 | AD2: 62.893989 | AE2: 92.803696 | AF2: 165.7 | AG2: 236.22725 | AH2: 0 | AI2: 0 | AJ2: 0 | AK2: 0 | AL2: 0 | AM2: 0 | AN2: 0 | AO2: 0 | AP2: 0 | AQ2: 0 | AR2: 0 | AS2: 0 | AT2: 0
A3: 0 | B3: 3.06 | C3: 0 | D3: 0 | E3: 1.8 | F3: 0 | G3: 2.4 | H3: 0 | I3: 0 | J3: 0 | K3: 3.5 | L3: 0 | M3: 0 | N3: 1.5 | O3: 0 | P3: 0 | Q3: 6.1032985e+08 | R3: 49299400 | S3: 79696215 | T3: 73515900 | U3: 17273338 | V3: 218.84361 | W3: 1.4047733 | X3: 44.150003 | Y3: 789.4182 | Z3: 1.0925813e-18 | AA3: 20.496791 | AB3: 91.85 | AC3: -409.30686 | AD3: 62.770888 | AE3: 92.649087 | AF3: 144.29 | AG3: 225.61165 | AH3: 0 | AI3: 0 | AJ3: 0 | AK3: 0 | AL3: 0 | AM3: 0 | AN3: 0 | AO3: 0 | AP3: 0 | AQ3: 0 | AR3: 0 | AS3: 0 | AT3: 0
A4: 0 | B4: 0 | C4: 3 | D4: 0 | E4: 1.8 | F4: 0 | G4: 2.4 | H4: 0 | I4: 0 | J4: 0 | K4: 3.5 | L4: 0 | M4: 0 | N4: 1.5 | O4: 0 | P4: 0 | Q4: 6.1021388e+08 | R4: 49299400 | S4: 79696222 | T4: 73515900 | U4: 17276556 | V4: 226.35625 | W4: 1.3578019 | X4: 43.825054 | Y4: 784.40115 | Z4: 3.4208688e-17 | AA4: 22.567996 | AB4: 91.85 | AC4: -223.83348 | AD4: 62.712003 | AE4: 92.58961 | AF4: 165.7 | AG4: 240.08799 | AH4: 0 | AI4: 0 | AJ4: 0 | AK4: 0 | AL4: 0 | AM4: 0 | AN4: 0 | AO4: 0 | AP4: 0 | AQ4: 0 | AR4: 0 | AS4: 0 | AT4: 0
A5: 0 | B5: 0 | C5: 0 | D5: 2.14 | E5: 1.8 | F5: 0 | G5: 2.4 | H5: 0 | I5: 0 | J5: 0 | K5: 3.5 | L5: 0 | M5: 0 | N5: 1.5 | O5: 0 | P5: 0 | Q5: 6.1117432e+08 | R5: 49299400 | S5: 79696220 | T5: 73515900 | U5: 17282171 | V5: 227.76256 | W5: 1.3522808 | X5: 43.799328 | Y5: 783.02942 | Z5: 9.5818693e-17 | AA5: 23.631204 | AB5: 91.85 | AC5: -236.05295 | AD5: 62.84089 | AE5: 92.754747 | AF5: 165.7 | AG5: 248.14986 | AH5: 0 | AI5: 0 | AJ5: 0 | AK5: 0 | AL5: 0 | AM5: 0 | AN5: 0 | AO5: 0 | AP5: 0 | AQ5: 0 | AR5: 0 | AS5: 0 | AT5: 0
A6: 2.2 | B6: 0 | C6: 0 | D6: 0 | E6: 0 | F6: 2.1 | G6: 2.4 | H6: 0 | I6: 0 | J6: 0 | K6: 3.5 | L6: 0 | M6: 0 | N6: 1.5 | O6: 0 | P6: 0 | Q6: 6.1292992e+08 | R6: 49299400 | S6: 79696218 | T6: 73515900 | U6: 17292551 | V6: 229.94819 | W6: 1.3446104 | X6: 43.782389 | Y6: 782.81258 | Z6: 9.9353966e-17 | AA6: 23.233849 | AB6: 91.85 | AC6: -210.71554 | AD6: 60.201367 | AE6: 85.755318 | AF6: 165.7 | AG6: 236.54225 | AH6: 0 | AI6: 0 | AJ6: 0 | AK6: 0 | AL6: 0 | AM6: 0 | AN6: 0 | AO6: 0 | AP6: 0 | AQ6: 0 | AR6: 0 | AS6: 0 | AT6: 0
A7: 2.2 | B7: 0 | C7: 0 | D7: 0 | E7: 1.8 | F7: 0 | G7: 0 | H7: 2.06 | I7: 0 | J7: 0 | K7: 3.5 | L7: 0 | M7: 0 | N7: 1.5 | O7: 0 | P7: 0 | Q7: 6.1022226e+08 | R7: 49299400 | S7: 79696219 | T7: 73515900 | U7: 17277313 | V7: 221.47288 | W7: 1.3877664 | X7: 43.827521 | Y7: 781.96459 | Z7: 7.4077346e-17 | AA7: 23.640585 | AB7: 100.934 | AC7: -266.75403 | AD7: 66.160863 | AE7: 96.509472 | AF7: 165.7 | AG7: 234.27269 | AH7: 0 | AI7: 0 | AJ7: 0 | AK7: 0 | AL7: 0 | AM7: 0 | AN7: 0 | AO7: 0 | AP7: 0 | AQ7: 0 | AR7: 0 | AS7: 0 | AT7: 0
A8: 2.2 | B8: 0 | C8: 0 | D8: 0 | E8: 1.8 | F8: 0 | G8: 0 | H8: 0 | I8: 1.77 | J8: 0 | K8: 3.5 | L8: 0 | M8: 0 | N8: 1.5 | O8: 0 | P8: 0 | Q8: 6.106117e+08 | R8: 49299400 | S8: 79696219 | T8: 73515900 | U8: 17280254 | V8: 200.83185 | W8: 1.5317142 | X8: 43.989155 | Y8: 785.60619 | Z8: 4.5327332e-18 | AA8: 22.36114 | AB8: 100.934 | AC8: -201.55224 | AD8: 66.359557 | AE8: 97.480562 | AF8: 144.29 | AG8: 224.0432 | AH8: 0 | AI8: 0 | AJ8: 0 | AK8: 0 | AL8: 0 | AM8: 0 | AN8: 0 | AO8: 0 | AP8: 0 | AQ8: 0 | AR8: 0 | AS8: 0 | AT8: 0
A9: 2.2 | B9: 0 | C9: 0 | D9: 0 | E9: 1.8 | F9: 0 | G9: 0 | H9: 0 | I9: 0 | J9: 2.06 | K9: 3.5 | L9: 0 | M9: 0 | N9: 1.5 | O9: 0 | P9: 0 | Q9: 6.1055587e+08 | R9: 49299400 | S9: 79696217 | T9: 73515900 | U9: 17280901 | V9: 189.18952 | W9: 1.6257724 | X9: 44.093695 | Y9: 789.57451 | Z9: 1.9305737e-18 | AA9: 22.397373 | AB9: 100.934 | AC9: -431.52667 | AD9: 67.634517 | AE9: 98.073459 | AF9: 144.29 | AG9: 223.00542 | AH9: 0 | AI9: 0 | AJ9: 0 | AK9: 0 | AL9: 0 | AM9: 0 | AN9: 0 | AO9: 0 | AP9: 0 | AQ9: 0 | AR9: 0 | AS9: 0 | AT9: 0
A10: 2.2 | B10: 0 | C10: 0 | D10: 0 | E10: 1.8 | F10: 0 | G10: 2.4 | H10: 0 | I10: 0 | J10: 0 | K10: 0 | L10: 3.44 | M10: 0 | N10: 1.5 | O10: 0 | P10: 0 | Q10: 6.1136813e+08 | R10: 49299400 | S10: 79696219 | T10: 73515900 | U10: 17284392 | V10: 223.48124 | W10: 1.3787757 | X10: 44.847495 | Y10: 795.87606 | Z10: 1.0528969e-16 | AA10: 7.9858759 | AB10: 91.85 | AC10: -266.61469 | AD10: 62.913751 | AE10: 92.770769 | AF10: 165.7 | AG10: 236.04358 | AH10: 0 | AI10: 0 | AJ10: 0 | AK10: 0 | AL10: 0 | AM10: 0 | AN10: 0.017655162 | AO10: 0 | AP10: 0 | AQ10: 0 | AR10: 0 | AS10: 0 | AT10: 0
A11: 2.2 | B11: 0 | C11: 0 | D11: 0 | E11: 1.8 | F11: 0 | G11: 2.4 | H11: 0 | I11: 0 | J11: 0 | K11: 0 | L11: 0 | M11: 2.69 | N11: 1.5 | O11: 0 | P11: 0 | Q11: 6.1319854e+08 | R11: 49299400 | S11: 79696222 | T11: 73515900 | U11: 17297885 | V11: 221.6161 | W11: 1.3959866 | X11: 44.083419 | Y11: 785.88391 | Z11: 2.5749648e-15 | AA11: 9.2745358 | AB11: 91.85 | AC11: -253.98815 | AD11: 64.194233 | AE11: 92.892523 | AF11: 165.7 | AG11: 229.03933 | AH11: 0 | AI11: 0 | AJ11: 0 | AK11: 0 | AL11: 0 | AM11: 0 | AN11: 0 | AO11: 0 | AP11: 0 | AQ11: 0 | AR11: 0 | AS11: 0 | AT11: 0
A12: 2.2 | B12: 0 | C12: 0 | D12: 0 | E12: 1.8 | F12: 0 | G12: 2.4 | H12: 0 | I12: 0 | J12: 0 | K12: 3.5 | L12: 0 | M12: 0 | N12: 0 | O12: 1.24 | P12: 0 | Q12: 6.1168221e+08 | R12: 49299400 | S12: 79696219 | T12: 73515900 | U12: 17284051 | V12: 224.9303 | W12: 1.3708412 | X12: 43.627156 | Y12: 778.5875 | Z12: 1.1092455e-15 | AA12: 19.328862 | AB12: 91.85 | AC12: -238.8943 | AD12: 62.863346 | AE12: 92.780075 | AF12: 165.7 | AG12: 233.45594 | AH12: 0 | AI12: 0 | AJ12: 0 | AK12: 0 | AL12: 0 | AM12: 0 | AN12: 0 | AO12: 0 | AP12: 0 | AQ12: 0 | AR12: 0 | AS12: 0 | AT12: 0
A13: 2.2 | B13: 0 | C13: 0 | D13: 0 | E13: 1.8 | F13: 0 | G13: 2.4 | H13: 0 | I13: 0 | J13: 0 | K13: 3.5 | L13: 0 | M13: 0 | N13: 0 | O13: 0 | P13: 1.3 | Q13: 6.1161518e+08 | R13: 49299400 | S13: 79696219 | T13: 73515900 | U13: 17283468 | V13: 226.27121 | W13: 1.3625163 | X13: 43.608097 | Y13: 779.54591 | Z13: 1.0407078e-15 | AA13: 19.207163 | AB13: 91.85 | AC13: -238.80564 | AD13: 62.840801 | AE13: 92.759473 | AF13: 165.7 | AG13: 231.17584 | AH13: 0 | AI13: 0 | AJ13: 0 | AK13: 0 | AL13: 0 | AM13: 0 | AN13: 0 | AO13: 0 | AP13: 0 | AQ13: 0 | AR13: 0 | AS13: 0 | AT13: 0
U15: MIN | V15: =MIN(V3:V13) -> 189.18952 | X15: =MIN(X3:X13) -> 43.608097 | Y15: =MIN(Y3:Y13) -> 778.5875 | Z15: =MIN(Z3:Z13) -> 1.0925813e-18 | AA15: =MIN(AA3:AA13) -> 7.9858759 | AB15: =MIN(AB3:AB13) -> 91.85 | AC15: =MIN(AC3:AC13) -> -431.52667 | AD15: =MIN(AD3:AD13) -> 60.201367 | AE15: =MIN(AE3:AE13) -> 85.755318 | ... AG15: =MIN(AG3:AG13) -> 223.00542
U16: MAX | V16: =MAX(V3:V13) -> 229.94819 | X16: =MAX(X3:X13) -> 44.847495 | Y16: =MAX(Y3:Y13) -> 795.87606 | Z16: =MAX(Z3:Z13) -> 2.5749648e-15 | AA16: =MAX(AA3:AA13) -> 23.640585 | AB16: =MAX(AB3:AB13) -> 100.934 | AC16: =MAX(AC3:AC13) -> -201.55224 | AD16: =MAX(AD3:AD13) -> 67.634517 | AE16: =MAX(AE3:AE13) -> 98.073459 | ... AG16: =MAX(AG3:AG13) -> 248.14986
U18: LOWER | V18: =V15-V$2 -> -38.289215 | X18: =X15-X$2 -> -0.1755358 | Y18: =Y15-Y$2 -> -4.260834 | Z18: =Z15-Z$2 -> -1.2489213e-16 | AA18: =AA15-AA$2 -> -15.55867 | AB18: =AB15-AB$2 -> 0 | AC18: =AC15-AC$2 -> -192.02607 | AD18: =AD15-AD$2 -> -2.6926223 | AE18: =AE15-AE$2 -> -7.0483781 | ... AG18: =AG15-AG$2 -> -13.221822
U19: HIGHER | V19: =V16-V$2 -> 2.469459 | X19: =X16-X$2 -> 1.0638621 | Y19: =Y16-Y$2 -> 13.02773 | Z19: =Z16-Z$2 -> 2.4489801e-15 | AA19: =AA16-AA$2 -> 0.096039189 | AB19: =AB16-AB$2 -> 9.084 | AC19: =AC16-AC$2 -> 37.948366 | AD19: =AD16-AD$2 -> 4.7405273 | AE19: =AE16-AE$2 -> 5.2697622 | ... AG19: =AG16-AG$2 -> 11.922619
U21: AVERAGE | V21: =AVERAGE(V2:V13) -> 219.84854 | X21: =AVERAGE(X2:X13) -> 43.951412 | Y21: =AVERAGE(Y2:Y13) -> 784.96236 | Z21: =AVERAGE(Z2:Z13) -> 4.3893392e-16 | AA21: =AVERAGE(AA2:AA13) -> 19.805827 | AB21: =AVERAGE(AB2:AB13) -> 94.121 | AC21: =AVERAGE(AC2:AC13) -> -268.12876 | AD21: =AVERAGE(AD2:AD13) -> 63.69885 | AE21: =AVERAGE(AE2:AE13) -> 93.318233 | ... AG21: =AVERAGE(AG2:AG13) -> 233.13792

Sheet 20250531_223825_Grid
A1: PYROTEMP | B1: GAS.N | C1: GAS.F | D1: GAS.RR | E1: SAF.N | F1: SAF.F | G1: SAF.RR | H1: DSL.N | I1: DSL.F | J1: DSL.RR | K1: TCC | L1: TOC | M1: TRC | N1: TPS | O1: TUC | P1: SAF | Q1: MJSP | R1: LHV | S1: SG | T1: SLF | U1: ARM | V1: MBP | W1: MFP | X1: GT10 | Y1: GT90 | Z1: DFP | AA1: DT90 | AB1: ERRSIM | AC1: ERR_0 | AD1: ERR_1 | AE1: ERR_2 | AF1: ERR_3 | AG1: ERR_4 | AH1: ERR_5 | AI1: ERR_6 | AJ1: ERR_7 | AK1: ERR_8 | AL1: ERR_9 | AM1: ERR_10 | AN1: ERR_11
A2: 930 | B2: 30 | C2: 15 | D2: 2.95 | E2: 20 | F2: 12 | G2: 0.56748 | H2: 20 | I2: 12 | J2: 1.4 | K2: 6.1161518e+08 | L2: 49299400 | M2: 79696219 | N2: 73515900 | O2: 17283468 | P2: 226.27121 | Q2: 1.3625163 | R2: 43.608097 | S2: 779.54591 | T2: 1.0407078e-15 | U2: 19.207163 | V2: 91.85 | W2: -238.80564 | X2: 62.840801 | Y2: 92.759473 | Z2: 165.7 | AA2: 231.17584 | AB2: 0 | AC2: 0 | AD2: 0 | AE2: 0 | AF2: 0 | AG2: 0 | AH2: 5.491046 | AI2: 0 | AJ2: 0 | AK2: 0 | AL2: 0 | AM2: 0 | AN2: 0
A3: 930 | B3: 30 | C3: 15 | D3: 2.95 | E3: 20 | F3: 12 | G3: 0.56748 | H3: 20 | I3: 12 | J3: 1.4 | K3: 6.1161518e+08 | L3: 49299400 | M3: 79696219 | N3: 73515900 | O3: 15885038 | P3: 226.27121 | Q3: 1.3625163 | R3: 43.608097 | S3: 779.54591 | T3: 1.0407078e-15 | U3: 19.207163 | V3: 91.85 | W3: -238.80564 | X3: 62.840801 | Y3: 92.759473 | Z3: 165.7 | AA3: 231.17584 | AB3: 99 | AC3: 0 | AD3: 0 | AE3: 0 | AF3: 0 | AG3: 0 | AH3: 5.491046 | AI3: 0 | AJ3: 0 | AK3: 0 | AL3: 0 | AM3: 0 | AN3: 0
A4: 930 | B4: 30 | C4: 15 | D4: 2.95 | E4: 20 | F4: 12 | G4: 0.56748 | H4: 20 | I4: 12 | J4: 0.7 | K4: 5.8337241e+08 | L4: 50126300 | M4: 79694719 | N4: 71705400 | O4: 15885038 | P4: 226.28026 | Q4: 1.3291829 | R4: 43.608097 | S4: 779.54344 | T4: 1.0405959e-15 | U4: 19.206405 | V4: 91.85 | W4: -238.82056 | X4: 62.841637 | Y4: 92.759895 | Z4: 165.7 | AA4: 232.05796 | AB4: 0 | AC4: 0 | AD4: 0 | AE4: 0 | AF4: 0 | AG4: 0 | AH4: 5.491994 | AI4: 0 | AJ4: 0 | AK4: 0 | AL4: 0 | AM4: 0 | AN4: 0
A5: 910 | B5: 30 | C5: 15 | D5: 2.95 | E5: 20 | F5: 12 | G5: 0.56748 | H5: 20 | I5: 12 | J5: 1.4 | K5: 5.8317356e+08 | L5: 50218400 | M5: 79674146 | N5: 71200300 | O5: 15890480 | P5: 224.98823 | Q5: 1.3479332 | R5: 43.608513 | S5: 779.51119 | T5: 1.0467246e-15 | U5: 19.201057 | V5: 91.85 | W5: -238.6967 | X5: 62.86712 | Y5: 92.770307 | Z5: 165.7 | AA5: 231.1767 | AB5: 0 | AC5: 0 | AD5: 0 | AE5: 0 | AF5: 0 | AG5: 0 | AH5: 5.4986785 | AI5: 0 | AJ5: 0 | AK5: 0 | AL5: 0 | AM5: 0 | AN5: 0
A6: 915 | B6: 30 | C6: 15 | D6: 2.95 | E6: 20 | F6: 12 | G6: 0.56748 | H6: 20 | I6: 12 | J6: 1.4 | K6: 5.8333011e+08 | L6: 50224700 | M6: 79680038 | N6: 71333200 | O6: 15890348 | P6: 225.35302 | Q6: 1.3437429 | R6: 43.608394 | S6: 779.52111 | T6: 1.0450046e-15 | U6: 19.202834 | V6: 91.85 | W6: -238.72859 | X6: 62.859629 | Y6: 92.76722 | Z6: 165.7 | AA6: 231.17645 | AB6: 0 | AC6: 0 | AD6: 0 | AE6: 0 | AF6: 0 | AG6: 0 | AH6: 5.4964569 | AI6: 0 | AJ6: 0 | AK6: 0 | AL6: 0 | AM6: 0 | AN6: 0
A7: 920 | B7: 30 | C7: 15 | D7: 2.95 | E7: 20 | F7: 12 | G7: 0.56748 | H7: 20 | I7: 12 | J7: 1.4 | K7: 5.8329352e+08 | L7: 50345900 | M7: 79686030 | N7: 71468900 | O7: 15892966 | P7: 225.72636 | Q7: 1.3411268 | R7: 43.608273 | S7: 779.53127 | T7: 1.0432256e-15 | U7: 19.204589 | V7: 91.85 | W7: -238.75682 | X7: 62.851832 | Y7: 92.76401 | Z7: 165.7 | AA7: 231.1762 | AB7: 0 | AC7: 0 | AD7: 0 | AE7: 0 | AF7: 0 | AG7: 0 | AH7: 5.4942638 | AI7: 0 | AJ7: 0 | AK7: 0 | AL7: 0 | AM7: 0 | AN7: 0
A8: 925 | B8: 30 | C8: 15 | D8: 2.95 | E8: 20 | F8: 12 | G8: 0.56748 | H8: 20 | I8: 12 | J8: 1.4 | K8: 5.8296965e+08 | L8: 50348700 | M8: 79688627 | N8: 71528500 | O8: 15883165 | P8: 225.88994 | Q8: 1.3380723 | R8: 43.608222 | S8: 779.53549 | T8: 1.0425018e-15 | U8: 19.20536 | V8: 91.85 | W8: -238.77223 | X8: 62.848628 | Y8: 92.762671 | Z8: 165.7 | AA8: 231.1762 | AB8: 0 | AC8: 0 | AD8: 0 | AE8: 0 | AF8: 0 | AG8: 0 | AH8: 5.4932997 | AI8: 0 | AJ8: 0 | AK8: 0 | AL8: 0 | AM8: 0 | AN8: 0
A9: 930 | B9: 30 | C9: 15 | D9: 2.95 | E9: 20 | F9: 12 | G9: 0.56748 | H9: 20 | I9: 12 | J9: 1.4 | K9: 5.8342518e+08 | L9: 50125800 | M9: 79694719 | N9: 71667300 | O9: 15885038 | P9: 226.27121 | Q9: 1.3301279 | R9: 43.608097 | S9: 779.54591 | T9: 1.0407078e-15 | U9: 19.207163 | V9: 91.85 | W9: -238.80564 | X9: 62.840801 | Y9: 92.759473 | Z9: 165.7 | AA9: 231.17584 | AB9: 0 | AC9: 0 | AD9: 0 | AE9: 0 | AF9: 0 | AG9: 0 | AH9: 5.491046 | AI9: 0 | AJ9: 0 | AK9: 0 | AL9: 0 | AM9: 0 | AN9: 0
A10: 935 | B10: 30 | C10: 15 | D10: 2.95 | E10: 20 | F10: 12 | G10: 0.56748 | H10: 20 | I10: 12 | J10: 1.4 | K10: 5.8369341e+08 | L10: 50125800 | M10: 79694709 | N10: 71667300 | O10: 15888926 | P10: 226.80973 | Q10: 1.3277726 | R10: 43.607933 | S10: 779.55907 | T10: 1.0383002e-15 | U10: 19.209976 | V10: 91.85 | W10: -238.85192 | X10: 62.829986 | Y10: 92.755045 | Z10: 165.7 | AA10: 231.17554 | AB10: 100 | AC10: 0 | AD10: 0 | AE10: 0 | AF10: 0 | AG10: 0 | AH10: 5.4875299 | AI10: 0 | AJ10: 0 | AK10: 0 | AL10: 0 | AM10: 0 | AN10: 0
A11: 940 | B11: 30 | C11: 15 | D11: 2.95 | E11: 20 | F11: 12 | G11: 0.56748 | H11: 20 | I11: 12 | J11: 1.4 | K11: 5.8355473e+08 | L11: 50150800 | M11: 79707302 | N11: 71953500 | O11: 15889686 | P11: 227.05774 | Q11: 1.3208296 | R11: 43.607837 | S11: 779.56754 | T11: 1.0370076e-15 | U11: 19.210819 | V11: 91.85 | W11: -238.87539 | X11: 62.825009 | Y11: 92.752925 | Z11: 165.7 | AA11: 231.17554 | AB11: 0 | AC11: 0 | AD11: 0 | AE11: 0 | AF11: 0 | AG11: 0 | AH11: 5.4864767 | AI11: 0 | AJ11: 0 | AK11: 0 | AL11: 0 | AM11: 0 | AN11: 0
A12: 945 | B12: 30 | C12: 15 | D12: 2.95 | E12: 20 | F12: 12 | G12: 0.56748 | H12: 20 | I12: 12 | J12: 1.4 | K12: 5.8161796e+08 | L12: 50239400 | M12: 79713794 | N12: 72101300 | O12: 15892403 | P12: 227.46274 | Q12: 1.3115487 | R12: 43.607701 | S12: 779.57881 | T12: 1.0351314e-15 | U12: 19.212742 | V12: 91.85 | W12: -238.91914 | X12: 62.816919 | Y12: 92.749678 | Z12: 165.7 | AA12: 231.17504 | AB12: 0 | AC12: 0 | AD12: 0 | AE12: 0 | AF12: 0 | AG12: 0 | AH12: 5.4840719 | AI12: 0 | AJ12: 0 | AK12: 0 | AL12: 0 | AM12: 0 | AN12: 0
A13: 950 | B13: 30 | C13: 15 | D13: 2.95 | E13: 20 | F13: 12 | G13: 0.56748 | H13: 20 | I13: 12 | J13: 1.4 | K13: 5.8176236e+08 | L13: 50246500 | M13: 79720385 | N13: 72251900 | O13: 15895414 | P13: 227.87759 | Q13: 1.3068114 | R13: 43.607562 | S13: 779.59033 | T13: 1.0331681e-15 | U13: 19.214579 | V13: 91.85 | W13: -238.95343 | X13: 62.808644 | Y13: 92.746222 | Z13: 165.7 | AA13: 231.17477 | AB13: 0 | AC13: 0 | AD13: 0 | AE13: 0 | AF13: 0 | AG13: 0 | AH13: 5.4817766 | AI13: 0 | AJ13: 0 | AK13: 0 | AL13: 0 | AM13: 0 | AN13: 0
... A114: 930 | B114: 30 | C114: 15 | D114: 2.95 | E114: 20 | F114: 12 | G114: 0.56748 | H114: 20 | I114: 12 | J114: 1.4 | K114: 5.8342528e+08 | L114: 50125800 | M114: 79694719 | N114: 71667300 | O114: 15885042 | P114: 226.27121 | Q114: 1.3301282 | R114: 43.608134 | S114: 779.54574 | T114: 1.0407078e-15 | U114: 19.207163 | V114: 91.85 | W114: -238.8056 | X114: 62.840859 | Y114: 92.759473 | Z114: 165.7 | AA114: 231.17584 | AB114: 0 | AC114: 0 | AD114: 0 | AE114: 0 | AF114: 0 | AG114: 0 | AH114: 5.491046 | AI114: 0 | AJ114: 0 | AK114: 0 | AL114: 0 | AM114: 0 | AN114: 0

Sheet 20250601_103250_BO_LCOsaf
A1: PYROTEMP | B1: GAS.N | C1: GAS.F | D1: GAS.RR | E1: SAF.N | F1: SAF.F | G1: SAF.RR | H1: DSL.N | I1: DSL.F | J1: DSL.RR | K1: TCC | L1: TOC | M1: TRC | N1: TPS | O1: TUC | P1: SAF | Q1: MJSP | R1: LHV | S1: SG | T1: SLF | U1: ARM | V1: MBP | W1: MFP | X1: GT10 | Y1: GT90 | Z1: DFP | AA1: DT90 | AB1: ERRSIM | AC1: ERR_0 | AD1: ERR_1 | AE1: ERR_2 | AF1: ERR_3 | AG1: ERR_4 | AH1: ERR_5 | AI1: ERR_6 | AJ1: ERR_7 | AK1: ERR_8 | AL1: ERR_9 | AM1: ERR_10 | AN1: ERR_11
A2: 930 | B2: 30 | C2: 15 | D2: 2.95 | E2: 20 | F2: 12 | G2: 0.56748 | H2: 20 | I2: 12 | J2: 1.4 | K2: 5.0875118e+08 | L2: 54426600 | M2: 79694719 | N2: 71667300 | O2: 15885038 | P2: 226.27121 | Q2: 1.1899968 | R2: 43.608097 | S2: 779.54591 | T2: 1.0407078e-15 | U2: 19.207163 | V2: 91.85 | W2: -238.80564 | X2: 62.840801 | Y2: 92.759473 | Z2: 165.7 | AA2: 231.17584 | AB2: 0 | AC2: 0 | AD2: 0 | AE2: 0 | AF2: 0 | AG2: 0 | AH2: 0 | AI2: 0 | AJ2: 0 | AK2: 0 | AL2: 0 | AM2: 0 | AN2: 0 | AP2: =SUM(AB2:AN2)+Q2 -> 1.1899968
A3: 932.8258 | B3: 38 | C3: 11 | D3: 1.9570408 | E3: 17 | F3: 12 | G3: 1.0176171 | H3: 25 | I3: 13 | J3: 0.60783206 | K3: 5.0886799e+08 | L3: 54465400 | M3: 79698114 | N3: 71648000 | O3: 15885700 | P3: 225.9308 | Q3: 1.193276 | R3: 43.587002 | S3: 780.22505 | T3: 3.6100111e-16 | U3: 19.119093 | V3: 100.934 | W3: -227.26382 | X3: 62.862939 | Y3: 93.330005 | Z3: 144.29 | AA3: 231.67196 | AB3: 0 | AC3: 0 | AD3: 0 | AE3: 0 | AF3: 0 | AG3: 0 | AH3: 0 | AI3: 0 | AJ3: 0 | AK3: 0 | AL3: 0 | AM3: 0 | AN3: 0 | AP3: =SUM(AB3:AN3)+Q3 -> 1.193276
A4: 940.38324 | B4: 30 | C4: 13 | D4: 8.4054462 | E4: 21 | F4: 5 | G4: 0.38889723 | H4: 14 | I4: 12 | J4: 0.6920114 | K4: 5.0917752e+08 | L4: 54465400 | M4: 79698100 | N4: 71648000 | O4: 15894902 | P4: 227.39489 | Q4: 1.1865171 | R4: 43.658115 | S4: 780.00313 | T4: 2.7850556e-09 | U4: 19.644649 | V4: 100.934 | W4: -238.47691 | X4: 62.86131 | Y4: 92.430064 | Z4: 180.981 | AA4: 236.67807 | AB4: 100 | AC4: 0 | AD4: 0 | AE4: 0 | AF4: 0 | AG4: 0 | AH4: 0 | AI4: 0 | AJ4: 0 | AK4: 0 | AL4: 0 | AM4: 0 | AN4: 0 | AP4: =SUM(AB4:AN4)+Q4 -> 101.18652
A5: 928.81863 | B5: 39 | C5: 12 | D5: 12.232089 | E5: 21 | F5: 9 | G5: 0.84194989 | H5: 20 | I5: 8 | J5: 0.53540527 | K5: 5.1046911e+08 | L5: 54477700 | M5: 79693421 | N5: 71805800 | O5: 15889482 | P5: 225.61504 | Q5: 1.1969168 | R5: 43.636575 | S5: 780.10155 | T5: 1.4829106e-13 | U5: 19.214192 | V5: 100.934 | W5: -238.00293 | X5: 62.839306 | Y5: 92.117291 | Z5: 180.981 | AA5: 232.61131 | AB5: 0 | AC5: 0 | AD5: 0 | AE5: 0 | AF5: 0 | AG5: 0 | AH5: 0 | AI5: 0 | AJ5: 0 | AK5: 0 | AL5: 0 | AM5: 0 | AN5: 0 | AP5: =SUM(AB5:AN5)+Q5 -> 1.1969168
A6: 932.71169 | B6: 28 | C6: 12 | D6: 14.27294 | E6: 28 | F6: 5 | G6: 0.38285839 | H6: 18 | I6: 11 | J6: 0.88069386 | K6: 5.1051383e+08 | L6: 54483600 | M6: 79698315 | N6: 72125400 | O6: 15892167 | P6: 226.16191 | Q6: 1.1880338 | R6: 43.661391 | S6: 780.12636 | T6: 2.8412616e-09 | U6: 19.684661 | V6: 100.934 | W6: -237.45277 | X6: 62.835447 | Y6: 92.389195 | Z6: 180.981 | AA6: 232.43481 | AB6: 0 | AC6: 0 | AD6: 0 | AE6: 0 | AF6: 0 | AG6: 0 | AH6: 0 | AI6: 0 | AJ6: 0 | AK6: 0 | AL6: 0 | AM6: 0 | AN6: 0 | AP6: =SUM(AB6:AN6)+Q6 -> 1.1880338
A7: 950.85127 | B7: 30 | C7: 14 | D7: 1.3752561 | E7: 29 | F7: 6 | G7: 0.64496521 | H7: 27 | I7: 11 | J7: 0.57796828 | K7: 5.0934551e+08 | L7: 54485400 | M7: 79721684 | N7: 72797900 | O7: 15895110 | P7: 226.24115 | Q7: 1.1710257 | R7: 43.620665 | S7: 780.31598 | T7: 1.2206393e-10 | U7: 19.46117 | V7: 80.72 | W7: -200.39379 | X7: 62.894697 | Y7: 93.619419 | Z7: 203.285 | AA7: 232.09086 | AB7: 0 | AC7: 0 | AD7: 0 | AE7: 0 | AF7: 0 | AG7: 0 | AH7: 0 | AI7: 0 | AJ7: 0 | AK7: 0 | AL7: 0 | AM7: 0 | AN7: 0 | AP7: =SUM(AB7:AN7)+Q7 -> 1.1710257
A8: 940.64793 | B8: 38 | C8: 15 | D8: 13.319674 | E8: 15 | F8: 7 | G8: 0.84298623 | H8: 20 | I8: 13 | J8: 0.54903319 | K8: 5.1075141e+08 | L8: 54505100 | M8: 79708201 | N8: 72090600 | O8: 15894911 | P8: 226.90811 | Q8: 1.185933 | R8: 43.625594 | S8: 779.8572 | T8: 1.2170997e-11 | U8: 19.276682 | V8: 100.934 | W8: -238.59127 | X8: 62.823846 | Y8: 92.114848 | Z8: 177.97 | AA8: 232.77447 | AB8: 0 | AC8: 0 | AD8: 0 | AE8: 0 | AF8: 0 | AG8: 0 | AH8: 0 | AI8: 0 | AJ8: 0 | AK8: 0 | AL8: 0 | AM8: 0 | AN8: 0 | AP8: =SUM(AB8:AN8)+Q8 -> 1.185933
A9: 934.05767 | B9: 35 | C9: 16 | D9: 12.745643 | E9: 24 | F9: 14 | G9: 1.1205531 | H9: 19 | I9: 14 | J9: 0.65109529 | K9: 5.1076324e+08 | L9: 54502200 | M9: 79699812 | N9: 71902900 | O9: 15892028 | P9: 225.61393 | Q9: 1.1963872 | R9: 43.636797 | S9: 780.70223 | T9: 2.6828389e-18 | U9: 19.139936 | V9: 100.934 | W9: -239.05057 | X9: 62.839244 | Y9: 92.212796 | Z9: 180.981 | AA9: 232.86471 | AB9: 0 | AC9: 0 | AD9: 0 | AE9: 0 | AF9: 0 | AG9: 0 | AH9: 0 | AI9: 0 | AJ9: 0 | AK9: 0 | AL9: 0 | AM9: 0 | AN9: 0 | AP9: =SUM(AB9:AN9)+Q9 -> 1.1963872
A10: 919.15979 | B10: 36 | C10: 11 | D10: 2.7914271 | E10: 19 | F10: 13 | G10: 0.47704335 | H10: 13 | I10: 10 | J10: 1.0744599 | K10: 5.0858818e+08 | L10: 54416700 | M10: 79684932 | N10: 71219500 | O10: 15892811 | P10: 226.29459 | Q10: 1.197927 | R10: 43.567696 | S10: 779.40666 | T10: 3.423516e-16 | U10: 19.157133 | V10: 100.934 | W10: -236.58943 | X10: 62.878482 | Y10: 92.797868 | Z10: 144.29 | AA10: 232.29071 | AB10: 0 | AC10: 0 | AD10: 0 | AE10: 0 | AF10: 0 | AG10: 0 | AH10: 0 | AI10: 0 | AJ10: 0 | AK10: 0 | AL10: 0 | AM10: 0 | AN10: 0 | AP10: =SUM(AB10:AN10)+Q10 -> 1.197927
A11: 934.5534 | B11: 28 | C11: 13 | D11: 12.373254 | E11: 26 | F11: 13 | G11: 0.77161039 | H11: 28 | I11: 12 | J11: 1.1492731 | K11: 5.1066995e+08 | L11: 54484500 | M11: 79700411 | N11: 71893800 | O11: 15891981 | P11: 226.00118 | Q11: 1.193889 | R11: 43.633828 | S11: 780.15627 | T11: 4.25925e-17 | U11: 19.16775 | V11: 100.934 | W11: -238.28188 | X11: 62.831502 | Y11: 92.40473 | Z11: 180.981 | AA11: 230.87048 | AB11: 0 | AC11: 0 | AD11: 0 | AE11: 0 | AF11: 0 | AG11: 0 | AH11: 0 | AI11: 0 | AJ11: 0 | AK11: 0 | AL11: 0 | AM11: 0 | AN11: 0 | AP11: =SUM(AB11:AN11)+Q11 -> 1.193889
A12: 925.04123 | B12: 32 | C12: 11 | D12: 12.858003 | E12: 15 | F12: 8 | G12: 0.47594915 | H12: 25 | I12: 9 | J12: 0.64647931 | K12: 5.1018103e+08 | L12: 54455500 | M12: 79688627 | N12: 71387800 | O12: 15888370 | P12: 226.1302 | Q12: 1.2010517 | R12: 43.595892 | S12: 779.66249 | T12: 5.6683459e-12 | U12: 19.335739 | V12: 100.934 | W12: -239.47823 | X12: 62.846381 | Y12: 92.29674 | Z12: 165.7 | AA12: 231.5855 | AB12: 0 | AC12: 0 | AD12: 0 | AE12: 0 | AF12: 0 | AG12: 0 | AH12: 0 | AI12: 0 | AJ12: 0 | AK12: 0 | AL12: 0 | AM12: 0 | AN12: 0 | AP12: =SUM(AB12:AN12)+Q12 -> 1.2010517
A13: 935.12603 | B13: 30 | C13: 10 | D13: 6.7742024 | E13: 21 | F13: 7 | G13: 0.81573169 | H13: 23 | I13: 10 | J13: 0.68271343 | K13: 5.0961668e+08 | L13: 54466400 | M13: 79701210 | N13: 71991600 | O13: 15889309 | P13: 226.13389 | Q13: 1.187764 | R13: 43.637992 | S13: 780.07427 | T13: 1.0669796e-11 | U13: 19.281234 | V13: 100.934 | W13: -237.08673 | X13: 62.832688 | Y13: 92.476133 | Z13: 180.981 | AA13: 231.95348 | AB13: 0 | AC13: 0 | AD13: 0 | AE13: 0 | AF13: 0 | AG13: 0 | AH13: 0 | AI13: 0 | AJ13: 0 | AK13: 0 | AL13: 0 | AM13: 0 | AN13: 0 | AP13: =SUM(AB13:AN13)+Q13 -> 1.187764
... A122: 913.85289 | B122: 39 | C122: 15 | D122: 14.337636 | E122: 15 | F122: 5 | G122: 0.51508707 | H122: 18 | I122: 9 | J122: 0.8126411 | K122: 5.1077268e+08 | L122: 54462600 | M122: 79678740 | N122: 71454500 | O122: 15897265 | P122: 225.15531 | Q122: 1.2068674 | R122: 43.636206 | S122: 779.90531 | T122: 1.8185195e-09 | U122: 19.540354 | V122: 100.934 | W122: -238.39858 | X122: 62.858586 | Y122: 92.088968 | Z122: 177.97 | AA122: 231.93897 | AB122: 0 | AC122: 0 | AD122: 0 | AE122: 0 | AF122: 0 | AG122: 0 | AH122: 0 | AI122: 0 | AJ122: 0 | AK122: 0 | AL122: 0 | AM122: 0 | AN122: 0 | AP122: =SUM(AB122:AN122)+Q122 -> 1.2068674

Sheet 20250602_094223
A1: PYROTEMP | B1: GAS.N | C1: GAS.F | D1: GAS.RR | E1: SAF.N | F1: SAF.F | G1: SAF.RR | H1: DSL.N | I1: DSL.F | J1: DSL.RR | K1: TCC | L1: TOC | M1: TRC | N1: TPS | O1: TUC | P1: SAF | Q1: MJSP | R1: LHV | S1: SG | T1: SLF | U1: ARM | V1: MBP | W1: MFP | X1: GT10 | Y1: GT90 | Z1: DFP | AA1: DT90 | AB1: ERRSIM | AC1: ERR_0 | AD1: ERR_1 | AE1: ERR_2 | AF1: ERR_3 | AG1: ERR_4 | AH1: ERR_5 | AI1: ERR_6 | AJ1: ERR_7 | AK1: ERR_8 | AL1: ERR_9 | AM1: ERR_10 | AN1: ERR_11
A2: 930 | B2: 30 | C2: 18 | D2: 2.95 | E2: 20 | F2: 12 | G2: 0.56748 | H2: 20 | I2: 12 | J2: 1.4 | K2: 5.0873362e+08 | L2: 54426700 | M2: 79694819 | N2: 54566700 | O2: 15885043 | P2: 210.83243 | Q2: 1.6351299 | R2: 43.636126 | S2: 779.72034 | T2: 2.9525345e-12 | U2: 19.33049 | V2: 91.85 | W2: -239.19747 | X2: 62.838961 | Y2: 92.781374 | Z2: 177.97 | AA2: 231.50352 | AB2: 0 | AC2: 0 | AD2: 0 | AE2: 0 | AF2: 0 | AG2: 0 | AH2: 0 | AI2: 0 | AJ2: 0 | AK2: 0 | AL2: 0 | AM2: 0 | AN2: 0 | AP2: =SUM(AB2:AN2)+Q2 -> 1.6351299
A3: 949.18259 | B3: 28 | C3: 12 | D3: 1.1753461 | E3: 14 | F3: 9 | G3: 0.78809415 | H3: 14 | I3: 10 | J3: 1.1305654 | K3: 5.0860951e+08 | L3: 54446800 | M3: 79719186 | N3: 55109300 | O3: 15894035 | P3: 210.64974 | Q3: 1.6251986 | R3: 43.548725 | S3: 780.29876 | T3: 3.0829349e-13 | U3: 19.274027 | V3: 80.72 | W3: -172.6729 | X3: 62.987199 | Y3: 94.390744 | Z3: 144.29 | AA3: 231.57482 | AB3: 0 | AC3: 0 | AD3: 0 | AE3: 0 | AF3: 0 | AG3: 0 | AH3: 0 | AI3: 0 | AJ3: 0 | AK3: 0 | AL3: 0 | AM3: 0 | AN3: 0 | AP3: =SUM(AB3:AN3)+Q3 -> 1.6251986
A4: 938.24477 | B4: 30 | C4: 16 | D4: 9.3469501 | E4: 19 | F4: 9 | G4: 0.49935054 | H4: 16 | I4: 13 | J4: 0.69234796 | K4: 5.0969991e+08 | L4: 54481000 | M4: 79705205 | N4: 54767600 | O4: 15892413 | P4: 211.84304 | Q4: 1.6273711 | R4: 43.626227 | S4: 779.57988 | T4: 5.5603498e-13 | U4: 19.311314 | V4: 100.934 | W4: -238.95107 | X4: 62.847553 | Y4: 92.408772 | Z4: 177.97 | AA4: 234.0473 | AB4: 0 | AC4: 0 | AD4: 0 | AE4: 0 | AF4: 0 | AG4: 0 | AH4: 0 | AI4: 0 | AJ4: 0 | AK4: 0 | AL4: 0 | AM4: 0 | AN4: 0 | AP4: =SUM(AB4:AN4)+Q4 -> 1.6273711
A5: 953.83873 | B5: 36 | C5: 19 | D5: 8.6951146 | E5: 19 | F5: 10 | G5: 1.1897507 | H5: 19 | I5: 7 | J5: 1.1660761 | K5: 5.1047096e+08 | L5: 54515200 | M5: 79721883 | N5: 54978000 | O5: 15918404 | P5: 212.34342 | Q5: 1.6223383 | R5: 43.633361 | S5: 780.47978 | T5: 1.1187977e-14 | U5: 19.182357 | V5: 100.934 | W5: -238.86208 | X5: 62.804239 | Y5: 92.261509 | Z5: 177.97 | AA5: 231.45799 | AB5: 0 | AC5: 0 | AD5: 0 | AE5: 0 | AF5: 0 | AG5: 0 | AH5: 0 | AI5: 0 | AJ5: 0 | AK5: 0 | AL5: 0 | AM5: 0 | AN5: 0 | AP5: =SUM(AB5:AN5)+Q5 -> 1.6223383
A6: 954.7892 | B6: 29 | C6: 11 | D6: 10.23591 | E6: 10 | F6: 8 | G6: 0.93073004 | H6: 14 | I6: 9 | J6: 1.2764627 | K6: 5.1043827e+08 | L6: 54498200 | M6: 79722481 | N6: 53753700 | O6: 15919831 | P6: 213.89957 | Q6: 1.6353474 | R6: 43.466079 | S6: 780.39368 | T6: 3.0563103e-12 | U6: 18.863848 | V6: 100.934 | W6: -240.54022 | X6: 62.81314 | Y6: 92.400079 | Z6: 100.934 | AA6: 229.62634 | AB6: 0 | AC6: 0 | AD6: 0 | AE6: 0 | AF6: 0 | AG6: 0 | AH6: 0 | AI6: 0 | AJ6: 0 | AK6: 0 | AL6: 0 | AM6: 0 | AN6: 0 | AP6: =SUM(AB6:AN6)+Q6 -> 1.6353474
A7: 941.9015 | B7: 33 | C7: 16 | D7: 11.327322 | E7: 15 | F7: 8 | G7: 0.70816342 | H7: 28 | I7: 7 | J7: 0.33617782 | K7: 5.1073678e+08 | L7: 54525400 | M7: 79714604 | N7: 54743300 | O7: 15896436 | P7: 211.60435 | Q7: 1.6339663 | R7: 43.60934 | S7: 779.8735 | T7: 2.1726649e-12 | U7: 19.287391 | V7: 100.934 | W7: -238.42951 | X7: 62.783484 | Y7: 92.258207 | Z7: 165.7 | AA7: 234.54223 | AB7: 0 | AC7: 0 | AD7: 0 | AE7: 0 | AF7: 0 | AG7: 0 | AH7: 0 | AI7: 0 | AJ7: 0 | AK7: 0 | AL7: 0 | AM7: 0 | AN7: 0 | AP7: =SUM(AB7:AN7)+Q7 -> 1.6339663
A8: 927.54872 | B8: 38 | C8: 13 | D8: 12.538485 | E8: 28 | F8: 12 | G8: 0.43001855 | H8: 27 | I8: 8 | J8: 0.80715636 | K8: 5.1074973e+08 | L8: 54512200 | M8: 79691923 | N8: 54545700 | O8: 15889126 | P8: 210.80476 | Q8: 1.6440672 | R8: 43.64066 | S8: 779.51778 | T8: 2.0676307e-15 | U8: 19.329821 | V8: 100.934 | W8: -237.43809 | X8: 62.841622 | Y8: 92.134947 | Z8: 180.981 | AA8: 231.79146 | AB8: 0 | AC8: 0 | AD8: 0 | AE8: 0 | AF8: 0 | AG8: 0 | AH8: 0 | AI8: 0 | AJ8: 0 | AK8: 0 | AL8: 0 | AM8: 0 | AN8: 0 | AP8: =SUM(AB8:AN8)+Q8 -> 1.6440672
A9: 946.31129 | B9: 38 | C9: 10 | D9: 3.1409269 | E9: 12 | F9: 8 | G9: 0.438867 | H9: 28 | I9: 9 | J9: 0.75662014 | K9: 5.0958724e+08 | L9: 54496000 | M9: 79715091 | N9: 53998800 | O9: 15893243 | P9: 212.93797 | Q9: 1.6348926 | R9: 43.505299 | S9: 780.05409 | T9: 1.0536847e-11 | U9: 19.192634 | V9: 100.934 | W9: -237.41332 | X9: 62.822727 | Y9: 92.7097 | Z9: 121.522 | AA9: 230.21755 | AB9: 0 | AC9: 0 | AD9: 0 | AE9: 0 | AF9: 0 | AG9: 0 | AH9: 0 | AI9: 0 | AJ9: 0 | AK9: 0 | AL9: 0 | AM9: 0 | AN9: 0 | AP9: =SUM(AB9:AN9)+Q9 -> 1.6348926
A10: 916.74353 | B10: 36 | C10: 10 | D10: 8.8082325 | E10: 20 | F10: 7 | G10: 0.89330792 | H10: 26 | I10: 9 | J10: 0.75484308 | K10: 5.1017321e+08 | L10: 54461300 | M10: 79682235 | N10: 54332100 | O10: 15895125 | P10: 210.08998 | Q10: 1.6512164 | R10: 43.638735 | S10: 780.06872 | T10: 9.408178e-12 | U10: 19.262033 | V10: 100.934 | W10: -237.32924 | X10: 62.855538 | Y10: 92.28595 | Z10: 180.981 | AA10: 231.64706 | AB10: 0 | AC10: 0 | AD10: 0 | AE10: 0 | AF10: 0 | AG10: 0 | AH10: 0 | AI10: 0 | AJ10: 0 | AK10: 0 | AL10: 0 | AM10: 0 | AN10: 0 | AP10: =SUM(AB10:AN10)+Q10 -> 1.6512164
A11: 921.80942 | B11: 27 | C11: 19 | D11: 3.2858724 | E11: 17 | F11: 11 | G11: 0.82763085 | H11: 14 | I11: 10 | J11: 0.7611326 | K11: 5.0823845e+08 | L11: 54419200 | M11: 79688127 | N11: 54344700 | O11: 15893816 | P11: 210.53093 | Q11: 1.6403725 | R11: 43.610573 | S11: 779.71065 | T11: 3.243157e-11 | U11: 19.152465 | V11: 80.72 | W11: -243.42582 | X11: 62.857774 | Y11: 92.838609 | Z11: 165.7 | AA11: 232.75054 | AB11: 0 | AC11: 0 | AD11: 0 | AE11: 0 | AF11: 0 | AG11: 0 | AH11: 0 | AI11: 0 | AJ11: 0 | AK11: 0 | AL11: 0 | AM11: 0 | AN11: 0 | AP11: =SUM(AB11:AN11)+Q11 -> 1.6403725
A12: 957.4442 | B12: 31 | C12: 14 | D12: 1.8905868 | E12: 24 | F12: 8 | G12: 0.44414667 | H12: 29 | I12: 13 | J12: 1.0424229 | K12: 5.040117e+08 | L12: 54419200 | M12: 79688202 | N12: 54344700 | O12: 16376900 | P12: 204.64776 | Q12: 1.6735086 | R12: 43.638097 | S12: 779.82261 | T12: 4.9909084e-12 | U12: 19.424631 | V12: 91.85 | W12: -230.97038 | X12: 62.919982 | Y12: 93.099866 | Z12: 180.981 | AA12: 231.19336 | AB12: 100 | AC12: 0 | AD12: 0 | AE12: 0 | AF12: 0 | AG12: 0 | AH12: 0 | AI12: 0 | AJ12: 0 | AK12: 0 | AL12: 0 | AM12: 0 | AN12: 0 | AP12: =SUM(AB12:AN12)+Q12 -> 101.67351
A13: 944.26398 | B13: 27 | C13: 15 | D13: 13.858453 | E13: 27 | F13: 12 | G13: 1.0030608 | H13: 17 | I13: 13 | J13: 1.284956 | K13: 5.110019e+08 | L13: 54491700 | M13: 79712795 | N13: 54874600 | O13: 15897829 | P13: 211.75788 | Q13: 1.630192 | R13: 43.638951 | S13: 780.71722 | T13: 1.5351652e-16 | U13: 19.160389 | V13: 100.934 | W13: -239.06403 | X13: 62.821607 | Y13: 92.423269 | Z13: 180.981 | AA13: 231.9992 | AB13: 0 | AC13: 0 | AD13: 0 | AE13: 0 | AF13: 0 | AG13: 0 | AH13: 0 | AI13: 0 | AJ13: 0 | AK13: 0 | AL13: 0 | AM13: 0 | AN13: 0 | AP13: =SUM(AB13:AN13)+Q13 -> 1.630192
... A72: 910 | B72: 27 | C72: 10 | D72: 1 | E72: 10 | F72: 5 | G72: 1.2 | H72: 15 | I72: 13 | J72: 0.3 | K72: 5.0785842e+08 | L72: 54390300 | M72: 79693767 | N72: 54940200 | O72: 15895612 | P72: 205.72013 | Q72: 1.6640804 | R72: 43.573 | S72: 780.25937 | T72: 5.9146445e-10 | U72: 19.407733 | V72: 80.72 | W72: -149.05364 | X72: 63.052139 | Y72: 94.909849 | Z72: 144.29 | AA72: 238.82943 | AB72: 0 | AC72: 0 | AD72: 0 | AE72: 0 | AF72: 0 | AG72: 0 | AH72: 0 | AI72: 0 | AJ72: 0 | AK72: 0 | AL72: 0 | AM72: 0 | AN72: 0 | AP72: =SUM(AB72:AN72)+Q72 -> 1.6640804

Sheet 20250601_211036_BO_LCOgas
A1: PYROTEMP | B1: GAS.N | C1: GAS.F | D1: GAS.RR | E1: SAF.N | F1: SAF.F | G1: SAF.RR | H1: DSL.N | I1: DSL.F | J1: DSL.RR | K1: TCC | L1: TOC | M1: TRC | N1: TPS | O1: TUC | P1: SAF | Q1: MJSP | R1: LHV | S1: SG | T1: SLF | U1: ARM | V1: MBP | W1: MFP | X1: GT10 | Y1: GT90 | Z1: DFP | AA1: DT90 | AB1: ERRSIM | AC1: ERR_0 | AD1: ERR_1 | AE1: ERR_2 | AF1: ERR_3 | AG1: ERR_4 | AH1: ERR_5 | AI1: ERR_6 | AJ1: ERR_7 | AK1: ERR_8 | AL1: ERR_9 | AM1: ERR_10 | AN1: ERR_11
A2: 930 | B2: 30 | C2: 15 | D2: 2.95 | E2: 20 | F2: 12 | G2: 0.56748 | H2: 20 | I2: 12 | J2: 1.4 | K2: 5.0875118e+08 | L2: 54426600 | M2: 79694719 | N2: 148888000 | O2: 15885042 | P2: 211.09205 | Q2: -0.33926643 | R2: 43.608097 | S2: 779.54591 | T2: 1.0407078e-15 | U2: 19.207163 | V2: 91.85 | W2: -238.80564 | X2: 62.840801 | Y2: 92.75942 | Z2: 165.7 | AA2: 231.17584 | AB2: 0 | AC2: 0 | AD2: 0 | AE2: 0 | AF2: 0 | AG2: 0 | AH2: 0 | AI2: 0 | AJ2: 0 | AK2: 0 | AL2: 0 | AM2: 0 | AN2: 0 | AO2: =SUM(AB2:AN2)+Q2 -> -0.33926643
A3: 935.61483 | B3: 34 | C3: 14 | D3: 8.3883608 | E3: 19 | F3: 6 | G3: 0.51441569 | H3: 23 | I3: 14 | J3: 0.31617107 | K3: 5.0977513e+08 | L3: 54488800 | M3: 79707015 | N3: 149237000 | O3: 15891766 | P3: 210.93363 | Q3: -0.34222786 | R3: 43.641509 | S3: 779.96828 | T3: 2.164078e-10 | U3: 19.496817 | V3: 100.934 | W3: -237.15727 | X3: 62.794705 | Y3: 92.294169 | Z3: 177.97 | AA3: 235.62688 | AB3: 0 | AC3: 0 | AD3: 0 | AE3: 0 | AF3: 0 | AG3: 0 | AH3: 0 | AI3: 0 | AJ3: 0 | AK3: 0 | AL3: 0 | AM3: 0 | AN3: 0 | AO3: =SUM(AB3:AN3)+Q3 -> -0.34222786
A4: 944.70076 | B4: 31 | C4: 18 | D4: 5.2002681 | E4: 19 | F4: 6 | G4: 0.88635726 | H4: 11 | I4: 8 | J4: 0.79981637 | K4: 5.0935315e+08 | L4: 54474800 | M4: 79713594 | N4: 149855000 | O4: 15893662 | P4: 212.08603 | Q4: -0.35487341 | R4: 43.640585 | S4: 779.99351 | T4: 8.3475175e-11 | U4: 19.306044 | V4: 100.934 | W4: -238.77664 | X4: 62.834219 | Y4: 92.541323 | Z4: 180.981 | AA4: 234.10405 | AB4: 0 | AC4: 0 | AD4: 0 | AE4: 0 | AF4: 0 | AG4: 0 | AH4: 0 | AI4: 0 | AJ4: 0 | AK4: 0 | AL4: 0 | AM4: 0 | AN4: 0 | AO4: =SUM(AB4:AN4)+Q4 -> -0.35487341
A5: 922.24729 | B5: 31 | C5: 10 | D5: 9.6441614 | E5: 23 | F5: 6 | G5: 0.73515994 | H5: 28 | I5: 11 | J5: 0.34568831 | K5: 5.0994657e+08 | L5: 54488300 | M5: 79690629 | N5: 148750000 | O5: 15896341 | P5: 210.33628 | Q5: -0.33243626 | R5: 43.642619 | S5: 780.05664 | T5: 1.0768654e-10 | U5: 19.35858 | V5: 100.934 | W5: -236.9758 | X5: 62.834007 | Y5: 92.369294 | Z5: 180.981 | AA5: 234.71535 | AB5: 0 | AC5: 0 | AD5: 0 | AE5: 0 | AF5: 0 | AG5: 0 | AH5: 0 | AI5: 0 | AJ5: 0 | AK5: 0 | AL5: 0 | AM5: 0 | AN5: 0 | AO5: =SUM(AB5:AN5)+Q5 -> -0.33243626
A6: 944.63973 | B6: 34 | C6: 16 | D6: 4.3022445 | E6: 14 | F6: 8 | G6: 0.43896131 | H6: 17 | I6: 14 | J6: 0.76960871 | K6: 5.108221e+08 | L6: 54488300 | M6: 79690592 | N6: 148750000 | O6: 15894731 | P6: 212.82082 | Q6: -0.32576253 | R6: 43.572685 | S6: 779.69656 | T6: 7.8187654e-12 | U6: 19.31058 | V6: 100.934 | W6: -241.10422 | X6: 62.839004 | Y6: 92.537477 | Z6: 144.29 | AA6: 232.69446 | AB6: 100 | AC6: 0 | AD6: 0 | AE6: 0 | AF6: 0 | AG6: 0 | AH6: 0 | AI6: 0 | AJ6: 0 | AK6: 0 | AL6: 0 | AM6: 0 | AN6: 0 | AO6: =SUM(AB6:AN6)+Q6 -> 99.674237
A7: 930.30252 | B7: 34 | C7: 12 | D7: 8.8429776 | E7: 20 | F7: 5 | G7: 0.7019769 | H7: 14 | I7: 11 | J7: 0.86347187 | K7: 5.0965745e+08 | L7: 54457800 | M7: 79695218 | N7: 149106000 | O7: 15888451 | P7: 211.00741 | Q7: -0.34039478 | R7: 43.647512 | S7: 779.93417 | T7: 1.0452206e-09 | U7: 19.42948 | V7: 100.934 | W7: -237.7719 | X7: 62.855003 | Y7: 92.31801 | Z7: 180.981 | AA7: 233.7377 | AB7: 0 | AC7: 0 | AD7: 0 | AE7: 0 | AF7: 0 | AG7: 0 | AH7: 0 | AI7: 0 | AJ7: 0 | AK7: 0 | AL7: 0 | AM7: 0 | AN7: 0 | AO7: =SUM(AB7:AN7)+Q7 -> -0.34039478
A8: 915.62533 | B8: 28 | C8: 17 | D8: 7.840218 | E8: 24 | F8: 12 | G8: 0.78857788 | H8: 14 | I8: 7 | J8: 0.96624996 | K8: 5.0953979e+08 | L8: 54442200 | M8: 79680837 | N8: 148316000 | O8: 15894349 | P8: 210.0105 | Q8: -0.32611334 | R8: 43.63402 | S8: 780.09011 | T8: 5.1110428e-14 | U8: 19.171411 | V8: 91.85 | W8: -238.69583 | X8: 62.857389 | Y8: 92.509062 | Z8: 180.981 | AA8: 232.27784 | AB8: 0 | AC8: 0 | AD8: 0 | AE8: 0 | AF8: 0 | AG8: 0 | AH8: 0 | AI8: 0 | AJ8: 0 | AK8: 0 | AL8: 0 | AM8: 0 | AN8: 0 | AO8: =SUM(AB8:AN8)+Q8 -> -0.32611334
A9: 918.93668 | B9: 35 | C9: 13 | D9: 13.721937 | E9: 10 | F9: 5 | G9: 0.79617413 | H9: 25 | I9: 11 | J9: 0.98364838 | K9: 5.1076992e+08 | L9: 54467900 | M9: 79684532 | N9: 148334000 | O9: 15898276 | P9: 210.67209 | Q9: -0.32096402 | R9: 43.584117 | S9: 779.85605 | T9: 1.1693506e-09 | U9: 19.362917 | V9: 100.934 | W9: -239.9759 | X9: 62.850872 | Y9: 92.202845 | Z9: 144.29 | AA9: 230.59808 | AB9: 0 | AC9: 0 | AD9: 0 | AE9: 0 | AF9: 0 | AG9: 0 | AH9: 0 | AI9: 0 | AJ9: 0 | AK9: 0 | AL9: 0 | AM9: 0 | AN9: 0 | AO9: =SUM(AB9:AN9)+Q9 -> -0.32096402
A10: 919.83854 | B10: 31 | C10: 10 | D10: 7.4307963 | E10: 25 | F10: 5 | G10: 0.62297793 | H10: 18 | I10: 13 | J10: 1.0445799 | K10: 5.0956773e+08 | L10: 54450900 | M10: 79685931 | N10: 148607000 | O10: 15895315 | P10: 210.28934 | Q10: -0.33151671 | R10: 43.649642 | S10: 780.01918 | T10: 1.2212444e-09 | U10: 19.470893 | V10: 100.934 | W10: -236.83448 | X10: 62.854824 | Y10: 92.438537 | Z10: 203.285 | AA10: 232.40666 | AB10: 0 | AC10: 0 | AD10: 0 | AE10: 0 | AF10: 0 | AG10: 0 | AH10: 0 | AI10: 0 | AJ10: 0 | AK10: 0 | AL10: 0 | AM10: 0 | AN10: 0 | AO10: =SUM(AB10:AN10)+Q10 -> -0.33151671
A11: 924.82816 | B11: 33 | C11: 15 | D11: 7.1606767 | E11: 14 | F11: 8 | G11: 0.95768226 | H11: 18 | I11: 7 | J11: 0.94874752 | K11: 5.0914383e+08 | L11: 54434900 | M11: 79688427 | N11: 148588000 | O11: 15885327 | P11: 210.67766 | Q11: -0.3322087 | R11: 43.610601 | S11: 779.88762 | T11: 1.3714981e-12 | U11: 19.207634 | V11: 100.934 | W11: -239.0008 | X11: 62.846648 | Y11: 92.38342 | Z11: 165.7 | AA11: 231.50266 | AB11: 0 | AC11: 0 | AD11: 0 | AE11: 0 | AF11: 0 | AG11: 0 | AH11: 0 | AI11: 0 | AJ11: 0 | AK11: 0 | AL11: 0 | AM11: 0 | AN11: 0 | AO11: =SUM(AB11:AN11)+Q11 -> -0.3322087
A12: 925.30672 | B12: 30 | C12: 17 | D12: 14.887077 | E12: 15 | F12: 5 | G12: 1.032683 | H12: 25 | I12: 8 | J12: 1.1672921 | K12: 5.1056711e+08 | L12: 54472300 | M12: 79689026 | N12: 148659000 | O12: 15889522 | P12: 210.54167 | Q12: -0.32853865 | R12: 43.637477 | S12: 779.92298 | T12: 6.7855628e-10 | U12: 19.367597 | V12: 100.934 | W12: -238.12184 | X12: 62.845516 | Y12: 92.338058 | Z12: 177.97 | AA12: 231.19434 | AB12: 0 | AC12: 0 | AD12: 0 | AE12: 0 | AF12: 0 | AG12: 0 | AH12: 0 | AI12: 0 | AJ12: 0 | AK12: 0 | AL12: 0 | AM12: 0 | AN12: 0 | AO12: =SUM(AB12:AN12)+Q12 -> -0.32853865
A13: 912.02452 | B13: 33 | C13: 17 | D13: 6.7692281 | E13: 21 | F13: 12 | G13: 0.51240674 | H13: 20 | I13: 11 | J13: 1.0754204 | K13: 5.094245e+08 | L13: 54440800 | M13: 79676543 | N13: 148192000 | O13: 15892905 | P13: 210.05732 | Q13: -0.32383685 | R13: 43.615602 | S13: 779.46953 | T13: 1.3649586e-15 | U13: 19.23664 | V13: 100.934 | W13: -238.59966 | X13: 62.862077 | Y13: 92.412348 | Z13: 177.97 | AA13: 231.51781 | AB13: 0 | AC13: 0 | AD13: 0 | AE13: 0 | AF13: 0 | AG13: 0 | AH13: 0 | AI13: 0 | AJ13: 0 | AK13: 0 | AL13: 0 | AM13: 0 | AN13: 0 | AO13: =SUM(AB13:AN13)+Q13 -> -0.32383685
... A121: 936.77945 | B121: 29 | C121: 13 | D121: 6.8526134 | E121: 17 | F121: 7 | G121: 0.9750543 | H121: 29 | I121: 9 | J121: 0.96750926 | K121: 5.0955467e+08 | L121: 54468600 | M121: 79703208 | N121: 149222000 | O121: 15890136 | P121: 211.35201 | Q121: -0.34236713 | R121: 43.633343 | S121: 780.04715 | T121: 8.9289103e-12 | U121: 19.262423 | V121: 100.934 | W121: -238.13334 | X121: 62.828471 | Y121: 92.480888 | Z121: 177.97 | AA121: 231.25243 | AB121: 0 | AC121: 0 | AD121: 0 | AE121: 0 | AF121: 0 | AG121: 0 | AH121: 0 | AI121: 0 | AJ121: 0 | AK121: 0 | AL121: 0 | AM121: 0 | AN121: 0 | AO121: =SUM(AB121:AN121)+Q121 -> -0.34236713

Sheet 20250602_012254_BO_LCOdiesel
A1: PYROTEMP | B1: GAS.N | C1: GAS.F | D1: GAS.RR | E1: SAF.N | F1: SAF.F | G1: SAF.RR | H1: DSL.N | I1: DSL.F | J1: DSL.RR | K1: TCC | L1: TOC | M1: TRC | N1: TPS | O1: TUC | P1: SAF | Q1: MJSP | R1: LHV | S1: SG | T1: SLF | U1: ARM | V1: MBP | W1: MFP | X1: GT10 | Y1: GT90 | Z1: DFP | AA1: DT90 | AB1: ERRSIM | AC1: ERR_0 | AD1: ERR_1 | AE1: ERR_2 | AF1: ERR_3 | AG1: ERR_4 | AH1: ERR_5 | AI1: ERR_6 | AJ1: ERR_7 | AK1: ERR_8 | AL1: ERR_9 | AM1: ERR_10 | AN1: ERR_11
A2: 930 | B2: 30 | C2: 18 | D2: 2.95 | E2: 20 | F2: 12 | G2: 0.56748 | H2: 20 | I2: 12 | J2: 1.4 | K2: 5.0875145e+08 | L2: 54426600 | M2: 79694719 | N2: 156936000 | O2: 15885037 | P2: 94.298784 | Q2: -1.1362064 | R2: 43.610077 | S2: 779.51589 | T2: 1.4472486e-13 | U2: 19.210471 | V2: 91.85 | W2: -240.1279 | X2: 62.839121 | Y2: 92.781455 | Z2: 165.7 | AA2: 231.15929 | AB2: 99 | AC2: 0 | AD2: 0 | AE2: 0 | AF2: 0 | AG2: 0 | AH2: 0 | AI2: 0 | AJ2: 0 | AK2: 0 | AL2: 0 | AM2: 0 | AN2: 0
A3: 914.89571 | B3: 39 | C3: 13 | D3: 9.1381903 | E3: 16 | F3: 6 | G3: 0.63085039 | H3: 19 | I3: 12 | J3: 1.3879705 | K3: 5.1014974e+08 | L3: 54447900 | M3: 79679938 | N3: 156212000 | O3: 15894821 | P3: 94.360656 | Q3: -1.0905354 | R3: 43.634199 | S3: 779.78195 | T3: 1.5620718e-10 | U3: 19.38877 | V3: 100.934 | W3: -237.98273 | X3: 62.857627 | Y3: 92.190847 | Z3: 177.97 | AA3: 231.53674 | AB3: 0 | AC3: 0 | AD3: 0 | AE3: 0 | AF3: 0 | AG3: 0 | AH3: 0 | AI3: 0 | AJ3: 0 | AK3: 0 | AL3: 0 | AM3: 0 | AN3: 0
A4: 951.22876 | B4: 38 | C4: 14 | D4: 4.1479064 | E4: 12 | F4: 6 | G4: 0.91862434 | H4: 13 | I4: 8 | J4: 0.48774938 | K4: 5.0938772e+08 | L4: 54484400 | M4: 79722383 | N4: 158276000 | O4: 15897037 | P4: 95.209731 | Q4: -1.1802471 | R4: 43.607445 | S4: 779.83715 | T4: 1.0180268e-10 | U4: 19.300985 | V4: 100.934 | W4: -239.0944 | X4: 62.815063 | Y4: 92.479574 | Z4: 165.7 | AA4: 233.68184 | AB4: 0 | AC4: 0 | AD4: 0 | AE4: 0 | AF4: 0 | AG4: 0 | AH4: 0 | AI4: 0 | AJ4: 0 | AK4: 0 | AL4: 0 | AM4: 0 | AN4: 0
A5: 914.96843 | B5: 39 | C5: 13 | D5: 9.0314991 | E5: 16 | F5: 6 | G5: 0.70403299 | H5: 19 | I5: 12 | J5: 1.244523 | K5: 5.09981e+08 | L5: 54447100 | M5: 79680038 | N5: 156210000 | O5: 15894785 | P5: 94.384528 | Q5: -1.0914171 | R5: 43.634776 | S5: 779.80156 | T5: 1.2950579e-10 | U5: 19.361268 | V5: 100.934 | W5: -237.92605 | X5: 62.857779 | Y5: 92.194223 | Z5: 177.97 | AA5: 231.61806 | AB5: 0 | AC5: 0 | AD5: 0 | AE5: 0 | AF5: 0 | AG5: 0 | AH5: 0 | AI5: 0 | AJ5: 0 | AK5: 0 | AL5: 0 | AM5: 0 | AN5: 0
A6: 960 | B6: 27 | C6: 19 | D6: 1 | E6: 29 | F6: 14 | G6: 1.2 | H6: 29 | I6: 7 | J6: 0.3 | K6: 5.0606074e+08 | L6: 54447100 | M6: 79680110 | N6: 156210000 | O6: 16378329 | P6: 96.8248 | Q6: -1.0913958 | R6: 43.6831 | S6: 781.02385 | T6: 2.4026432e-09 | U6: 19.74118 | V6: 68.71 | W6: -167.59892 | X6: 63.102435 | Y6: 95.092418 | Z6: 180.981 | AA6: 233.92085 | AB6: 100 | AC6: 0 | AD6: 0 | AE6: 0 | AF6: 0 | AG6: 0 | AH6: 0 | AI6: 0 | AJ6: 0 | AK6: 0 | AL6: 0 | AM6: 0 | AN6: 0
A7: 935.39943 | B7: 39 | C7: 10 | D7: 15 | E7: 10 | F7: 5 | G7: 0.3 | H7: 10 | I7: 7 | J7: 0.3 | K7: 5.1073029e+08 | L7: 54497700 | M7: 79711121 | N7: 157524000 | O7: 15897150 | P7: 92.300122 | Q7: -1.1709768 | R7: 43.524059 | S7: 780.69154 | T7: 6.8068942e-09 | U7: 19.584909 | V7: 100.934 | W7: -242.38264 | X7: 62.829746 | Y7: 92.085296 | Z7: 144.29 | AA7: 236.25545 | AB7: 0 | AC7: 0 | AD7: 0 | AE7: 0 | AF7: 0 | AG7: 0 | AH7: 0 | AI7: 0 | AJ7: 0 | AK7: 0 | AL7: 0 | AM7: 0 | AN7: 0
A8: 950.74062 | B8: 33 | C8: 15 | D8: 7.540875 | E8: 24 | F8: 5 | G8: 0.90517361 | H8: 22 | I8: 10 | J8: 0.9615591 | K8: 5.1035119e+08 | L8: 54515200 | M8: 79721484 | N8: 157985000 | O8: 15898344 | P8: 95.782304 | Q8: -1.1515323 | R8: 43.645408 | S8: 780.21215 | T8: 7.032687e-10 | U8: 19.383182 | V8: 100.934 | W8: -237.98171 | X8: 62.805248 | Y8: 92.35377 | Z8: 203.285 | AA8: 231.55464 | AB8: 0 | AC8: 0 | AD8: 0 | AE8: 0 | AF8: 0 | AG8: 0 | AH8: 0 | AI8: 0 | AJ8: 0 | AK8: 0 | AL8: 0 | AM8: 0 | AN8: 0
A9: 950.14223 | B9: 34 | C9: 19 | D9: 12.177773 | E9: 25 | F9: 10 | G9: 0.55443503 | H9: 29 | I9: 11 | J9: 1.0010834 | K9: 5.1115821e+08 | L9: 54548500 | M9: 79720685 | N9: 158045000 | O9: 15900429 | P9: 95.609426 | Q9: -1.1491171 | R9: 43.637279 | S9: 779.76629 | T9: 4.7335781e-14 | U9: 19.277283 | V9: 100.934 | W9: -237.95389 | X9: 62.805716 | Y9: 92.245155 | Z9: 180.981 | AA9: 231.22068 | AB9: 0 | AC9: 0 | AD9: 0 | AE9: 0 | AF9: 0 | AG9: 0 | AH9: 0 | AI9: 0 | AJ9: 0 | AK9: 0 | AL9: 0 | AM9: 0 | AN9: 0
A10: 954.62574 | B10: 34 | C10: 16 | D10: 12.69578 | E10: 21 | F10: 13 | G10: 0.71172181 | H10: 20 | I10: 13 | J10: 1.0532753 | K10: 5.1119623e+08 | L10: 54532300 | M10: 79722982 | N10: 158225000 | O10: 15921003 | P10: 95.177695 | Q10: -1.1631582 | R10: 43.616399 | S10: 779.8171 | T10: 7.2766777e-17 | U10: 19.165056 | V10: 100.934 | W10: -238.91224 | X10: 62.804083 | Y10: 92.227633 | Z10: 177.97 | AA10: 231.57654 | AB10: 0 | AC10: 0 | AD10: 0 | AE10: 0 | AF10: 0 | AG10: 0 | AH10: 0 | AI10: 0 | AJ10: 0 | AK10: 0 | AL10: 0 | AM10: 0 | AN10: 0
A11: 914.22755 | B11: 34 | C11: 18 | D11: 9.1730086 | E11: 22 | F11: 13 | G11: 0.47312371 | H11: 20 | I11: 7 | J11: 1.3960807 | K11: 5.100438e+08 | L11: 54447000 | M11: 79679139 | N11: 156294000 | O11: 15894668 | P11: 93.915297 | Q11: -1.1003692 | R11: 43.613374 | S11: 779.41341 | T11: 2.5278396e-16 | U11: 19.247982 | V11: 100.934 | W11: -238.69099 | X11: 62.858004 | Y11: 92.315551 | Z11: 177.97 | AA11: 231.31192 | AB11: 0 | AC11: 0 | AD11: 0 | AE11: 0 | AF11: 0 | AG11: 0 | AH11: 0 | AI11: 0 | AJ11: 0 | AK11: 0 | AL11: 0 | AM11: 0 | AN11: 0
A12: 919.00315 | B12: 38 | C12: 17 | D12: 8.4748484 | E12: 26 | F12: 8 | G12: 0.661668 | H12: 20 | I12: 14 | J12: 0.97235318 | K12: 5.1003764e+08 | L12: 54464300 | M12: 79684932 | N12: 156391000 | O12: 15895601 | P12: 94.754164 | Q12: -1.0943847 | R12: 43.641352 | S12: 779.95281 | T12: 1.8142545e-12 | U12: 19.271638 | V12: 100.934 | W12: -237.80132 | X12: 62.852585 | Y12: 92.231701 | Z12: 180.981 | AA12: 232.1465 | AB12: 0 | AC12: 0 | AD12: 0 | AE12: 0 | AF12: 0 | AG12: 0 | AH12: 0 | AI12: 0 | AJ12: 0 | AK12: 0 | AL12: 0 | AM12: 0 | AN12: 0
A13: 946.08347 | B13: 35 | C13: 12 | D13: 9.8782204 | E13: 12 | F13: 7 | G13: 0.49097271 | H13: 16 | I13: 10 | J13: 0.96312033 | K13: 5.1027633e+08 | L13: 54491400 | M13: 79714992 | N13: 158151000 | O13: 15896751 | P13: 93.127034 | Q13: -1.1939077 | R13: 43.556145 | S13: 779.83757 | T13: 4.5874883e-11 | U13: 19.289386 | V13: 100.934 | W13: -240.84038 | X13: 62.817256 | Y13: 92.254346 | Z13: 144.29 | AA13: 230.95121 | AB13: 0 | AC13: 0 | AD13: 0 | AE13: 0 | AF13: 0 | AG13: 0 | AH13: 0 | AI13: 0 | AJ13: 0 | AK13: 0 | AL13: 0 | AM13: 0 | AN13: 0
... A127: 934.93785 | B127: 28 | C127: 13 | D127: 8.7655621 | E127: 10 | F127: 8 | G127: 0.3 | H127: 12 | I127: 9 | J127: 0.71810095 | K127: 5.0952694e+08 | L127: 54446500 | M127: 79699510 | N127: 158926000 | O127: 15890955 | P127: 84.783573 | Q127: -1.3600881 | R127: 43.340299 | S127: 782.29 | T127: 8.2382092e-11 | U127: 19.016592 | V127: 100.934 | W127: -242.85273 | X127: 62.909955 | Y127: 92.499967 | Z127: 100.934 | AA127: 227.9936 | AB127: 0 | AC127: 0 | AD127: 0 | AE127: 0 | AF127: 0 | AG127: 0 | AH127: 0 | AI127: 0 | AJ127: 0 | AK127: 0 | AL127: 0 | AM127: 0 | AN127: 0

Sheet ASWXL.Disable

Sheet InteractiveSheet
A1: Name | B1: Value | C1: Units | D1: Status | E1: Variable Name | F1: Object ID1 | G1: Object ID2 | H1: Container | I1: Container Type | M1: Name | N1: Value | O1: Units | P1: Status | Q1: Variable Name | R1: Object ID1 | S1: Object ID2 | T1: Container | U1: Container Type
A2: Settings.economics_active | B2: 1 | E2: economics_active | F2: Settings | L2: LHV | M2: 326SAF.STRM_UPP | N2: 43.599905 | O2: MJ/kg | P2: Calculated | Q2: STRM_UPP | R2: LHVMS-15 | S2: MIXED | T2: 326SAF | U2: MATERIAL
A3: Settings.auto_evaluate | B3: 1 | E3: auto_evaluate | F3: Settings | L3: SG | M3: 326SAF.STRM_UPP | N3: 0.78018145 | P3: Calculated | Q3: STRM_UPP | R3: SG-R | S3: MIXED | T3: 326SAF | U3: MATERIAL
L4: SLF | M4: 326SAF.STRM_UPP | N4: 2.4231449e-15 | P4: Calculated | Q4: STRM_UPP | R4: MASSFRS | S4: MIXED | T4: 326SAF | U4: MATERIAL
L5: ARM | N5: =SUM(B22:B30)*100 -> 19.126645 | O5: vol%
A6: Name | B6: Value | C6: Units | D6: Status | E6: Variable Name | F6: Object ID1 | G6: Object ID2 | H6: Container | I6: Container Type | L6: Flash Point (Minimum Boiling Point) | N6: =(FrzPt!L84-32)*5/9 -> 100.934 | O6: C
A7: PYROIN.EXPR2 | B7: 938.64219 | D7: Specified | E7: EXPR2 | H7: PYROIN | I7: DESIGN-SPEC | J7: 930 | L7: Freezing Point (Maximum Freezing Point) | N7: =FrzPt!S87 -> -237.33676 | O7: C
A8: T-310.NSTAGE | B8: 30 | D8: Specified | E8: NSTAGE | H8: T-310 | I8: RADFRAC | J8: 30 | L8: Gas T10 | N8: =DiesFlash!P2 -> 62.830338 | O8: C
A9: T-310.FEED_STAGE | B9: 10 | D9: Specified | E9: FEED_STAGE | F9: 310-1 | H9: T-310 | I9: RADFRAC | J9: 15 | L9: Gas T90 | N9: =DiesFlash!P3 -> 92.64466 | O9: C
A10: T-310.BASIS_RR | B10: 4.1453563 | D10: Specified | E10: BASIS_RR | H10: T-310 | I10: RADFRAC | J10: 2.95 | L10: Dies Flash | N10: =(DiesFlash!L84-32)*5/9 -> 144.29 | O10: C
A11: T-320.NSTAGE | B11: 16 | D11: Specified | E11: NSTAGE | H11: T-320 | I11: RADFRAC | J11: 20 | L11: Dies T90 | N11: =DiesFlash!P4 -> 231.70335 | O11: C
A12: T-320.FEED_STAGE | B12: 11 | D12: Specified | E12: FEED_STAGE | F12: 322 | H12: T-320 | I12: RADFRAC | J12: 10
A13: T-320.BASIS_RR | B13: 1.0975169 | D13: Specified | E13: BASIS_RR | H13: T-320 | I13: RADFRAC | J13: 0.567477
A14: T-330.NSTAGE | B14: 18 | D14: Specified | E14: NSTAGE | H14: T-330 | I14: RADFRAC | J14: 20
A15: T-330.FEED_STAGE | B15: 7 | D15: Specified | E15: FEED_STAGE | F15: 330 | H15: T-330 | I15: RADFRAC | J15: 12
A16: T-330.BASIS_RR | B16: 0.75389199 | D16: Specified | E16: BASIS_RR | H16: T-330 | I16: RADFRAC | J16: 1.4
A21: Name | B21: Value | C21: Units | D21: Status | E21: Variable Name | F21: Object ID1 | G21: Object ID2 | H21: Container | I21: Container Type
A22: 326SAF.STRM_UPP | B22: 0.15751895 | D22: Calculated | E22: STRM_UPP | F22: VLSTDFR | G22: MIXED | H22: 326SAF | I22: MATERIAL
A23: 326SAF.STRM_UPP | B23: 0 | D23: Calculated | E23: STRM_UPP | F23: VLSTDFR | G23: MIXED | H23: 326SAF | I23: MATERIAL | M23: Costing Result
A24: 326SAF.STRM_UPP | B24: 0.032720367 | D24: Calculated | E24: STRM_UPP | F24: VLSTDFR | G24: MIXED | H24: 326SAF | I24: MATERIAL | M24: Total Capital Cost [USD] | N24: USD | O24: =Cost!D4 -> 1.663204e+08
A25: 326SAF.STRM_UPP | B25: 3.0836645e-05 | D25: Calculated | E25: STRM_UPP | F25: VLSTDFR | G25: MIXED | H25: 326SAF | I25: MATERIAL | M25: Total Operating Cost [USD/Year] | N25: USD/Year | O25: =Cost!D5 -> 0
A26: 326SAF.STRM_UPP | B26: 4.5012858e-07 | D26: Calculated | E26: STRM_UPP | F26: VLSTDFR | G26: MIXED | H26: 326SAF | I26: MATERIAL | M26: Total Raw Materials Cost [USD/Year] | N26: USD/Year | O26: =Cost!D6 -> 34004.597
A27: 326SAF.STRM_UPP | B27: 1.2071739e-16 | D27: Calculated | E27: STRM_UPP | F27: VLSTDFR | G27: MIXED | H27: 326SAF | I27: MATERIAL | M27: Total Product Sales [USD/Year] | N27: USD/Year | O27: =Cost!D7 -> 0
A28: 326SAF.STRM_UPP | B28: 0.00099584568 | D28: Calculated | E28: STRM_UPP | F28: VLSTDFR | G28: MIXED | H28: 326SAF | I28: MATERIAL | M28: Total Utilities Cost [USD/Year] | N28: USD/Year | O28: =Cost!D8 -> 15889638
A29: 326SAF.STRM_UPP | B29: 1.7237337e-15 | D29: Calculated | E29: STRM_UPP | F29: VLSTDFR | G29: MIXED | H29: 326SAF | I29: MATERIAL | M29: Main Product | N29: cuft/hr | O29: =B83 -> 211.62373
A30: 326SAF.STRM_UPP | B30: 8.2695918e-20 | D30: Calculated | E30: STRM_UPP | F30: VLSTDFR | G30: MIXED | H30: 326SAF | I30: MATERIAL
A34: Name | B34: Value | C34: Units | D34: Status | E34: Variable Name | F34: Object ID1 | G34: Object ID2 | H34: Container | I34: Container Type
A35: Utility-Sum.TOTUTCOST | B35: 1986.2047 | C35: $/hr | D35: Calculated | E35: TOTUTCOST | H35: UTIL-SUMMARY | I35: DATA
A36: 326SAF.VOLFLMX | B36: 226.53826 | C36: cuft/hr | D36: Calculated | E36: VOLFLMX | F36: MIXED | H36: 326SAF | I36: MATERIAL
A37: 510.MASSFLMX | B37: 6654.7636 | C37: lb/hr | D37: Calculated | E37: MASSFLMX | F37: MIXED | H37: 510 | I37: MATERIAL
A38: 200.VLSTDMX | B38: 829.00636 | C38: cuft/hr | D38: Calculated | E38: VLSTDMX | F38: MIXED | H38: 200 | I38: MATERIAL
A39: 404.VOLFLMX | B39: 165519.71 | C39: cuft/hr | D39: Calculated | E39: VOLFLMX | F39: MIXED | H39: 404 | I39: MATERIAL
A40: 622X.MASSFLMX | B40: 446452.17 | C40: lb/hr | D40: Calculated | E40: MASSFLMX | F40: MIXED | H40: 622X | I40: MATERIAL
A41: 255.VOLFLMX | B41: 9236.3253 | C41: cuft/hr | D41: Calculated | E41: VOLFLMX | F41: MIXED | H41: 255 | I41: MATERIAL
A42: 210.VOLFLMX | B42: 8512.449 | C42: cuft/hr | D42: Calculated | E42: VOLFLMX | F42: MIXED | H42: 210 | I42: MATERIAL
A43: 272.VOLFLMX | B43: 42495.301 | C43: cuft/hr | D43: Calculated | E43: VOLFLMX | F43: MIXED | H43: 272 | I43: MATERIAL
A45: Pyrolysis
A46: Name | B46: Value | C46: Units | D46: Status | E46: Variable Name | F46: Object ID1 | G46: Object ID2 | H46: Container | I46: Container Type
A47: R-110.COEF1 | B47: 0.041453235 | D47: Specified | E47: COEF1 | F47: 1 | G47: ACIDS | H47: R-110 | I47: RSTOIC | J47: 0.041453235
A48: R-110.COEF1 | B48: 0.040554755 | D48: Specified | E48: COEF1 | F48: 1 | G48: ALCOHOLS | H48: R-110 | I48: RSTOIC | J48: 0.040554755
A49: R-110.COEF1 | B49: 0.071700882 | D49: Specified | E49: COEF1 | F49: 1 | G49: KETONES | H49: R-110 | I49: RSTOIC | J49: 0.071700882
A50: R-110.COEF1 | B50: 0.029348836 | D50: Specified | E50: COEF1 | F50: 1 | G50: ALDEHYDE | H50: R-110 | I50: RSTOIC | J50: 0.029348836
A51: R-110.COEF1 | B51: 0.019435118 | D51: Specified | E51: COEF1 | F51: 1 | G51: GUAIACOL | H51: R-110 | I51: RSTOIC | J51: 0.019435118
A52: R-110.COEF1 | B52: 0.023586365 | D52: Specified | E52: COEF1 | F52: 1 | G52: SUGLMW | H52: R-110 | I52: RSTOIC | J52: 0.023586365
A53: R-110.COEF1 | B53: 0.063366911 | D53: Specified | E53: COEF1 | F53: 1 | G53: SUGHMW | H53: R-110 | I53: RSTOIC | J53: 0.063366911
A54: R-110.COEF1 | B54: 0.02920146 | D54: Specified | E54: COEF1 | F54: 1 | G54: LIGLMW-A | H54: R-110 | I54: RSTOIC | J54: 0.02920146
A55: R-110.COEF1 | B55: 0.008419469 | D55: Specified | E55: COEF1 | F55: 1 | G55: LIGLMW-B | H55: R-110 | I55: RSTOIC | J55: 0.008419469
A56: R-110.COEF1 | B56: 0.006378986 | D56: Specified | E56: COEF1 | F56: 1 | G56: EXTRACT | H56: R-110 | I56: RSTOIC | J56: 0.006378986
A57: R-110.COEF1 | B57: 0.014863687 | D57: Specified | E57: COEF1 | F57: 1 | G57: LIGHMW-A | H57: R-110 | I57: RSTOIC | J57: 0.014863687
A58: R-110.COEF1 | B58: 0.003137103 | D58: Specified | E58: COEF1 | F58: 1 | G58: LIGHMW-B | H58: R-110 | I58: RSTOIC | J58: 0.003137103
... A60: R-110.COEF1 | B60: 8.69609e-05 | D60: Specified | E60: COEF1 | F60: 1 | G60: S-COMP | H60: R-110 | I60: RSTOIC | J60: 8.69609e-05
A62: Hydrotreated Product
A63: Name | B63: Value | C63: Units | D63: Status | E63: Variable Name | F63: Object ID1 | G63: Object ID2 | H63: Container | I63: Container Type
A64: R-225.2HT-MAIN.MOLE_YIELD | B64: 2.2 | D64: Specified | E64: MOLE_YIELD | F64: PHENOLS | G64: MIXED | H64: R-225.2HT-MAIN | I64: RYIELD
A65: R-225.2HT-MAIN.MOLE_YIELD | B65: 0 | D65: Specified | E65: MOLE_YIELD | F65: PHENOL1 | G65: MIXED | H65: R-225.2HT-MAIN | I65: RYIELD
A66: R-225.2HT-MAIN.MOLE_YIELD | B66: 0 | D66: Specified | E66: MOLE_YIELD | F66: PHENOL2 | G66: MIXED | H66: R-225.2HT-MAIN | I66: RYIELD
A67: R-225.2HT-MAIN.MOLE_YIELD | B67: 0 | D67: Specified | E67: MOLE_YIELD | F67: PHENOL3 | G67: MIXED | H67: R-225.2HT-MAIN | I67: RYIELD
A68: R-225.2HT-MAIN.MOLE_YIELD | B68: 1.8 | D68: Specified | E68: MOLE_YIELD | F68: CYC5-A | G68: MIXED | H68: R-225.2HT-MAIN | I68: RYIELD
A69: R-225.2HT-MAIN.MOLE_YIELD | B69: 0 | D69: Specified | E69: MOLE_YIELD | F69: CYC5-A1 | G69: MIXED | H69: R-225.2HT-MAIN | I69: RYIELD
A70: R-225.2HT-MAIN.MOLE_YIELD | B70: 2.4 | D70: Specified | E70: MOLE_YIELD | F70: CYC6-A | G70: MIXED | H70: R-225.2HT-MAIN | I70: RYIELD
A71: R-225.2HT-MAIN.MOLE_YIELD | B71: 0 | D71: Specified | E71: MOLE_YIELD | F71: CYC6-A1 | G71: MIXED | H71: R-225.2HT-MAIN | I71: RYIELD
A72: R-225.2HT-MAIN.MOLE_YIELD | B72: 0 | D72: Specified | E72: MOLE_YIELD | F72: CYC6-A2 | G72: MIXED | H72: R-225.2HT-MAIN | I72: RYIELD
A73: R-225.2HT-MAIN.MOLE_YIELD | B73: 0 | D73: Specified | E73: MOLE_YIELD | F73: CYC6-A3 | G73: MIXED | H73: R-225.2HT-MAIN | I73: RYIELD
A74: R-225.2HT-MAIN.MOLE_YIELD | B74: 3.5 | D74: Specified | E74: MOLE_YIELD | F74: ARM-A | G74: MIXED | H74: R-225.2HT-MAIN | I74: RYIELD
A75: R-225.2HT-MAIN.MOLE_YIELD | B75: 0 | D75: Specified | E75: MOLE_YIELD | F75: ARM-A1 | G75: MIXED | H75: R-225.2HT-MAIN | I75: RYIELD
... A79: R-225.2HT-MAIN.MOLE_YIELD | B79: 1.3 | D79: Specified | E79: MOLE_YIELD | F79: ARM-B2 | G79: MIXED | H79: R-225.2HT-MAIN | I79: RYIELD
A81: Name | B81: Value | C81: Units | D81: Status | E81: Variable Name | F81: Object ID1 | G81: Object ID2 | H81: Container | I81: Container Type
A82: 316GAS.VLSTDMX | B82: 145.23279 | C82: cuft/hr | D82: Calculated | E82: VLSTDMX | F82: MIXED | H82: 316GAS | I82: MATERIAL | J82: 0.75757$/lb
A83: 326SAF.VLSTDMX | B83: 211.62373 | C83: cuft/hr | D83: Calculated | E83: VLSTDMX | F83: MIXED | H83: 326SAF | I83: MATERIAL | J83: 0.6$/lb
A84: 336DIES.VLSTDMX | B84: 94.327428 | C84: cuft/hr | D84: Calculated | E84: VLSTDMX | F84: MIXED | H84: 336DIES | I84: MATERIAL | M84: US national price (Jan 2024-Jan 2025)
A85: Stream-Price.PRICE | B85: 0.87 | C85: $/l | D85: Specified | E85: PRICE | F85: 316GAS | H85: STREAM-PRICE | I85: DATA | M85: $ 0.87/L
A86: Stream-Price.PRICE | B86: 0 | C86: $/l | D86: Specified | E86: PRICE | F86: 326SAF | H86: STREAM-PRICE | I86: DATA | M86: $ 2.4/L
A87: Stream-Price.PRICE | B87: 0.99 | C87: $/l | D87: Specified | E87: PRICE | F87: 336DIES | H87: STREAM-PRICE | I87: DATA | M87: $ 0.99/L

Sheet FrzPt
A1: Name | B1: Value | C1: Units | D1: Status | E1: Variable Name | F1: Object ID1 | G1: Object ID2 | H1: Container | I1: Container Type | K1: Pure BP (F) | Q1: LIQ PRESSURE
A2: 326SAF.MASSFRAC | B2: 0 | D2: Calculated | E2: MASSFRAC | F2: MIXED | G2: WATER | H2: 326SAF | I2: MATERIAL | K2: 212 | L2: =IF(FrzPt!B2>0.0001, K2, FALSE) -> FALSE | Q2: Pentane
A3: 326SAF.MASSFRAC | B3: 0 | D3: Calculated | E3: MASSFRAC | F3: MIXED | G3: H2 | H3: 326SAF | I3: MATERIAL | K3: -422.968 | L3: =IF(FrzPt!B3>0.0001, K3, FALSE) -> FALSE | P3: HIGH (volatile) | Q3: SC-PARAF | R3: Gasoline | S3: Gasoline
A4: 326SAF.MASSFRAC | B4: 0 | D4: Calculated | E4: MASSFRAC | F4: MIXED | G4: O2 | H4: 326SAF | I4: MATERIAL | K4: -297.3316 | L4: =IF(FrzPt!B4>0.0001, K4, FALSE) -> FALSE | Q4: CYC6-A
A5: 326SAF.MASSFRAC | B5: 0 | D5: Calculated | E5: MASSFRAC | F5: MIXED | G5: N2 | H5: 326SAF | I5: MATERIAL | K5: -320.4508 | L5: =IF(FrzPt!B5>0.0001, K5, FALSE) -> FALSE | Q5: I-PRF-A
A6: 326SAF.MASSFRAC | B6: 0 | D6: Calculated | E6: MASSFRAC | F6: MIXED | G6: AR | H6: 326SAF | I6: MATERIAL | K6: -302.566 | L6: =IF(FrzPt!B6>0.0001, K6, FALSE) -> FALSE | Q6: CYC5-A
A7: 326SAF.MASSFRAC | B7: 0 | D7: Calculated | E7: MASSFRAC | F7: MIXED | G7: CO | H7: 326SAF | I7: MATERIAL | K7: -312.61 | L7: =IF(FrzPt!B7>0.0001, K7, FALSE) -> FALSE | Q7: CYC6-HCK
A8: 326SAF.MASSFRAC | B8: 0 | D8: Calculated | E8: MASSFRAC | F8: MIXED | G8: CO2 | H8: 326SAF | I8: MATERIAL | K8: -109.21 | L8: =IF(FrzPt!B8>0.0001, K8, FALSE) -> FALSE | Q8: CYC5-B | S8: SAF
A9: 326SAF.MASSFRAC | B9: 0 | D9: Calculated | E9: MASSFRAC | F9: MIXED | G9: METHANE | H9: 326SAF | I9: MATERIAL | K9: -258.664 | L9: =IF(FrzPt!B9>0.0001, K9, FALSE) -> FALSE | Q9: N-HCK-B
A10: 326SAF.MASSFRAC | B10: 0 | D10: Calculated | E10: MASSFRAC | F10: MIXED | G10: ETHANE | H10: 326SAF | I10: MATERIAL | K10: -127.444 | L10: =IF(FrzPt!B10>0.0001, K10, FALSE) -> FALSE | Q10: ARM-A
A11: 326SAF.MASSFRAC | B11: 0 | D11: Calculated | E11: MASSFRAC | F11: MIXED | G11: PROPANE | H11: 326SAF | I11: MATERIAL | K11: -43.798 | L11: =IF(FrzPt!B11>0.0001, K11, FALSE) -> FALSE | Q11: N-HCK-A | R11: Diesel
A12: 326SAF.MASSFRAC | B12: 0 | D12: Calculated | E12: MASSFRAC | F12: MIXED | G12: N-BUTANE | H12: 326SAF | I12: MATERIAL | K12: 31.118 | L12: =IF(FrzPt!B12>0.0001, K12, FALSE) -> FALSE | Q12: I-PRF-B
A13: 326SAF.MASSFRAC | B13: 0 | D13: Calculated | E13: MASSFRAC | F13: MIXED | G13: ETHENE | H13: 326SAF | I13: MATERIAL | K13: -154.732 | L13: =IF(FrzPt!B13>0.0001, K13, FALSE) -> FALSE | Q13: N-COMP
A14: 326SAF.MASSFRAC | B14: 0 | D14: Calculated | E14: MASSFRAC | F14: MIXED | G14: PROPENE | H14: 326SAF | I14: MATERIAL | K14: -53.86 | L14: =IF(FrzPt!B14>0.0001, K14, FALSE) -> FALSE | Q14: INDANS
A15: 326SAF.MASSFRAC | B15: 0 | D15: Calculated | E15: MASSFRAC | F15: MIXED | G15: 1-BUTENE | H15: 326SAF | I15: MATERIAL | K15: 20.768 | L15: =IF(FrzPt!B15>0.0001, K15, FALSE) -> FALSE | Q15: ARM-B
A16: 326SAF.MASSFRAC | B16: 0 | D16: Calculated | E16: MASSFRAC | F16: MIXED | G16: SO2 | H16: 326SAF | I16: MATERIAL | K16: 13.964 | L16: =IF(FrzPt!B16>0.0001, K16, FALSE) -> FALSE | Q16: CYC6-B
A17: 326SAF.MASSFRAC | B17: 0 | D17: Calculated | E17: MASSFRAC | F17: MIXED | G17: NO2 | H17: 326SAF | I17: MATERIAL | K17: 69.8 | L17: =IF(FrzPt!B17>0.0001, K17, FALSE) -> FALSE | Q17: PHENOLS | S17: Diesel
A18: 326SAF.MASSFRAC | B18: 3.183615e-05 | D18: Calculated | E18: MASSFRAC | F18: MIXED | G18: ACIDS | H18: 326SAF | I18: MATERIAL | K18: 341.42 | L18: =IF(FrzPt!B18>0.0001, K18, FALSE) -> FALSE | Q18: CYC7PLUS
A19: 326SAF.MASSFRAC | B19: 1.9427568e-14 | D19: Calculated | E19: MASSFRAC | F19: MIXED | G19: ALDEHYDE | H19: 326SAF | I19: MATERIAL | K19: 544.73 | L19: =IF(FrzPt!B19>0.0001, K19, FALSE) -> FALSE | Q19: MC-PARAF
A20: 326SAF.MASSFRAC | B20: 4.0703746e-05 | D20: Calculated | E20: MASSFRAC | F20: MIXED | G20: KETONES | H20: 326SAF | I20: MATERIAL | K20: 293.9 | L20: =IF(FrzPt!B20>0.0001, K20, FALSE) -> FALSE | Q20: INDENES
A21: 326SAF.MASSFRAC | B21: 6.9303604e-11 | D21: Calculated | E21: MASSFRAC | F21: MIXED | G21: ALCOHOLS | H21: 326SAF | I21: MATERIAL | K21: 546.89 | L21: =IF(FrzPt!B21>0.0001, K21, FALSE) -> FALSE | Q21: BICYCLOS
A22: 326SAF.MASSFRAC | B22: 6.8794226e-12 | D22: Calculated | E22: MASSFRAC | F22: MIXED | G22: GUAIACOL | H22: 326SAF | I22: MATERIAL | K22: 510.8 | L22: =IF(FrzPt!B22>0.0001, K22, FALSE) -> FALSE | Q22: NAPHTHAL
A23: 326SAF.MASSFRAC | B23: 6.6764728e-25 | D23: Calculated | E23: MASSFRAC | F23: MIXED | G23: SUGLMW | H23: 326SAF | I23: MATERIAL | K23: 704.93 | L23: =IF(FrzPt!B23>0.0001, K23, FALSE) -> FALSE | Q23: DIP-COMP
A24: 326SAF.MASSFRAC | B24: 0 | D24: Calculated | E24: MASSFRAC | F24: MIXED | G24: SUGHMW | H24: 326SAF | I24: MATERIAL | K24: 1160.33 | L24: =IF(FrzPt!B24>0.0001, K24, FALSE) -> FALSE | Q24: 124-NAPH
A25: 326SAF.MASSFRAC | B25: 3.0340783e-28 | D25: Calculated | E25: MASSFRAC | F25: MIXED | G25: EXTRACT | H25: 326SAF | I25: MATERIAL | K25: 701.33 | L25: =IF(FrzPt!B25>0.0001, K25, FALSE) -> FALSE | Q25: POLY-ARM | R25: Hydrocracking | S25: D30
A26: 326SAF.MASSFRAC | B26: 1.9888383e-30 | D26: Calculated | E26: MASSFRAC | F26: MIXED | G26: LIGLMW-A | H26: 326SAF | I26: MATERIAL | K26: 742.73 | L26: =IF(FrzPt!B26>0.0001, K26, FALSE) -> FALSE | Q26: EXTR-INT | S26: D33
A27: 326SAF.MASSFRAC | B27: 3.4654202e-13 | D27: Calculated | E27: MASSFRAC | F27: MIXED | G27: LIGLMW-B | H27: 326SAF | I27: MATERIAL | K27: 545.288 | L27: =IF(FrzPt!B27>0.0001, K27, FALSE) -> FALSE | Q27: PHENANTH | S27: D23
A28: 326SAF.MASSFRAC | B28: 0 | D28: Calculated | E28: MASSFRAC | F28: MIXED | G28: LIGHMW-A | H28: 326SAF | I28: MATERIAL | K28: 1198.4 | L28: =IF(FrzPt!B28>0.0001, K28, FALSE) -> FALSE | Q28: PYRENES | S28: D24
A29: 326SAF.MASSFRAC | B29: 0 | D29: Calculated | E29: MASSFRAC | F29: MIXED | G29: LIGHMW-B | H29: 326SAF | I29: MATERIAL | K29: 1172.4 | L29: =IF(FrzPt!B29>0.0001, K29, FALSE) -> FALSE | Q29: LGLM-INT | S29: D32
A30: 326SAF.MASSFRAC | B30: 0.0013264338 | D30: Calculated | E30: MASSFRAC | F30: MIXED | G30: N-COMP | H30: 326SAF | I30: MATERIAL | K30: 338.99 | L30: =IF(FrzPt!B30>0.0001, K30, FALSE) -> 338.99
A31: 326SAF.MASSFRAC | B31: 1.3926774e-14 | D31: Calculated | E31: MASSFRAC | F31: MIXED | G31: S-COMP | H31: 326SAF | I31: MATERIAL | K31: 628.6262 | L31: =IF(FrzPt!B31>0.0001, K31, FALSE) -> FALSE
A32: 326SAF.MASSFRAC | B32: 0 | D32: Calculated | E32: MASSFRAC | F32: MIXED | G32: S | H32: 326SAF | I32: MATERIAL | K32: 832.4132 | L32: =IF(FrzPt!B32>0.0001, K32, FALSE) -> FALSE
A33: 326SAF.MASSFRAC | B33: 0 | D33: Calculated | E33: MASSFRAC | F33: MIXED | G33: C | H33: 326SAF | I33: MATERIAL | L33: =IF(FrzPt!B33>0.0001, K33, FALSE) -> FALSE | S33: No Carbons
A34: 326SAF.MASSFRAC | B34: 0 | D34: Calculated | E34: MASSFRAC | F34: MIXED | G34: ASH | H34: 326SAF | I34: MATERIAL | K34: 4046.09 | L34: =IF(FrzPt!B34>0.0001, K34, FALSE) -> FALSE | S34: 7 | T34: 8 | U34: 9 | V34: 10 | W34: 11 | X34: 12 | Y34: 13 | Z34: 14 | AA34: 15 | AB34: 16 | AC34: 17 | AD34: 18 | AE34: 19
A35: 326SAF.MASSFRAC | B35: 0 | D35: Calculated | E35: MASSFRAC | F35: MIXED | G35: SAND | H35: 326SAF | I35: MATERIAL | K35: 4046.09 | L35: =IF(FrzPt!B35>0.0001, K35, FALSE) -> FALSE | Q35: Class | R35: 1 | T35: N-HCK-B | U35: N-HCK-A | X35: MC-PARAF
A36: 326SAF.MASSFRAC | B36: 1.6349205e-05 | D36: Calculated | E36: MASSFRAC | F36: MIXED | G36: ACID-INT | H36: 326SAF | I36: MATERIAL | K36: 325.886 | L36: =IF(FrzPt!B36>0.0001, K36, FALSE) -> FALSE | R36: 2 | S36: I-PRF-A | V36: I-PRF-B
A37: 326SAF.MASSFRAC | B37: 1.7638674e-06 | D37: Calculated | E37: MASSFRAC | F37: MIXED | G37: CRBN-INT | H37: 326SAF | I37: MATERIAL | K37: 369.68 | L37: =IF(FrzPt!B37>0.0001, K37, FALSE) -> FALSE | R37: 3
A38: 326SAF.MASSFRAC | B38: 0 | D38: Calculated | E38: MASSFRAC | F38: MIXED | G38: LGHM-INT | H38: 326SAF | I38: MATERIAL | K38: 360.716 | L38: =IF(FrzPt!B38>0.0001, K38, FALSE) -> FALSE | R38: 4 | S38: CYC5-A, CYC6-HCK, CYC6-A1, CYC6-A2 | V38: CYC6-B
A39: 326SAF.MASSFRAC | B39: 0 | D39: Calculated | E39: MASSFRAC | F39: MIXED | G39: SG-INT-A | H39: 326SAF | I39: MATERIAL | K39: 650.93 | L39: =IF(FrzPt!B39>0.0001, K39, FALSE) -> FALSE | R39: 5 | S39: PHENOL1 | T39: CYC5-B, PHENOL3 | V39: PHENOLS
A40: 326SAF.MASSFRAC | B40: 0 | D40: Calculated | E40: MASSFRAC | F40: MIXED | G40: SG-INT-B | H40: 326SAF | I40: MATERIAL | K40: 814.55 | L40: =IF(FrzPt!B40>0.0001, K40, FALSE) -> FALSE | R40: 6 | X40: BICYCLOS, CYC7+ | AB40: 무시된 값들 (엄청 적긴 함)
A41: 326SAF.MASSFRAC | B41: 4.6767225e-10 | D41: Calculated | E41: MASSFRAC | F41: MIXED | G41: SC-PARAF | H41: 326SAF | I41: MATERIAL | K41: 155.678 | L41: =IF(FrzPt!B41>0.0001, K41, FALSE) -> FALSE | R41: 7
A42: 326SAF.MASSFRAC | B42: 0.028531581 | D42: Calculated | E42: MASSFRAC | F42: MIXED | G42: MC-PARAF | H42: 326SAF | I42: MATERIAL | K42: 421.34 | L42: =IF(FrzPt!B42>0.0001, K42, FALSE) -> 421.34 | R42: 8 | S42: ARM-A1 | T42: ARM-A, ARM-A2 | U42: N-COMP, ARM-B2 | V42: ARM-B | X42: ARM-B1
A43: 326SAF.MASSFRAC | B43: 1.9990156e-05 | D43: Calculated | E43: MASSFRAC | F43: MIXED | G43: I-PRF-A | H43: 326SAF | I43: MATERIAL | K43: 197.33 | L43: =IF(FrzPt!B43>0.0001, K43, FALSE) -> FALSE | R43: 9 | X43: INDENES, NAPHTHAL | Z43: DIP-COMP | AB43: POLY-ARM
A44: 326SAF.MASSFRAC | B44: 0.13792989 | D44: Calculated | E44: MASSFRAC | F44: MIXED | G44: I-PRF-B | H44: 326SAF | I44: MATERIAL | K44: 330.26 | L44: =IF(FrzPt!B44>0.0001, K44, FALSE) -> 330.26 | R44: 10 | U44: INDAN | AB44: 124-NAPH
A45: 326SAF.MASSFRAC | B45: 0.03162037 | D45: Calculated | E45: MASSFRAC | F45: MIXED | G45: CYC5-A | H45: 326SAF | I45: MATERIAL | K45: 218.246 | L45: =IF(FrzPt!B45>0.0001, K45, FALSE) -> 218.246
A46: 326SAF.MASSFRAC | B46: 0.11412831 | D46: Calculated | E46: MASSFRAC | F46: MIXED | G46: CYC5-B | H46: 326SAF | I46: MATERIAL | K46: 250.7396 | L46: =IF(FrzPt!B46>0.0001, K46, FALSE) -> 250.7396 | S46: 7 | T46: 8 | U46: 9 | V46: 10 | W46: 11 | X46: 12 | Y46: 13 | Z46: 14 | AA46: 15 | AB46: 16 | AC46: 17 | AD46: 18 | AE46: 19
A47: 326SAF.MASSFRAC | B47: 5.5384542e-07 | D47: Calculated | E47: MASSFRAC | F47: MIXED | G47: CYC6-A | H47: 326SAF | I47: MATERIAL | K47: 177.296 | L47: =IF(FrzPt!B47>0.0001, K47, FALSE) -> FALSE | R47: 1 | T47: =B69 -> 0.10524168 | U47: =B68 -> 0.19147323 | X47: =B42 -> 0.028531581
A48: 326SAF.MASSFRAC | B48: 0.078656627 | D48: Calculated | E48: MASSFRAC | F48: MIXED | G48: CYC6-B | H48: 326SAF | I48: MATERIAL | K48: 357.7658 | L48: =IF(FrzPt!B48>0.0001, K48, FALSE) -> 357.7658 | R48: 2 | S48: =B43 -> 1.9990156e-05 | V48: =B44 -> 0.13792989
A49: 326SAF.MASSFRAC | B49: 3.9859695e-05 | D49: Calculated | E49: MASSFRAC | F49: MIXED | G49: BICYCLOS | H49: 326SAF | I49: MATERIAL | K49: 462.272 | L49: =IF(FrzPt!B49>0.0001, K49, FALSE) -> FALSE | R49: 3
A50: 326SAF.MASSFRAC | B50: 0.043473968 | D50: Calculated | E50: MASSFRAC | F50: MIXED | G50: CYC7PLUS | H50: 326SAF | I50: MATERIAL | K50: 397.913 | L50: =IF(FrzPt!B50>0.0001, K50, FALSE) -> 397.913 | R50: 4 | S50: =B45+B67+B76+B77 -> 0.074750651 | V50: =+B48 -> 0.078656627
A51: 326SAF.MASSFRAC | B51: 0.17841343 | D51: Calculated | E51: MASSFRAC | F51: MIXED | G51: ARM-A | H51: 326SAF | I51: MATERIAL | K51: 291.722 | L51: =IF(FrzPt!B51>0.0001, K51, FALSE) -> 291.722 | R51: 5 | S51: =+B72 -> 0 | T51: =+B46+B74 -> 0.11412831 | V51: 0
A52: 326SAF.MASSFRAC | B52: 0 | D52: Calculated | E52: MASSFRAC | F52: MIXED | G52: ARM-B | H52: 326SAF | I52: MATERIAL | K52: 378.14 | L52: =IF(FrzPt!B52>0.0001, K52, FALSE) -> FALSE | R52: 6 | X52: =+B49+B50 -> 0.043513828
A53: 326SAF.MASSFRAC | B53: 1.7017774e-16 | D53: Calculated | E53: MASSFRAC | F53: MIXED | G53: PHENANTH | H53: 326SAF | I53: MATERIAL | K53: 670.91 | L53: =IF(FrzPt!B53>0.0001, K53, FALSE) -> FALSE | R53: 7
A54: 326SAF.MASSFRAC | B54: 1.2626539e-19 | D54: Calculated | E54: MASSFRAC | F54: MIXED | G54: PYRENES | H54: 326SAF | I54: MATERIAL | K54: 742.64 | L54: =IF(FrzPt!B54>0.0001, K54, FALSE) -> FALSE | R54: 8 | S54: =+B79 -> 0 | T54: =+B51+B80 -> 0.17841343 | U54: =+B30+B82 -> 0.0056748994 | V54: =+B52 -> 0 | X54: =+B81 -> 0
A55: 326SAF.MASSFRAC | B55: 5.9366415e-10 | D55: Calculated | E55: MASSFRAC | F55: MIXED | G55: DIP-COMP | H55: 326SAF | I55: MATERIAL | K55: 536.9 | L55: =IF(FrzPt!B55>0.0001, K55, FALSE) -> FALSE | R55: 9 | X55: =+B57+B59 -> 4.0863586e-05 | Z55: =+B55 -> 5.9366415e-10 | AB55: =+B60 -> 2.4257371e-15
A56: 326SAF.MASSFRAC | B56: 0.040291875 | D56: Calculated | E56: MASSFRAC | F56: MIXED | G56: INDANS | H56: 326SAF | I56: MATERIAL | K56: 352.346 | L56: =IF(FrzPt!B56>0.0001, K56, FALSE) -> 352.346 | R56: 10 | U56: =+B56 -> 0.040291875 | AB56: =+B58 -> 4.1055947e-14
A57: 326SAF.MASSFRAC | B57: 4.028246e-05 | D57: Calculated | E57: MASSFRAC | F57: MIXED | G57: INDENES | H57: 326SAF | I57: MATERIAL | K57: 456.53 | L57: =IF(FrzPt!B57>0.0001, K57, FALSE) -> FALSE
A58: 326SAF.MASSFRAC | B58: 4.1055947e-14 | D58: Calculated | E58: MASSFRAC | F58: MIXED | G58: 124-NAPH | H58: 326SAF | I58: MATERIAL | K58: 590.441 | L58: =IF(FrzPt!B58>0.0001, K58, FALSE) -> FALSE | S58: =SUMIF(S62:AE71, "<>", S47:AE56) -> 0.998626
A59: 326SAF.MASSFRAC | B59: 5.8112596e-07 | D59: Calculated | E59: MASSFRAC | F59: MIXED | G59: NAPHTHAL | H59: 326SAF | I59: MATERIAL | K59: 505.4 | L59: =IF(FrzPt!B59>0.0001, K59, FALSE) -> FALSE
A60: 326SAF.MASSFRAC | B60: 2.4257371e-15 | D60: Calculated | E60: MASSFRAC | F60: MIXED | G60: POLY-ARM | H60: 326SAF | I60: MATERIAL | K60: 633.2 | L60: =IF(FrzPt!B60>0.0001, K60, FALSE) -> FALSE
A61: 326SAF.MASSFRAC | B61: 0.0012419303 | D61: Calculated | E61: MASSFRAC | F61: MIXED | G61: PHENOLS | H61: 326SAF | I61: MATERIAL | K61: 450.5 | L61: =IF(FrzPt!B61>0.0001, K61, FALSE) -> 450.5 | Q61: Freezing Matrix | R61: Class | S61: C7 | T61: C8 | U61: C9 | V61: C10 | W61: C11 | X61: C12 | Y61: C13 | Z61: C14 | AA61: C15 | AB61: C16 | AC61: C17 | AD61: C18 | AE61: C19 | AG61: L
A62: 326SAF.MASSFRAC | B62: 0 | D62: Calculated | E62: MASSFRAC | F62: MIXED | G62: SULFAGN | H62: 326SAF | I62: MATERIAL | K62: 99.194 | L62: =IF(FrzPt!B62>0.0001, K62, FALSE) -> FALSE | R62: Class 1 | S62: -91 | T62: -56.8 | U62: -51 | V62: -30 | W62: -25.6 | X62: -12 | Y62: -5.5 | Z62: 5.9 | AA62: 10 | AB62: 18.2 | AC62: 22 | AD62: 28 | AE62: 30 | AG62: 3.02
A63: 326SAF.MASSFRAC | B63: 0 | D63: Calculated | E63: MASSFRAC | F63: MIXED | G63: PENTANE | H63: 326SAF | I63: MATERIAL | K63: 96.908 | L63: =IF(FrzPt!B63>0.0001, K63, FALSE) -> FALSE | R63: Class 2 | S63: -136.9 | T63: -117.6 | U63: -100.3 | V63: -86.5 | W63: -74 | X63: -60.8 | Y63: -51.8 | Z63: -32 | AA63: -22.5 | AB63: -24 | AC63: -8.2 | AD63: -2.9 | AE63: -1.7 | AG63: 2.22
A64: 326SAF.MASSFRAC | B64: 0 | D64: Calculated | E64: MASSFRAC | F64: MIXED | G64: H2S | H64: 326SAF | I64: MATERIAL | K64: -76.63 | L64: =IF(FrzPt!B64>0.0001, K64, FALSE) -> FALSE | R64: Class 3 | S64: -126 | T64: -112.7 | U64: -111.2 | V64: -53.9 | W64: -69.2 | X64: -57.3 | Y64: -57 | Z64: -57 | AA64: -10.1 | AB64: -3.7 | AC64: 3.7 | AD64: -46.5 | AE64: -10.3 | AG64: -1.75
A65: 326SAF.MASSFRAC | B65: 6.9665568e-31 | D65: Calculated | E65: MASSFRAC | F65: MIXED | G65: LGLM-INT | H65: 326SAF | I65: MATERIAL | K65: 1100.7392 | L65: =IF(FrzPt!B65>0.0001, K65, FALSE) -> FALSE | R65: Class 4 | S65: -126.6 | T65: -115 | U65: -97.6 | V65: -74.7 | W65: -65.3 | X65: -43 | Y65: -30.5 | Z65: -24.4 | AA65: -16.2 | AG65: -1.41
A66: 326SAF.MASSFRAC | B66: 2.244881e-21 | D66: Calculated | E66: MASSFRAC | F66: MIXED | G66: EXTR-INT | H66: 326SAF | I66: MATERIAL | K66: 666.41 | L66: =IF(FrzPt!B66>0.0001, K66, FALSE) -> FALSE | R66: Class 5 | S66: -110.1 | T66: -66.1 | U66: -94.7 | V66: -85.3 | W66: -52.7 | X66: -23.1 | Y66: -35.4 | Z66: -18.8 | AA66: -60.5 | AB66: -9.6 | AG66: 2.6
A67: 326SAF.MASSFRAC | B67: 0.043130281 | D67: Calculated | E67: MASSFRAC | F67: MIXED | G67: CYC6-HCK | H67: 326SAF | I67: MATERIAL | K67: 213.6812 | L67: =IF(FrzPt!B67>0.0001, K67, FALSE) -> 213.6812 | R67: Class 6 | T67: -93 | U67: -30 | V67: -36.7 | W67: -45.3 | X67: -19 | Y67: -66.6 | Z67: -55.9 | AA67: -23.7 | AG67: 3.31
A68: 326SAF.MASSFRAC | B68: 0.19147323 | D68: Calculated | E68: MASSFRAC | F68: MIXED | G68: N-HCK-A | H68: 326SAF | I68: MATERIAL | K68: 303.368 | L68: =IF(FrzPt!B68>0.0001, K68, FALSE) -> 303.368 | R68: Class 7 | S68: -95 | T68: -95 | U68: -97.7 | V68: -68.2 | W68: -52.3 | X68: -43.3 | Y68: -48 | Z68: -38 | AG68: -10
A69: 326SAF.MASSFRAC | B69: 0.10524168 | D69: Calculated | E69: MASSFRAC | F69: MIXED | G69: N-HCK-B | H69: 326SAF | I69: MATERIAL | K69: 258.116 | L69: =IF(FrzPt!B69>0.0001, K69, FALSE) -> 258.116 | R69: Class 8 | T69: -19.9 | U69: -70.6 | V69: -45.2 | W69: -45.7 | X69: -25.4 | Y69: -45.7 | AG69: 1.54
A70: 326SAF.MASSFRAC | D70: Not calculated | E70: MASSFRAC | F70: MIXED | G70: BIOMASS | H70: 326SAF | I70: MATERIAL | L70: =IF(FrzPt!B70>0.0001, K70, FALSE) -> FALSE | R70: Class 9 | U70: -2 | V70: 80.3 | W70: 2 | Z70: -5 | AG70: -9.99
A71: 326SAF.MASSFRAC | D71: Not calculated | E71: MASSFRAC | F71: MIXED | G71: CHAR | H71: 326SAF | I71: MATERIAL | L71: =IF(FrzPt!B71>0.0001, K71, FALSE) -> FALSE | R71: Class 10 | U71: -51.4 | V71: -35.8 | W71: -24 | X71: 4 | Y71: -29.6 | AG71: 2.79
A72: 326SAF.MASSFRAC | B72: 0 | D72: Calculated | E72: MASSFRAC | F72: MIXED | G72: PHENOL1 | H72: 326SAF | I72: MATERIAL | K72: 395.5694 | L72: =IF(FrzPt!B72>0.0001, K72, FALSE) -> FALSE
A73: 326SAF.MASSFRAC | B73: 0 | D73: Calculated | E73: MASSFRAC | F73: MIXED | G73: PHENOL2 | H73: 326SAF | I73: MATERIAL | K73: 475.952 | L73: =IF(FrzPt!B73>0.0001, K73, FALSE) -> FALSE | R73: K | S73: 9.99 | T73: 2.98 | U73: 4.77 | V73: 2.8 | W73: -1.4 | X73: 5.19 | Y73: -3.29 | Z73: 5.3 | AA73: 6.69 | AB73: 0.08 | AC73: 8.52 | AD73: 9.98 | AE73: -0.32
A74: 326SAF.MASSFRAC | B74: 0 | D74: Calculated | E74: MASSFRAC | F74: MIXED | G74: PHENOL3 | H74: 326SAF | I74: MATERIAL | K74: 501.8 | L74: =IF(FrzPt!B74>0.0001, K74, FALSE) -> FALSE
A75: 326SAF.MASSFRAC | B75: 0 | D75: Calculated | E75: MASSFRAC | F75: MIXED | G75: CYC5-A1 | H75: 326SAF | I75: MATERIAL | K75: 161.258 | L75: =IF(FrzPt!B75>0.0001, K75, FALSE) -> FALSE | Q75: Element-wise calculation result
A76: 326SAF.MASSFRAC | B76: 0 | D76: Calculated | E76: MASSFRAC | F76: MIXED | G76: CYC6-A1 | H76: 326SAF | I76: MATERIAL | K76: 213.6812 | L76: =IF(FrzPt!B76>0.0001, K76, FALSE) -> FALSE | R76: Class 1 | S76: =S47*S62*S$73*$AG62 -> 0 | T76: =T47*T62*T$73*$AG62 -> -53.797154 | U76: =U47*U62*U$73*$AG62 -> -140.67067 | V76: =V47*V62*V$73*$AG62 -> 0 | W76: =W47*W62*W$73*$AG62 -> 0 | X76: =X47*X62*X$73*$AG62 -> -5.3663795 | Y76: =Y47*Y62*Y$73*$AG62 -> 0 | Z76: =Z47*Z62*Z$73*$AG62 -> 0 | ... AE76: =AE47*AE62*AE$73*$AG62 -> 0
A77: 326SAF.MASSFRAC | B77: 0 | D77: Calculated | E77: MASSFRAC | F77: MIXED | G77: CYC6-A2 | H77: 326SAF | I77: MATERIAL | K77: 271.0058 | L77: =IF(FrzPt!B77>0.0001, K77, FALSE) -> FALSE | R77: Class 2 | S77: =S48*S63*S$73*$AG63 -> -0.060692929 | T77: =T48*T63*T$73*$AG63 -> 0 | U77: =U48*U63*U$73*$AG63 -> 0 | V77: =V48*V63*V$73*$AG63 -> -74.162698 | W77: =W48*W63*W$73*$AG63 -> 0 | X77: =X48*X63*X$73*$AG63 -> 0 | Y77: =Y48*Y63*Y$73*$AG63 -> 0 | Z77: =Z48*Z63*Z$73*$AG63 -> 0 | ... AE77: =AE48*AE63*AE$73*$AG63 -> 0
A78: 326SAF.MASSFRAC | B78: 0 | D78: Calculated | E78: MASSFRAC | F78: MIXED | G78: CYC6-A3 | H78: 326SAF | I78: MATERIAL | K78: 312.026 | L78: =IF(FrzPt!B78>0.0001, K78, FALSE) -> FALSE | R78: Class 3 | S78: =S49*S64*S$73*$AG64 -> 0 | T78: =T49*T64*T$73*$AG64 -> 0 | U78: =U49*U64*U$73*$AG64 -> 0 | V78: =V49*V64*V$73*$AG64 -> 0 | W78: =W49*W64*W$73*$AG64 -> 0 | X78: =X49*X64*X$73*$AG64 -> 0 | Y78: =Y49*Y64*Y$73*$AG64 -> 0 | Z78: =Z49*Z64*Z$73*$AG64 -> 0 | ... AE78: =AE49*AE64*AE$73*$AG64 -> 0
A79: 326SAF.MASSFRAC | B79: 0 | D79: Calculated | E79: MASSFRAC | F79: MIXED | G79: ARM-A1 | H79: 326SAF | I79: MATERIAL | K79: 308.444 | L79: =IF(FrzPt!B79>0.0001, K79, FALSE) -> FALSE | R79: Class 4 | S79: =S50*S65*S$73*$AG65 -> 133.30096 | T79: =T50*T65*T$73*$AG65 -> 0 | U79: =U50*U65*U$73*$AG65 -> 0 | V79: =V50*V65*V$73*$AG65 -> 23.197066 | W79: =W50*W65*W$73*$AG65 -> 0 | X79: =X50*X65*X$73*$AG65 -> 0 | Y79: =Y50*Y65*Y$73*$AG65 -> 0 | Z79: =Z50*Z65*Z$73*$AG65 -> 0 | ... AE79: =AE50*AE65*AE$73*$AG65 -> 0
A80: 326SAF.MASSFRAC | B80: 0 | D80: Calculated | E80: MASSFRAC | F80: MIXED | G80: ARM-A2 | H80: 326SAF | I80: MATERIAL | K80: 404.0672 | L80: =IF(FrzPt!B80>0.0001, K80, FALSE) -> FALSE | R80: Class 5 | S80: =S51*S66*S$73*$AG66 -> 0 | T80: =T51*T66*T$73*$AG66 -> -58.449993 | U80: =U51*U66*U$73*$AG66 -> 0 | V80: =V51*V66*V$73*$AG66 -> 0 | W80: =W51*W66*W$73*$AG66 -> 0 | X80: =X51*X66*X$73*$AG66 -> 0 | Y80: =Y51*Y66*Y$73*$AG66 -> 0 | Z80: =Z51*Z66*Z$73*$AG66 -> 0 | ... AE80: =AE51*AE66*AE$73*$AG66 -> 0
A81: 326SAF.MASSFRAC | B81: 0 | D81: Calculated | E81: MASSFRAC | F81: MIXED | G81: ARM-B1 | H81: 326SAF | I81: MATERIAL | K81: 464.216 | L81: =IF(FrzPt!B81>0.0001, K81, FALSE) -> FALSE | R81: Class 6 | S81: =S52*S67*S$73*$AG67 -> 0 | T81: =T52*T67*T$73*$AG67 -> 0 | U81: =U52*U67*U$73*$AG67 -> 0 | V81: =V52*V67*V$73*$AG67 -> 0 | W81: =W52*W67*W$73*$AG67 -> 0 | X81: =X52*X67*X$73*$AG67 -> -14.202874 | Y81: =Y52*Y67*Y$73*$AG67 -> 0 | Z81: =Z52*Z67*Z$73*$AG67 -> 0 | ... AE81: =AE52*AE67*AE$73*$AG67 -> 0
A82: 326SAF.MASSFRAC | B82: 0.0043484657 | D82: Calculated | E82: MASSFRAC | F82: MIXED | G82: ARM-B2 | H82: 326SAF | I82: MATERIAL | K82: 428.4518 | L82: =IF(FrzPt!B82>0.0001, K82, FALSE) -> 428.4518 | R82: Class 7 | S82: =S53*S68*S$73*$AG68 -> 0 | T82: =T53*T68*T$73*$AG68 -> 0 | U82: =U53*U68*U$73*$AG68 -> 0 | V82: =V53*V68*V$73*$AG68 -> 0 | W82: =W53*W68*W$73*$AG68 -> 0 | X82: =X53*X68*X$73*$AG68 -> 0 | Y82: =Y53*Y68*Y$73*$AG68 -> 0 | Z82: =Z53*Z68*Z$73*$AG68 -> 0 | ... AE82: =AE53*AE68*AE$73*$AG68 -> 0
L83: Minimum BP | R83: Class 8 | S83: =S54*S69*S$73*$AG69 -> 0 | T83: =T54*T69*T$73*$AG69 -> -16.293621 | U83: =U54*U69*U$73*$AG69 -> -2.9430794 | V83: =V54*V69*V$73*$AG69 -> 0 | W83: =W54*W69*W$73*$AG69 -> 0 | X83: =X54*X69*X$73*$AG69 -> 0 | Y83: =Y54*Y69*Y$73*$AG69 -> 0 | Z83: =Z54*Z69*Z$73*$AG69 -> 0 | ... AE83: =AE54*AE69*AE$73*$AG69 -> 0
L84: =MIN(L2:L82) -> 213.6812 | R84: Class 9 | S84: =S55*S70*S$73*$AG70 -> 0 | T84: =T55*T70*T$73*$AG70 -> 0 | U84: =U55*U70*U$73*$AG70 -> 0 | V84: =V55*V70*V$73*$AG70 -> 0 | W84: =W55*W70*W$73*$AG70 -> 0 | X84: =X55*X70*X$73*$AG70 -> 0 | Y84: =Y55*Y70*Y$73*$AG70 -> 0 | Z84: =Z55*Z70*Z$73*$AG70 -> 1.5716368e-07 | ... AE84: =AE55*AE70*AE$73*$AG70 -> 0
R85: Class 10 | S85: =S56*S71*S$73*$AG71 -> 0 | T85: =T56*T71*T$73*$AG71 -> 0 | U85: =U56*U71*U$73*$AG71 -> -27.561521 | V85: =V56*V71*V$73*$AG71 -> 0 | W85: =W56*W71*W$73*$AG71 -> 0 | X85: =X56*X71*X$73*$AG71 -> 0 | Y85: =Y56*Y71*Y$73*$AG71 -> 0 | Z85: =Z56*Z71*Z$73*$AG71 -> 0 | ... AE85: =AE56*AE71*AE$73*$AG71 -> 0
Q87: Freezing point | S87: =SUM(S76:AE85)/S58 -> -237.33676

Sheet DiesFlash
A1: Name | B1: Value | C1: Units | D1: Status | E1: Variable Name | F1: Object ID1 | G1: Object ID2 | H1: Container | I1: Container Type | K1: Pure BP (F) | O1: Name | P1: Value | Q1: Units | R1: Status | S1: Variable Name | T1: Object ID1 | U1: Object ID2 | V1: Container | W1: Container Type
A2: 336DIES.MASSFRAC | B2: 0 | D2: Calculated | E2: MASSFRAC | F2: MIXED | G2: WATER | H2: 336DIES | I2: MATERIAL | K2: 212 | L2: =IF(B2>0.0001, K2, FALSE) -> FALSE | O2: 316GAS.STRM_UPP | P2: 62.830338 | Q2: C | R2: Calculated | S2: STRM_UPP | T2: D86-10 | U2: MIXED | V2: 316GAS | W2: MATERIAL
A3: 336DIES.MASSFRAC | B3: 0 | D3: Calculated | E3: MASSFRAC | F3: MIXED | G3: H2 | H3: 336DIES | I3: MATERIAL | K3: -422.968 | L3: =IF(B3>0.0001, K3, FALSE) -> FALSE | O3: 316GAS.STRM_UPP | P3: 92.64466 | Q3: C | R3: Calculated | S3: STRM_UPP | T3: D86-90 | U3: MIXED | V3: 316GAS | W3: MATERIAL
A4: 336DIES.MASSFRAC | B4: 0 | D4: Calculated | E4: MASSFRAC | F4: MIXED | G4: O2 | H4: 336DIES | I4: MATERIAL | K4: -297.3316 | L4: =IF(B4>0.0001, K4, FALSE) -> FALSE | O4: 336DIES.STRM_UPP | P4: 231.70335 | Q4: C | R4: Calculated | S4: STRM_UPP | T4: D86-90 | U4: MIXED | V4: 336DIES | W4: MATERIAL
A5: 336DIES.MASSFRAC | B5: 0 | D5: Calculated | E5: MASSFRAC | F5: MIXED | G5: N2 | H5: 336DIES | I5: MATERIAL | K5: -320.4508 | L5: =IF(B5>0.0001, K5, FALSE) -> FALSE
A6: 336DIES.MASSFRAC | B6: 0 | D6: Calculated | E6: MASSFRAC | F6: MIXED | G6: AR | H6: 336DIES | I6: MATERIAL | K6: -302.566 | L6: =IF(B6>0.0001, K6, FALSE) -> FALSE
A7: 336DIES.MASSFRAC | B7: 0 | D7: Calculated | E7: MASSFRAC | F7: MIXED | G7: CO | H7: 336DIES | I7: MATERIAL | K7: -312.61 | L7: =IF(B7>0.0001, K7, FALSE) -> FALSE
A8: 336DIES.MASSFRAC | B8: 0 | D8: Calculated | E8: MASSFRAC | F8: MIXED | G8: CO2 | H8: 336DIES | I8: MATERIAL | K8: -109.21 | L8: =IF(B8>0.0001, K8, FALSE) -> FALSE
A9: 336DIES.MASSFRAC | B9: 0 | D9: Calculated | E9: MASSFRAC | F9: MIXED | G9: METHANE | H9: 336DIES | I9: MATERIAL | K9: -258.664 | L9: =IF(B9>0.0001, K9, FALSE) -> FALSE
A10: 336DIES.MASSFRAC | B10: 0 | D10: Calculated | E10: MASSFRAC | F10: MIXED | G10: ETHANE | H10: 336DIES | I10: MATERIAL | K10: -127.444 | L10: =IF(B10>0.0001, K10, FALSE) -> FALSE
A11: 336DIES.MASSFRAC | B11: 0 | D11: Calculated | E11: MASSFRAC | F11: MIXED | G11: PROPANE | H11: 336DIES | I11: MATERIAL | K11: -43.798 | L11: =IF(B11>0.0001, K11, FALSE) -> FALSE
A12: 336DIES.MASSFRAC | B12: 0 | D12: Calculated | E12: MASSFRAC | F12: MIXED | G12: N-BUTANE | H12: 336DIES | I12: MATERIAL | K12: 31.118 | L12: =IF(B12>0.0001, K12, FALSE) -> FALSE
A13: 336DIES.MASSFRAC | B13: 0 | D13: Calculated | E13: MASSFRAC | F13: MIXED | G13: ETHENE | H13: 336DIES | I13: MATERIAL | K13: -154.732 | L13: =IF(B13>0.0001, K13, FALSE) -> FALSE
A14: 336DIES.MASSFRAC | B14: 0 | D14: Calculated | E14: MASSFRAC | F14: MIXED | G14: PROPENE | H14: 336DIES | I14: MATERIAL | K14: -53.86 | L14: =IF(B14>0.0001, K14, FALSE) -> FALSE
A15: 336DIES.MASSFRAC | B15: 0 | D15: Calculated | E15: MASSFRAC | F15: MIXED | G15: 1-BUTENE | H15: 336DIES | I15: MATERIAL | K15: 20.768 | L15: =IF(B15>0.0001, K15, FALSE) -> FALSE
A16: 336DIES.MASSFRAC | B16: 0 | D16: Calculated | E16: MASSFRAC | F16: MIXED | G16: SO2 | H16: 336DIES | I16: MATERIAL | K16: 13.964 | L16: =IF(B16>0.0001, K16, FALSE) -> FALSE
... A32: 336DIES.MASSFRAC | B32: 0 | D32: Calculated | E32: MASSFRAC | F32: MIXED | G32: S | H32: 336DIES | I32: MATERIAL | K32: 832.4132 | L32: =IF(B32>0.0001, K32, FALSE) -> FALSE
A33: 336DIES.MASSFRAC | B33: 0 | D33: Calculated | E33: MASSFRAC | F33: MIXED | G33: C | H33: 336DIES | I33: MATERIAL | L33: =IF(B33>0.0001, K33, FALSE) -> FALSE
A34: 336DIES.MASSFRAC | B34: 0 | D34: Calculated | E34: MASSFRAC | F34: MIXED | G34: ASH | H34: 336DIES | I34: MATERIAL | K34: 4046.09 | L34: =IF(B34>0.0001, K34, FALSE) -> FALSE
A35: 336DIES.MASSFRAC | B35: 0 | D35: Calculated | E35: MASSFRAC | F35: MIXED | G35: SAND | H35: 336DIES | I35: MATERIAL | K35: 4046.09 | L35: =IF(B35>0.0001, K35, FALSE) -> FALSE
A36: 336DIES.MASSFRAC | B36: 1.8700548e-08 | D36: Calculated | E36: MASSFRAC | F36: MIXED | G36: ACID-INT | H36: 336DIES | I36: MATERIAL | K36: 325.886 | L36: =IF(B36>0.0001, K36, FALSE) -> FALSE
A37: 336DIES.MASSFRAC | B37: 7.7713339e-09 | D37: Calculated | E37: MASSFRAC | F37: MIXED | G37: CRBN-INT | H37: 336DIES | I37: MATERIAL | K37: 369.68 | L37: =IF(B37>0.0001, K37, FALSE) -> FALSE
A38: 336DIES.MASSFRAC | B38: 0 | D38: Calculated | E38: MASSFRAC | F38: MIXED | G38: LGHM-INT | H38: 336DIES | I38: MATERIAL | K38: 360.716 | L38: =IF(B38>0.0001, K38, FALSE) -> FALSE
A39: 336DIES.MASSFRAC | B39: 0 | D39: Calculated | E39: MASSFRAC | F39: MIXED | G39: SG-INT-A | H39: 336DIES | I39: MATERIAL | K39: 650.93 | L39: =IF(B39>0.0001, K39, FALSE) -> FALSE
A40: 336DIES.MASSFRAC | B40: 0 | D40: Calculated | E40: MASSFRAC | F40: MIXED | G40: SG-INT-B | H40: 336DIES | I40: MATERIAL | K40: 814.55 | L40: =IF(B40>0.0001, K40, FALSE) -> FALSE
A41: 336DIES.MASSFRAC | B41: 0 | D41: Calculated | E41: MASSFRAC | F41: MIXED | G41: SC-PARAF | H41: 336DIES | I41: MATERIAL | K41: 155.678 | L41: =IF(B41>0.0001, K41, FALSE) -> FALSE
A42: 336DIES.MASSFRAC | B42: 0.21079982 | D42: Calculated | E42: MASSFRAC | F42: MIXED | G42: MC-PARAF | H42: 336DIES | I42: MATERIAL | K42: 421.34 | L42: =IF(B42>0.0001, K42, FALSE) -> 421.34
A43: 336DIES.MASSFRAC | B43: 3.6155648e-11 | D43: Calculated | E43: MASSFRAC | F43: MIXED | G43: I-PRF-A | H43: 336DIES | I43: MATERIAL | K43: 197.33 | L43: =IF(B43>0.0001, K43, FALSE) -> FALSE
A44: 336DIES.MASSFRAC | B44: 0.00052334018 | D44: Calculated | E44: MASSFRAC | F44: MIXED | G44: I-PRF-B | H44: 336DIES | I44: MATERIAL | K44: 330.26 | L44: =IF(B44>0.0001, K44, FALSE) -> 330.26
A45: 336DIES.MASSFRAC | B45: 3.9172703e-07 | D45: Calculated | E45: MASSFRAC | F45: MIXED | G45: CYC5-A | H45: 336DIES | I45: MATERIAL | K45: 218.246 | L45: =IF(B45>0.0001, K45, FALSE) -> FALSE
... A80: 336DIES.MASSFRAC | B80: 0.11950517 | D80: Calculated | E80: MASSFRAC | F80: MIXED | G80: ARM-B2 | H80: 336DIES | I80: MATERIAL | K80: 428.4518 | L80: =IF(B80>0.0001, K80, FALSE) -> 428.4518
A81: 336DIES.MASSFRAC | D81: Not calculated | E81: MASSFRAC | F81: MIXED | G81: BIOMASS | H81: 336DIES | I81: MATERIAL | L81: =IF(B81>0.0001, K81, FALSE) -> FALSE
A82: 336DIES.MASSFRAC | D82: Not calculated | E82: MASSFRAC | F82: MIXED | G82: CHAR | H82: 336DIES | I82: MATERIAL | L82: =IF(B82>0.0001, K82, FALSE) -> FALSE
L83: MinBP
L84: =MIN(L2:L82) -> 291.722

Sheet Cost
A3: Summary
A4: Total Capital Cost [USD] | D4: =B4+SUM(R20:R26) -> 1.663204e+08
A5: Total Operating Cost [USD/Year] | D5: =B5 -> 0
A6: Total Raw Materials Cost [USD/Year] | D6: =B6+U22 -> 34004.597
A7: Total Product Sales [USD/Year] | D7: =B7 -> 0
A8: Total Utilities Cost [USD/Year] | D8: =B16*8000 -> 15889638
A9: Desired Rate of Return [Percent/'Year]
A10: P.O. Period [Year]
A11: Equipment Cost [USD]
A12: Total Installed Cost [USD]
A14: For Quotation
A15: Name | B15: Value | C15: Units | D15: Status | E15: Variable Name | F15: Object ID1 | G15: Object ID2 | H15: Container | I15: Container Type
A16: Utility-Sum.TOTUTCOST | B16: 1986.2047 | C16: $/hr | D16: Calculated | E16: TOTUTCOST | H16: UTIL-SUMMARY | I16: DATA
L18: Base
A19: Name | B19: Value | C19: Units | D19: Status | E19: Variable Name | F19: Object ID1 | G19: Object ID2 | H19: Container | I19: Container Type | L19: Equipment | M19: Scaling Stream | N19: Original Flow | O19: Unit | Q19: CAPEX [1Q-2022$] at Base | R19: Base CAPEX | T19: OPEX at Base | U19: Base OPEX | W19: LHSV | X19: Unit Price
A20: 510.MASSFLMX | B20: 6654.7636 | C20: lb/hr | D20: Calculated | E20: MASSFLMX | F20: MIXED | H20: 510 | I20: MATERIAL | L20: R-510 | M20: #340 | N20: 9600 | O20: lb/hr | Q20: 5266304 | R20: =Q20*B20/N20 -> 3650625.9
A21: 200.VLSTDMX | B21: 829.00636 | C21: cuft/hr | D21: Calculated | E21: VLSTDMX | F21: MIXED | H21: 200 | I21: MATERIAL | L21: R-225 | M21: #200 | N21: 2058 | O21: liq scfh | Q21: 7020728 | R21: =Q21*B21/N21 -> 2828099.2
A22: 404.VOLFLMX | B22: 165519.71 | C22: cuft/hr | D22: Calculated | E22: VOLFLMX | F22: MIXED | H22: 404 | I22: MATERIAL | L22: PSA | M22: #404 | N22: 24717.514 | O22: cuft/hr | Q22: 780993 | R22: =Q22*B22/N22 -> 5229884.3 | T22: 5078 | U22: =T22/N22*B22 -> 34004.597
A23: 622X.MASSFLMX | B23: 446452.17 | C23: lb/hr | D23: Calculated | E23: MASSFLMX | F23: MIXED | H23: 622X | I23: MATERIAL | L23: CCS | M23: #622x | N23: 862853 | O23: lb/hr | Q23: 297930841 | R23: =Q23*B23/N23 -> 1.5415357e+08
A24: 255.VOLFLMX | B24: 9236.3253 | C24: cuft/hr | D24: Calculated | E24: VOLFLMX | F24: MIXED | H24: 255 | I24: MATERIAL | L24: R-202-cat | M24: #255 | N24: 35.315 | O24: cuft/hr | R24: =B24/N24/W24*X24 -> 99120.604 | W24: 0.5 | X24: 189.49333
A25: 210.VOLFLMX | B25: 8512.449 | C25: cuft/hr | D25: Calculated | E25: VOLFLMX | F25: MIXED | H25: 210 | I25: MATERIAL | L25: R-220-cat | M25: #210 | N25: 35.315 | O25: cuft/hr | R25: =B25/N25/W25*X25 -> 91352.249 | W25: 0.5 | X25: 189.49333
A26: 272.VOLFLMX | B26: 42495.301 | C26: cuft/hr | D26: Calculated | E26: VOLFLMX | F26: MIXED | H26: 272 | I26: MATERIAL | L26: R-225-cat | M26: #272 | N26: 35.315 | O26: cuft/hr | R26: =B26/N26/W26*X26 -> 267752.42 | W26: 0.22 | X26: 48.952444
