Workbook

Sheet ASWXL.Storage
A1: ASWXL Storage Version 40.0.0.10 | B1: C:\Program Files\AspenTech\Aspen Simulation Workbook V14.0
A2: UEsDBBQAAAAIAJuByVpVb1JLuDABADAKCgAYAEIAQXNwZW5UZWNoLkFTV1hMLldvcmtib29rTlU2AE5VQ1gYAEEAcwBwAGUAbgBUAGUAYwBoAC4AQQBTAFcAWABMAC4AVwBvAHIAawBiAG8AbwBrAAoABAAAAAAA7L0JnBvJdR5O7pJckntoV7dkyYLolWVbO0P0DYyHVDAYDAdaYGY0GC53LekPNTE9Q4gYYISD5Mhx4vvIHTt24iRO4vi+7/u+7/vI6SRO4px2EieOE+fSv15faAxeA9Xoqm6gp7m/fYMGqrteV/X33qvqr16dO3/u3LmPkn/wF/499RgRn1LoHRvtPaNxb7lQu/NyZbmwv99sv5B5yej2mp32DTm7DP8J2RcyxUGrP+gaN9rGoN/VWy9kdgZ3W83Gi8bJXue+0b6R1RsNRWpkc/kDMZvbP7gIFb3x9PXvdLr373Y6919Dfny8/qDxVL3XPBq09D6prfdcXW/0mw+MmvvVU/XjrnFgdI12w+g9VW+2m/2m3mp+xNh/pn6k9/pGd13v6zWj//rRw2X7Bl7n+brYafe7nVbL6D5d7+rtQ6Oqt/VDo/tU/bDbGRwXGqSK3mvq+qDfOSKVN/b0w9vH+3rfeGt93WgZfWNPv9sy7twz2uZhs324C1d5R31glio9ahitjUG7Yd4KFNsmt+7c75vrPf2BUWm27xv75Pa2yTXMeyUnvsX8qXR019jfH/vxbfWDTrdhbAxarV3joGv07m23dwftYufoGFTahyYDvTcMHXqnqh+/vt4HPddaevt+sdOCuzba/d6b63rvoXkHBVPDHb1tlNpwvH+B/DtH/iPS/Hfh8XPXTvfbS3q3CYWL0IDmBeDxUU4XG/7cs74ZduXomW8fe/BqZfh/WB5KPX+61I77NIxe7vzHni4JPW59hE9Q5vInTC4zfD6g9FtOF971PDJQ4GNOF7g1fIpMlcx/mbH7PNVdUPS7H6+dkKf0aKT5bhlto9tsLK83zS/07skHxfe9zy5Y63fJ8/dC5qjX6HRbzbsexJqApcDrXU3TlYaiCnlJNghqP/DC+4JqUW73JZGTEtt3P0R0YHvxDzC+3HnovCuPgwDoXLkI4hL0/ZUnQMLhZRBXiLj4x8T4TnpooPgTD/TWwKjXz12GS8OVyXNELnTlSbjMU3B4Eb6lxOelut7t6ieX6o3OoN2/MP7Mlp3z3vcBEyLmDT1te4iLF0JB/HTlbx2rfHimt/pn7Ka7eJHKTrwWitYPB839i/Ut/ch4iljrXqPbPIYfn6s/aPaaYPT6tb7e7Q+On6u3muQBa+91qqTNCZh7r64bD4iFrHQOa8SxVJpHzf4FYkMPScnOoWk+H/UtvD1plSzAbb2+fkdv9ouDbq/TBWNPjHKbFHlzfaM16N0bqmfXQq7+ZJ3oWIS2MLrP1CvEL9U6rQfGXvPIeHW9YNt7V8+n6+SK7tHlOrliUe8Zb7S9zfoAFFo/aetHzQYp2XtDfd86sHzWRtf48IDYyZPXjH5/m3jQ3jOmrB0bDVOdx8+fN58zx/xD8z9pw/AW0fn8+ctLk56CEjSKfZ9m21jm7/LT58+PPafQfZ4HhtyRWfiS2fUX/pBAxFszPPWP1fXH6ncfqzceq+8/Vjceqx88Vj98rH7vsXrzsfqHHqvfPzf8d/mJJx6z/33eV9x74VXvvbX2ZZ/ye1/85c/98aVLz5Lf37lzQiz8Sa/Zq7+n0zZ6dUURSFDR79QVTQBP+94BiS76J5eeMy93/o9Iw1x6NTyU5n3skK69BJHL82JDzelSTltShOzBkizK2lJ+X9GXDCWv6IIgHKhZ9cprzWb41HedO/clf3DnTypf8zufTy70OvvpNv9dec6B2iVabweG5Wqlo+9vkBCh033CNmOXISLQu0b32U29d6/Y2Td2up0HzX2jexm+gCf7ArFkvUsvgYHpEdvyOAHYk5ffgtj8snOt57Efx64PPff77829+5NBs6twR1feAOKNcF+g7hTfDPbsDU7ctmscdSC0sm/rystHrVrjnnGkP0k+rTcPDm519SPywD5jq2aXMw3Hm8DovJmIn/mix1ff/eiolXlg2/hrwnL2WoY0ZIdEt4c3rg36B0uCeu3dN5++uvqot9Iza8g0929cc7W6liHIOzT6YFJ6x3rDuHHtXr9/vHL9Oqn2mKBvudM9vA4le0ZfWH7U27+WIVW2eytHvX67R1ua+qqPhkUfPny4/FAyS4rZrHD95WrFaqOhBgTqOrnNbtu+t94SsQDdTq9z0F9qdI5WSLklq9TwnONu53j6OVDqWkbvE4N4d0DsTKd7tG4c6MR33rj2YUDPQdMgSpMI+YhYBZ+fSbtnMtDydrEMsVDGSONbyq2Ue/aDceNavzsw3O9v9wxierum2W7oLcP+2byudeWGGSE/2js5Nuxv7e/vdZoNI3PUbG83GsR637hGnowj/ZFzNGjfJTZx31FyeOKoqmRw4LhOUApaZcXztInes/0VGv7as8z16Z+wqsvrbjPsGvr+drt1cqp1CmQIU243uuZZzm99UvGNa+RqxN65JYM/49cpNITreSrsmc6Tc50ep8+y6tHnhEYR08B6VNjvDOyHJDIVTPcebyvYjjReJczgOl4VzFFjhH2xet3PmJi/4EbI/MnWm8Lq7flZveyZtnpzY4HMZy5eFUiQuEl6yejudh56NLnb6bQMnTTPvhMTHOitXrTGkajm6an50w8eYwib9H68XbjW6ZL+K3QhGmKGo9ma405zv39vzrrJNIK1/kkrZqTtNftzoQfAndQ5B5qU222jaz29MT63VYPUUWjvFw2Y78Ee3giVqfX1/gCLQlwAbb+4+CFJpdnrc4xAzDogDIkwpijea7b2I66TuMTtgwNyTkTo4f58FJzJijMdng5bIVbrXOy0BkftGA2z7ahi9lGH7U7X2J/HmIahtZnFUY2GD1HXv0bOjjiE4Wv+qp19o5XOVPppyHqmMvgTNzezBqfnLWNQwZ63tB/Sqn6yqT8wts22IRfZ68atX6XzcCSUj6OJjo/jVmEOZlXBNMWrwY4+MiMRgwbDt+hzMNsY89sGE5jFln507FZb1E27Yf+WsX+cq3DLxLKP1uZvc6l1sdPed9/unFYbfmzCR2M/MxevgEAh27NN0nUOnJ8TIU3s7pHgKRJkNYFFajdUzBPSeq85jA52us1OlzxeN64tiYKsyTlJlXPur8Nwc8MBiPm9G0zU+np7X+/u2+SE3gsZ+9Nmc3/fiPlOLe6j5eROP7XWbxnnx0BtsWc/PQvXFFaY7tMUzo9JbwpnFIc3hvMrz+aIec5kXfB9BuzfEnjP4oR7FhN6z9KEe5bOAtTL6/KEJpDPRhMoE5pAORtNoE5oAvUsNEFFv2u0zsKNwjoDvdmGuZ0EmnT37up4UOv+zjOujXm6xn4Fn8Bbs7U4CzBdb/aOW/oJHoLbP56ZAcmgc1TvWJoiE1jtZj/TOchUDb036BqZ7WHBpLdLUW/XS8D6qZf3EVuntzPmrxnr9VjiZzNMDkvdXGmGtAb8mHF/THxjrDfJQc+cSzsDdwtGoG5SbFHzYP+S+GYYhj9FvW8cdrr4zLkdAnnLJL5pzEnd+rafFzF/ntl3LGKDuM5jguc4Ew2xqffqpnfoGu3xtiC/Zry/Jr45yr2WoR+MN0S5l6nYPyS+DaxIorw/wWBY8UR5PblGgztd1nlvm/LC+K1g5duJpUfESbT1Fv+e5N1OUx7RJBDUHYZmuqoS1XBu+JHpqsopqs31qsqNVvPYXrJ3ainUPGiXrvlM13ymaz7TNZ/pms/gIVO66jNd9Yk/Iem6z3TdZ7ruM133eRbXfe7ph6JpBLEZhbO95tPKGOHR0508Jr9kXB51rHio7rd8dDQ7dU60JO2FM2GgIVlPDc7UiLh6VhvGr6CVf31cPzsv+3ytBDJhgy6ksmATe9ZDEzOogg5mYl/jBVsKOGucx9twDtI2kjb0UdBqwzlQMV1/yEdTe3E7vnzWzIoec1JTa+U7vlB2DvSbvgbZVNJa04sb97laezxP2kLibysRerx97JN3wHXKI1F3tG+mYrbK5M6rJgc81u7RD8fmsOJRA96FxezJ4TGMVo2IRrTptF46rZdO66XTemd6Wi9lC6EapmyhlC2U8nFSPk7Kx0n5OCkfx6NOhFFJSshJCTk+I4FIQtO4Y1DL7MU8H7fRacccu2wNju4a3XmIou509eM941E/ZgdQBifU7HSLnVYn5hS+8HRErAZf82Jh7gwZmUqzPQ8R5x2jeXgvZnibD3K5vW88SsrTbE2qnqGnOfVWqbea/HQkylvtdDsHzZYxuvIznbZNp23nf9rWJIDNpWZzPaFM9NvdG3tXOg+abXW2D0h79WKcpttrHhmmu3mgt2JmbhBN5oDimL5+SF8/pK8f0tcP6euHwOF0Sg7ztEis3J+UoDZiFVOCWkpQOwMEtVrDaOvdZied00jnNEaGv+XtNR2isrkcm6cTLjNoBrarSP6HS82lgnM9IzTfCcnmYFYonQRJJ0HSSZB0EoRpuK8/MIqd48l7rEaPoVjnZtCQ0eiRavpb4N7nzTXtGk0SEjX1VvMjxpypVtUb3c6acUCG2jWjX24fD/q9QqPffIDlpICyGatwhpTOWMUzTvkJNxZ56g/Pfe0O2lR3RMrN760UDogpmnonZqn5vpFTzxrUSP+kWaUn2Jx2oXbHGc/XT1UV4/NHcZfQabPcHjkvvqdx0n0Nn8Vgt+VcO3IvW+k09L69zdHoDcGvmeHPsZK+bP92WsWtzGnHZ0ZNbhsL3LSMZnIufUnibY1YJ6Ct1xPQ3DFTDtK3NfPztiba9yKcbY5xrHf1fqfbK7cPOhwNzq1uZ3BMaou369aNRvNIb0WqB7sOtMrf6zTd6/hcAW580G6SKu37NrNVvmgMU7LtdEk7dE/IV7ZpH1ZiatsyGuShyDw61vv3blxbvn79qNdv91as5JxNK7vB9ZFzDppGa985wSoNGLnu1dTSyU9Jz8Wh9YudNukZHbDFQzkrUgugntPnpM1ENu24x6cdSYT5cgW0JVopwRUyF4hOV8q1glNLusszZ2tsgUFje/wnz9aWw6rqcM45IcyrK4tmdXM4cjAFcG3AKFgtDgoFhr+37bSwbXd6CzDO+qqsnssILFZuFpXmwmaNoCvLpMk52i03KwBRzDManN0YOKkVuSkKjcFW2Sia13zm2KrNCYXjeSIC2d7TOSbihqP5jo9Jw9tvC1m3t2dVNBM1vausmSvrWfTKRFnvIlrmymIr+Oq4QxyOMrbYu010JSHXu3UtWt3HG0263/BOC+d6M7/jERpjHB07yqPkdn8x9+b4hDSLO71vnHSNA6wnkfpISaM7ucP53cuYfzJvyNLf74ZGRnD+NzQ6auR3C95Z9AB34XElpx51W/8x38UHN6Psrlm7wccqheiKWe2cZ+VHgJvB3Mjke6JwgHxvdBboeEKCyXc3FovwvZdTQUow+OAhQDgUzRhWzAym0eAeC/Xt+8EGPVGOH4Ldy/Tb4H4H+LiG+uE6PSIM91gFHl+yfqDGkc7ggYrQak24kRlN1kx3Edxeed6ceCZybNXdd0fsZ4KGe73N6trH1Z3FnQfRebj32ww6mw8YRRxC656jfsLZPt0RPNnjDT86ZRy27cNOQAd93ulugfa5n+UWQrospoFQlBGQ/apm7M0N0vwCt7dA2CsuavtuttI4eEfea1Pby2jdKkuHGoUrdeIaFKmzNXgElmY0DEB1Dx4MRGteRogVocPhaE3LCH8FMSsaFx7MVHtyiopk0Zka94wj/ealjzl37tzvfenrV/ebBweH3RXrj36UeXTUIpe2Zh9vXBt02/YZvaWjZqPb6XUO+kuNztEKKbdklbpmn2NdYto5TkVLD4itXXUbybrGdMbWzdURp5qx1W/un/K2Q45Et/NwGzrYZHjZxe/pveI9c3O3G9ea7Z7R7Rtw6fL6zezqdSJXYU72ZnnrpVJtr1ra2ltZ3uv09VaGDN/3B41+pqa3jN7qdbPUqrnF5E1Ny4qSlCXnW8er5vrim7dr69dfMfTu6nXreNXkeu0aemv1uvlxdYf06M29zvGyfnxs3sJyrfmRZvswo7f3M8VOr08+L5ceGY0BrJWoDY5gPnh5qm7mZVdrzaNByySE39w56XZaJ71mr/6eTtvo1RVFqDfb/U5d0YT6QadrP02r1z3nrFo74N0ENd6+pq1et49Xh3sy3jRXA61e93yzOtwD0fnV882qZ5/Rm7c6nf3V695vVt2NPT1NOvxu1eE8O1d2j1crzfZ9d+tP+8qj361u3/0QAZ7Z7mijeX63y55+EJwyTtcPSW/4FUdKkAdMGL0YfEG+FW+e7mD4SYSfpJvjjwP8KMGPMoE++aNYf1T4U9HvGi1cF+un1fVm77iln/jr7C2wWtTb9RKsMARoDA9WN/Ve3bT4XaMNP40cr5Z7LUM/MNFkfVq9PgJPWhiLCIwFChgLHhhvL2d2IOPq/rVRxJ6GKm+YXttZ9qrCAaBCNmKE8oHmsI188Lg9AYXDk8eht+0B3LUdD8ROYdLCFopJ2cSbDyaVUyj0dDiKvpHf5wh1EoI6kQJ1oo/zXDd6za6xn9nV+0amc5DZNfokSBhFo3gajqRdGiRuuf5O3rj0044DQPMR41PkA1C/FgvlPv0uGpMH9VMHgbFf0TlCtIwgWqJAtDQxHN4mj6QOzWk26yieBS0vktgtxoD4tHYc8KxEjGdPo3ILiU83G4OY+PQlYw2KTyvjGxWfLjhHcFYQOMsUcJYnwvl2v0keuKbRQ+CsiYqWj3N4e1o5DmjORT2+dduUG5hPtxoDMJ++ZKxgPq2ML5hPF5wjMKsImBUKMCvTpqqgGzNF/bgJx+OQlsWcqGqoh45ktgpRjwOo5YhB7WlVnrNWSOOxmbxCLhz3HBai0qSpLKT4HKFdQ9CuUqBd9aAdgdw6GYE0+nBkNj48OKfG16KsKbk8B7SjVfOY3RKjHj0Pm4zHIBprNh8MY/DxH0hjFx7HMA5JC8oWFiXrj/8QGasIGx9j5dhBUggLyRwCSY0CktpEB7yrP8xUddjrizwnWESdz+ezYowRNaYgB9iqUUfVbrty879YyzHwvthlY/W9mEK+nhcrPEd+N4+APEcB8txkv2vHGRMcr5AXZCmvcHC8eN08PK8Q9TzXsM04gBhvNxauF78yD9+L14SAEy84R97Xs9htiMw8BTLzXmQafWjF3rLR6LQ7R81Gr66buSVPYdHFoNnPsDfaodGdADr/yzKFmblJm3Xl2j3D6L+9IK6Uow53BS5gG285P6DZbT0BXuPXQqDlXiYYoMavjYBpvNAokAAc9WJn0O6bUPIcRgUmjPck0BCfhCwKp44+6Hd6OjsgeS7IEkJmRy4wSjzNEgIfnqswRIbnqhgmPD/PGxpQ+hAVf8hLINp5ZXe7vLVcenlnV3Rg4NkCAxo2c9whD2qm081YOegyD+D5yJBnNlM7NhoZ49Fx1+j1SOnljLnyW2/3X4DiG51uv6u3PQUyzXaGeIOjHrxK3mh1HvbAI5ALdsk37cy6cdBsG5nr7pnmz73lzC5sGL/UaDUb9zP9TsbimGbcNgIS7wuZ/j2jnRn0SJN19cMlEn8s7Xc7x1C+0Tk+gUrM0j1IyUqq2ffUaNdDOtlz67Y5yEvaspBX1VGrAJtt+5sE99YgEto2L9czuRiH7SVos2W72c20yE7jc/a62ko5apLjsOk4ETXs5vS1K1YzT7AqdtOPGRTLUFAaEfsitv0g2vZ18lB13dqH3wx/rFv3UKqVb20t1XZKRU8x67dVK8H/TbjB5kHTII1hfzNiouzK8aC3Xt4fiXvheKLtGupQJMPdw073xE9H93dPiC3EEWJjhC6BhtEleClde0uSkF3equ0VbpUwO7g1OLprdMFsEftGLvYCMWWN1gDSvhLz0t434NLmoKdr3O00W0YXtybScKhsAg54ZdYHC3Q38+SfDTfaAGSt1Wnc7y1bt2CZFOdGONuU3EoZf7EM6Tx8TYr140wWReIzarZa0NeMmC07wYo4rR3OjDhXGbMjdvX+ZmS3sL6xWwhmQqy05ObjZj1yzjcj1sXRiZ95WatsF1+cS8OC8coEGmKZII0Zlo1Sab3ua1w2DBKNmHYl0zbtDG47hPwp2yGcsh2SEN5yDDVdJl8uCdxtSH6ljFNHedkQaMb5syHeJ2R8fGN3RbDBjX1SNPbEYyDses+izcDIawINe02Qx2zGWqFWrtV3dzGLsWsctAaPMsDh62Q+YXhkQKv3m60W0HXh+BMzD+81G/fIGAyiFTL4OegaRuYhvMswR3B6q5VpwL4VUMI47pPiZBRFoNHcz+zcgx9uvKQfd7pLleaHB839pQ1y+h04u9A+qYHF8jFVwrKknLZWpSVBOWWxhKz7b9R0TX5hgNitYWtxtldCdqXssxiFm8WyWpOV0VrTSVvcrG5XiKmxPjO0Y8N+CBcNDa8TaTwklN4FTY0GQ0OVYjFtZlfV7dmEm9VCrXYV+vBqbW/9pe3KVbsv3QJxm0KM+ifQcP8EZdQUilGMy4TT1orpuEyMeFwmCMRG4S82udkohgYqkDUS4x2ZienILHLTgvEMBRqioaCOmRY2IzNp1HrAo2OZCnH2IZmIDclE/hPFgkiMB/6ClpvxkObReEwZkoli4AGZiE0TczEi3uGYyHV+eH7NBMZ9FGjIj4I2ZiYWeTCWXZaiGIqJ0Q/FJGKppEgtldmW8zIQm2i9ohmIcQt/0oEYKzOIsUMFGnqokBs1g1IkAzGR50BMinogJhMLhS/T4hZLiTHFUlK8AzEpHYhFbVpEjN4q0PBbhfyYaWEyEMtxGIdJ2DgMnjbetkMhtgPPwsDLduTm0XRMGYZJ2cDDMDglGhPiHYbB1c+ikcBouyINbVfMjhmJxR6GeUiEHMdhUvTjMJVYKnwtHL9xGEtaYdiB2ET7Fc1AjFv4kw7EWBlCjLEt0jC2RS9j28r2cbJUGxwt723v3d4rbtf2RlYwmFEPLL6DDxSmY9fokZ7tZZzltN4atgd9MCWeitivwbPtxyePGxaJhEASh0RUW51+pmb0/awLtBur4OdU4/paEU+jT1pMO+yHcMbEc6Exa3J7r1xZqt2uVgu7r0xkLxf2Cr4WBZq4obca0ON+IZFHiRH7Megc1Ts2aJ+/vq+fXH3++r0uEUfNNpEEGw3yp0P6dunE0OEH65uHhnGf/DG/u2+deN8887639H27RLVqFYG/w1/h6MRco+7VIoRJW28eGW1Y/HAT7nRpt7BnDhadL02k1nc7D6FvMPr1qUbGwro4ljaKaCJNqkyaXt61JKq1wsZybW+3Wr+9szNmx2hWD/e7hn7UW7YvZVss54rLL1WIO9jYXa6WXy6tgyErVJYLu9WlAv91jrDQkcNKxwitl922vlbLavMJBmvYseNDN7tnPCv9zT7yLO83e8uTtdbuNydV7ZhVs38fs2iOmv62rEpguVuGyk7bM69lsq/vG+yYGB6C3wfSpE1KhepcghrjPIs0nGdRmgtQr/EHtURAjb9zSkE9M6jXpoB6jTOo15IMaoyULNKQkkU5dlCXt9YLWzX+qJYJqjmk0zu7qHY6zhfWTgFuuHYqSC6wMYqtSEOxFZV5AHZpqxQBshWC7MWeQpg/ZFs9NwnaVgme2LZqSC64MZKrSENyFdXYwb1V2Nnc24RO5I1ulaCbQxa+s4vuYdf5wntYhBu+h1UkF+AYPVWkoaeKWuwA39ksbRW29jb5A1wjAOeQt+TsAnzYdb4AHxbhBvBhFckFOEa8FGmIl2JuLgC+XYkgPM8RfHPYnOJs49vsuYnwNktwRbdZQ2LBLWHUR5GG+ijm4wf3duWVpcJulT+68wTdHDaGO8PodrvOH95uEX74dqtILsAx2qJEQ1uUsvED/JXdSCbXpOxKWcJzYaT4ng3fTs/5w9spwQ/dTg3JBTdGxZNoqHiSEADcQUh4U1Be2XypWlsSFC/MecO7Kq7cXkD6ikn6hKtEhXKnb+hhPoGVx3Vazb6+L9lurT+43rp7taG3rh8eXb0Ff+8fXn0PiPv2wX3zqGqXrFpH7mHVKVat7jTMr6w/E9h0iC0ZsuOA07tU2oKpwJ0grLk5Nj0Yb06i4c1J0fLmareWdiO1NtLK7ZRX42tkoDsW08AkKnBAN5um2m06WoIcGM6N3VqkAJZXbqcUGl8A2z2SYjh2DGN8OImGDycF4cONBv+Fblc/mRnN6zl1SWC84th8oFKMjmDUaeeAe0XaZ3FDpFOBb9xevLpx9cWru7NG2Xul6k5pt7B3ezfQ0pTQEBd4bYgnYcw4iYYZJyHMOMtyw+pJVm7auaLtnu/AU8DYPW90P7LDba+thRzCD7sRcc6OK7Zds90jjmueYgDs0tzwb18/uR4Z47pJNFw3CeG6cYfrJuscjDZWpZXyAg6AY8fqpkgN1E0s/yIrlG5OSrO48BDF2GoSDVtNQthq3CG6zQmi8kp5AYe4sUN0mx6i2zwhup1oiGJ8M4mGbyYhfDPuEN3iBFFlpbyAyz1ih+gWPUS3eEJ0K8kQlTHWmETDGpMQ1hh3iBY4DUrVlfICrtmIHaIF+hFpgedwtJDksaiM8b5kGt6XjPC+uEO0uM0Honx2i008RKE7KCEKRblBFC6eXIhi7C2Zhr0lI+ytCCDKKdL13X01xehkjNKHukWuw9FiosejMsZ0kmmYTjLCdOIO02ppb7OwxTolvA1V301OU6hOgqrbJ5Rwdctzg6xbQ3Jhi1GcZBqKk4xQnLjDlidqJ2z1meJ2Em4DwpY7apMPWozTJNNwmmSE08QdtDu72zv8UOu/+WWK2kmodXuFErZueX4rkZwakgtcjKkk0zCV5DiYSltLa7f3+CHXf+fJFLkTX9643UL7Csc9gd+LHLeK5IIX4y3JNLwlOQ7eEomCStyg678VYwrdKaFyKVioXOIdKpeSDVqMySTTMJnkOJhMEALxQ63/9oQpaqeFykFg65bnGionHLgYv0mm4TfJcfCbBIh/+CHXf3PAFLmTkDvsFkroDk/ght1hFYkFr4Ixn2Qa5pMcB/Opxuud7YSt8lLcTsJtLcBb2xrXt7a1RL+1VTD+k0LDf1Li4D9tcQOqRoCaUqBmmIsKANQtrkDdSjZQMRaUQsOCUuJgQRWK5XXWCekcqOYIVFMm1AyEYqtPaDnFVml+tGLr+skFLMaHUmj4UEocfKhCZb20+co6r/FrnmA2pUTNgFm3W2hh657AD7luFckFL8aKUmhYUUocrKgXS3vb7BPAOjklsitlMaVFBceu2yuU0HXLc0OuW0NygYsxoxQaZpQSBzOqUClub7LfeMFBrkCQm1KjZvG6TrdQe13nBI5e16kiueDF2FEKDTtKiYMddet2oVwobrPOtOiAd0G3E48dvMNuoQTv8ARu4B1WkVzwYuwohYYdpcTBjqrdvlWp3uEE3QXdNDx26DqdQvvixy7O792PXUFyQYuxoxQadpQSBzuK9McmN9Au6J7g8wDazWCg3eQN2s1kgxZjRik0zCglDmZU6eU9crDHCbULut937Kh1e4WWieyU50dFdmpILHBVjBWl0LCilDhYUZUyRD9LBU7IXdC9vGNH7rBbKKE7PIEbdodVJBe8GFNKpWFKqXEwpeweWeME3gXdp3tewLsWFLxr/MG7lmTwYuwplYY9pcbBniI9ssnR8y7oJtzzAN7NoJ53k7/n3Uy658WYVCoNk0qNg0ll9wgvz7uge2zPC3gDed5N/p53M+meF2NSqTRMKjUOJtXWUnG7usNpw48F3T47dug6nUKd7cIqzjHXhVVBckGLsahUGhaVGgeLqsYTtAIBbcqhmuG1UDDQ1niDtpZ40GLsKZWGPaXGwZ7ixHmURILXlDY1A17pocoTpUkGKMaQUmkYUmocDKkiJ4DCvncpOWqGROb0acx5JjFPMkAxNpRKw4ZS42BDFWqbnCAqE4imVKgZ1g1Aj9AuGYCy/FYLwNWTC1SMAaXSMKDUOBhQtcLWOiekKgSpKf1phmjX7BLagNcszC/mNS+fWLBqGOtJpWE9qbHsglcsry+VtzjxFSWVADZlPc2WvMLqlgD5K6wTuKawsKpILngx1pNGw3rSYtkfb3dtiyN4NQLelPU0w9DV7RbaEax7Ar+BrFtFcsGLsZ40GtaTFgvr6dZmlSN4cwS8KetpBuKE2y20xAn3BH7ECbeK5IIXYz1pNKwnLQ7WU+0W9AcvyqKUJ+BNWU8zjHPdbqEd67on8BvvulUkF7wY60mjYT1pcbCe7B7hRFmUsytlOeU9zQxeesri8ATe4E0yZVHD2E8aDftJi4X9VFzaKexC33IBr0DAm/KfZgCv2y204HVP4Adet4rkghdjQWk0LCgtDhZUlS94RQLelAw1w07UQcFb5Q/e6hkAL8aQ0mgYUlocDKny0s7uBq8hrywR7KY8qeDYdXuFErpueW7IdWtILnAx5pRGw5zS4mBOWR3Ca7grE+Cm7KlZgUs/2nXLcwZuose6GJNKo2FSaXEwqYqvFBVuDlchuE25VDO83bU7hfbdrl2c35tdu4LEgjaHMao0GkaVFgejyuwPXs5WJaBN+VQzgpbe1zrF+YI2yZ42hzGpcjRMqlwsTKpXiio3T6sR0KY8qplAqwbztCpvT6sm29NiDKocDYMqFweDyuwPXp42R0Cb8qdmBG0gT6vy9rRqsj0txpzK0TCncnEwp9bKpEcq25zWw8t5AtuUORUctsNuoQTu8ARu0B1WkVzwYsypHA1zKhcHc4r0h7ZTuc0JvEp2paykzKmZfK7dLfRe1z6Bp9+1q0gueDHmVI6GOZWLZfe93SqvIa4iEOSmtKkZ1vlZfUK7yM8qzW+Fn3X95AIWY0vlaNhSuTjYUtAdnIa3ikgAm1KlZgMs/ejWLs0VsIke22IMqRwNQyoXB0NqZ7O0Vdja45SnRpEIZlOKVHDMDruFErbDE7ghd1hFcsGLsaRyNCypXBwsqZ1XdkvcdpVXZILdlCU1A3adXqGFrlOeH3KdGpILXIwllaNhSeXiYEmtl3c4ZkRWFILclCcVHLnDbqGE7vAEbtgdVpFY8OYxtlSOhi2Vi4MtVd5aL2zxcroqgW7KlpqBmmx3Ci0z2S7Oj5hsV5Bc0GJsqTwNWyofB1uK9AfHUFkjqE3pUjOhNlCo7JbniduEh8p5jDGVp2FM5eNgTAmivLRV2OE1QZUjyE05U8GRO+wWSugOT+CG3WEVyQUvxpzK0zCn8nEwp6A39jah37iAN0/AmzKnZtiuy+0W2g273BP4bdnlVpFc8GLMqTwNcyofB3NqZ7vyylJht8oHvGp2paymzKkZppfdbqGdX3ZP4DfB7FaRXPBizKk8DXMqHwdzCl7WbVc4jXdVgWA35U7N9lrX7JUAb3XN8lxf6po1JBe4GIMqT8Ogysey697tykbh1hYn4IoEuCmHaoZccU6v0KaKc8rzyxTn1JBc4GJMqjwNkyofC5OqtLVX2CpxAq5EgJsSqWbwuE6v0Hpcpzw/j+vUkFzgYiyqPA2LKh8Hi2pT5BUmywS0KYMqOGjNHqEErFmWG1jNqycXqBhrKk/DmsrHwZqq3Kpw3H5EVQhaU9bULNuPVIJuP1Lhv/1IJenbjwhZjDaVp6FN5eOgTZVe3tvliF6VoDclTgVH77BbKNE7PIEbeodVJBi9GH/KxPRU+JJScaWu2Sy+yAm/GsFvSqGaMXmN2S1B0teYJ/BNYGNWkWD8YjQqE9UU+I2DSLUFPcJrNb2aI/BNeVQzUDGcXqFlYjjl+RExnBoSjF2MRWUimgK7sfCozD7htLBezRPspjSqWbFLv7TeLc8Zu0leXi9kMRKViWgK7FLQqNgljduGb/hAVsuulLXIyFOhUBpfdji7/amTw9nlOeaGs2tIMDgxkpQJWQpwUtCkmI1lNwu7nJApEGRGRo1aSGRajU87WjUL8xupmpdPMCAx8pMJUwpAeulPipC1QFSpvjwW5t5uN/u9gPEuXNALTnLdZftJYYrLYqdHYCkShylmP7kMja83+s0HRu2eYcC+1dpKWToj806kyadB2OzdqRC2UDp1xz3rpDHsmmqEBa598RHkDjpH9c4xtE/v5q3Do+v7+slV+Huve9U+cg+Omm340zMaV+8fmj+RP+QnIuEn8qdD+nXpxNDN7+xy1mG/024b3t+tL8zPlSVy0DMvaH+8534JF27dNX8jf8j3RNrfDS9GDqAy8sc8rNqKVy3Nq/alhuWdb6wD+/JV6/rVkStX3WsiVxm9jHsd50KnruS51NiFPJc5/dvwJ6vFoArr0z3nq2FpT6O6Teo0qNucp2pwK1i97n0Wppn09eaR0e4BrAADSxuV7TvwZDlfmuatvtt5uIDmH6PQmU6Bwvx7SXRiNrv8UqW2t87I+sP1bOtvX5an8ScxmShgxj9HjP8ZmbUUs5OMv9u3nG2/qQVv218oblSv3r3bMm0G/CUmozE46JvH5gfnC7Ah5gewuY3BkV3iyCpwZP9+5DExcOQUNr841M3rwx/Tczj13ncud9++3n3nVOt38yzrnJb5ddU5s2qrXHV1rjpKV12tq87lq/blq87lq7ZGVUel6vDK7qU91x5e3D3TOXVWM/rSduV2tZQoQ4pRGk3zSmFIvaRGOSsvk+ZhFkbD9RxDal2WpyEViSEVMUOaJ4b0jEwhyzBR4W9Inb7lbEhNLVJDmhrSRTOkGOXUNK8UhtRLOlVF8WW2MxLmFSOckpCIMZUQYypnV8ryGVkZDW0+D3MSlh7ppEQ6KZFOSvB2AQLGWzYdA4UL8DKXRUVhGkvD9aKLpWVi/mXM/AvE/J+RxfUipKmNPZY2tUhj6TSWXjRDilLIBSoKueClkItClq0hHb7bi8CQKsSQKpghFYkhPSPJDsSJr/YiM6RRvNlLDWlqSFkbUpTLL1Bx+QUvl1/URLaGlFwvOkOqEkOqYoZUIob0jCSfIC0+D4YUtEgNaWpIF82QogsrBKqFFQKysIKlLR0lhPI0p8j7MWJapXR1crRGlBVHNLWjqR2N2o6ii1wEqkUugneRCzEO/Wb7sLesD4jtMh4Qq0DuccSewm1YHyxrCtbr0OhOMKg+1+RtQ4kJZW9BLbOHm8+b1mjWPmBGtj/VbD5m1GnlCYb01IXGzenwGsEs6qkL25bVawBPlRgl0A9xarag5zAy/KDrUASqdSiCdx3K7pIgZJeL26UNwQHNutFrdJvH1hPe6TXhEc30+p1m416zc2T0u81GptExDg6ajaZBTBV50DM9o0W60NjPHHc7+4NGnxQ4OiaYaPeXSeN5LuhAcjkrC7IiiZLigtN8vqHNrA80oc9aq9O431u2bqLchrjHvJVlYblQLK/XIop+ZI2MHzlw7Cdj19uEHFBsta0vfM02n4Bd+5Eax6zg3bkZOmm4VGYYHkkzBUS2Tv7x0G5tb7tcHI+Gan29P+jdrB0bjeZB0yDtYn9DwHCgD1r9m0LpXdDOzuHU+Mnr2+GWR44nWhDEW69VtiHXxGQ/LsTix9HlNwLV8htBmQ87lFUUWVO42aFKcXtzuxKZKcoRU8SB8T3VFLmtuKimyO6n1BotsDVCV4MIVKtBBHUurJEmaNlsLidyskYvlva2t0qRGaM8MUYcWNPTjNGwERfUGNndlNqiBbZF6IIKgWpBhaDNhS0S85Kcy8G0LqfIaL20+cp6KSJjpGRXygoH1vE0YzRsxQU1Rk4/pdZoga0RuipBoFqVIOTmwhoJeVlSTGW4WKNbtwvlQnG7EpU1Eog14kCCnWaNhq24oNbI6afUGi2uNRJRgrxARZAX8nNhjURJyamSymvWqHb7VqV6JypbJBJbxIFHOjUycttwQW2R1UupJVpgS4QyzEUqhrmYnQtLpEqSquYFgZ8l2ozOEknEEkX+EtzbhotriTZTS7TQlgilaItUFG1RmAtLJObFrCDzmi6qlMHZLhWiMkUyMUUc9jabPl1kN+KCWiKnm1JbtMC2CGU5i1QsZ1GcC1uUzclCXoas7zyN0VpUxkghxojD1m3TjNGwFRfbGq2l1miBrRHKFRapuMKiNB/WSJW0XD7HKzSC7cQKxb2ojJFKjBGHtR5TjZHbiAtqjOxuSm3RAtsilHctUvGuxfngXQsyTLrmNH6R0WaUwzSNGKMYqNfDVlxQY+T0U2qNFtgaoexrkYp9Lc4H+zorCZJm7lvE0xpFNk7LEWsUA/t62IqLbY3ScdoiWyOUfS1Ssa/F+WBfEyBpWVHlNU7bWipuV3eiskV5YotiIF8P23BBbZHVS6klWmBLhHKvRSrutTgH3OvcsppXs/nSUpYbvyhKS6RmV8pq1MzrkTZcUEtUSy3RolsilHctUvGuxVHetSgqy+Lm3lK1UN5arm5XSvVXyqXKOmaXXmkaLWJsjG5m0G72M0d6r5fpHGT6nb7eyhwYxBCRI9cG9TL9e3o/o3eNTLvTz7SaPTBVei9TJk3Z7+EmSlz2X6Jm4vWmkHX/2RAOZrTgftdJwznfuPduWbJhCyzvbJa2olthq8rEmuHEgH534G/MrB9nsmVmY8dhw7zP3KQs9p6ncdyi2d3jsWuuGaPaIdPfmo2qN8Gs2boFN2vZ1KSdNmkSSt4WqcjbYn6OTVp2zgyaEJVBU4hBw8kFvAwan7xDUZozITVnCTFnKANcomKAS/Mcoc2POSu+UlSWCpGZszwxZ/i8V2rOxs2Z3TmpOUuIOUNp5BIVjVxKozNKc6ZGZ840YaWs4QuFU3OGmjM1NWfJMWcoE12iYqLL2dScUZszMSpzJhJzhq81Ts2ZnzkTU3OWEHOGUtklKiq7LKTmjNqcSVGZM4mYM3zBcmrO/MyZlJqzhJgzlA0vUbHhZTE1ZxTmrLBbjXCsqRBrlr4JoLVmVt+kxiwhxgwl00tUZHpZSo0ZrTGLbKSpEmOGL1NMjZmPMUsHmkkxZigXX6Li4styaswojdlaZJFZjhgzfGFRasxwY7aWRmZJMWYonV+iovPLSmrMaI1ZZJFZnhizlKERyJilkVlSjBm6IkCiWhEgq6kxo6bPRmXNVDLOVNNxZjD6bGrOEmLOZHQ1gES1GkDWUnNGbc6ieqOpasSc4Ql1UnPmZ87SN5pJMWfoagCZajWAPM+rAYRl/41z4lkPEJU9yxF7Fu3MmdnWC2vRrN5JDVpCDBq6HkCmWg8gz/N6AHFZnieDpkZm0LTsSlnDs2nwW38uL7ZBU1ODlhiDhq4IkKlWBCjzvCJAWvZP9hMLUSMqeyYTexZtPg2zqRfWnpmdk5qzhJgzdEWATLUiQJnnFQHCnJmzqFLAahoxZ9HOnwkLb87WUnOWEHOGrgiQqVYEKN4VAZKkrpdLteVqoVbb2C0UHStmPuLQ/RSWotbvGvpRb9m51vagbxoG+5KWQVi+U9gr7TI2C+tNo7fR0nv33l4QV8octlbdIna4ZvT9TAI0UCgrsKaTG4ereLBvN6evPbCbeZIhcDtz3Ay4sLfNgN0tlGbALj1mBlyd/PFfhVPLhcq4BfAC2K7AF9Ogige25uE4PGt7u6VCdRpys7EgF6W/y1T0d0WKBbmbIj/YSitlDvuQJh+2myI1ZqEoP8DC1ROMVpTfLVPxuxU5FrRuc0SrvFLmsFVn8tG6TY/Wba5o3U42WlECs0xFYFaUWNC6xRGtsJllitbgaN2iR+sWV7RuJRutKENXpmLoKmosaC1wHMACvTVFa3C0FuhHrwWuQ9dCosetCkpAlakIqIoWC1qL2/zQCrPPKVqDoxX6hBKtUJQfWuHqCUYryq9UqPiVSi4mtHIMhXMrZQ7bBZ4FuNLHwkW+Q9disseuCkogVKgIhEo+FsRWS3ubha0SP9TmV8ocNtZLPmrdjqF9ueuU54det4oEIxhlzClUjDk1GwuCeQNYyK6UBQ470iUfwgERzB/AZwC/KEVMoaKIqUIs+N3Z3d7hC2CBABjPip8CeCKA3a6hRLBbnh+E3SoSjGGUF6VQ8aLUeHhRW0trt/f4glgkIE7JUbO8CXL7hvZ9kHsCx7dCbh0JxjHKklKoWFJqPCwpEiCVuKJYIihOuVKzxdKlYLF0iXssXUo4flHelELFm1Lj4U1BdMQXwDIBcEqfmjGWDoJgtzzfWDrpGEbZVAoVm0qNh00lQGjEF8QKAXHKqpoBxMO+oUTx8AR+MB7WkWAcozwrhYpnpcbDs6rxfBcsqATCKdVqBgjXArwNrvF9G1xL9ttgFWVbKVRsKzUettUWV8xqBLMp4WqWKawAmN3ii9mthGMW5VypVJwrNR7OVaFYXq9xRG2OoDblXc1CarY6hpbXbJXmSG22KkgwdlH2lUrFvlLjYV8VKuulzVfWeY518wS+KQFrFvi6fUOLYPcEjiB260gwjlEOlkrFwdLi4WC9WNrb3ipx9MJidqUspiSsGWDsdg0lit3y/EDsVpFgDKM8LJWKh6XFw8MqVIrbm9sVniAWCIhTItZMvtjpG2pf7JzA0xc7dSQYxygXS6XiYmnxcLFu3S6UC8XtCkccQ56qlIs1A46HfUOJ4+EJ/HA8rCPBOEa5WCoVF0uLh4tVu32rUr3DEcUSQXHKxZrlFZLdM7RvkeziHF8k2TUkGL8oF0ul4mJp8XCxSKdscsWvTPCbUrFmw+9mMPxucsfvZsLxi/KwVCoelhYPD6v08h452OMIYIUAOKVhzUKGdrqGlg3tlOdIh3aqSDCGUQ6WSsXB0uLhYFXKEBjBDgjcQKwSEKdErBlAPOwbShQPT+AH42EdycWxhvKyVCpelhYPL8vuljWOONYIjlNy1uw4XguK47UIcLyWaByjXC2NiqulxcPVIt2yydkf5wiOU7rWbDjeDOqPNyPwx5uJ98cob0uj4m1p8fC27G7h6Y/zBMcpb2t2HAfyx5sR+OPNxPtjlLelUfG2cvHwtraWitvVHY47o2RXylJK25opa4fVM9Q5O6ziPDN2WDUkGL8oZ0uj4mzl4uFs1XjjVyD4TRlbs7xjCobfGnf81pKPX5SrpVFxtXLxcLU4ki0lkUA3JWnNAl161HIFbKKxivKxNCo+Vi4ePlaRI1ZhB8GUijVLbnf6zO5c87onGqso90qj4l7l4uFeFWqbHNEqE7SmxKtZljFAt9CuYICyHBcvwOUTjFmUb6VR8a1y8fCtaoWtdY6gVQhoU7LVLOGw2S+0EbFZmGNQbF4/wbhFOVYaFccqF9N+gsXy+lJ5iyNRUlIJdlOO1YwpOKy+CZCFwzqBbyIOq47k4jiHcqw0Ko5VLqadBnfXtjjjWCM4TjlWswxz3b6hHe26J3Ac9Lp1JBjHKMcqR8WxysXEsbq1WeWM4xzBccqxmoWb4fYNLTfDPYEjN8OtI8E4RjlWOSqOVS4ejlXtFnQKT66klCc4TjlWs4yJ3b6hHRe7J3AcG7t1JBjHKMcqR8WxysfDsbK7hSNXUs6ulOWUZTU7jum5ksMTuOM40VzJHMq1ylFxrfIxca2KSzuF3cIGRxwLBMcp22oWHLt9Q4tj9wSOOHbrSDCOUc5VjopzlY+Hc1Xlj2OR4DilXs2y6XdQHFcjwHH1LOAY5WPlqPhY+Xj4WOWlnd0NnsNjWSIwTllZM8DY7RpKFLvl+YHYrSLBGEZ5WjkqnlY+Hp6W1Ss8h8YywXDK1ZoZw/QjY7c8bwwne1yM8rZyVLytfDy8reIrRYWrG1YIhFPm1ixvje2eoX1nbBfn+MbYriHB+EX5Wzkq/lY+Hv6W2Sk8XbBK8Juyt2bFL70Hdopzxm+i/W8e5W3lqHhb+Zh4W68UVa7+VyP4TVlbs+FXDeZ/Ve7+V022/82jfK08FV8rHw9fy+wUnv43R/CbsrVmxW8g/6ty979qwv0vytPKU/G08vHwtNbKpFsq2xyX8st5guCUpzUDgod9Q4nh4Qn8UDysI8E4RnlaeRqelpiNh6dFOkXbqdzmiGMlu1JWUp7WbJ7Y7ht6X2yfwNUb23UkGMcoTytPw9MSszHtY7hb5TkcVgQC4pSkNctiRKtjaFciWqU5LkO0KkgwdlFuVp6GmyVm4+FmQZ9wHAorIsFuSsyaEbv0I2G7NF/sJnscjPKx8jR8LDEbDx9rZ7O0Vdja45h4R5EIfFNC1gzwHfYNJYKHJ/AD8bCOBOMY5WTlaThZYjYeTtbOK7slc3d2bjCWCYxTTtYsMHa6hhbFTnmOIHaqSDCGUU5WnoaTJWbj4WStl3c4Z4ZWFALilJU1A4iHfUOJ4uEJ/GA8rCPBOEa5WXkabpaYjYebVd5aL2zxdMUqQXHKzZqFHm33DC072i7OkRxt15BY/IpZlJuVp+Fmidl4uFmkUzjH0hoBcErOmg3AgWJptzxXCCc8lhazGD/LRDYFhuPhZwmivLRV2OE5r5UjIE4ZWjOAeNg3lCgensAPxsM6EoxjjKdlopsCx/HwtKBL9jah87jhOE9wnPK0ZtntzO0b2v3O3BM47njm1pFgHGM8LRPd03EsxMPT2tmuvLJU2K3yw7GaXSmrKU9rlglqt29oZ6jdEzhOUbt1JBjHGE/LRDcFjuPhacHrv+0Kx7GxKhAYp0ytGV8Xm10T4G2xWZ7vy2KzigRjGONrmcimwHBM+xfermwUbm1xxLBIMJwytmZJied0DW1GPKc8x4R4ThUJxjDG2zKRTYHhmHhbpa29wlaJI4YlguGUtjWLH3a6htYPO+U5+mGnigRjGONsmcimwHA8nK1NkWccLRP8pnytGfBrdgslds2y/HBrXj7BmMU4WiaSKTAbD0ercqvCeZ8WVSHATTlaM+3TUgm6T0slgn1aKknfp0XMYhwtE90UOI6Ho1V6eW+XM45VguOUpTUDjod9Q4nj4Qn8cDysI7k4FjCuloluChzHmEdrs/giRxxrBMcpWWvWTDxm3wTJxWOewDkbj1lHgnGM8rUEKr6WEA9fawv6hGcGADVHYJzStWaheThdQ8vycMpzJHk4VSQYwyhXS6DiagkxcbXMXuGYCUDNEwynVK2ZMUyfC8AtzxvDSc4HIAooT0ug4mmJMfG0zDf2Aj8Ma9mVspbStGbmdwgB+R0Cf36HkGgMoxwtgYqjJcbJ0RI5YlggGE45WjNjWAyIYZE/hsVEYxjlaAlUHC0xHo6W1SsSRwyLBMMpR2tmDEsBMSzxx7CUaAyjHC2BiqMlxsPRsjbO4RlLSwTDKUdr5k2W6GNptzzvbZaSHUujHC2BiqMlxsPRsjbf4IlhmWA45WnNvFFLIAyr/DGsJh3DKGdLoOJsibHtdUh6hed4WCEYTilbM2OYfjzslueN4WSPh1G+lkDF1xJj2++Q9ArP8bBKMJzStWbGMP142C3PG8OJHg+LKFdLoOJqifFwtczc/TxDaY1AOGVqzbrJA30k7RTnvM1DouNoEeVoiVQcLTEejpbZKTzD6BzBb0rRmhW/9FG0U5wzfhMdQ4soP0uk4meJ8fCzzP03ePrfPMFvSs+adaOWYP53jbv/XUu2/0W5WSIVN0uKh5tldgpH/5vLrpRzKTVrVvwG879r3P3vWrL9L8rLEql4WRINL4sZbNfK2/ANR9wKBLeR0bFCQTXGPYXtTqDeUtguz3NHYbuKBIMUJV6JVMQriYZ4xW5+ebOwyxGhIkFoZGSrxUSo1QO0c8hmYY4TyOb1EwxMlE0lUrGppBE2lajWChtsgl/rUhHGvhvdj+z0o0ZnzHGv2cjzFvbaSqVR71TcogwqkYpBJclx4Zb1nJOD20jj3qThlsV0E0vcJnu2CWVNiVSsKUmJCbfM3/U4uD1L80ysccvkNQ9D3Cb8LQ/KlBKpmFKSGhduOfnbM/V+hzluWdArWOI20f5WQtlRIhU7StJiwC0ffqMD3LNErGAJXIbURkbQPQPMRgllRklUzCgpFxt2OQXLZ4rUyB67TJYWMMVuouNlCWVFSVSsKCkfG3Z5BcxnaU0Be+wyWdrHFLvJjplRRpRExYiSs/Fgl8P6ege7Z2lNH2Psslpazw67SV9ZL6FsKImKDSULMWCXT34bB7tnaU09S+wyTG3DCLtnILONhJKkJCqSlCzGhl1e492zlNOGPXaZpJZjit1kj3dRHpVExaOS4+BR8cnv6mD3LOWUY49dJqldmWI32TEzyqWSqLhU8giXSlBvFWrL5Far9ds7O2PYvd1u9ntBQWxd0waxc+nl9Zy6JGRtLO9t70E3ciItb4srdxYQy0EgbLbxBAgPe3QcwlZPeDDsYtpC8E27d+DjJCjbxcaBbCsXFsj29UdgPOgc1TvH0F69m8WrG1dfvLq7et375TSgrzePjHYP2nuvVN0p7Rb2bu+au4s6X5vPfH2383ABzQJK1ZKoqFqyEp9ZyEdkFqSVOwsYnkdpFvKpWUigWUCZYBIVE0zGcmaxtQuji5tiMQzyyp0FnHNjut4pVsvAau1TahoCmgYZJZtJVGQzWRuPGF7armxUqi9zCBjsKy/bjx5LS2A+oAuC+ZnG+9OiArfXpg73LUhPG+PbJ3GLAOzr+8K8UNyoXr17t3V9Xz8x/97rXm0MDvrmsfnB+eKo2bY+9IwG+XBklziyChzZvx9d75DeXjoxdOtbp7D5xaFuXh/+QOn7Tr33ncvdt6933znV+t08yzqnZX5ddc6s2ipXXZ2rjtJVV+uqc/mqffmqc/mqrVHVUak6vLJ7ac+1hxd3z3ROndVQkgfqdrW0tFHZvpMUQ4ky+2QqZp+M5TxjailHQ6jUVHLMrRKZrWQVE6XGMjWWURtLlEopU1Ep5TwSVVZqe+t8okrryjxM5c0ytLne6DcfGLV7hnHWVutPDTqdTk2DztSOpnYUtaMorVWmorUqCK2VqR0deVUfsR2ViB1dwJl8Li/rI7OjjF7Pp3Y0taNR21GUYixTUYwVLOEiU0N6avAerSWViSVdwFcfnMb2UZnSdGyf2tJFtaUo5VumonwrXsq3BdelnW6zYSzv7JaLJcecrhu9Rrd5bJk7+DnTOcj07xmZnnnKMmlJTwnL+t7MLmsK+Q+wC4eWKb75/PXWXWKlzM9URtnoD46XR1Qrt8EsmwouO2NJ3lZZIVaZwwIuy5TiJnnYgMOvGNjom1aeWOvziLWGlva11d4emGCw7cdm3Fw7HRXMXjtnjRlsC49LdnX+Vnu9sFcYt9i1vt4f9G7Wjo1G86BpkJayvyFP+oE+aPUBrs7HEfvuKORr4J+/fnh09fnr9w+JqCz1O+2r8MQTUbWk9cf6nsi2McGQgXEYOfaaNdPYeA49Nu72VnnPaRrExN2ELSPcA8zanW61oa0zH5v6tq0tPEpXq9uV0lXipollvQr/28+WW8hjH4VY7CNKq5epaPWKxNE+craM9uiQt2VUiWXksCx9smVMiE20uyigTbTPmh+baCuU2sTFsYnocgWZarmCIvOMGVXOVtEZ6PE2ixoxixwy7UwJGNWEGEanlwJaRue0+TGNjkapbVwc24iu2ZCp1mwoSHrd09xs2jc4Lu96r7ZdsVnXlfJ7b5f5T0LmsyvlfGRJdWnN1JoejnE97b3NJMI19MEEurXTL/58a68BcEqPGIXTT+uefmi3kPdRHX6L0d+y1mPofdFo2Xa7iuHZ06+PMUYE6/reCXizU5DLlx6Rh6qtt5A6Tv2E38gUsI3dm6fu7Kgm10/VF0Q3vBFodPO0i0cZYZpqzkOw52ejzB9marLhg+EJvMx5fyh7s9jp9d++Jq+sCQ4fxrS4mwSMRhcMv43Oke+ghOdqo8VO/bC60Woem+rb3tMuefrr1cKg39nodI/0/s1HLVOT4TdbHfCAnhKrax24/0KXOLV9uMGRY/Nad5r7xFratQ2/WLUrPWlZi+Kbfc8R3GKzfegel4nn7VqXNh9/z+Fq1egSFdv7RcP0U/3ugNRz6ksnhth+cRg8XB/pU9q+n+mRHIIW7fsxD/B84Xlh5fny8xL+KFi3ONdPghjFkyDF+iSgXBSaKCXIk1BQV8qCurCPgRzFY6DE+hhgr9JpXqRL05xBQVAWuu/VKPpei7XvsVd/NC/+5EAmQBRWylJ2YZ+DXBTPQT7W5wB7xUHzgkMJ8hxUhZXb8sI+BUI0sWG8wSE2rUszqatOeA6sfExORJjzGR0swhMQSUwoxBsUYpNXNFNX2vRoIL9SFhc3GhAiCQWFeGNBLK8ETVaJXMDBoSSDLZAXd3goRBIcCvFGhwKWS4Amk0A+4OMgq/A4qIsbIgqRxIhCvEGigE0bCjTzhsKkiUPsgVAleCDc/b0W74EQI4kWxXijRQGdS6SaTJw0mzhM45OAoFGMJGgU4w0aBWwqUaCZSxQmTSZ6HoRteBDuPL+4w0cxkvBRjDd8FLC5RIFmMlGYNJuIeYicZRi0xX0gIokgxZgjSGyCUaCZYRQCTTHCA5GHByK/uDGkGEkMKUYSQ1aavb7vQwE/zvQG2jzbeg3tfLQYStZMpPNxlfTY9sFBzzA5S8ODUyqDGkHVnunl6SS1JVRtgbHaM73pm6S2hqotMlZ7pjdTk9TOompLjNWe6aXKJLVlVG2ZsdozvQOYpLaIqq0wVnumKetJaguo2ipjtWeaZ52kdg5VW2Os9kwThJPUVlG1c4zVnm0my1FWQPTOR2K4Z5xycbQVsccbf76Zaz7b3MBEzXGDwtrrzDiYnag57uZZO54Zh18TNY/G98w4TpioOR4RsnY/AuY2BWq/iWqO20TWHkjAPKdA7TpRzfG4kLUTEjDnKVB7T1Rz3H0y90OY/xSoHSiqOe6J8qxHPpgHFahdKKa5iIfjAvNBG5rpldqJSpjq0ThREU27SO1EZUxz3Iky1xwdclI7UVRz3Imydv8ivntpKM1xJ8ra/Yt4Io9QmuNOlLX7F9El9tROFNUcd6Ks3b+ILoSldqKo5rgTZe3+RXSZGrUTRTWPZgwqorufUDtRVHPcibJ2/xK6OQO1E8U0l3Anytr9S5gPlah9qIJpHo0PlTAfKlH7UFTzaAaiEuZDJWofimoezUAU3QF8+gbgjroqpjnuiZg/LZgPnb798UTNcU/E/GnBfOj0zV8nao57IuZPC+ZDp299OVFz3BOxjlvQ7fmm7843UXPcE7GOW9AdxKZvIDZJcxn3RKzjFnSDo+n7G03UHPdErOMWdMeR6RuOTNQc90Ss4xY0/f/07P8TNcc9Eeu4BU24PT3f9kTN8dEc82kLNMft9BS3E1X3caKsvSiaUnJ6RsmJquNeVGD+zhlzo9OTvU1UHXejAms/iiZlmp6TaaLquB8VWDtSNGfK9JQpE1X3eUPH2pPKmCeVQ3lSxWdilLUrVTBXKodypYrPoI61L1UwX6qE8qWKz8woa2eqYM5UCeVMFR8aEWtvqmDeVAnlTRXcm4qsvamCeVMllDdVcG8qsvamCuZNlVDeVPEZk7L2pgpKKgrlTRUf7hlzFhfmTZVQ3lTBvanI2psqmDdVQnlTBfemImtvqmDeVAnlTVXcm4qsvamKeVMllDdVcW8qsvamKuZN1VDeVPWZI2XtTVXMm6qhvKnq86KRtTdVMW+qhvKmqs+bRtbeVMW8qRrKm6q4N5VYe1MV86ZqKG+q4t5UYu1NVcybqqG8qeozxcvam6ooTTeUN1Vxbyox50Vj3lQN5U1V3JtKrL2pinlTNZQ31Xw49Ky9qYZ5UzWUN9Vwbyqx9qYa5k21UN5Uw72pxNqbapg31UJ5U83nlSNrb6ph3lQL5U01H/Ira2+qYd5UC+VNNR/iDmtvqmHeVAvlTTXcm8qsvamGeVMtlDfVcG8qs/amGuZNtVDeVPN5Y8ram2rowpdQ3lTDvanMfKUR5k21UN40h3tTmflqI8ybaqG8aQ73pjJrb5rDvGkulDfN4d5UZu1Nc5g3zYXypjncm8qsvWkO86a5UN40h3tThbU3zWHeNBfKm+Z81pKw9qY5zJvmQnnTnA8PlrU3zWHeNBfKm+Zwb6qw9qY5zJvmQnnTHO5NFdbeNId501wob5rzISCx9qY5dClpKG+ax72pwtqb5jFvmgvlTfO4N1WYr9/FvGk+lDfN+6zzZu1N85g3zYfypnncmyqsvWke86b5UN40j3tTlbU3zWPeNB/Km+Zxb6qy9qZ5zJvmQ3nTvM/STNbeNI9503wob5r3WVbC2pvmMW+aD+VN87g3VVl70zzmTfOhvGke96Yqa2+ax7xpPpQ3FbI+hF7mC5GzaHaGUP5UyPqk8WC+FjmLp2gI5VKFLO5TVfZ5MdA0DdlQXlXI4m5VZe1WSUWo9qEcq5DFPavG2rOSilDtqX2rhmofzToZUg+qPLV3xZWPZqkMqQdVntq/4spHs1qG1IMqT+1hceWjWTBD6kGVp/axuPLRrJkh9aDKU3tZVHkhmmUzApoCybylMMpHs3JGwPMg0SdCyqHKR5RPyCcVErWPRZX3sfPMrQ2eDYk+HRKuvM8rPubKox6WPiMSrrzPtCRz5VEPS58UCVfeZyjFXHnUw9LnRcKVx+08e2uDelj61Ei4tcHtPPOIHk+ORJ8dCVcet/PMA3o8PxJ9giRM+Yhy9Qh4hiT6FElYlkHBJ3Mccx+F5kgS6JMk5VHlfVZKMlcedbD0eZJw5X1WdzBXHk83SO1gceV9GKnMlUcdLH22JFx5HxYNc+VRB0ufMAlX3ufNH3PlUQdLnzMJV95ntpK58qiDpU+bhCrvk06OeXSAJk4S6DMn4crjTop5dIDmThLokyfhyuMDKebRAZo+SaDPn4Qr77N2kvl0H5pCSaDPoYRr7+NimftYNI2SQJ9HCdfeZ7KSfUpf1MnS51LCtfdJScDcy6LplAT6fEq49j5ZCZi7WTSlkkCfU0lAk7T75Jpj/9yjfpY+r5KP9j7LKZlrjzpa+txKuPY+uTjYP/eop6XPr+SjfUThJZpiSaDPsYRr75PZinmIhqZZEujzLPloH02eRQFNtSTQ51ryeXKiybUooOmWBPp8Sz7a+8yDMA900JxLAn3SJR/1fdJzMLeZaN4lgT7xko/6PmEm+z0A8FT6Id2tX9Ir5uNaNP+SQJ+AyUd9n0CTvdlEHS59EiYf9SOaVEDTMAn0eZh8tI9o2h7NxCTQp2LCtfdLxsQ80kSzMQn06Zh81Pex+ux38EBdLn1KJgGd//ZLysRce9Tl0mdl8tE+otl7NC+TQJ+YyUf7aNLWC2hqJoE+N5OP9tGkrhfQ7EwCfXomH+2jSV8voAmaBPoMTT7aR5PCXkBzNAn0SZp8tI8mjb2ApmkS6PM0+Wgf0RALzdQk0KdqwrX3SdbEfIiFJmsS6LM1+Wgf1RALTdgk0Gds8lHfx9ky97Zo0iaBPmuTj/o+Qyzm7hZN3CTQZ27yUd9niMXc36LJmwT67E0+6vsMsZg7XDSBk0CfwclHfZ/JfPb7xaEelz6Lk4/6PrP5zF0umshJoM/k5KO+z2w+c5+LJnMS6LM5+ajvk2uYudNFEzoJ9BmdcPV9cjoxTx8roEmdBPqsTj7q+2RJZO510cROAn1mJx/1fWjIzL0umtxJoM/u5KO+zxiXuddFEzwJ9BmefNT3yT/M3OuiSZ4E+ixPPur7sNSYe1000ZNAn+nJR32fBT/MvS6a7Emgz/bko75PLmL2W7WiXpc+45OP+j75iJl7XTTpk0Cf9clHfZ+X6My9Lpr4SaDP/ISr75P7iXmaWQFN/iTQZ3/yUd8nmyJzr4smgBLoM0D5qO+TUZG510WTQAn0WaB81PfJqsjc66KJoAT6TFA+6vtMLTP3umgyKIE+G5SP+j6Lr5h7XTQhlECfEcpHfR/+DnOviyaFEuizQvmo77PQlrnXRRNDCfSZoXzU98lbzH6XdNTr0meH8lHfJ3cxc6+LJogS6DNE4er75Ihino5WQJNECfRZonzU98m6yNzroomiBPpMUT7q+2ReZO510WRRAn22KB/1fbIvMve6aMIogT5jlI/6PvmMmXtdNGmUQJ81ykd9nze6zL0umjhKoM8c5aO+z6Jn5l4XTR4l0GeP8lHfhzbL3OuiCaQE+gxSPur7JLhg7nXRJFICfRYpH/V9chwz97poIimBPpMUqr7ok0qKedpaEU0lJdDnkvJR3yc7I2uvK6LJpET6ZFI+6vtkaGTtdUU0m5RIn03KR32fLI2sva6IppMS6dNJ+ajvk/eYtdcV0XxSIn0+KR/1fXIfs/a6IppRSqTPKOWjvg+RirXXFdGcUiJ9Tikf9X2SjbD2uiKaVUqkzyrlo74PcZm11xXRvFIifV4pH/V9Ekux9roimllKpM8shavvk3KEeXpbEc0tJdLnlvJR3yeFI3Ovi2aXEumzS/mo75PDkbnXRfNLifT5pXzU90niyNzrohmmRPoMUz7q++RHZu510RxTIn2OKR/1fXIkM/e6aJYpkT7LlI/6PnmSmXtdNM+USJ9nykd9H/4yc6+LZpoS6TNN+ajvs0aUuddFc02J9LmmfNT3yULC3Oui2aZE+mxTuPo+eUiYZ78V0YRTYoCEU7j6PikdmXtdNOWUSJ9yykd93OtqzL0umnRKpE865aM+7nU15l4XTTsl0qed8lHfJ3cyc6+LJp4S6RNP+aiPe12NuddFU0+J9KmnfNTHva7G3OuiyadE+uRTPurjXldj7nXR9FMiffopH/V9lg0x97poAiqRPgGVj/o+q3SZe100BZVIn4IKV1/yyf7F3OuiSahE+iRUPur75P9i7nXRLFQifRYqH/Vxr5tj7nXRNFQifRoqLOO/KOFOl4P2qNOlT0OFa4/7XA6PDupz6dNQ4dr7uFz2uEVdLn0aKlx7H4/L3GiiaahE+jRUuPY+Dpe5x0LTUIn0aahw7X38LfNwAU1DJdKnocK193G3zGM1NA2VSJ+GCtXeJxMS+0AZTUMl0qehwrX3GeIyH6WgaahE+jRUuPY+I1zmQ0Q0DZVIn4YK195ngMvc16JZqMQAWahEVP1oUlqLaBIqMUASKlz7aHJai2gOKjFADipc+2jSDopoCioxQAoqCdXeZ40oc+1RXxsgAxWqvU8WJPZPDuprA2SgwrX3WavCXHvU1wbIQIVr70OaZa09moBKDJCACtfeh73DXHvU1wbIP4Vr7/Makbn2qK8NkH9KRrUPtRlcod/vNu8O+saY6u4vWJtPbXGiDLEmoJJ7nZsv6a2BsXp9+MVqsdMaHLWhpP1pddPQ95vtQ6esc7haPmx3usb+zQO91SPfO4du23jzotX6Jy0DvrE+2DfvqZb2zlF+OcWdC6fvfEs/or1xqyj1fQtj9y2Ev280qqK4b5G6x4XwPT5+52L4O8cisqnxGNFAOn3nt9vNfg+7c3H8zu2yIe5cCn/nWDQ3NZYjGsin77zW1/sD9Nal8Vt3Coe4dzn8vWOx4NRIkGigjD/v3SZo54d3GXvsrVMyoYGvhG8ILKycGlRao8DRhiivC9j9K+P3v333Q0ajnzFPCHHzavibx6LSqTFp2dw08fTNi9jNqxNuXgx181r4m8eC2qkhbdncjGv05ouddl9vto0u1gTaeBN4yodogVz4FkD5jVPj4rK584JPE9T3To5RO5Cb0A72SSEaI8+gMfANr2lin7Gwj1/wI44HPwyiPp+tPGnufSzw4xkAIXfPIPbD9wKlif6EsfCPZxCE3D2D+A/fTJQmAhTGQkC+gRBy/wyiQHw/Upo4UBgLBCMMhpDGYBAW4vub0gSGwlhkyDkgQhqAQTiI75FKExAKSETINShCGoBBSIjvs0oTFApjUWEUgRHSCgxiQ3zDVproUPAPD2eKjTIBYyOkPRhEivgmsDShojAWK/ILjqTxe2cQGOKEXprAUKSfD2QQHI3fvchiQhBfhUNz92OhIc/gCLl7BqGhD52Y5u7HQkO+wRFy/wyCQ5yPTBMcimPBYYTBEdIYDCJFnN1MEymKY5Ei5+AIaQAG0SHOj6aJDkUkOuQaHCENwCA6xBnWNNGhOBYdRhEcIa3AIETEido0IaLoHyJGEhwh7cEgWMSZ3zTBojgWLPILjuTxe2cQGOK0cZrAUBwLDHkGR8jdMwgNUdb5dNI5PIljoSHP4Gj87iUGoSFKWp/OWYe7HwsN+QZHyP2zeGeMBYfTWe9w/8hr48iCI6QxGESKKIt+OokeGmMsUuQcHCENwCA6RIn403n40ABIdMg1OEIagEF0iHL5p1P5oQHGosMogiOkFRiEiOiagOlLAqAV/EPESIIjpD0YBIvoKoPpiwygPcaCRX7BkTJ+7wwCQ3SNwvQlCnDvY4Ehz+AIuXsGoSG6xmH6Ege4+7HQkGdwhNw9g9AQXSMxfYkE4HAsNOQbHI3fv8wgOERXWUxfZAH3j7xSjiw4QhqDQaSILtqYvmYDGmMsUuQcHCENwIJkiEWH05d9QAMg0SHX4AhpAAbRIbp0ZPrKEWiAsegwiuAIaQUGISK6BGX6ChRoBf8QMZLgCGkPBsEiuqhl+poWaI+xYJFfcKSO3zuDwBBdEjN9RQzc+1hgyDM4Qu6eQWiILqmZvqIG7n4sNOQZHCF3zyA0RJfkTF+RA3c/FhryDY6Q+2cQHKKLeqav6QE7hLxSjiw4Gm8MhUGkiK4Rmr5ECBpjLFLkHBwhDcAgOkS3uZ++yz00ABIdcg2OkAZgEB0qWHSo0ESHylh0GEVwhLQCi+UoWIio0ISIin+IGElwhLQHg2BRQdeoUC1SGQsW+QVH2vi9MwgMFSwwVGgCQ2UsMOQZHCF3zyA0VLDQUKEJDZWx0JBncITcPYPQUMFCQ4UmNFTGQkO+wRFy/wyCQxULDhWa4FBBXilHFhwhjcEgUlSxSFGliRTVsUiRc3A0
A3: 3gAqg+hQxaJDlSY6VJHokGtwhDQAg+hQxaJDlSY6VMeiwyiCI6QVGISIKhYiqjQhouofIkYSHCHtwSBYVLFgUaUJFtWxYJFfcJQbv3cWa5exwFClCQxVZPkyv+AIuXsGoaGKrlimWrI8FhryDI6Qu2cQGqpYaKjShIbqWGjINzhC7p9BcKhiwaFKExyqyCvlyIIjpDEYRIoaFimqNJGiOhYpcg6OkAZgEB1qWHSo0USHGhIdcg2OxhtAYxAdalh0qNFEh9pYdBhFcIS0AoMQUcNCRI0mRNT8Q8RIgiOkPRgEixoWLGo0waI2FizyC47y4/fOIDDUsMBQowkMNWQ5M7/gCLl7BqGhhoWGGk1oqI2FhjyDI+TuWeSywUJDjSY01MZCQ77BEXL/DIJDDc1nQ5XQBnmlHFlwhDQGg0hRwyJFjSZS1MYiRc7BEdIADKLDHBYdajTRoYZEh1yDI6QBGESHOSw6zNFEh7mx6DCK4Gi8FXIMQsQcFiLmaELEnH+IGElwhLQHg2AxhwWLOZpgMTcWLHJM8jie3TLHIDLMYZFhjiYyzCHrmTlmekRun0FwmMOCwxxNcJgbCw65pntEbp9BdJjDosMcTXSYG4sOOed8RBqAQYCYwwLEHE2AmENeK0eX+BFpDRbZD7FwMUcTLuaQBIh8sz8iLcAgRsyhORCpkiAiMSLfFJBICzAIEvNYkJijCRJz/kkQeeaBRJqBQaiYx0LFPE2omPcPFSMJkpAGyTOIGvNY1JiniRrzUabCRjJhMggR81iImKcJEfPR5sNGbp9BkJjHgsQ8TZCYjzYpNnL7DILEPBYk5mmCxHzUmbGRBmAQJuaxMDFPEybmY02PjbQGg5gxj8WMeZqYMR95jmykBRjEiXksTszTxIn5yBNlIy3AIlU2FifmaeLEfDzZspFmYJIvG02YTZUxm3HK7MBhEtIiLJJmZ/Gs2XRpsyPMmz2y9ZZ112b94RsATZ2dpcqdnY00eTbaBCzSZ2fR/NlZqgTa2UgzaKNNwCKHdhZNop2lyqKdjTiNNtoILBJpZ9FM2lmqVNrZOHNpoy3CIpt2Fk2nnaXKp52NOqE22gosUmpn0ZzaWaqk2tmos2qjrcAir3YWTaydpcqsnY0ltTbaFCySa2fR7NpZqvTa2Zjza6ONwiK2RDdjMZuKolEiTLI9sqGg0wBM9l9BQ0m6HVjGt2DhGkkhTcBkGxaffVjoNmKJNN022gQsgkl8Mxa63VjGt2PhHElhjcAinMT3ZKHblGV8V5YoIymsRVjElvguLXTbtIzv08I7ksJagUU8iW/PQrc/C7ZBC99ICmsFFvEkvkcL3SYt47u0RBJJYU3BIqjEd2uh265lwn4t0URSWKOwCC/xzVvodm8Z376FYyQ1nnFTYLFZi4Dv1kK3Xcv4fi1cIymsCVgEk+imLQLVri3C+LYtXCMppAlYbNwioDu3CFRbtwjje7dwjqSwRmARTqIbuAhUO7gI41u4RBlJYS3CIrZEt3QRqPZ0EcY3deEdSWGtwCKeRPdyEag2cxGw3Vz4RlJYK7CIJ9ENXQSqHV2E8S1dIomksKZgEVSiW7sIVHu7CBM2d4kmksIaZUJ4udaB2zN/9baI52vMe9L4TttzVshdWJU/armftzptovzwp9U7RvPwXp8UqRr7zcHR6nX7C2iiTrfc3jcekR+HB4VBv3Ok95sNs+mcEqvXPXrT3BvqFmm6eQHuDd2ujGYzlgW4N3SDCZps4gtwb2h2YJp0mAtwb2gaN5psTgtwb2guDpr8Awtwb+hiSprVcwtwbyjvnYb0vQD3hr5IouIoLcLN4Xwjqpdki3B7+AsgqombRbg9fDROFWMvwu2hQ2uqkfUiBCn4OxiqIfMixCn4yxWqsfAihCrhd7af79sLvW/9fN9e6A3p5/r2wu8vP9+3F3oL+fm+vdB7xM/37YXeBH6+by/0Hu/zfXuhd22f79sLvSf7fN9e6B3X5/v2Qm+lPt+3F3pn9Lm+vfCbn8d4e9bbp7Hb83wd8iXQdc+laKoL+V4maHUhX5UErS7k24ug1YV8oRC0upBz/EGrCzntHrS6kDPhQasLOTkdtLqw88WB6ws9hRu4xtCzqoFrDD3RGbjG0HOPgWsMPR0YuMbQM3SBaww9aRa4xtDzWIFrDD21FNjTh57tCVxj6AmYwDWGnhMJXGPoaYrANYaeOQhcY+jBfOAaQ4+vA9cYesgbuMbQo9DANYYeGAYO90OP1QLXiNkcicbmSDPaHAmzORKNzZFmHURhNkeisTnSjDZHQgdSVCOpGW2OhNkcicbmSDPaHAmzORKNzZFmtDkSZnMkGpsjzWhzJMzmSDQ2R5rR5kiYzZFobI40o82RMZsj0dgcaUabI2M2R6axOfKMNkfGbI5MY3PkGW2OjNkcmcbmyLPO3WA2R6axOfKMNkdG52+oJnBmtDkyZnNkGpsjz2hzZMzmyDQ2R57R5siYzZFpbI48o82RMZsj09gceUabo2A2R6axOfKMNif8ZvaBawy9Y3zgGkNv0R64xtB7ogeuMfT+44FrDL3Dd+AaQ++rHbjG0HtZB64x9P7RgWf/Q+/YHLjG0NsiB64x9D7EgWsMvfFv4BpDb7IbuMbQ29gGrjH05rGBawy9YWvgGkNvkhq4xtDbkgZ+BRh678/ANYbebDNwjaF3twxcY+idJAPXGHqvxsA1ht4hMXCNoXclDFxj6J0AA9cYeu+9wDWG3uAuMA8g9I5ygWsMvYVb4BpDb5cWuMbQG5IFrjH0LmCBawy98VbgGkPvdRW4xtCbSwWuMfQGToFrDL1hUmAyUOgNigLXGHovoMA1ht5sJ3CNoXe4CVxj6E1lAtcYeh+XwDWG3jglcI2hNycJXGPozUAC1xh6843gjMDQ+1wEr5LBRhLBK2WweUPwShlslxC8UgYbFASvlMGGAMErZZBzP3ilDFLcB6+UQUb54JUyyN0enDHMIDd68EoZ5CMPXimDDODBK2WQczt4pQxyXAevlEEa6eCVMsjaHLxSBkmSg1fKIB1x8EoZpPsNvqKAQYrd4JUySGobvFIGaWSDV8ogbWvwShlkRg1eKYNEpMErZZD3M3ilDDJsjlZaM471rt7vdHvl9kHHW+/oLzMtZLzV7QyOyXVuvrB63f28um40mkd6Cz4vr173HK1eH62TfFGo3Xm5sk6qJZ/tuqw/+tHNi5fPnTv3CYXesdHeMxr3ls2yy1B42T0N8oF2O62W0X2KFL5U7zxsG9031s1sni/pXTPj57DMa60fKs1ef/jlsHRztPTb6jvdzkGzZfhc7a31WsNok9M6tf5g/+TUr6+v7+mH4ye9zv56VAencPO0vuRr0azeq6/75ehF3jT84VSlFzz/3ni6Qe90uvfvdjr3HyMN+ALa2j73/5hv9yDKTb96c/zqEnrC5F6B8wT0vEm9BWd9EnoW2otQ/BMnFB+/90kXR+4cb1fkafBvV5+nBE5YmnwCcrPw/5XzIN4K4mNBvA1EBsTbQVwD8XEgngfxDhAfD+KdRFy8QsRbTle7Cyalqrf1Q6sWG79X6r17htGv6sdTHte3nv6xBufZVz0e1fsTQYsnicicPqnQaBi93oah9wddOE8ihV5daPSbD/S+UWseDVp6v9lpP13Y3x89Ig1Gih8324f20XsHeqvZP3nCOuo9Rf463dt7tbvinPx0+5iYWuM5y6aW2g+a3U77yGj3n7a+2R20oSOetY6Glb6q2Dk+sbqoAxWYx/Bhr2N++8y60TL6htNEz5YeHXe6/eH5z5aPRr+4an0Bl3hN2bTrDkjMZ+AZ6zvys3n4nHvoIMIu4By+hmjRPDgZucbrrO+GbWWd6H7rPXSu81y188AYucpr4JtT13jK/m544Jz/qh190PO027O7RrPd9Nz3a3aNo9NVPGt/5z3raKTW4Rd2R191v+g943607sA9dHWyvnGfh2fcY/Pnp0mfe56u2j3wwod6u/kRo/sMHA1/fKbW7xwPD9/0UtN4aD6u3icJQP8c/EJwfNA8HHTNspfhm0qHPDnwwX7MoOir4Xh4TfjqWfjK1M1GqFnG0d8CzWu8X9mtdCH4v485DUkzmLCqAASnv6e/p7+nv6e/p7/P8jv8f/63P/rRj/4x+f9xOPgt+8D85Te9B7/hPfh178GveQ9+1Xu1X/Ee/LL34Je8B7/oPfgF78HPey/9c96Dn/Ue/Iz34Ke9Bz/lPfhJ78FPeA9+3HvwY96DH/Ue/Ij34Ie9Bz/kPfhB78EPeA++33tz3+c9+F5vse/xHny39+C7vAff6T34Du/Bt3sPvs178K3eg2/xavDN3oNv8h58o/fgG7wHX++92td5f/la78HXeA++2nvOV3kPvtJzcAHmLb778dpJr28cLRdhwNWACKy3fMsgQ6FmY3m9aX6hd08+KL7vfXbBWr9LQq0XMke9Rqfbat59IfOS0e2RYjfk5Sz890KmOGjBgOZG2xj0u3rrhczO4G6r2XjRONnr3DfaN+5qmq40FFXIS7KRzeU/8ML7gmpRbvclkZMS1i5AbC/+AcaXg35+wr7O5WLn6FjvGt3Lm3rvXo3E7eceP3f5C89PaFP7b+nD1mjCucAHBa7d/AGYVjt35QPnrH9PPA0ShsjPwuP4ptOmtOyE9/C0Pv3sE884xS/A/2OWtzwcRJhj74tw1uNP1cmfF1udQ7lt9Ic3IZJbEGSau1DVvJHd3z/I3r0r6LqoX3ztOWQaw9vIpQdkFFQlDoAMXQrdrn4CnXWprsPHS/VGZ9DuX6k3Bt2K8cBoXTh34WNPX8x7gfd9AG7m8qvtOyAVdY1l88y67V6ufJCIryXtckUnHy6+johrYxMNtfLysHmKes+4Soo9V9/uNg+bbb210WwZO3r/3tV66eiusQ8Fnq6DdH54nXkEw3vyVKw3u+ReO92TZ+p2e24fm8ND59B6eF5Vh4Fmn3yyfn7aPd4hI//n3KPNTq/f1o+Mq1BZxWgf9u+dP3ce/pH7O3/5ijk/c5eI966vvL9EHtzDE5gfBRcLfwGs7988IePs95u3/f6dk26nddJr9urv6bSNXl1RhHqz3e/UFU2oH3S69hB6+e7943NX4LqXGkQoUy9O2gmu+n7nZ5i6urRPTr1aaJ/Yd37lObjeAXRLuW0XhMf2qv3Mn3v2DVAA/j+Eo+pL28s1Ax4dY7/SbN+/dO8cMmO30eke9dDpyktNUJ2+/LI5rIYdAI1LHyKnvttnPo4U2jOOjsnzYqwNmq19ozs6F7tcHHS75Cm9dJ9cpDDrRZxfe5daYXRZNw50guJn3+g07RERT8Jkw5+2rNmVNnRIB/rhyjHIC28i8hnb1Nldd8FEaVX/UKdL/jTb8Mes7wp5Uh80oQh04GXy7zG7Mz9q/7sIU5OBZ7CfqPfN+Rh77vHxC29BLDaYdLMY9esId/LxwyDA5F6ESVPq+fLz59zp0AvBKzXre9vU5kAmnq/WHzgzVLxapOdqmDk3+xw/734buFrC7PZsbxR46/jQ1fEaZrAmv7/grdyJqxy8FKB/W8LgyX9+Smuceu4Z1PgOX2wj72wY1Pfxvtj2ee3DoM53YiHX1DdHvB+zT3X1gzc8k98InTcNXLNN9IAaH5+oinn1T4MgF0LleQzkwfk98UEnHoeA/MLYKzZvFGve0Z8B8WdBfDqIzwDxmSA+C8Rng/gcEJ8L4vNAfD6ILwDx50D8eRB/AcRfBPGXQPxlEH8FxF8F8YUgvgjEXwPxxSC+BMRfB/E3QHwpiL8J4m+B+NsgvgzE3wHxd0H8PRBfDuLvg/gKEF8J4qtAfDWIrwHxtSC+DsTXg/gGEN8I4ptAfDOIbwHxrSC+DcS3g/gOEN8J4rtAfDeI7wHxvSC+D8T3g/gBED8I4odA/DCIHwHxoyB+DMSPg/gJED8J4qdA/DSInwHxsyB+DsTPg/gFEL8I4pdA/DKIXwHxqyB+DcSvg/gNEL8J4rdA/DaIfwDiH4L4RyD+MYh/AuKfgvgdEP8MxD8H8S9A/C6IfwniX4H41yB+D8S/AfFvQfw7EP8exH8A8R9B/D6IPwDxn0D8ZxD/BcQfgvivIP4biD8C8d9B/DGI/wHif4L4ExD/C8T/BvF/QPxfEP8PxEdBwFN75TyIx0A8DuICiIsgLoF4AsRlEPAS98pVEE+CeArE0yCeAfEqEM+CeA7Eq0G8BsRrQbwOxOtBvAHEG0G8CcSbQXwMiLeAeCuIjwXxNhAZEG8HcQ3Ex4F4HsQ7QHw8iHeC+AQQnwjik0C8C8QLIJZALIO4DiILQgAhgpBAyCAUECoIDUQORB7ECohPBrEK4gaImyDeDeJPgSiAWANRBLEOogRiA8QtEJsgyiDeA+JFEBUQVRBbILZB7IB4L4hdEDUQeyBug3gJxB0QL4N4BcSngHgfiPeD+ACI/w9EHcQHzdEwiLsgGiD2QRggDkAcgrgHogniQyDug2iBOALRBtEBAeb7yodBgDe70gPRBzEA8QDEQxCPQJyA+AiITwXxp0F8Gog/A+LPgvh0EJ8B4jNBfBaIzwbxOSA+F8Tngfh8EF8A4s+B+PMg/gKIvwjiL4H4yyD+Coi/CuILQXwRiL8G4otBfAmIvw7ib4D4UhB/E8TfAvG3QXwZiL8D4u+C+HsgvhzE3wfxFSC+EsRXgfhqEF8Dwpx1+DoQXw/iG0B8I4hvAvHNIL4FxLeC+DYQ3w7iO0B8J4jvAvHdIL4HxPeC+D4Q3w/iB0D8IIgfAvHDIH4ExI+C+DEQPw7iJ0D8JIifAvHTIH4GxM+C+DkQPw/iF0D8IohfAvHLIH4FxK+C+DUQvw7iN0D8JojfAvHbIP4BiH8I4h+B+Mcg/gmIfwrid0D8MxD/HMS/APG7IP4liH8F4l+D+D0Q/wbEvwXx70D8exD/AcR/BPH7IP4AxH8C8Z9B/BcQfwjiv4L4byD+CMR/B/HHIP4HiP8J4k9A/C8Q/xvE/wHxf0H8PxAfBQHxy5XzIB4D8TiICyAugrgE4gkQMNC9AvMvV66CeBLEUyCeBvEMiFeBeBbEcyBeDeI1IF4L4nUgXg/iDSDeCOJNIN4M4mNAvAXEW0F8LIi3gciAeDuIayA+DsTzIN5BxDMvE3FRJ3YcmRSDqbanjuot+PyS3hoYT9oHW/qR8Wr783qzd9zST+Crc+fPX4aJtD9FwoBLH08ufKG8tbF9BT5dhOH+GGXnVre5b06fVA0gO3SegArJxTqDPom0DP3o8m7nYRHm+J5y5nXIF71njEfHenvf2DffD/We3Osck6/NrR+e3ug0Bj1j3yJPPmsfkV83yQkt4/FzT0Adr3cmvreXSc2d7old22VnPuLKO4k0HeAnQEt9IhHgleEf+MaLMPtxA58oWtN7BtyXHeO+y4ylK/Y9DW8VanmODI+PjW7/BMrfae73773O+81LzV7zLgSi585dhufr3O9C/RdhzsVvzOCZ3RkGuOaU38iM6YVzz0+/gD1ZajbHJz1mTQZdgGmQieE2NO/VSkff39BhVnNsWv1ZKFkkgwxypw+a+5559gskRO5dMp+z3rlzjz9+7uLFJy9jdZWdaz2P/Th2/d9/b+7drwatrppctndBh75AxHmYwID7gQIQfly9atrXJSiwDAUGngLnzCsAIq5chwJZKPAQLyBAAREKnOAFJCggQ4FPxQsoUECFAp/mKXDRLAAtfEWDAjkAFgwEpg4XLtUN+OZy/cj67sL5N43CvXN4SAY25mnuVHjeNETk03kYZ5gDjk+G52CViBurqxnSwqTDjzKk7kbzoNkwp8N7mSPggDWN/YwgrMjiiqJkqp125j2Ddib/QkbMisrNm+c/3bngDbeOz3C+erf71Wc6XxWg2jUi3rF0054HJtpmmu3jQf909cvLy+c/yzmx6F7rs52vSu5Xn+N8dcv96nOdr8pQ43uIEDKZT8pkMncKu1vlrVuZO5vlSilT3CwVX4TD8tbO7b1MbadULG+Ui4W98vZW7fznORd5ES5SIWI1Y/4rbxXJ7+XaXmlrL7OxWyqRy+6VdjO10t4eXG29tFcq7pXWMxvbuxklU9vbLRWqtfOf71yvCtfbIqJiXa+2fXu3WMqsVbaLL2bsf97LmueT79ZLNXJ9Uzu38LDc+S9wrr8N198ZXv/G+L/M/8/eecdHUfz/n5MkJKF3EMGjKS2QXpBiGiSQAumAGFMOEkgjBQgWxC6CKAgqKCoICAiKDUUBQVFRARsoKiJYQRERsWH57Wvu3kNmNzNzSfzy+f3hPfTNZN47z9frPbt3u7d3t1tLU7OcbS7xx4KfYoQYJz/NLzDC3y4+xsWmUjMwIsTZyIhM8AuJiBCWS0q23UHcVHDTjBBLAwNi0sckmJbnTSPtF6DQt80jcDrAGW4bDvKvYTgoQFzSMDyfuJngZrk/EeEB57ih1om4k7jjwB1fl4nIOqefZZ2IBQSewJ8hd1HXRN51N3VlQ/4qI/TxGzaisKSwosB4FSg793wtccwwPVttC2lsDsctoq484PKN0MHYXIuM/T7OAdnpkyP7YNs9tKSDD15MXZMxuMAIw+1RRaV5U+29khMyYlP8A+x9Eh2VBaX5g+2ZsSONp2J8Ul97QU6FPdfhKLHnOyYVlhimK0vteaUl0x3lkx22JYQsBHKKEc5NUgU7bqgYbE/xCwwMGRgYGGbMamCE7V4aM5U7u4+6ioEpsToLrLOz+wmJowkvfFH64tqchQT4D4yLHu0Xl5xmW0pDpnFjy6gL37HxqrQaCz9nLDU2OtJ47bJrjD1AyCogpxuhU405M7YAY+3Zx4xLSY5Psj1Iy87gjpZTVzWGz7I6iqizo4cIeTWQ19TuaGxAXGxkmu1hWvZa7ugR6pqN4ddbHBnP9bo6WkHIOUDeIHEUyBytpGVv5I4epa6bMfwW7Bvt0cmJxu7I+TqfnBJj7AKwI0mLi7WPSEjOTI2LjU0bbFtFA2/FwNuMcJk9YUyqPTI+xR6daY9NMHZBKfHR9tToyITY9DH2OCPHXneMGhOj2T/RfoEh/vZYIwbYVhPuduDmGiGcLW7k7GP8wvz92V9h/tQbZLzYBAQ4ewNCgwxKQDiIAf4BtjXEugOseUboioxr6YhAe2pMSmz0uGij0AQ24DEaMB8D7jRCm3MbLVMIDIm0raWlFmCpu9hSfVJi09JTkvjSfW3raKm7sdRCvIoZzx2Ip7I41rmvN9wHBWcZpbF/DPdB4Vm29TR2EcbeY4SO5zbVxPSENGMp50jb47ToYiy6pDYzEX1tG2ipe7HUfUbo75R0KhpbanJ6GuywIoNCGTzEaSsky7aRht+P4UuN0O3chsr8BIcyUkSWc6TtCRqxDCMeqMVWgH9f25O01INYarkRwjA+OAyryYhM3thoa5oLDnEqOf8ytgpjOkNCbJsI9RBQD7PNcIxfoGt7MQ4T8ZJqRGMrM/aqGUYMYvlQVz4EW6GxlpEP9Lc9RbhHgFvBNsPUmMTI0diEjY0mIMS1yQVHYK0GBttj0hP9jCdMlGs7CcWzJ4o9254m1kqwHjXChfZe0X4RLuVw/BHk/CMg2PYMLb0KS682wuBz+xpjSayywABMgrFjYDGc7S3YEygwwMkJDLLHGTHQ9izR1oD2mBEG2q+xgxPi2sfAd2Bcmt343y9uXEyK2B1ne44Ia0FYx3ZXBsG1gzIGJUbGJ7n+dGqH2TbTmPUY83htG2VAX9vztNQGLLWRrX3UEIbVE+RacUERMVgzQQHO6Kov2D+GLcTWZ0Sw7QVCPQHUk2zS2IIRbFoigvihi/PQiA6ojP9dvUYL225QoH+WbQvRNoH2lBEGIBXkXCIAyCC2Boy2v3MQ/ggMcS5le5HGP43xzxgh5NxO+dz+c5Rx4NwLr1TG4BCjMsRQFjEDIYEBtpcI9CxAz7EZusZ1/BqIGUGMCzRgaAc5JyfEeI0wsOHnlFKy0mxbCbUZqOeNMMi5GsmNsVCNv1wrle/qsR1vI8QLQGwxQmsRMSYlxradFnoRC71U26oP7Gt7mZbaiqW2OdeXUU0oPzZP8wv2x+t4sD8mJtiYuDGpkca/QawvmPVhEw4NCLDtINp20F5m0zQyzUhh8wgNwMKh/s6nW2h4BOszhPxCA/1de6IIe3S0sSsyZnwnoXYAtZOh2DKBsBHkfAqydRUUFELHuXQYneEX5tq3GP/aXiHUK0C9yvaoLAdZYw8WwvZnzorDwsOxY/SLT0obaXuVBu7ie+dd1PU6WG9g5+43LDqnKM/1pTEcFxhvuNmb1ddo2d18+OvU9RbveoO69oC41wjBw+xRgJTg0DradVhRkuewJ5SWlp3bDYqHJbbdxNkHzjvsxY1GA8SOPPjB2Zu09LvcyFvU9T4AHxghaJhS0nVIE1/pcP54CX8E2N4mzH5gDmh87KGlP8TSHxkhsCevOV9845KYM9MeW14+KK20yG738x9oHGUEBMT29/e37SXKQV7NPur6BOBP3Z3WCPO0vkOcQ+B8JivHdYT5Li19mBt5j7qOAHDUOq1mydqn9X3CfAHMlxofH9DSX2Hpr+s2rYHhIWGxfsZR2H6ifMOrOUBdxwA+7ua04uBEnNYPifMdON9Ly3EeJn9ES5/gRg5S10kAfrRMq0Wy9mn9mDCngPlJ4+MTWvo0lv7Z/Wm1G9MaERwWxrbWT4lyhldziLp+Bfg3I4S6s7UG2M1vLG2fEel3kP4wQl+hoEpHTrn03e1hGnyWO/ucuv4C72/r5mv1UNs8HyEMvlTv1ahxnWwdpcE2Y5zXBY3rMu3+eLBp/4IojRtTcV9SlyfAXkbobgxi7/8Gu44wgMQ3ZwxTkTEjUiKjbV/RoCac8zV1+YCDM73dXHZqrrlCmpKKwbZvaERTjGjmUnY+knFeJxEh3nmGx1WP7Vsa1ByDWgiD7AE8hDo7goMHhoUG247RoJYY1EocFMgHBbsoA8MDIvxtx2lQawxqIw4KMg3yHxgWFhIcaPuOBrXlE/M9dbUHp0Nj5ykW1wQ7D97OTTCeYrEpthM0piPH/EBdnYG50Irx97dgTtKYLhzzI3V1BaabZXUH1ra6T9GgiznnJ+rqDk4PN1b3aRrREyN6ube6f6ZBvTHoEsnqprORIcEDQ4zX7DM06FIM6qNZ3eEDA8ICw22/0KC+GNRPtrqDXJSBoWHhIbZfaVB/DBogDgq2bCPBYREhYbbfaJAfn83fqWsQOP6WlRtYyzbyB40J4Jiz1BUETLBl5QbVtnL/pEEhnPMXdYWBE+7Gyv2bRkRgxGD3Vu4/NOgyDBoiey6HOTvCwo2VG2LDN3LYoKEYNEy2cl3ryXgzEGEcSdto0HAMulyzcgMGBoZHBNkuoEGRGBQlW7lBrpVrvF823jE3pkHRfDY9qCsWnBGN3dyxBVp3bJ5EGglSXGOcxlHtQWqeHPWisfHcWBPqGg1cQmPnKVbX5kLv3mhzSYzPMjY6bxqSyCk+1JUMyhjXxuKisPd+NTY6vMG1+dKIsRzSlLpSAUkzgh+2NtebitJy1wlJ5/tHIxNXaGx75XkF1a4ybc0IkM6ZzakrE8ysxnj7xI3Ru0wylho75tzKtdBbEGocp7ekrgmgX2Gls3et9FwbFx+bECOjtyIUfqzldaURmgsfzNla0wLZWOCqxngPzx7s9GdyQkJyJj5ii02ITYxNSku1R6bE2pOS0+yGgci05ER7VGRCZFJ07GBbGwLlAJTrVGKenM9uW1taII8X2o66HLyrPXVNBqbAWjteosSXK1ntHQhVyOkdqWsq6EVWuvHWXtwspeutE6GKOb0zdZWCXtbYcjBnfd4xtulg7kLCTAOmvE5PxS40tgJjK63r+yJaoAoLTDeC/7n1bTwx02NT2dnv1ORE/J0SHxmVEOtc7YnxqakGYqCtKzFmgDGzMc6xuBjxqfbEyHH2qFh7dGR6amyMPWqcPdI+PjYl2Q/n0l2frQ60dSMEfpfmNasxzjtyG2NSYjPik9NTyU/yCJc7cpMZn5AADSgMtF1MrKvBuqYx/6AJg1ymxVIG2+w05lqMuc4IbZ1jegSEBvYYwP4N7WHrTovN5iu5B3XNwcgbcLRsrLRA+/Sc8gp7SWkl/6Qif4D1TYrraDnM1pMoN3JwL+q6GeBbrNsmzqPV3PL5B4+WbbM3oW7l9Euo63bQ51peSoVjcfZSeimNuIND+lDXfEDuFF/VnSf37KJFW18asoBT+lHX3aAsNB+R4OSg3XxE0p/GLOKYAdS1GJglVkyYFeNHY+7lmIHUdT8wS0UMOz1ZAzMiITI1LtA2iMYs4xh/6noQmOUmjOtEJsekjkmIT7MF0JiHOCaQuh4BZoU4w9EmN/jcKsUWRENWckowda0CZbUROte6y8MZVVsILbyGjw+lrrUYv87iIsjqIoyGrOeUcOraAMpGd44BImjIE5wymLo2gfKUG8cAl9GIpzlkCHU9C8hzdT8GGEqAzZw5jLpeAHNLQ44BhhPqRU6/nLq2gr6tIccAkYTaDtTL1n1CFC2wAwvsrP8xQDSBXgHoVesxQAwtsIsXGktdr/OuEdS1G5g3G3IMMJJQb3F6HHXtAX1vQ44B4gm1j9NHUde7oL9Xv2OAQNtowrwPzAd1OgZIoLH7MfaAcw9ld2MP5We80wgOCcEeKsCWSJQPeW1J1HUQ4I8bsodKJtQnnD6Gug6B/pkbe6ixNOIwh6RQ1xFAjrqzh0qlIV9wShp1fQXK127todJpzDcck0Fdx4A57tYeKpPGfMcxWdR1Apgf3NpDjaMxJzlmPHWdAuYnt/ZQE2jMaY65grrOAPOLO3uoiTTkV065krp+B+UP9R4qmxY+y8dfRV1/Yfzf7uyhcmjIP5ySS102D5z59HBjD5VHQxp7ECWfujxB8fLQ76EcNKIJh0yiLh9AfD3qvIeaTICmnFlAXc3BbOHRgD1UIaFacvoU6moNehsr3f091FRCtQWqnYdlD1VEC7THAh086r2HKiZQR4A6eVj2UCW0QGdeaCl1deFdZdTVFZhu1trd30NNI9TFnF5OXd1B72Glu7+HqiBUT06vpK7eoF/iUa89VJCtijCXAtPHoy57qOk0ti/G9vOoyycOgeFhgfj8LNA2gyj9eW0zqcsP4IEelpfKmi/crpfKahoziGNmUVcAMIG1vC5EmF8XrqYhQZxyDXWFgBLqga9l1ThlGuxfc4dmPP1s19KAMM64jroiwBgsFuT81sA5RqLzhW42jbmMY66nrqHADPMw7YnwtQPLnmgOjRnOMTdQVyQwUWJF9L2FmhXdyE9ZcsZN/JQlGCM8TK/c+M6D+ZX7Zn5uklNu4accQRllLaiWs9q38nOSHHMbP+cITJKIYV+6qIFJSU1Ljo+23c5PSnLMXH7WEZgUsSbXNzRMNd3Bz0pyyjx+nhGUDHNN+IKHpab5/EQkx9zJTygCM97DdAiEb4jYTYdAC/gJR065i584BOVKD8vRAr5hYjpauJufS+SYhfysIDC51ppqOZJaxE8Ucsw9/EQhMJPMz+tQ4aMl1/N6MT+TyDFL+BlBYKZYn9f4ioz4vL6XnzHklPv4mT9QSsRngesLNsKz4H5+XpAzlvJzfGCU1zK91oOxZfzcHsc8wM/mATPdPL1B/ubDXaOiB/nZO45Zzs/GATPLcgQjPA3YEcxD/JwbhzzMT6kBcp3FS1AtT8lH+Pk1jlnBz68Bc0Mt68jy2ruSn0zjlEf5yTRQbjFvMGEBtWwwq/hZM45Zzc+aATPXupoYSFxNa/h5M455jJ83A+bOWjCBFsxafuKMY9bxE2fALLQUJbzouYpaz0+ccczj/MQZMEvEte38rtY5zJj0xDG2Dfy0GYds5KfNAFlaS0nh4eaSnuCnzTjmSX7aDJjl8OI3jF1PIgdX5bLnsqPeckdFVVGl8zdKm/hJMw55ip80A2SFh+vTNPX7tadp0ErOeYa6VoGzuhZOLW/YnqVBazjnOepaC846C6fWp+VmGrSec56nrg3gbLRyavt8/wUa9ATnbKGuTeA8ZeXU9hnwizToac55ibqeBec51zpXv7veSmM2c8w26noBmC21lFXL9w2206AXOedl6toKzjbXK4VyQ95BQ7Zzyk7q2gHKToubWo+NXqFBr3DOq9S1C5zXauHUMsm7aNDrnPMade0G503r7NT2Ovo6DXqLc96grj3g7LVwat317qZB+zjnTep6F5z3LCu9tuOJt2jM+xzzNnXtB+aAyU7tb5lse2jQh5yzl7oOgvOxyU6tJ6Fs+2jMJxzzDnUdAuYzD/bbq+gCRx4uLWgvK8ipcNgd06oKiwpzywurioVXoHdp7GGOe4+6jgB31AiX+g07d61De17Nr7DmlRaX4T4F+Yz2Pg39gtM+oK6veNd+6vqGdx2grmPQPO6B7xbb+/Uz3jZn5pTj4/8+FX3tMxzlDnthRUWVoZZfhYvw2OPZrz/TynNKKlzujEG2D4n2HWjfe7AfXzIamxV7ZYHDnlJVYsdvsasq7Cmu+ZhUWm4vLjU0cEOb8uJzvI+Id4IbPkhdJ3nXx9R1Cqo/efD39fzBLKRWFRfnlFfbSyfZa0yq8a6wtLyCLWL7hECnOftT6joD9i9G6GK3PsYUVFcUGqvHdogW/xWL/+bBf30qLu76nTnvcP6Umv/F3dk+I97v4P3hwT7hTHOUF+NSl9w7HuZfMFr+th0m1lmw/vRwfVqa6piO1Vs31ufE+gusvz34J6/sUTfWEWL9A1Yjz5os10boHisozHaUWDZPWoNfUFdjo8vLw7MuT9Ivaawnx31FXU2A8/ZkXy6vcaxRc/jXtKwPH/4NdTXlXd9SV3PedYy6WvKu49TVmnd9R11tedf31NUe7jp4uv1b8ZDgwUERtfxW/AQBO3KNH6irM+86SV1dIHuRp9u/Ff+RBnblrFPUdTFYds96/Qr8J4J0B6SHZ0N/BX6aeD3B6+X5b/8K/Gfi9wb/Es9/+1fgZ4h/Kfh9PP+tX4H/Qty+4Pbz/Nd+Bf4rgfsDPMBtw7pfgf9GXD9wB7o/EZpfgf9O3EHg+tdlItS/Av+DwAH8GXKWuoJ415/UFQL5UM+6/Ar8LxobxnF/U1cE7/qHui6DwhBP1Y9qcAUL54lCPtxGXcN51wXUFQlilGcdDnca09BoTvOgrlje5UldI3mXF3XFQ3OUZ8MOd5oQbTRoCZ4NPdzxJl4iN+xDXcm8y5e6xkI1xbPehztNCZTK2c2oKx3sDE/N4U5zWjwTi2d5NvRwpwXxxoE33rMhhzstiTUBrCs8G3K404pYE8G60rMhhzutiZUN1lUNONwJt7UhVg5fg22pKw/4fOXxSTta1sGHt6euybyrA3UV8q6O1DWVd3WirmLe1Zm6SnnXhdQ1jXd1oa4K3nURdVWhhunKGrrSsjP48G7UVY3hs4zQtrmvcRjEnoo5041n9bBhzX1tF9NiV/ORduq6FiOvUwp3p2Vn8+E9qGsO7+pJXTfyrl7UdTNEbjFCS5M5W29a5FYa5YFrYkmunIUrsjfJzq2aNMlR3iS7lF0I3ye7rLSiEE+qJtlF7EL0Ptl5OWU5eYWV1U2znZfwwhWjfLJnlBeya0f5ore0gl1GKruwIrnMUdI1Mae8oiCnKKo6xTHJeS+J/tnZhfmOkkrcoa+R63HBBbhyF65y73O7ZyP+eGRAo0b+lzdi17/3bYlLeRm7kEbe+ElCS1zTCw/vJri4FUuwK1xZLvdvvTIWlveZi3m5A2EewnyEOxEWGKEVrjLVEnTvFiw2Z7EZi01Z9GXRh0VvFpuw6MWiJ4seLDZm8QIWmX9254dWA1wSPndB9W6EhQiLEO5BWIywBOFehPsQ7kdYirAM4QGEBxGWwzauffUbk/iHxb9Z/IvFP1k8y+IfLP7OonP5X1n8hcUzLP7M4mkWf2LxFIs/sniSxR9YPMHi9yx+x+JxFo+x+C2L37D4NYtfsfgli1+weJTFIyx+zuJhFj9j8RCLn7L4CYsfs3iQxY9Y/JDFAyzuZ/EDFt9n8T0W32XxHRb3sbiXxT0svs3iWyy+yeJuFt9g8XUWX2NxF4uvsvgKiztZ3MHiyyxuZ3Ebi1tZfInFF1ncwuILLD7P4mYWn2PxWRafYfFpFp9icROLT7L4BIsbWdzA4uMsrmdxHYtrWXyMxTUsrmZxFYuPsriSxRUsPsLiwyw+xOJyFh9k8QEWl7G4lMX7WbyPxXtZXMLiYhbvYXERiwtZvJvFu1hcwOKdLM5ncR6Ld7A4l8U5LF7P4mwWr2PxWhavYfFqFmexWM3iTBZnsDidxSoWK1msYLGcxWkslrFYymIJi8UsFrE4lcUpLBayWMDiZBYnsehgMZ/FPBZzWcxh8SoWs1m8ksWJLF7B4gQWx7M4jsUsFjNZzGAxncU0FlNZTGFxLItjWExmMYnFRBYTWBzN4igW41mMY3EkiyNYjGUxhsVoFqNYjGTxchaHsziMxaEsDmHxMhYHsxjBYjiLYSyGshjCYjCLQSwGshjAoj+Lg1gcyKIfiwNY7M9iPxb7stiHxUtZvITF3iz2YrEniz1Y7M6incWLWezGYlcWL2KxC4sXstiZxU4sdmSxA4vtWWzHYlsW27DYmsVWLP4f7ywGul7YfR7Ca/3DCI8grEBYifAowiqE1QhrEB5DWIuwDmE9wuMIGxA2IjyB8CTCJoSnEJ5GeAbhWYTnEDYjPI/wAsIWhBcRXkLYirANYTvCywg7EHYivILwKsIuhNcQXkd4A2E3wpsIbyG8jbAHYS/CPoR3EN5FeA/hfYQPEPYjHED4EOEjhIMIHyN8gvApwiGEzxAOI3yOcAThKMIXCF8ifIXwNcI3CN8iHEM4jvAdwvcIJxB+QDiJ8CPCKYSfEE4j/IxwBuEXhF8RfkP4HeEPhLMIfyL8hfA3wj8IOJLxsSFcgNAYwQPBE8ELoQkCth8fHwRfhKYIzRCaI7RAaInQCqE1QhuEtgjtENojdEDoiNAJoTPChQhdEC5C6IrQDeFiBDtCd4QeCD0ReiH0RrgE4VKEPgh9Efoh9EcYgOCHMBBhEII/QgBCIEIQQjBCCEIoQhhCOEIEwmCEyxCGIAxFGIYwHOFyhEiEKIRohBiEWIQRCCMR4hDiEUYhjEZIQEhESEJIRhiDMBYhBSEVIQ0hHSEDIRMhC2EcwniECQhXIExEuBIhG+EqhByEXIQ8hHwEB8IkhMkIBQiFCFMQpiIUIRQjlCCUIpQhTEMoR6hAqESoQpiOMANhJkI1wiyEqxGuQbgW4TqE2QjXI8xBuAHhRoSbEG5GuAXhVoTbEG5HmItwB8I8hPkIdyIsQLgL4W6EhQiLEO5BWIywxAitBrkO51v5UyOAGoHUCKJGMDVCqBFKDVxYFa+kPvcCfR/C/QhLIRJOyWXoegDhQYTlRvDE5VLlV1XF67gvOhzluFSyJ7vAchPXJVp90wqMd1H5SPikFRbjllLFZc0SSp3nx3COxju9wjmwZezMPAe7A5jzXhS+rlMbhY4Kr5jS4pzCEu9417sjm4fN1sj43/hPcsez5ma/5wSR7k7Z9MrCooHnhM7dRBBL4X+vh4wZaB6ZWuO2cewGauyNo9cKtpWnpkVmJxr+sl+a9NqoNYdu81lpdHs9inmNGxcbn+QXOyY2wXl7MDbMZzXya4xwWfRg3CdscnlOsR23Nau4gr9Hc7Zqnl6iu6bbM3BLuiucb3hx3Vp2OduH2DMHptZ7NfQqtj6oi1ezAW43yqt5EsqoxuloqMWRczEwA75wMTeD+bycuUVkDneHuQPMnXLmqyIz0jpzu73c/XBFVH4Lym/LlfeKytHuVLMfzANy5kciM1bBnP/KIifzMJify5lHReZIBfOm4y7mMTCPy5nfi8x466yf8qrPx1DMxezW9zhdnIaLn+UufhFdjLa6OOvVwM+xREN/wdDfckONmgiGEq2GPJv8yx+EiQZxuXgvHGxLDPqKBpOtBls2+Zc/SRMNtobBNnKD7USDY60GOzf5lz6KE411gbGL5Ma6icZSrcZ6Nvm3PssTnfWGs0vkzvqIztKtzvzcnjLNh4FOY+EuY4NgzF9uLFA0lmk1Fub+ulR/migai4CxwXJjQ0Rj46zGIuuyLpUfR4rOouEsRu5shOhsguK1mjMTwUySM8eIzIkK5rEF9zmZmWBmyZnjRWa2dQazm9ThE1VRPAfiuXLxfFE8x52CpoJZJGeWiMw8a0EVTaRX9mZSo72WOqWqIDVdLjVTlHIo7P+22cWcDeb1cuYNInOy1f6tTRp+bXHR0+3wNFfuaZ7oqdDq6e4mblycnIn++JlLdBFE75GLLhFFpyomlzMfBHO5nPmwyCy2FrLKOrl1vjy66GkNPD0m97RO9FRq9fREE/311UXNTdB8Sq75jKg5TTG3X3suczJfBPMlOXObyKyw1vGKdW7rfIV35ungAJenXfD0mtzTG6KnKqunPU0Ul4gXxfZB7B252Hui2AzFpHLmQTA/ljM/FZnV1gKOWCe1zhepFz19AU9fyj19LXq62urpu9on1XntT1HsBMR+kIv9KIpd686k/grmb3LmHyJztrWAfyyTWvfr7DNP76a6PNm8DewF3lJPHt6CpzlWT7hHqfRC/aJYU4g1k4u1EMVuVEwqZ7YHs4Oc2Ulk3mwtoKu3u7cKEJUvhrJdrtxDVL7Vqnypd8PuNSD66Qs//eR+Boh+brf6CfBuwM0KRDNBMBMsNxMqmrnDauYyb93dDkTFoVAcJle8XFScb1WM9a71dglMZtcsl8xIyMTJZUaJMgusMsnetd5vQZQZC5kUuUyaKHO3VWacdx1u2CCKT4D4FXLxK0XxRVbxPG/5HR9ELQe0Jsm1CkStxVat4trmM8I0n6WQKZPLlIsy91plZnjX7Z4Ton419GfJ9a8R9e+36s/x1t60gkluecQleSMkb5JL3iJKLrNK3lHLzAb49xVl5kPmTrnMXaLMg1aZxd71v22G6OVeeLlP7mWp6OUhq5eHvBt23w3RzyPws0Lu51HRzyNWP2u9G3DjDtHMeph5XG5mo2hmpdXM097KO3+Ics9C7jm53POi3Cqr3FbvBt06hNl58g2Xne2w87Lczk7Rzhqrnde963zvEdHCblh4U27hbdHCWquFd73duHmJKPo+RD+Qix4QRddbRT+p7fU1oK8ocwgyn8llPhdlNlhlvvKu/+1TRC/fwMu3ci/HRS9PWL2c9G7Q/VdEO6dg5ye5nZ9FO5usdn73ruMNXJiBVSddBs7CwJ9yA3+LBp62GmjsU987wIhOPA2Ol5eP1Am+0FPDybNWJ8196n8LGdFLS3hpJffSRvSy2eqlo0/d70EjeugMDxfKPVwkenjB6qG7T203sWEq3TwfcKr0hEovucolosqLVpX+PrXeBUeU8YPMQLmMvyiz1SoT4tOg2+iIdsJgJ1xuZ7BoZ7vVznCf+t+HR/QSCS9Rci8xopcdVi/xPvW/kY/oZTS8JMi9JIleXrF6SfVx905ATLmqt0s5HcoZcuUsUXmX4u3/3/1dzGwwr5Izc0Xm69ZqJvsofjYlihVCbIpcrEgU2+1OARVgVsqZ00XmW+4wrwXzOjnzepG5xzopN/vU83ZKopFbYeQ2uZG5opF9ViMLfJT3QRLl7obcQrncPaLcu6pT9yku5jIwH5Azl4vM960lrPSp3x2hRB+r4GO13Mdjoo/9Vh8b3JhKLvcE5J6Uyz0lyn1oldvsU697UjlP7le7bLwAG1vkNl4SbRxUfWBAzFfAfFXOfE1kfmIt7S13nx3mW1SJRvbAyF65kXdEI4esRvbLVmmNU9pc7kPIfSSX+1iUO+zOXB4B86ic+aXIPGIt4Zj12eHWjb2Yj88fdvn4Dj6+l/v4QfTxhdXHaTemksudgdwvcrnfRLmvrHJ/1e3ZQbcWYzbmnH3IaeMf2GjkK7Vxga9g4xvFGq3o8bCT6WOM8fKVM5uJzGPW0lr71vPmZqKRtjDSTm6kg2jkO6uRLr7Ku5KJcl0h100uZxflTrgzl5eC2UfO7CcyT1pLGORbv/uziT4C4CNQ7iNY9HHK6iOiLlN5GeSGyOWGiXKnrXLRvvW6QxyzcSZyhdNGLGyMkNuIE22cUazRbwtczGQwx8iZKSLzV2tpmb71vkedaGUcrIyXW7lCtPK71UqOb13uJieq50E9X64+SVQ/687k4kezXiVyZpnI/MtaUZXl6eLebfZEHzPgY6bcxyzRxz9WH7MbMLNzoH6DXP0mUR239jOp316nZw+/0R+zUTT3UaeNO2BjntzGnaKNxhYb51YwZy4Gc4mceZ/I9LSW9qCvO7caFFUfgurDctUVomoTdypZC+Y6OfNxkeljrWSTr/YGaUxy4iaX5NOQfEYu+Zwo2dQq+aKvO3dYE1W3QnWbXPVlUbW5VXWXr+QWbcLtFkXV16H6hlz1TVG1pVV1n6/6Bn7O+zWKqu9C9T256geiamur6kFfyU3ihBs+iqqfQPVTuepnompbxebJmV+B+bWc+a3IbG+t5ISvG7ecZKIpH7lET0L0R7noT6JoR0UhnPk7mH/ImX+KzM7WQmxN3bjppSja2Bji5dFUKurVVBDt4k4hzcFsIWe2EpldrYW0b+rObTdF1Y5Q7SRXvVBUvdidSrqD2UPO7CUyu1sr6dvUvZe+uH9ckv0hOUAuOVCU7GmVDGrq9ksfVw2BaqhcNVxU7W1VHdq09pc+8dajoupwqF4uV40SVS+1qo5sqn7pc967VFSNh+oouWqCqNrXqjq2qfr+mM6bn4qqqVBNk6tmiKr9raoTmkpusCncPZWpDrlklVN1IlSvlKteJar6KZ4UnDkZzAI5c4rIHGStpNTyOlXLtXtF0WkQLZeLVoqiAe4UcjWY18iZ14nMIGshN1pep2q7g6yoejNUb5Gr3iaqhrhTyQIw75IzF4rMMGsl97r5OhWY6JK8H5JL5ZIPiJIRVslH3H+d4qorofqoXHW1qHqZVXW95HVKvIuuqLoBqhvlqk+KqkOtqs/KXqeE2/CKqpuh+rxcdYuoOtyqul3zOuW8j6+ougOqO+Wqr4qqkVbV3bLXKeFGwKLqW1B9W666V1SNVjwpLq10MfeDeUDO/EhkxlorOdS03rciFq0chpXP5VaOilZGWq1807QOt6YRxY9B/Lhc/HtRPN6duT0N5s9y5i8ic7S1oLNN9fepEjX/gubfcs1GzQTNRHfqaGKM8cLFVmS/8BSZydY6WjbT3imLSXZZ5pJsDck2csl2ouRYRRmc2QXMi+TMbiIz1VpGz2Z1vVeX6KA3HFwid9BHdJDuTlWDwPSXMwNFZqa1qrBm9b9bmOglAl4Gy70MEb2Mc6e+aDBj5MwRInOCtb7R1vrcvl+Z6CURXpLkXsaIXiZavaQ3M9/wjCm03ulSyIRCllxhvKiQbVXIblbfO6aJTnLgJFfuJF90kmN1UtjMfMs1UWEqFIrkCiWiQp5ia+HMKjCny5kzRabDHeZsMK+XM28QmZOtM3GrdQt0+65xopfb4WWu3Ms80Uuhor4mx1zMRWDeI2cuEZlTrfUts9bn9n3rmJdToatdv4uEl+VyLw+LXooV9XHmGjAfkzPXicxSa31PNKvf/d1FH5vg4ym5j2dEH9OsPl5oVtfjGy7+IsRfkotvE8UrrOKv1P7S9fVEl8IuKLwmV3hDVKiyKuxpVo9b1Ism9sHEO3IT74kmZlhNfNis7ve4Fz0chIeP5R4+FT1UWz0cacavN4yJGJMSmxGfnJ5KM5I8wjU/NB+Z8QkJMAmLJjNfwMyXcjNfi2autpr5rhn/xTRUXfMuro3BougJiP4gF/1RFL3WKnrGWKKtU7RHQGhgjwHs39Aeos6v0PlNrvOHqDNb8Wpx6CYX09bcYF7QXMr0aC4w51i9+zRnt2EOcOM2zPis2vVpm/Oc1HeHH3P9MhI2mslttBBt3KgojTPbg9lBzuwkMm+2lta1ef1vBC16uRhe7HIvPUQvt7pTX18w+8mZA0Tm7db6Apprb0XNJI94rXX9qhGSwXLJUFHyDkUZnDkUzGFy5uUic761jNjm+pthi5ojoRkn1xwlai5wp46xYKbImWki825rHeOau3E7blF0AkSvkIteKYoucqcQB5iT5MwCkbnYWkixtRDr/eWY6Ad+LtFSiJbJRctF0XsVhXBmNZiz5MxrROb91kLmiIXUfktyUfRGiN4kF71FFF3mTiHzwbxTzrxLZD5oLWSxqZBab4ouit4L0fvkoktF0YfcKeQRMFfImY+KzEeshaxtrr8tO9PcnebSXA/Nx+WaG0XNlYo6OPNZMJ+TM58XmausdWxtrroxvKi2HWovy9V2impr3KlgN5hvyplvi8y11gretawJ663pRc33ofmBXPOAqLnenToOgfmZnPm5yNxgreOr5m6edNx+tUvzG2h+K9c8Lmo+oaiDM0+B+ZOc+bPI3GSt43fLzrz2k45c8iwk/5RL/i1KPu1OGZ4tDKZXCykT17Ou+QM3axnNW9TrpCN30BIOWskdtBEdbHanqs5gXihnXiQyX7BW1b1FA086PrXC5aUnvPSSe7lE9PKioj7O9ANzoJzpLzK3WusLsdZXt5OO3EsYvITLvQwWvWy3ehneotZ37lwhEgpRcoUYUWGHVSG+RYNOOnIno+EkQe4kSXTyitVJaotaTzpyhXQoZMgVskSFXYqt5ZfdLmY2mFfJmbki83V3mIVgTpEzi0TmbutMTLNugXU76ci9VMBLpdzLdNHLW+7Udy2Y18mZ14vMPdb6brbWV7eTjtzLrfBym9zLXNHLPnfquxvMhXLmPSLzXWt997eo10lH59H31h9dPpbBxwNyH8tFH+9bfaxsUdeTjlx8FcRXy8UfE8X3W8U3tGDnUuxunEvx8x8YGBwSgnMpAaKNJ2DjSbmNp0QbHyrWL2e+AOYWOfMlkXnQWtoO6/Zbt3Mp3Msr8PKq3MtropdP3KlvD5h75cx3ROYha337W7h3LuWZjutcP0eD5EdyyY9FycOKMjjzCJhH5cwvReYRaxnHWrh5LoVrfgfN7+WaP4iaX7hTxxkwf5EzfxOZX1nr+KuFu+dSuOg/EMUNtGS/JmspiH7jTiE+xhgvXzmzmcg8Zi2kdUt3z6Vw0bYQbScX7SCKfqcoZO0wF7MrmN3kTLvIPGEtpHdLd8+lcNFLIdpHLtpPFD3pTiEBYAbKmcEi85S1kIiW7p5L4aKXQXSIXHSYKHranUJiwRwhZ8aJzDPWQhJbunkuhWsmQ3OMXDNF1PxVUcdDDhdzHJjj5cwrRObv1jpyWmrPpXC1PKjly9UmiWpn3amgGMwSObNMZP5lraDKsiYk51K45gxozpRrzhI1/3Gnjjlg3iBn3iQybR6WOm5v6ea5FK55BzTnyTXvFDUbWzTP1bFwnou5GMwlcuZ9ItPTWseDLd07l8IlH4Lkw3LJFaJkE3fKWAvmOjnzcZHpYy1jU8t6nUvhDp6Gg2fkDp4THTR1p6qtYG6TM18Wmc2tVe1q2cBzKdzL6/DyhtzLm6KXlor6bnzaxXwXzPfkzA9EZmtrfQet9dXtXAr38gm8fCr38pnopa3Vyxctaz2XwhW+gsLXcoVvRYX2VoUTLRt0LoU7OQknP8qd/CQ66Wh18mvLWs+lcIXfofCHXOFPUaGzO1tL41YG06OVlOnVSmB2UTE/djGbg9lCzmwlMrtaZ6J9qwaeS+FeOsJLJ7mXC0UvF7tTX3cwe8iZvURmd2t9fa311e1cCvfSH14GyL0MFL30dKe+EDBD5cxwkdnbWt/QVvU6lxIk+hgOH5fLfUSJPi61+hjZqq7nUipt610/yIL4KLl4gije1yo+tlVdfgUeGB4WiCuMBIo2UmEjTW4jQ7TRX7F+OXMimFfKmVeJTD9raY5WlrdSNd/c1ngrxUUnQ7RALjpFFB3kTiHTwCyXMytFZoC1kOpW1uPFiNqOF7nm1dC8Rq55nagZ5E4dN4N5i5x5m8gMsdYxvxWu1V3jN1/B/jVP/hiHJExxSh+X4gIo3iVXXCgqhimq4Mz7wVwqZz4gMiOsVTwiblbOaw6eqyLx3NuQLcNcoish+qhcdLUoepmiEM7cAOZGOfNJkTnUWsizrUznTHDZxFrPmXDRzRB9Xi66RRQd7k4hO8DcKWe+KjIjrYXsFrcruvKjebviim9B8W254l5RMdqdKvaDeUDO/EhkxlqrONTK9O4W162s7d3t6atcmoeh+blc86ioOVJRB2ceA/O4nPm9yIy31nHKullJfqLKRU9D9Ge56C+i6Gh3CvkLzL/lzEatBWaitRDP1kIh7OKhNQpJSU1Ljo8WRZsYQ7xwf2rZj6JE0WR3CmkNZhs5s53IHGstpHNrYctyXaq0li1rz60uzS7QvEiu2U3UTFXUwZm9wbxEzuwjMtOtdfi1Nm1ZuNZqrVsWFx0EUX+5aKAomulOIRFgDpYzh4jMcdZCIlubPj7A5WLttXx8wDWjoRkj1xwhak5wp45EMJPkzDEic6K1jvTWlnO8uOBtLed4t210iWZCNEsuOl4UzVYUwpk5YObKmfkiM8daSKF1y5J8DsJFp0K0SC5aIormuVNIFZjT5cyZItNhLeRa0xphFx2u9ZiXi86G6PVy0RtE0cnuFHI7mHPlzHkis9BayN2tLce8uG6y9Zj3+f0uzUXQvEeuuUTUnKqogzMfBHO5nPmwyCy21rGqtXBs4rrus+XYhCuugeJjcsV1omKpO1VsAvMpOfMZkTnNWsULtTzRa/8wh4u+CNGX5KLbRNEKdwrZBeZrcuYbIrPKWsge8xM9yN/8wa1ru9r4p0t0H0TfkYu+J4rOUBTCmQfB/FjO/FRkVlsLOdLa8kF6zUL4uXcu+QUkv5RLfi1KXu1OGSfA/EHO/FFkXmst44xlfQRJDha56K8Q/U0u+ocoOtudQmxtDOYFbaRMjzYCc461EJ821terWt+jP9jzcdePeaDZTK7ZQtS8UVEHZ7YHs4Oc2Ulk3myto2sb0w4kLECyA+GiF0PULhftIYre6k4hfcHsJ2cOEJm3WwsJaGN5yWKlWF+yuGgQRIPloqGi6B3uFDIUzGFy5uUic761kNhaCgmstZBFo1yiIyEaJxcdJYouUBTCmWPBTJEz00Tm3dZCxlk2LeGNYY1Ni4tOgOgVctErRdFF7hTiAHOSnFkgMhdbCyluI7z2Om9qcK6QMemJY0TJUkiWySXLRcl73SmjGsxZcuY1IvN+axlzatmwwsOVG9aNEL1JLnqLKLpMUcgd01zM+WDeKWfeJTIftBayGOvDb9hIRwk7TV8y2Z7LPr8td1RUFVVW8Ds0cMl7IXmfXHKpKPmQO2U8AuYKOfNRkfmItYy1bVxX/9F/G4urrofq43LVjaLqSncqeRbM5+TM50XmKmslW2upRPJ1LK66Haovy1V3iqprFJVcd5+LuRvMN+XMt0XmWmsl71oqkR4wctX3ofqBXPWAqLrenUoOgfmZnPm5yNxgreQrayWya3Vy1W+g+q1c9bio+oQ7lZwC8yc582eRuclaye/WSmQXweOqZ6H6p1z1b1H1aUUlM7e7mJ5tDaZXWynTu63AfNZaSfO2rl/Ra79HykVbQrSVXLSNKLrZnUI6g3mhnHmRyHzBWkj3ttaNS3L9VK7aE6q95KqXiKovulOJH5gD5Ux/kbnVWklIW9fdynU791s+d2mGQTNcrjlY1NyuqIMzI8GMkjNjROYOax3xljUi/XSHq46GaoJcNUlUfcWdStLBzJAzs0TmLmslE2upRPJ056rZUL1Krporqr7uTiWFYE6RM4tE5m5rJdOszxLZu91xTTa4fmYD1Uq56nRR9S1FJZx5LZjXyZnXi8w91kputlQiPWHKVW+F6m1y1bmi6j53KrkbzIVy5j0i811rJfdbXoJl5+K56DKIPiAXXS6Kvu9OIavAXC1nPiYy91sL2WBaJbV/HUlUfQKqT8pVnxJVP1RUEj/QxXwBzC1y5ksi86C1kh2mVVLrj2BE0Vcg+qpc9DVR9BN3CtkD5l458x2RechayH5jiT5+w6ILHHlT8a6krCCnwmF3TKsqLCrMLS+sKra8Q+HiH0L8I7n4x6L4YVVB6S7mETCPyplfiswj1oKOGUtc6jcstbDYdQ88e17N++HllRaXFTkqHfnn6iHt76D9vVz7B1H7C3fqOQPmL3LmbyLzK3eY/4DZqJ2UeUE7gfmNghl7jYvpY4zx8pUzm4nMY9Z5b90Od7y09+vXz27PzCnHBVX7VPS1z3CUO+yFFRVVxoznV5VjE4svKauqtKeV55RUuNaQMUi00xZ22sntdBDtfGe108VYYojLDtu47ZUFDntKVYk9tTKnsqrCnuLarCeVltuLSw2T8SVGs1hiqCsMdZMbsouGTrgz55eC2UfO7CcyT7rDDAAzUM4MFpmnrBMX0Y5/i5c/2CymVhUX55RX20sn2Ws8uWLLy0vLK+x8xoJXupxcBidD5E6GiU5OK6rjzFgwR8iZcSLzjLW6RGOJLnbrY0xBdUWh8UIh6iVDb4xcL0XU+9Wql+ncDK165aVljvLKat6RWl1R6Sjmf/EJFg2Ng6HxckNXiIZ+txrKaceu0JbmKC8uLMkp4usPD3+TScvfopk8mMmXm5kkmjlrNTO1netycamO6XidaICZYpgpkZspE838ZTVT1Y5fu4496m5m4JsuMzNgZqbczCzRzD9WM7MFM67XU/fMBIWJZubAzA1yMzeJZmye8iciZ94B5jw5806R2djC9FrUrq7HHVx8McSXyMXvE8U9FQVdNHXBbuevfsB8WM5cITKbWAta047dfLfGCV5zAQefd4mthdg6udjjopiPogDOfBrMZ+TM50RmUwXzmYCp+5w/8AFzm5z5sshsrmBuvPA6J/N1MN+QM98UmS0VzMx28WedP9QB8z058wOR2dod5idgfipnfiYy2yqYp1vPm5LAfmID5tdy5rcis711IzthLDF0yBDsPnKLjN0Fbl1YOMnYcTkPbotL842/jCOtgIDBIcGDgyKMtyMl9lHGQU/EAHugf2DIsGHM0bfhLkcn4ehHuaOfREcdFVVy5u9g/iFn/ikyOyuYn2W7mI3bG0yP9lKmV3uB2cU6c02NJXr7DTMmLs9RUYGnZyE7DDXNID1XuXJzKLeQK7cSlbu6U01HMDvJmReKzIut1VxsLBEg/JjLnhkXnxBrj46LjR6NP+OTxqSn2VPHxEbHj4iPjkyLT05KFV10h4seche9RBfdrS76tucHN/FJ0YZAfGpabFKafURKbKzhC78sSo1NS4OdmNi02Oi02Bh2UdwQ1+VnTYb6w9AAuaGBoqGeVkNBxhLO24vYU5PTU6Jj7VEJyXhX7nzU9MUMGH0xsamGQTY/fOFzy4kGQ2AwVG4wXDTY22pw6DmDQ60Pey1NzXLM4Me3uAwOh8HL5QajRIOXWg2ONJZw/SIxzS8wwnyoMS42lZqBEa53CfynHjUeScmisXgYGyU3liAa62s1NtZYIpaUA/DVIZMgbxppvwBFAaKzVDhLkzvLEJ31tzqb4PaUBfnXmLKgAHFJ85RNhLEr5cauEo35WY053F+X4QHnjIVq1uVkGCuQG5siGhtkNVZal3WZda6ALGEx67qcBmflcmeVorMAxWv13g0u5tVgXiNnXicyg9xh3gzmLXLmbSIzxDqD89uzo+cRhSWFFQXG/r7s3G6txDHDtFMTxRdA/C65+EJRPMydgu4Hc6mc+YDIjHCHuRLMR+XM1SLzMuskrW/Pjsija57+y8XNfvhenottgNhGudiTothQRQGvfeBibgbzeTlzi8gc7g5zB5g75cxXRWakdVJ2t6/j6VGu/Ra035Zr7xW1o92pZz+YB+TMj0RmrDvMw2B+LmceFZkj3WEeA/O4nPm9yIy3zvup9g0/PcrtnIadn+V2fhHtjLbaOdv+3zg9+uxZl6G/YOhvuaFGHQRDiYo558wmxhgv7w5Spq/ITHaH2RrMNnJmO5E51jpxnTs06PQod9IFTi6SO+kmOkl1p7reYF4iZ/YRmenW6vw6uHF6lOsNgp6/XC9Q1Mu06oV1+DdOj67rMd9pKAKGBssNDRENjbMaiuzQ0NOj3Ew0zMTIzYwQzUywmhndoaGnR7mZRJhJkpsZI5qZaDWT3qGhp0e5mUyYyZKbGS+aybaaye5Q/9Oj4aKZHJjJlZvJF83kKJ6Is4ccnsqYU8EskjNLRGaetcCKDrqziQdyXWJVEJsuF5spijkUBXDmbDCvlzNvEJmTFcwL23sWM+btYM6VM+eJzEIFs/XioirGXATmPXLmEpE5VcH84f2TixnzQTCXy5kPi8xiBTM8+icncw2Yj8mZ60RmqYL5faevjjLmJjCfkjOfEZnTFMwe17iYL4L5kpy5TWRWKJhPbPX6gzF3gfmanPmGyKyyPhn2aJ8MvY+5xPZB7B252Hui2AxFAZx5EMyP5cxPRWa1tYAjxhJtm/sOGeI8wsqZbhztDRvW3JfpbNs042+m8wV0vpTrfC3qXK3wHndltZN5Aswf5MwfRea1Vu9ntJPPxX6F2G9ysT9EsdnuFGDraDAv6ChlenQUmHMUzKzXw/5hzKZgNpMzW4jMGxXMgrXHbYnsV01gdpAzO4nMm60T3dVYoqVpExE1LoaGXa7RQ9S4VeF7/DsuZl8w+8mZAwRmy9sNpv/ljRpdcPLF7UOyKstzUh3lhTlFhbMc5XbjGKXCOCQb2iNgoH8Pe05ZWZHrDMTQHhmFjhk9jA3ebh9SRod2JTnFjqE9eibkVJdWVWY4x/awD6p1qejSoqrikooexlulqY7qoT0qy6scPezTc4qqjGRwqBNtHRZvHDMGYFBJVVERjaqJcI2zjkwtLa/EV7l6DIuuqqgsLR4yiBaQDskorCjMLXLEl+Q7ZvYY5u/+iB7D4MWN5TML8ysLegwLDIxwY+EkI/YYhrZz8ixDrB21zF7g+Zo9V22h4W6Xlu+oyCsvLMMG1pAKg/4320fA/932EebOtuecQ/YMasjsBf9vZi/w/272woPcnr2qksLKiobMXsj/ZvbcqbCesxfi/uxVsBNNDZm+0PP84hQQEOZ+dfwURUMqDDvPFQa787LkLHByeWlVWUNqC69XbWTU/f2E0VlcVtkQpxHney248/LmLK6odIajvCG1Bfj//7uJVZWVNbC483bw5youKNTt4iqryxq05w04b4dmTr95pUXxMfW0et6OsbjVMTmVBfU0e94OabjZlJySyY6Keto9b8cQ3G4Ce80pyikuq6fl87bf5pbT2StJAyyftx0xtxxdWpI/tsp4a11ZXU/P9dvBNtRzBt5S1NPxedvRnnvqOXLyk0uK6jnFgedt53nuyVdYMhXTXIhDy3q6Pm97Re46KqeisJ4vcIHnfz+XnDvFkVeZZuyg62n5/O/vnJbxZz0t/4/eyAf/H7wV5ZOSkVNemGOMbMC0/I/eoYf8X05LfIz1ENy92ThvO25xNtw5qG7AbFjfbbk3G+f/mCA+xnp6xT2v5/9YID7G+tx2z+v5PwqIj7E+4dw7eXz+DwDiY6xPB/e8nv/dfkJOrqOonm7P225ffK1x5wxfvV9rjAO3ypzCEkd5Pefkf/RZhTvn2ho+J9n1P+AKOv/v2WMck3Kqiirr6ff8v2mPKawoK8qprv+hUND5f9deVVqcXco+4Kvne4eg/8Hb9pyS7NiSSmNzjs+vp+n/wfv2gsKi/Ozo0qqS+m7Q53+fHVNY7CipqPeb4ODzv+dOLymszE4pnVFPw+d/933upTk6p9IxubS8nqdJgs//W3h2wiE7uSEvHsHn/108f/Gop+PzvxuMy6nIZq8e5Y76PhHP/74wvqLIkTOpnnbP/27Q+eocn+/29mz+0wSOzKssnO4YUVhkbGiplfjNiexrVzWXjC3BqZT8Wg/wzONcPtm3vvSzZR7t/FQssqqy1PWp2qScogqLpNpBYkq603ZFj2HX4XtqPY1XBEdocGRkbGRkZMwgPCLHRtIjMXKyEUdUxo7PGj/CERdVPT4raVZCUYF/XvGIuLzioqkJJeOCEqYkVsSPGF+UV5JUlhsYHJFUHTwrYUpeVWL0jMljgzIq8uMyqsenBVSNz8rAuIqE6Kix+ZmjKnIykxLGZxWl5wZWFuVO8Q8ZNyU2KDEzMWR88djApJEpBYmZY2dGjYWvyMCUkRmBKVkFM/KKM2blVYeMy48bVZASNKpsfHRIZk5mRpDRFz0uK6koYWpAakbG+LLxWfkjczJn+o/PGhWTGzizYnxmkn9OZkQVqy0qSegbWzxi1vjUyoqcrCT/yJkz0xzGv+Mz/avGBkZU5I7MmJI/smh6bkli1disUdXjsooS2XKYl8ipMYhRxjQZj7z0oKJZ+SMzKhOmJk3PHTmzaFxQijEfIbMSpo6oNuoOSRtp5J3LjswKLDI0AmZFZUTMyskqK4oeERFoeJ0FP1GGx+jIyaOi2CqIR4hDiHWuGDYh0WPT8c+oKObDPzomMg9OskzzFDsuK6Xg/34dMS9lbq+joprrJz6aTcjI8cnGXGG9BORmhvB1Z2xj+LdsXIp8nRnzP63WuqeOL8uNSykyGFXjq0POsdIjZhj/FuSPjKiOmoFpq8s6Lx3FDEfGjmTrfqyrz7lq2MqKnMG2jdGsPdb5NMKi0efao6Jn8FUZ42yV1li3LJkUOTMywbl9MV4SW3hsYmIMfEQV6J6TIxg4Jkm+nHM9GNvnqIK8wPSqjOKionx/Y9uNy6jMpbmbasxdcTgrOYr6Jo93rafg2MjUmXL+VBcL82jMa35mQFVKcVGF8RypTs0MKc6dEQxssrPmcLYZsAmIippi8BNz
A4: MkPKjXFV40cWuZ67/nwCo1PYkqNYjEwfg5gQm1KUPzUjOC9uVFFeUGJVZlxK9bj0/OqczLFc39g2zNvYqNzi8dOd6zEl3ZEVVRQVW1mWWzw2IcV4vuaNnFngyEgpcsSNTSTv6UEpBjOkJCpjfIFRXxFbRWPjjQ05+NzqYrxxac6X0XHsCTIioNJSU1ZqZER8dH70uMyxJdGTY1PYKju3bUQ5a3W+Zoxg6z0/13gdqcrBeipOKWPbaZH/5DGpkSXGc2LqqBmlCcIuYMgg8dvIw3T5Rv89/nv89/jv8d/jv8d/j/8e/z3+e/z3+O/x3+O/x3+P/x7/Pf57/Pf4tx6ecz0bNeoRWVHmKElz5BUMjEzNzEoYGJNTmTMwDR8spTmKy4pyKnG78Eae2fgQxzu72FHsKKks9czGb6WaZFeUVpXnOWweHh599ZxE59gLDFz32pd2LYhvHWGpnsqlUpk2lsP/XoM6NmrUDR/Q+bGfO/ixn5ZU+OET/go/5xXUfPyNZTz3ffvPP3p9m8Fswn6LnZ3dyPsCmrK9xmB3bFmHo8d2hzHjmHWvIFzeoYZbZtMnuCPuxWRIwCP0bG8aDWiy0fNodJixXEfzaCoyHJDXa0JeqwmZT5DLjOUukkD88GMtnyEgvVKTtLMm6U4iDce0MojP5RiyveaQbTWHLKAh0cZyTWuWHoOBL9YcuKXGQM+7jEGRtc47u7tPRk4529Tw9Yjy0qIiR3l/oT+zPAc/N8KW7JVdOqPEUd46uxIJ9jsv5zf1m2bn8dHNnVkIpJTOMDbvRp3M4pml5VNzS0unYt22NycZFpkBdfGMAWxb8UHNPnG4zkdXo9UC03G3MQOYBWduNOWaI7dQyCVRrhlyi4TcWMo1Re4eIZdGOV/kFgu5TMr5ILdEyI2nnDdy9wq5iZRrgtx9Qu4qynkhd7+Qy6OcJ3JLhdwkymF12pYJuULKNUbuASFXRDn2dHxQyJVSjm2my4VcOeXYK8BDRn+vWtcq/bahxsbWYgwuolJB11JxbXuNswvzvbILS4ymUYOHt3ojKaxlI7EYiEyNx//ROXkFDhpDL42siIuNgOeVTxWeaA8bRaAQnvobjRlIPWJO/YVGNVIrzKk/0bgaqZXm1Fk0rkXqUXPqDzRmI7XKnPodjTlIrTanfkPjRqTWmFO/onEzUo+ZU7+gcStSa82pM2jcjtQ6c+pnNO5Aar05dRqN+Ug9bk79hMYCpDaYU6fQuBupjebUj2gsQuoJc+okGouRetKc+gGNe5HaZE6dQON+pJ4yp75HYxlST5tT36HxIFLPmFPH0XgIqWfNqWNoPILUc+bUt2isRGqzOfUNGquQet6c+hqNNUi9YE59hcZapLaYU1+isZ7tQcypL9DYgNRL5tRRNJ5Aaqs5dQSNTUhtM6c+R+Nptpszpw6j8SxSL5tTn6GxGakd5tQhNF5Aaqc59SkaL7K9sDn1CRpbkXrVnPoYje1I7TKnDqKxA6nXzKmP0HiFHTuYUx+isQupN8ypA2i8jtRuc2o/GruRetOc+gCNt9jBjjn1Php7kHrbnHoPjX1I7TGn3kXjXaT2mlPvoPE+UvvMqX1o7EfqHXNqLxofIvWuObUHjYNIvWdOvY3GJ0i9b069hcYhpD4wp95E4zBS+82p3WgcQeqAOfUGGl8g9aE59ToaXyH1kTn1GhrfIHXQnNqFxjGkPjanXkXjO6Q+MadeQeMEUp+aUzvROInUIXNqBxqnkPrMnHoZjdNIHTantqNxBqnPzaltaPyK1BFzaisavyN11Jx6CY2zSH1hTr2Ixl9IfWlObUHjH6S+MqdeQMPWyej52px6Ho3GSH1jTm1GwxOpb82p59BogtQxc+pZNHyQOm5OPYNGU6S+M6eeRqM5Ut+bU0+h0RKpE+bUJjRaI/WDOfUkGm2ROmlOPYFGe6R+NKc2otERqVPm1AY0OiP1kzn1OBpdkDptTq1HoytSP5tT61gDqTPm1Fo0uiP1izn1GBo9kfrVnFqDRm+kfjOnVqNxKVK/m1Or0OiL1B/m1KNo9EfqrDm1Eg0/pP40p1agMQipv8ypR9AIQOpvc+phNIKQ+secegiNEKRwSC6klqMRhpTNnHoQjQikLjCnHkDjMqQam1PL0BiKlIc5tRSN4Uh5mlP3oxGJlJc5dR8a0Ug1MafuRSMWKW9zagkaI5HyMacWoxGPlK85dQ8ao5Fqak4tQiMRqWbm1EI0kpFqbk7djcZYpFqYU3ehkYpUS3NqARrpSLUyp+5EIxOp1ubUfDTGIdXGnJqHxgSk2ppTd6AxEal25tRcNLKRam9OzUEjB6kO5tT1aOQh1dGcmo2GA6lO5tR1aExGqrM5dS0ahUhdaE5dg8ZUpLqYU1ejUYzURebULDRKkepqTlWjMQ2pbubUTDQqkLrYnJqBRhVSdnNqOhozkOpuTlWhUY1UD3OqEo2rkeppTlWgcS1SvcypcjRmI9XbnJqGxhykLjGnytC4EalLzalSNG5Gqo85VYLGrUj1NaeK0bgdqX7mVBEadyDV35yaisZ8pAaYU1PQWICUnzlViMbdSA00pwrQWITUIHNqMhqLkfI3pyahcS9SAeaUA437kQo0p/LRWIZUkDmVh8aDSAWbU7loPIRUiDmVg8YjSIWaU1ehsRKpMHMqG41VSIWbU1eisQapCHNqIhprkRpsTl2BxnqkLjOnJqCxAakh5tR4NJ5Aaqg5NQ6NTUgNM6ey0HgaqeHmVCYazyJ1uTmVgcZmpCLNqXQ0XkAqypxKQ+NFpKLNqVQ0tiIVY06loLEdqVhzaiwaO5AaYU6NQeMVpEaaU8lo7EIqzpxKQuN1pOLNqUQ0diM1ypxKQOMtpEabU6PR2INUgjk1Co19SCWaU/FovItUkjkVh8b7SCWbUyPR2I/UGHNqBBofIjXWnIpF4yBSKeZUDBqfIJVqTkWjcQipNHMqCo3DSKWbU5FoHEEqw5y6HI0vkMo0p4aj8RVSWeYUvuPs8w1S48ypoWgcQ2q8OTUEje+QmmBOXYbGCaSuMKcGo3ESqYnmVAQap5C60pwKR+M0UtnmVBgaZ5C6ypwKReNXpHLMqRA0fkcq15wKRuMsUnnmVBAafyGVb04FovEPUg5zKgANW2ejZ5I55Y9GY6Qmm1OD0PBEqsCcGohGE6QKzSk/NHyQmmJODUCjKVJTzan+aDRHqsic6odGS6SKzam+aLRGqsSc6oNGW6RKzalL0WiPVJk5dQkaHZGaZk71RqMzUuXmVC80uiBVYU71RKMrUpXmVA/WQKrKnOqORnekpptTdjR6IjXDnML/Pr2RmmlOdUPjUqSqzSn26UVfpGaZUxeh0R+pq82pLmj4IXWNOXUhGoOQutac6oxGAFLXmVOd0AhCarY51RGNEKSuN6c6oBGG1Bxzqj0aEUjdYE61Q+MypG40p9qiMRSpm8ypNmgMR+pmc4pdfz4SqVvMqVZoRCN1qznVEo1YpG4zp/DRls9IpG43p/DJlk88UnPNKXyw5TMaqTvMKXyu5ZOI1DxzCh9r+SQjNd+cwqdaPmORutOcwodaPqlILTCn8JmWTzpSd5lTXmhkInW3OeWJxjikFppT+MjIZwJSi8wpfJ7lMxGpe8wp9olhNlKLzSnWyEFqiTmFh0+ekfK810h1ru3jzYoCh6MSwq7PrZxfAvDN5jkPm035uSj/LNPLYQh5RJdWVPqgZbvPkISsMznZ6PKJKXRUjCjKqSjwwZ+2+4UlCuFzRPmsMZU+aNqWCtmpRlerePxIO4f9OjYV3nzQ67nMq5ZP69JLCktL2Ee00fhILQ+/jGXfIcjOKS/PqfbKzsNlFzwadaz1Y90JE899TlvUmT5pNHSg5VPcmT5fpJ6Szs5Zty2nntLOzi3OcyVmvqh0cnCJo3JgdGm5Y2BCqfP+DLi1G7ahpsXZecakVOBzet/i7EmFzkunNSvOLioscSRVFec6yo0/ih2VBaX5tFBVURHGNy/OrqjMyZs6otzor7Dh4dFVUEvlafyOesJEvDHA/15l8DzcB/+Ygq/nasNXd8KkVxYWDRzj/E2XsQJjCtlk5pTj1bdRB9dS2TP9/YMis9MrHOWw2DgpJtrHuaYqCotNC8UZ2wgWMnXH5ztKKgsrq71nuDYvVo6NvZN5FHOK1zOvCsPgkDHV5aVF1bjWwKjSEkdFdkhIQHZhSWVpdkhYQPak0nLXFTyz01KTEwKzyx2VVSUO9Gcb69irEiUW4F4bfo4yRxG7w4bXdKPzIgvWoBkjBs4sqphp22BYwMqsbcac02Z70khj6nw2kl0f2PWBovO+HpCxbdaTthDpeSVph570KpF2Kklv6Ul7ifS2krRfT/qISAeUpMN60lEifa4kHdOTvifScSXptJ70C5F+VpL+0pOw92Gkv5WkJk20JF8ieTdRkVrrSe2I1EZJ6qIndSPSRUpSbz2pD5EuUZIG6UmBRPJXkiL0pCFEGqwkRetJI4gUoyQl6kljiJSkJGXqSeOJlKUk5ehJ+UTKVZKm6kklRCpSkqr0pJlEmq4kzdaTbiDS9UrS7XrSPCLNVZIW6UlLiHSPkvSgnvQwkZYrSWv0pHVEekxJ2qQnPUOkp5SkF/WkbUR6SUnapSe9QaTXlKR9etJ7RHpHSTqoJ31KpI+VpC/0pK+J9KWSdEJP+pFIPyhJv+pJfxDpNyXJ5q0leXi7SBd4q0hN9aQWRGqmJLXXkzoRqYOSdLGe1INIdiWpr540gEj9lKQgPSmUSMFK0lA96XIiDVOSRupJo4gUpySN1ZPSiJSiJE3Qk64k0hVKkkNPKiDSJCWpVE8qJ1KZklStJ11DpFlK0o160i1EuklJmq8n3UWkO5Wke/WkpUS6T0l6RE96lEgrlKT1etJGIj2uJD2rJz1PpOeUpO160k4ivawk7daT3ibSm0rS+3rSASJ9oCQd0pM+J9JnStI3etJxIn2rJJ3Sk34m0k9K0lk96W8i/akkefpoSd4+LpKXj4rUUk9qQ6RWSlJnPekiIl2oJPXUky4hUi8lyU9P8ifSQCUpTE8aTKRwJSlST4ohUpSSNFpPSiJSgpKUridlESlDScrWk3KJdJWSVKgnFRFpipJUoSdNJ1KlknStnnQ9ka5Tkm7Vk+YS6TYl6W496R4iLVSSlulJy4n0gJK0Sk96jEirlaQn9KSniPSkkvSCnvQSkbYoSa/oSa8R6VUlaY+e9A6R9ipJH+pJHxPpIyXpiJ70JZGOKknf6Uk/EOl7JemMnvQbkX5Rkv7Rky7wdZHwyaic5OOrJTUjkq+S1FZP6kCkdkpSVz3JTqRuStKlelI/IvVRkgL0pGAiBSpJl+lJw4g0REmK1ZPiiDRCSUrWk1KINEZJGqcnXUGk8UpSnp40iUj5SlKxnlRGpBIlaYaeNItIM5WkOXrSTUS6QUm6Q0+6k0jzlKTFetJ9RFqiJD2kJ60g0sNK0lo96XEirVOSntaTniPSM0rSVj3pZSJtU5Je15PeJNIbStK7etIHRHpPSfpET/qMSJ8qSV/pSd8S6Wsl6aSe9BORflSSfteT/iTSH0pS46ZakldTF8mjqYrUXE9qRaQWSlJHPelCInVSkrrrSb2I1ENJ6q8nDSTSACUpRE8KJ1KokjRcT4oi0uVKUryelECkUUpSqp6UQaQ0JWminnQVka5UkibrSVOIVKAkTdOTKolUriRdrSddR6RrlKSb9aTbiHSLkrRAT1pIpLuUpPv1pAeItFRJWqknrSbSo0rSBj3pSSJtVJI260lbiPS8krRDT3qVSDuVpLf0pL1EeltJ2q8nfUSkA0rSYT3pKJE+V5KO6UnfE+m4knRaT/qFSD8rSX/pSfgSsPP7T0pSk2Zaki+RvJupSK31pHZEaqMkddGTuhHpIiWpt57Uh0iXKEmD9KRAIvkrSRF60hAiDVaSovWkEUSKUZIS9aQxREpSkjL1pPFEylKScvSkfCLlKklT9aQSIhUpSVV60kwiTVeSZutJNxDpeiXpdj1pHpHmKkmL9KQlRLpHSXpQT3qYSMuVpDV60joiPaYkbdKTniHSU0rSi3rSNiK9pCTt0pPeINJrStI+Pek9Ir2jJB3Ukz4l0sdK0hd60tdE+lJJOqEn/UikH5SkX/WkP4j0m5Jka64leTSn7z81V5Ga6kktiNRMSWqvJ3UiUgcl6WI9qQeR7EpSXz1pAJH6KUlBelIokYKVpKF60uVEGqYkjdSTRhEpTkkaqyelESlFSZqgJ11JpCuUJIeeVECkSUpSqZ5UTqQyJalaT7qGSLOUpBv1pFuIdJOSNF9PuotIdypJ9+pJS4l0n5L0iJ70KJFWKEnr9aSNRHpcSXpWT3qeSM8pSdv1pJ1EellJ2q0nvU2kN5Wk9/WkA0T6QEk6pCd9TqTPlKRv9KTjRPpWSTqlJ/1MpJ+UpLN60t9E+lNJ8myhJXm3oO8/tVCRWupJbYjUSknqrCddRKQLlaSeetIlROqlJPnpSf5EGqgkhelJg4kUriRF6kkxRIpSkkbrSUlESlCS0vWkLCJlKEnZelIuka5Skgr1pCIiTVGSKvSk6USqVJKu1ZOuJ9J1StKtetJcIt2mJN2tJ91DpIVK0jI9aTmRHlCSVulJjxFptZL0hJ70FJGeVJJe0JNeItIWJekVPek1Ir2qJO3Rk94h0l4l6UM96WMifaQkHdGTviTSUSXpOz3pByJ9rySd0ZN+I9IvStI/etIFLen7Ty1VJJ+WWlIzIvkqSW31pA5EaqckddWT7ETqpiRdqif1I1IfJSlATwomUqCSdJmeNIxIQ5SkWD0pjkgjlKRkPSmFSGOUpHF60hVEGq8k5elJk4iUryQV60llRCpRkmboSbOINFNJmqMn3USkG5SkO/SkO4k0T0larCfdR6QlStJDetIKIj2sJK3Vkx4n0jol6Wk96TkiPaMkbdWTXibSNiXpdT3pTSK9oSS9qyd9QKT3lKRP9KTPiPSpkvSVnvQtkb5Wkk7qST8R6Ucl6Xc96U8i/aEkNW6lJXm1ou8/tVKRmutJrYjUQknqqCddSKROSlJ3PakXkXooSf31pIFEGqAkhehJ4UQKVZKG60lRRLpcSYrXkxKINEpJStWTMoiUpiRN1JOuItKVStJkPWkKkQqUpGl6UiWRypWkq/Wk64h0jZJ0s550G5FuUZIW6EkLiXSXknS/nvQAkZYqSSv1pNVEelRJ2qAnPUmkjUrSZj1pC5GeV5J26EmvEmmnkvSWnrSXSG8rSfv1pI+IdEBJOqwnHSXS50rSMT3peyIdV5JO60m/EOlnJekvPQnXYnR+/0lJatJaS/IlkndrFam1ntSOSG2UpC56UjciXaQk9daT+hDpEiVpkJ4USCR/JSlCTxpCpMFKUrSeNIJIMUpSop40hkhJSlKmnjSeSFlKUo6elE+kXCVpqp5UQqQiJalKT5pJpOlK0mw96QYiXa8k3a4nzSPSXCVpkZ60hEj3KEkP6kkPE2m5krRGT1pHpMeUpE160jNEekpJelFP2kakl5SkXXrSG0R6TUnapye9R6R3lKSDetKnRPpYSfpCT/qaSF8qSSf0pB+J9IOS9Kue9AeRflOSbG20JI829P2nNipSUz2pBZGaKUnt9aROROqgJF2sJ/Ugkl1J6qsnDSBSPyUpSE8KJVKwkjRUT7qcSMOUpJF60igixSlJY/WkNCKlKEkT9KQriXSFkuTQkwqINElJKtWTyolUpiRV60nXEGmWknSjnnQLkW5SkubrSXcR6U4l6V49aSmR7lOSHtGTHiXSCiVpvZ60kUiPK0nP6knPE+k5JWm7nrSTSC8rSbv1pLeJ9KaS9L6edIBIHyhJh/Skz4n0mZL0jZ50nEjfKkmn9KSfifSTknRWT/qbSH8qSZ5ttSTvtvT9p7YqUks9qQ2RWilJnfWki4h0oZLUU0+6hEi9lCQ/PcmfSAOVpDA9aTCRwpWkSD0phkhRStJoPSmJSAlKUrqelEWkDCUpW0/KJdJVSlKhnlREpClKUoWeNJ1IlUrStXrS9US6Tkm6VU+aS6TblKS79aR7iLRQSVqmJy0n0gNK0io96TEirVaSntCTniLSk0rSC3rSS0TaoiS9oie9RqRXlaQ9etI7RNqrJH2oJ31MpI+UpCN60pdEOqokfacn/UCk75WkM3rSb0T6RUn6R0+6oB19/6mdiuTTTktqRiRfJamtntSBSO2UpK56kp1I3ZSkS/WkfkTqoyQF6EnBRApUki7Tk4YRaYiSFKsnxRFphJKUrCelEGmMkjROT7qCSOOVpDw9aRKR8pWkYj2pjEglStIMPWkWkWYqSXP0pJuIdIOSdIeedCeR5ilJi/Wk+4i0REl6SE9aQaSHlaS1etLjRFqnJD2tJz1HpGeUpK160stE2qYkva4nvUmkN5Skd/WkD4j0npL0iZ70GZE+VZK+0pO+JdLXStJJPeknIv2oJP2uJ/1JpD+UpMbttSSv9vT9p/YqUnM9qRWRWihJHfWkC4nUSUnqrif1IlIPJam/njSQSAOUpBA9KZxIoUrScD0pikiXK0nxelICkUYpSal6UgaR0pSkiXrSVUS6UkmarCdNIVKBkjRNT6okUrmSdLWedB2RrlGSbtaTbiPSLUrSAj1pIZHuUpLu15MeINJSJWmlnrSaSI8qSRv0pCeJtFFJ2qwnbSHS80rSDj3pVSLtVJLe0pP2EultJWm/nvQRkQ4oSYf1pKNE+lxJOqYnfU+k40rSaT3pFyL9rCT9pSfhlrjO7z8pSU06aEm+RPLuoCK11pPaEamNktRFT+pGpP/H3FnHNfX1cRyMwcWaiS22oiAbjcXoSQrYgcRUlJKwu7uxu7tQsfNnd3d3d9dzP9s9u2fcu6lzfzw+rx/Pvuxzzvv7Pvcu2d0ta3Cmqr+fqQaZqZrBmer8fiY5mcnB4Ezuv5+pHpnJw+BM3r+fyY/M5GNwpuDfzxRGZgoxOFOz38/UkszU3OBM0b+fKY7MFGNwps6/nymJzJRgcKaM38/UnczU1eBM/X4/00AyU3+DM434/UyjyUwjDc406fczTSEzTTY40+zfzzSPzDTH4ExLfz/TCjLTMoMzrf/9TBvJTBsMzrT99zPtIjPtMDjTgd/PdJjMdNDgTKd+P9NZMtNpgzNd+f1M18lMVw3OdO/3Mz0kM903ONOL38/0msz00uBMn34/01cy02eDM5lb/3amPNbk80/WhmbK9/uZCpKZ8hucqfjvZypJZiphcKYKv5+pEpnJxuBMNX8/U20yk62hmfI6sNfWzHnOcZ/o9Gj7yOiYBFWkKjElITpdFaxKVCWlJ5dlx0mj2ifEp6ivjUiPTs9Iyx/VMTotMj49QRWe3M0iqqMqOk6VWgC/DFBfZH+rjjRJik9PY4uiKLyi01Te7H9Asb8rhN8pQ72ik5L4AeGR3skJGYlJTFRScmh79rdpBaLS4xNV6tOud41OsFJX6mnzRUWnp6fGx2Skq9KsoqIz0pObxceld8wfFZoazzauPr95vigF+3u/5NTE6HSrqKD4JLb/HgmqAlFeyalsm81U8R06pueLYpnJqcqkOFX3QlFKtKNNFtHUdFyq+RU/hokK7apKTY2PU+WLStesETuSvYz14XhYofikDuqqWFSiKrWDSpEU562ClnodmagUVkeVmpRWOCotIyaNHZwBg6bRqWlm6hO74595HrM85J+5ublZ7tyaE5SbW0rscm5R/qTzafZe8UnAh8Z0Yn8TFJ+Wrj53vE3OIeotTC0fUg7B8bGpyWnJ7dPtQ9u3j49V2au3RXKKvW/3WFWCffME9enq+XXGINvfDtKuMOJ2v43TGwAjav12BL99/i8bqix6AyQ7UmgKWX7zfhE90tJViTqb01/F7oDxsfbYku1krVpxkQj25pDUobZNYlpscmpCfExtm6aq1DR2RH0newf8r7aNd0ZCekaqqn6SKiM9NTqhtk1YRkxCfGygqkdkcmdVUv0YV9do51hnF5m7o5PKwc29TZsV5n/QgKhMhO5uHI+dq7Zgn1PEsXsm1am6UXvZH/TqEB0b6+wYy3bZXu7gFte+TZtc6tuIxLKqmVmxiPjEjAT1XmxD4GnkZqT9p7lXtKqKzwB9uPrr129vEZjBgr0fylBFRZlZqjcQ+1/e9+zYv76hCOc6+OrXr7zv2Ln+YncVznIWs7xlZ/m7vVg40UVM9Iad6G92buE0n9hpzF+z08AMzZm/Yi+gQQDMX7IXAEEs7wv2wp/cNIQUfnNqf5gzxaviERqb14l90MMDH7t7WOvbPXLuHdxUpTDe/CHbGXYRkM0fsBewzbHBzO/TavdotbuUmvkdOnabjt2iYzfZC1gFUZ8q8KmKftx4n2p/6VND7XOJ9rlI+1ygGz1PN3qObvQsHTtDx07TsVOGfBzh44R+6vE+zn9583VV+xymfQ7RPgfpRg/Qjf5HN7qfju2jY3vp2B5DPl7w8UY/nsRHc5WeTeFbFcO20a1v5VpXt7GF7imb7mkz3dMmOraRjmXRsQ2GWg9D643Ruo+2dUn4X26KSPWmWEn7rKA3xXK60WV0o0vpRpfQscV0bBEdW2jIJwo+7dgfeQNYl+I571PU98W52aRlVHRcXKoqLU0SldyNfVTLF5WKq0Jx2TxPnpI5BzZLTu0ck5zcGfc5CtF7quDkOFUCu1Lqxw7v5KT0VDxyptbS+X2z1OiUFFUqZsF/kmi205Lqe9Vo9jG2qyqio0qVXlHh5u6hdHdgsJLM+LysVyArAyFJnJ4BMg+lm6tmwAQMCCEDOrADCvnEq9L8EqLTOlYMlXk0c9LkJiLXmOQ6sTkpn1NgQrkmOAnBSBJMFO/AxdFD6equGTAZA5qRASniA5xcPJQunGMmBrQkA9LEBzg6eSidHDUDpmBAGzKgKzsgv3dyGhuSsSsnd9GEpiLUjoR6IOSX2jMsXUduGkKxJNSbDZUQoINlHk24RZuOeHsS7yfeqZyd35FTm4EB8WTAQKpTZw+ljOt0JkIJJDSEDVmLrDCfn4V8MskPF20aktxqzUY8lcRHsfF86h68nDy8ZNw6zGEzeTPY66sInqpFKPGfd3RsRxW5J5BobkJpSezLF/a1V2xGWnpyYhj71IB94cYOj42PTsCTRHLryhvVISM+Lk8U+4O9ceXJbVbb0MsWzRNan3h1GZ3aA7cU2Z90VSuCQmNURT2j+Ps2pPJxT3X92fbUTyokY9klqh/JPtFhb63q2y96UkUnptk7yl0iFH72oRnpKRnp9hGR4cFRTcLC7CMjQoPsg5XNfX3sg5SNmyh9mHG4D0ph76b+vnOdZzmFyH0Fkxd3cEm4J/z161dJF6b4kJcPQ9bNLd1mbLWGyu618PEgdvNhE0omsXBH3f5V6RkpnIVdWKrmyRwUwsKV3r72jo4uPkrfCGYy7sk7swx0zlPjOar/tryJDz3LeA1pGewY86tI3dM12St7EOo0drD8r6jqxWSmA9peAI3joB5O392rWb31Gn5t55aTg4YtPAVoLwKd/ddQmYu/IoKZA2i0ABrFQcvsv7F0Z94GQdkrNp5sX6BPu5OA9iHQBexgmfj+oVlIsoM0DYqI9Alurtk1mIVgthYwW5JtOvFY04b7fwSMN5cvKOoU7tUbzH6EuZQd7PAH+6QuchmQzQTIJhyyVLcdSy16uyvXBvmcbPfpq7IbkAMIcpV+pHoRxZGrgQwXIMM4ZPqNTw0eBaQ0WlWx06NCYw5Gva7BXjmIINf/8cqGBvkFaZkbwAwWMAM5ptvQdSt35BvhvUT59nH0gxtPXoE5hDA3/6mmDjIbyAAB0o9D2mXlnjfkmp3Pqu9jfKeMerGmI5DDCHI7O7jhn2hq72F83Fzs3B24+5jI0EhFELMDHXgLOlBwHTT8ZesWu3GDz4gn2c1muLmky6rh7x2kgz3s4AZ/IG2ogb1ooIGggXpcA5MezphvnislYMqh6mH/5beYXgMNjCINHDCmAZluAwfRgLugAVeugUaWk2+W+LhbOWudvMNTy3z1qqOBMaSBo+xg9z+4QQUrIiL8whXeHDkswDckNEjGHFO/vuTYZlq2nGz/KbLbh4Pa+44KCE3ZXaH48RmIjyPsU//CljOnMVkdAduOY7cc61G1/9OgwJWLOuzJGpI4UX0HO4Gwz/8L25G5gMlsBewaHHtY+KX4O5La/nNGPnP2X3RCigcF80mEfcU4tncLb2c7hYy5ismqCtiVOfZc5+2WA6/0arSriXWGo8w5cyrimYR902i2C9i3MJmNgF2eY6usdqZeyF4QkGUferzffxnHpiA+lbDv/QtbztzHZGUE7FIcO6jwd9WXfceUS790/Lym6LZ6mYhPJ+zH/8J2ZJ5gshICdjGOnWtL9do9hu/yHHV3efFtT3uPUD+DmEnYL9jK7e/ZivBgLPlLzFVYgC7EoRVHFt1c3WKd58ouBzdlJVXpimc95rMJ+u0/oOXMO8yVX4C24tDtas2c1OBKsuecGS+ilpwv4DwR8bkE/cl4tJeM+Yy5LATovBy6xZWhR66PCvOc9G537Q57ulSegPh8gv7+D2g58wNz5RKgzTj0gmqX1g8Izxuw2zb3wmtNVoWMR3whQZuz966uf/KYlnNHC1CEM7lw1/zjSk7ytysa8pFGw1WjvxQMnFj1wbsZr7Pn7a/CXrmYkCXsYA8jyF7KUPyGsQD8swD+kYM7DL74+tXxOX7LHn8peKjG8fn7AF9K4Pmq6b15GYRzS54f7HcC9huObf28UIeXU7t4TRqZb0xAWkiHvWAvJ2zpv7BlTGGwXwrYzzm25e7P7bvPO6hYmu2wfczQD3F7wF5J2MX/gc3ewEqA/UTAfsSxcw/reX30EdeA3Tueveu/9ujL3WCvJuzS/8KWMWXAvi9g3+XYZXNZjTjR9oZifpHsC0WypuTeBfZawq5g5M5G7k9tAL8lgN/g4EcPh2V/WbvSf/3kNz5jciX13wn4egKv8k9wOVMV8KsC+GUO3uaj/8e2v4r6j4y2Xlb2YanJOwDPIvCa/wSXMbaAXxDAz3HwHc3yH7t+9nTIrlLd4+632Ph6O+CbCNzeeLj6qUMdwE8L4Cc5+OiRm8o/uFDBd/lPb/Mq+1UftwGeTeCORsLJcyYnwI8J4Ec4+PiguaN3nD0VPOjq4XbLX34puBXwrQTu9k9wOeMO+EEB/D8OfvjbfdmLx8M8d5Vrujus2cfELYBvJ/D6/wSXMQ0A3yuA7+bgzS7Ve/mwV+egKfkSPTwt5+3PBnwngXsZCQ+xC/AOtPNivAHfIYBv4+ABi+XOKUFWgYsGyNs+z2Pnuhnw3QTu/09wBRMAeLYAvomDmz25X2N79dchi78kDKrrljf/JsD3EngQO7iusTc1ls8Eg75BQF/H0at+WxZdrIRLwLLezao717vSfyPo+wm9sZF03+aR4XbKkEgmHPTVAvpKjl7TTdEz7XnuwHFlF1Wt83hb6yzQDxB6UyPpQf5BwWp6M9CXCehLOHq3MdXXPU6a6bPBLfZU3fYbFRtAP0TordjBLkbQA+QRTGuAFwrA8zmw/bQKDeUXpwZuKtlp0LLcYbL1AB8h4HbG3tJ8QyIVIb5MNOBzBPBZHHzOKt+FaXPOew2Q5ut11P3AhXWAHyNwlZHwiCZBfgr/EKY94NMF8KkcvPORo5fL9KmsXBscFNasy4NOawE/QeCd/uk+JoLpDPhkAXwiBz85VLmryY/dAdNy/8hMc7hyZQ3gpwg82ci9LSw0qIUd+3yCSQF9nIA+hqMvO3C1/1uX14q1W1erKuyfXn416GcIPd1IeogiLCAyQBHEZIA+UkAfztGHHU2udXl6us+QXja7rvqMPbMK9HOE3sNIukzuZIcOmJ6gDxHQB3H0eivuFf9ps89ro2Tc+IPTqjErQb9A6H2N3OzKEB/fEN8Iph/g/QXwvhz87fSGlrVWVQ3d+fJo6bWR92evAPwSgQ8y8hkkC1eERDCDwe4lYPfg2DdsHLp7TVgePGtwyx4PLnn6LQf7CmEPN3LZfZRhdt6hwWHMCNC7CujpHP1scsy7Xj3c/ZYmPJv5Ky0ycBno1wh9jLG3thbh6mUfC3gXATyZgy8Mzn/l/o0hfhPLdZ0X0ubIgKWA3yDwicbe2tibuiIkMoCZBHqCgN6Jo0senrwcObiZ95ozw59dTbgwbQnotwh9ajW9L45//3KJmQZ0BwFaxaEzFw4K8do9J2TOA0nu/fuXWCwG+g5Bz/oHtIKZDXSMAN2OQz/L61y4deuZPuuly4f1Sr53cRHQ9wh6vvHPJVzDgppEMAtAbyOgt+LoSw6MOnkvz0bPxYlV05Y3iJQsBP0BoS8xku6lZPlBoRHMUtCbC+hNOfraG4frrBoUG7rKqfnmo4d771wA+iNCX2nkzVz9PMqLWQV2hIDdmGOPfGuX7jljp8/uQyfO9V5/qdV8sJ8Q9rp/YSuY9WCHCNhBHDt4a0fXuHNV/LMqlFxq3li1bR7Yzwh7k/FsZ9Z7M9hKAdufYy9dcjzcY8pyn42JI/MVGNw6Yy7YLwh727+wFcx2sH0EbC9y5ya/Z+3e2st306x5Mxr8Oms5B+xXhL3b2McUu7BwP1Z8D+ANBfD6HNwnrFW1BmMrBE21q90iNa3g29mAvyHw//4JrmAOAO4hgLtx8CnTB6+v9XSZ16INm9+XT9u2dRbg7wj8iJG3s2BvuzBFuMKPOQq6s4DuyNFbz/XzPHnazzOrn/3ZdZLpvWaC/oHQTxpJjyD0U6A7COj2HP3Y6tiQhrOuBU66uynP2y/zq88A/ROhnzOW7o/XC+xmPw96LQG9Jke3G/KkxKysBl79D8y0b3069ut00L8Q+uV/oyuYK6BXE9CrcPTKp8o+HNRxUcBOx4GnPQ60GDsN9G+EfsPoV0sBmldLN0GvKKBX4OjJWRWatvue6b9sb5LZNffdP6eC/oPQ7xr72BLuFaKm3wO9rIBemqOX8qk8ZXLSpoAhe7cXUwyZVGMK6L8I/ZGRdIW30kdNfwy6tYBenNziFE+OOVXpH7Dqe8t8/W075MoE3bwkR39u5PvdEYoQH+YFyEUEZClHdlnV4cn70719NgQHJG9x3B01GeTchPzGyNeoiogA5i3ABQTgfBx40rIGVyu+3aWcElKqyLluzQZNAjgvAX9kBzsZs7mZT8BaCrASDvuh3+1qKwstDZz84eO4Yt06+E0E1oJgvxmJjWC+A5tbgDXnsLOmtFg3pVf9RrvzX0msIJ05YwKwDMGaVTfugSxC8yzdnB1u/vNyTvb3yxp26Qvvi9huPuc95LHsW9cNFf3Gg52PsPMayQ7RsCVgfxGwP3Hsb+UvDAwaUSJwof/bd9+a1u06DuwChG1V3ci7FCV7n9KMvTvNB/p7Af0tR59j3fH9ss5Xg5cmP3r3MtNs1FjQCxF6oX+jKxgp6K8E9BccvXXZaaVSqlb23XDc/l79HbccxoBemNCLGU8PUrsXB/2pgP6Yo4fXKX6ze6vdAcPvfOzRt/6zZqNBL0ropf6NrmBKg/5AQL/H0WOe26abTbDz3/ir8Z4261tbjwK9OKGXr27c8xe87afwjmQqAH5bAL/JwTfPeqBo3HqGT9a7Ya227rq2eyTg1gRe2dgbWxNsdqYK2NcE7Csc+1OAvODDxRdDp+yvdWGqz6nDI8AuRdg1jGezy87UBPuigH2eY9/2eFFk9eO2ioEVrt/rWuH2zOFglyFsOyM3uX8ThVLhHRrE2IN+RkA/xdEXfFk6t2mx0aGjM50mDgssP2kY6OUIXW4kXRHkHRqA994cQT8uoB/l6MrvmZfaBpwJzXQ8EfO8ofT+UNArELqrkTtcoG9kKN6KcAP8kAB+gIOXujFn9O2BVbyHXl7g1cG2SL4hgFck8HpGq/v4BrTw8WXqg75PQN/D0SPK1zv28leFRrM6h7v0HfX0x2DQKxO6orqR7wewT10iGC+gdwrQ2zm0Z/zuIsHriiizS2ZEpCa3qjQI6KoE7VfduGcPIaFyxh/gLQLwZg4895wirI00UbnCaveYqRlXewwEuDoBBxoJjmDBQQBnCcDrOfDT4j/uZ19oosz8uH9EUfvlswYAXJOAw4zc1DI7ryaRviG+TGPQ1wjoqzh6b2XnwzFnFwRMumFubW4R2rE/6LUIvYmRe3lYeGgY4E0BXy6AL+XguyteywouogrKnl3occCWzYv7AW5H4C2NvGvzjQwAuxXYiwTsBRw7Y+POlTUfj/BcnDHj48Ra9m37gl2HsKOMXPYQLDv+pNEO9LkC+myOPn9PnpDG/geDVjRzqt6wu8K2D+gyQo/7h2UHXAX4DAF8Ggcf2HXwucuNLgSvaPF9wslGT7b1BtyRwOONX3awO4GdKWBPIk/fZNXa7k744bOySLn3p2rnfdkLbGfCTjJSPJiDJwM+XgAfy8HXD0l51WjPGOXa1/MGrD/wrkFPwF0JPM3I27g3extPB3iUADyCA4+aOW75x7aT/aaltAveO87VpgfA7gTcnR3sbBSY6QHuUAF3MMdNX+Y78GeNuz7z1m/ck29Jn+/dwa1LuH2M5CrCmb7gDhBw+3HctIhcV+vIU5Tz+zWftLdVQO9u4NYn3IFGckPkzCBwewu4PTnuhIjDZUese+g/6b8jjicr9SvVFdyGhDvMSC67fYeD203AzeC4h1TTOzcrXc9zrmXmBo+UvcUywFUQ7mgjuQFyZgy4qQJuCsdt+c02K+X1k6BB3VLiHrct2CYdXG/CnWDkA3UzRaRvODMR6EQBujOHHlxi9n7zp509p5k53WnwrP2zNKB9CXoKOzhQB+2VkBzbOc0+3E4ud9Ycdcb9Rh4QaResUIZwRzoEhwb5RrVQ+gZxf7vgPrI+Fd10FHTTnuvG/N1Tu14janpmbrK3lR+6k7WoEnulP+lmpqm6UXDdzEI3sYJuorlu7BNK9G70rFvQliH9vvTo97bkQnSjJN3MYwcH/Ws3mnfauXbmo522gnZac+3UtHFrfvPiy4BBLee0O5NXNmwB2gkk7Sw2UTvO2naWoJ0Wgnaace1kXq72I+Szld/GOWtntz9TauJ8tBNM2lnBDg7+13a4Dy9x/axEP5GCfsK5fqLT3xdpeeC1Ytj1Qte90oYrZqGfUNLPWtP1I+f6WYd+QgX9BHP9KJqU6TbUzstr9ewJB24w3rlmop/GpJ+Npthcmg9wcu1sQjuNBO0EcO3M9B04tNu5vSEb/DIsrvTosGIG2okg7Ww1WTsyrp1taMdX0I43145Vw2UlGkrivJb3fuLnEm+9ejraaULa2WWqdhRkdXajHU9BOw3ImyKbKk45V/tbyLQNif4Dqjt1nYZ2mpF29pusHbI6/6GduoJ23Ll2CqT8DHtQbHHI0L43Mwr1LyqbinZakHYOm2Jf5j4MyvVzBP24CPpx4vp5fWZLbaWih9dU65X5BxU8kzUF/bQi/ZwwXT9kc51EPzJBP3W4fqbkkXxWhWz1nne/1ZDLB+a9z0Q/bUg/Z03XD9le59BPbUE/tuQZaaxn+3vtLijmyedZxxRrOmEy+oki/VwyUT/OfD+X0U91QT9VuX6sS0he5eowqtH0suEdL7ovXz4J/USTfq6b7r6Q9HMD/VQS9GNDHtd3fPjv64gw/81LbbZnL6j1RVkeD7yknzum6yeC6+cu+ikn6KcM1092SkCH6LtbPLft63i+3utHQwLQj4r087B6zjf7tf3IZA4c2jvU109mL+Peauewj4AtKcCW4LCuz79cMttWwHvswEJtZzm1GX4A36/VgWCf/Q02hMY+B7aoAFuYw/r29pkZft7Jb+Umy+PLjnxb/R+w8QT7WvB6yQCWvMHOgd8AXFAAzs+Bx0Vb9447oAic/iDjvOyKtXw/wJ0J+IMRYPLc5CPAjABswYEb1u5esfHJgp6zzpgPTRo47NY+gBMJ+KvgibwBMPfWMsf9Bm4eATcXx/X3OOBeMmGk98abF8+NWrOv915wkwn3118KB1ErbYaDN39dygn+cUkDLv48uYzPzdTQuctatUxf/vbFHoC7EHCeGn8PJiudF+CvAvBnDvxyw4aFKzomeg3uVii48cPTbXcDnEbATI2/uSWp30fnsFbAfhBg33HY/eu/PaiviAydm0+hGLnx6rtdwGYQbMG/xAZpsYWAfS3AvuSwT2U91m3sONdnd6GpP2b1l3nvBLYbwRb9m2Um755z4GIAPxOAn3DgfcGf69c9/8Vv1uKksMVeva/sALgHAZf8GzB595gDlwL4oQB8nwO7d2vbMPJNB/9x3QtcztW+V5vtAPci4HI1/uKWxL1nznHLg3tHwL3Fca+5dTt47nWCcn122pSbQxqotoHbh3Ar/Z2w5i8FHLgywNcF4KsceEZ4uYMDfG96Lunpe7r8h2rrtgLcj4Cr18j5tQaGwHinnKPWAPWSgHqBo7Z7tuVa5cxpQQvLfN16eGvi3i2gDiDU2uzgyrrvAKjS0+OTOqTZ4+sHo1T4qobodBVjB8rZSzmPRj7NUW7lcZldav3l0GVPDsXOv38k9TY7ufkgQpHV+MPD+3UOQpcDeUKAPMYha2QfHlU3uH3Ikum1grdVs76ET0KaDyFIF3awnShS7ioX57mCd1jAO8jxpic36Nd8zeyA0V+aNyvyfGG5q+ANI7y6+nns1hPl1QNvv4C3l+Nl7Yhavn/NPp/hjzpFt8zv6R4B3gjC89TPc3YW5ynA2yXg7eB4dePXFF+0q71i2NQdnZfnO+h4vATesSQ8X3ZwHVGei1zeXOd9Ip7oB+JWATGbI2593HDpqe27/daMf7HwavPwOb4gjiHERnoNnRycxA0Dwdso4G3geHbSYOdS96p5Dl74XVZSdrbDruLsleMIL1T/ijrwW1Dn2yDCwFsr4K3mePNSzJyfe0QpVhdvkyv31xYeruBNILxIdrC9KM+Z32NyLGgTAFcIgMs4YEb5Kk6TTn4KGDrncTGz08rMdcXYKycRYAvBXdufHSuNQ1hbArxYcCezkAP/KJbfu8iyTO+NshLy26NyVaoJcCYBt61h1EHa5AjWKLDnCdhzOPYY247P9rjFKMZfKLJ/9PA9CTjXmPlUwo41jk2OsooDe6aAPZ1jx007V9Cnqo3/ylmdstreO3QY50Qzn07YHf+FrWDiwZ4iYE/m2PdKzp/bYNstnx1nS9erGzNpSzWwZxJ2Yg29fyj57YHxOMYqCfAJAvg4Du4fNqB6ya1FldPnBPoXexxcqirgswk81Ti49hCrNMBHC+AjObhrzAnvh59a+Szo7HnA+767fRXA5xJ4N+Pg2iOsuqu/zEQAH8LB396seHyhbV3PTe0sjjKpud5XBnw+gfcWPG35IzgOsOoD7kABtz/HVTRNa5z4YnPAtqOFpL1qrkisBO5Cwh1g3K5Gjq8aCHYfAbsXxza7V+xojCrWM3NDQ6nlqIlxFcFeTNhDjWOTw6uGgd1dwO7KsfNOG2Pp2KJC4OSUwu5h18IdcHZC86WEPcpIb+7oqtFgpwnYXTj2zoUFE/NtreK1Zd+juq3215lUAezlhD3euB1Ne3DVBMCTBPAEDn7uhGPDzHp2/jMO3m7dfK7ddZyN0XwlgWcaB9ceWzUF8HgBvAMHvzKnnu2Mk82Cspy6Te4X7HMHp400X03gM4yDaw+tmgl4nAAew8E39L7460z2a5/RRy9PGrikekZZwNcS+FzjNjk5smoe2FECdhuOHfFtwRZVxSD//nN8Ztnvuv++DNjrCXtRDaO+gYI7sGox0C0F6OYcOqlerS69dswPnpt8p7Bk51p5aaCzCHq5cWuuPa5qBeBNBPAIDj7w+Pfpd+6vDhhf9tSyNj+jzpQCfBOBrzHyZsYdVrUW7DABO4Rjd2pltlIuz+U9fNl1M4ugB5Ylwc4m7Cwjb2bkqKqNgAcK4EoOftS5Z1xw9V/BqwLnTXs1atM+a8C3EviWGno/B/3brxxhtoLsJyD7cOSOO1p/GdHHyW9i/2rbAz3qrMAZXM23E/JO48kKZhfICgG5IUc+uLxSfGrbnsqdP9YWfVamas/iIO8k5H1GP3XQHFK1H/B6ArgHBx+X+evdkgkyr0UdSk5MOHyqNc5Xa76bwA8ZB9ceUXUYcFcB3Jm86TBzeOvM95MCssv26uBeqrAEJ9Y130vgx427eXMHVJ0AWi5AO3BoZ7/wRn7urz2zrI8N3r1kYJkiQO8n6DP/gFYwZ4G2E6BrceiAwoMDlIW+N9qZ7RaZu8jSV4WBPkDQF41G43CqS0DXEKCrcejKk1p2PPTVym9JrxGF744pPlYK9CGCvvYPaAVzHejKAnRFDm3jGLl3xOcZvhPWb+p0qez5r4WAPkLQt418GOEOproDdnkBuyzHbtHugNX2xm6Npk4rmt/OOV+lgmAfI+wH/8JWMA/BLiVgW3Ns2x6BR5d8vu0/bH7S/hZRm5YUAPsEYT817gamPZTqGeDFBPAiHHy4f1HXUw0re06IGtrXbkLuoTjBtfkpAn9lHFx7JJX6+xQLCeAFOPhi+yuFu9874tv/WEj/a8y1hfkAP0Pg742EkwOpPgBuJYBbkmcOa0s2GB2e7bl78BarWk4ZkTijt/k5Av/yT3AF8xXwvAJ4bg6uzH59evU0m9CBLSPsCv20GohTj5tfIPCfxr4k4g6j+gW4mQD+8yJ3zzajzrMzsUcCB9jcdlj31svNEvBLBJ67pnEPJ+Qoqjz42s5vF3PCv3DwPvcs+wwqc8NnXMK8zYNO3oyyAPwKgVsaB9ceRMUA/lEAf8/BB+WpE1V5Q1vPMY3uT/bbnDJIAvg1Ai9Q06g3XNTHUBUE+I0A/IoD99/3ue1Rn9GhW2OC7bIXBXbLC/ANAi5S06hXoTiEqii4zwXcpxz3YuqKg7NKL/Bed2/+kdx1S03LA+4twrWuKfhq3j/a1ExJUB8JqA846jLX113ajerqP6LQzZoHUn325gb1DqGWNY4awZQD9a6Aepujjh76wGVdtzp+k1X3y92YGFAxF6j3CLViTaMeurjjpyoBfUOAvsah33U7s6Hfqh1Bs7Y1njWs6rHc5kA/IOhqxqG5w6eqA31ZgL7IoYdMrWJb0Mfab76yU/ylxVsZM6AfEXQt425P2qOnagN+TgA/w8EDR75/NrNoY//Fd651DBu+8+evouyVTwjc4Z/gCkYG+EkB/DgHX5frevTY9+O9Zp/Jrtf72YK9PwF/RuDORsM1x065AH5EAD/EwUuO/zlxZt3PXjO7mX1KP6Kq+gPwFwTu8U9wBVMX8P8E8H0cPMCzxq2kjyP850bflaQqvDp/B/wVgTesadSzFXLklCfYuwXsnRx7+McZeydvLRm42qbT4M23Llt9A/sNYfsYeSvTHDjlC/Q2AXoLh555+WDJIRZr/LJGbmlf2LK4+Veg3xG00mg0jptqBPQmATqLQ1t1b5gUX3JxwPTmeQ4OuHRj2xegPxB0iHGbW3vYVCjg6wTwNRw8yvWWc9qVhSFT1qjGfXVO//IZ8E8EHmHkQyY5aioS8JUC+HIOPq3SrqCBbfqGLlub2OdZxjjZJ8C/EHhz4/Y1ctBUC7CXCNiLOHatu/b3H76JDtrxpf5N61Ej53wE+xthtzFWnDtmqi3g8wXwuRzcv+o578MjryiWhR2SzEl60eID4D8IPKamcS/31YdMxYI8S0CewZE3fv7uPaPR5OAsyzxMf9usJe9B/kXIHYx7soAjpjqCO1XAzeS4Jfbcn7AvvZnvHIv25gWsYga8A9e8FMdNMI6LA6YSwZ0o4I7nuNXshuz7L53xGWSRXuHQt7zX34Kbm3C7GLeZtcdLpQI+RgAfxcG7HK0zOe3+nYCFyTGb5pfcJX8DeF4C72rc/k0Ol1J/hf1wAXsox04d0G5deLctPqOaXrzdIPL88NdgWxB2L+Pu0LijpdRf2D9IgB7AoYOCS/9q82uVcubL8d+8ntwc8wpohqD7G7fm2oOlBgDeVwDvzcF7HejWvFp8F88dNXpNOLboodNLwPMR+BDj1xzsoerzQAjY3Th2Bc9y5cqZq4LGrHk29dOj0K0vwC5A2CONXnOgRwGdLkCncui0dqkfx9d667Pqx4VBa4dc8HgOdCGCHmecNjlSajzYyQJ2IscunZDt8E1+03tn0ZQ6A+bcn/cM7MKEPdm42zYOlMoEt5OA25Hj1unTcmvLMIlycBsfu1m3JA+fgluUcKfX1PtlCoa5zAxgVQJsLId9MOXpzyYrG3lNKdjvXPldxW4+AbY4wc4xDqsIZ+YC206Abcthm/u7fNghqeK7rdfc2MFhz249BtaaYBcahw2RM4uAbSXAtuCwsxc5vY8YX0Ix2C5X8ojnfYo8ArYUwS4zDstu2+XANhVgIzns9XtdGmd6VA8dtrpv+6GDqwU/BLYMwa42DhsgZ9YA21iADeWwBcdmWtg2kDVau6jtleeZpRwfAFuOYDcY98CsOUQqC+QgAbkRR7b91XNG+MnFQQtevitw76xZt/sgVyDk7JqCs7+IknOcRILZAqj/xZwfEvG9SA4nvmPXw22Y/6Skh3WH7m3WajqgFQl0R029J+8Qh2q8uQ+jcaeu2IkOvATanlwHdnYn1vVP2u69QFZI0Xlr+3tT0UFl0sFednC9v+kgwt8uXAe/D/j6AnxdDr+kZ+T2zE3uXiM7rjpd+Wab8pOBr0rwB9nBnn+DDwpoGhxhJ3PWaeEQWnATbAMXroUDq/Nvix7k4LMjs8yprvW6L56AFqqTFo6xg/3/pgX1p5L8dBZB+7e34+jEUbAYMq4TswF+havHNQpanPG51vEOBVuPRSc1SSc4B1LAP3dC/uB9Bq3YC1qpTZ4uBt9NefLGyW/2taJv1jVNPz0GrdQirVwwyaJwf/e/iE5qCjqpznXS72rZOScqtfeZsjL4QacLVwuNRid2pJOrJlkU8ufJa2iliqCVSuS57JFr+abvyBUwp4f7o3Pf1r4fhVbqkFZumaIV7WcCbqOVCoJWynGtvNwYvzn8jnnI8kGrm7iaPf41Eq3ISCv3TbF9yB/pH6CT0oJOSnKd+C5Y6LpGWa9R1oyDqXmUT4eMQCeOpJMn7GA/E3SCP9k/RSPFBY0U5Rq5dnya7Ja1q+/Qpwuq+4ZmZQ1HI86kkZfsYN9/bUTzp+RX6EMq6KMgeRP8ypD5ijs9G60/Y2cR2Lfj7WHow5X08c5UfSiY9+gjn6APhuvjcMD7L/dPPgmZ+W1iVJcIJ8+h6MOd9PFZ8Iw0XJWWkZCeZhORkZgYndrDvkl6fEJ8eg87tiZNsfQmkd6hEZHMF7AlgvvUPBy78pJJHneHrg4Zeqp/oZOje3yxKIL7fML+wQ6uIfbx6kg7R0fy8WovnD4vKjyc+QmUuUDz1wXuIbR/l6vlvGO9F6wsyVyc9TP/hsJ4wCGoXLY5P9gpgvLz9fWJiohU+OP8dA5MbnaM+fcLOYFfOWD7RTXPKXPfU+zwaV/P37p/hfUANiRAC3Zwtd8BQ9QwxhKgTwLQBw4UVqpL6ei+pf23X7l2/Gz5iqlrAVIQUH5b/YsoFyxiAaDeClCvOdTh4t9ON5h1xW90VuN9eXzrF16fn73Sm6AKG1hEudgiyuVMEQBfCIDPOOCZKn1XjOk4KnBMvehihW7MOr8OQF8CLGFgEeU5FtEaoMcC0EMOZHVr/q4nDTcpx/34Uf/LpOtxawDyJ6AyBhZRJljEskDdE6DucKgy7+MsNgzq6LP15amB7X8ca7fOgr1SSVA2tjk/dy+CohdR5mAnYyoCeVOAvM4hfb3eyktsfeiZ1X3I+SWKjhvXAhlIkFUNLKMsxzJWA+iKAHSJA/3sfWSmRG7tOeZR2wNtW3ezWg1QMAHZ2uZ8nuaXkNwtDacHjU/qYKM5p3aavY8qLb5Dkh1OQYmnRKHaA/x8m4eFy5laaOG8oIWzXAt+jb4tL7tgrXLp8c/Fh8VU3rE2F143kBbqsINtxA+eUCXj8Im06K4qxgGIUxdy3m2d4BAtv9XY7hGT4TPUwrxa7a6Ka+3N8WKFIJwEy8kjYpOTkhPjY9OiNGdGZZwBOioAHeZA1WydXm6JSwmaukG55fjT1NM4zbp5BAG52wpeXcX3xEJGJ8XZ4ISq7GV77+iU+PToBJTqe2wsMeMB7AHBEu7nsCPHdd+W/2ypoGEt6s9+UrR/dQZXNiHYBuzgJr/D+nZXxWaoT/7KPUwoQ5r6RkQG+4ZEerD3EWxHNuHR3WyCo9NVqfHRCWnqgUxD9LVH0Ncurq+d4xPrPu1+JHTrQucv4YUtD+XBlc1IX962gr8pCvvyiU9VxabrroYPqNsF1K0cta/rodavD5UJmTrqRvHNs3c7WqlfdhNqADu4mQlWIyw1uRPbmQ23vTTroURnmwWdbeQ6a369kIv79+GeM4cd37qiXt2y2IHMW5HOgtnBjU3QmeYBPl7FbaMQ9LRe0NNarqcvn5r5zmlg7rtlQb+9NZRPi+PMvOZtSE/hJuopNEWVGq2+01D3FIGeVgl6WsH1dH7xne+/oh76Trc+36mpe81HOOG2eRTpqRk7OOKfesIdVqoqjt2j01U2ye1twlXpGalJTHN0tVTQ1WKuqxeV2hZ0n7TXe5XLzjH9g1fgYcDMPJp01Zod3OifuqoUZh9qbxPG3r6S4yoxbdDMAkEz87hmsi+6HN5QzT108NK6byvHDC9kqX4njTQTzQ4OM81OHpfB7uQR0QmqNCYGLc0WtDSTa2n+5wELmH3XAxZK23eJNO++BFdaJJRChP1Pyv6XR/x86ur7UZxemsF5rhmclrtAAYvEPx2JU5AzOF95gYIWSX86CKf1LlDIIvlP8zi5NoPzdjM41zeDc40zOIE2g9OUMzi5OYNzrDM4Q3YBi7xWVc3M7Aydo9orPimO3QihMbgTwVmb1eeNjopOTY3uIYmKTc5ISs9rpj6ZNJPBLrtE3R47aT/uXNP0XP6qJHanibXHNO1krVpxkQj1abBr2ySmxSanJsTH1LZpqkpNY0fUd7J3wP9q23izrwwyUlX1k1QZ6anRCbVtwjJiEuJjA1U9IpM7q5Lqx7i6RjvHOrvI3B2dVA5u7m3a5Fa3Gc/On5Y3Ki2+p8oyqqtmVrZFS0umq62Z9l+eEmzDK8z/oOOcK6X+0oCIjBh2R03PwBBynuvaNoKzYcex60ipqc3sZX8g5xAdG+vsGMtqtZc7uMW1NyTHPnLV+uMmW7XBdmMXoxu1GOal2MXAbsF0Z3+rvkerwlbYpjqLZl6V/Q0WTnd0DTK6F/tb9eOoo+hoJ9HRrmR0X/a36hutl+hob9HRvmT0AFvNjcU8THR0Y9HRkWT0YFvNicjNo0RHtxMbnRenQf+rk72jP6uo+CR2BwuITuuYu6zI7ocr0rGl1LevYbDCaUfBYoajmk6qEajmkGokqoWkGoVqGalGo1pNqjGoNpBqLKpsUo1DtYNU41HtJdUEVAdJNRHVMVJNQnWaVJNRXSBVJqqrpJqC6happqK6T6ppqJ6Qajqql6SageodqWai+kyqWah+kGo2KpxzU13NQWVBqrmo8pNqHqrCpJqPqgSpFqAqQ6qFqGxItQhVVVItRmVLqiWo6pBqKSonUi1D5U6q5agakGoFKm9SrUQVQKpVqIJJtRpVOKnWoGpGqrWoWpNqHapoUq1H1Z5UG1B1JlUWqhRSbUSVQapNqHqSajOqfqTKRjWYVFtQjSDVVlRjSbUN1SRSbUc1jVQ71A/epNqpfnZBql3qJz6k2q1+ckaqPeqnj6Taq36CS6p96ifipNqvfjFAqv/UL1lIdUD9uolUB9Uv10h1SP36kFSH1S9YSXVE/TqZVEfVL9RJdUz9DgGpjqvfmCDVCfX7IqQ6qX5DhlSnUH0n1WlU+Kp1dXUGlYRUZ1HlI9U5VFJSnUdVnFQXUJUm1UVUFUh1CVUVUl1GVZNUV1DZk+oqKkdSXUPlRqrrqOqT6gYqL1LdROVPqluogkh1G1VjUt1B1ZRUd1G1ItU9VO1IdR+VilQPUHUi1UNUyaR6hCqdVI9R9SDVE1R9SfUU1SBSPUM1nFTPUY0h1QtUE0n1EtVUUr1CNYtUr1HNJ9UbVEtI9RbVSlK9Q7WOVO9RbSLVB1TbSPUR1W5SfUL1H6k+ozpCqi+oTpLqK6pzpPqG6jKpvqO6QaofqO6S6ieqR6T6heo5qcxqsdUbUpmj+kiqXKi+kSo3KnzTjLrKgyovqfKisiKVBFUhUlmgKkYqS1SlSMWgKk8qK1SVSZUPVQ1S5UdlR6oCqOSkKojKlVSFUNUjlRSVglSFUfmRqgiqQFIVRRVGqmKompCqOKqWpCqBKopU1qjiSFUSVTypSqFKIlVpVGmkKoOqO6nKoupDqnKoBpKqPKphpKqAajSpbFBNIFVFVFNIVQnVTFJVRjWPVFVQLSZVVVQrSFUN1VpSVUe1kVQ1UG0lVU1Uu0hli2o/qWqhOkyq2qhOkMoO1VlS2aO6RKo6qK6TygHVHVLJUD0klRzVM1I5onpNKidUH0jljOorqVxQ/SKVKyocoaCu3FAxpHJHVZBUHqiKkqouqpKkqoeqHKnqo6pEqgaoqpOqIarapPJEJSOVApULqbxQ1SWVNypPUvmg8iWVL6pGpPJDFUoqf1SRpApA1YJUSlRtSdUIVSypAlF1JFUQqkRSBaNKJVUIqm6kCkXVm1RhqAaQqjGqoaQKRzWKVBGoxpMqElUmqZqgmkGqpqjmkqoZqkWkao5qOalaoFpDqpaoskjVCtUWUrVGtZNUbVDtI1VbVIdIFYXqOKnaoTpDqmhUF0kVg+oaqWJR3SZVHKoHpFKhekqq9qhekaoDqvek6ojqC6niUf0kVSdU+DOUuuqMypJUCagKkCoRVRFSJaGyJlUyqrKkSkFVkVRdUFUjVSqqWqRKQ+VAqnRUzqTKQOVBqq6oGpKqGyofUnVHpSRVD1QhpOqJKoJUvVA1J1VvVG1I1QdVDKn6spUUb3PgXRimH1sx/fFjAH4MxI9B+DGY/VHAqjB51WihfqFoTt5sqPnHr8/xqk/aneCGYOqh+DEM8xeQ9iLXDMcvR+DHSPwYhavzS/uSq0fjl2PwYyx+jMOP8cjkkw4gmQmoC0kHk3oiQpPwy4LmeN3Zhf3l88ZuDQvjVSteJbMv7BDJxPoMFw9MQWAqAiPEA9MQmI7ASPHADARmqm/c4oFZCMxWP46JB+YgMBeBMeKBeQjMR2CseGABAgsRGCceWITAYvV9jnhgCQJLEZggHliGwHIEJooHViCwEoFJ4oFVCKxGYLJ4YA0Ca9V3heKBdQisR2CKeGADAlkITBUPbERgEwLTxAObEchGYLp4YAsCW9X30OKBbQhsR2CmeGAHAjsRmCUe2IXAbgRmiwf2ILAXgTnigX0I7Fc/cIgH/kPgAALzxAMHETiEwHzxwGEEjiCwQDxwFIFjCCwUDxxH4IT68Uw8cBKBUwgsFg+cRuAMAkvEA2cROIfAUvHAeQQuILBMPHARgUvqh1nxwGUEriCwQjxwFYFrCKwUD1xH4AYCq8QDNxG4hcBq8cBtBO4gsEY8cBeBewisFQ/cR+ABAuvEAw8ReITAevHAYwSeILBBPPAUgWcIZIkHniPwAoGN4oGXCLxCYJN44DUCbxDYLB54i8A7BLLFA+8R+IDAFvHARwQ+IbBVPPAZgS8IbBMPfEXgGwLbxQPfEfiBwA7xwE8EfiGwUzxgVpv9Yc7+MN8lHsiFQG4EdosH8iCQF4E94gEJAhYI7BUPWCLAILBPPGCFQD4E9osH8iNQAIH/xAMFESiEwAHxgBSBwggcFA8UQaAoAofEA8UQKI7AYfFACQSsETgiHiiJQCkEjooHSiNQBoFj4oGyCJRD4Lh4oDwCFRA4IR6wQaAiAifFA5UQqIzAKfFAFQSqInBaPFANgeoInBEP1ECgJgJnxQO2CNRC4Jx4oDYCdgicFw/YI1AHgQviAQcEZAhcFA/IEXBE4JJ4wAkBZwQuiwdcEHBF4Ip4wA0BdwSuigc8EKiLwDXxQD0E6iNwXTzQAIGGCNwQD3gioEDgpnjACwFvBG6JB3wQ8EXgtnjADwF/BO6IBwIQUCJwVzzQCIFABO6JB4IQCEbgvnggBIFQBB6IB8IQaIzAQ/FAOAIRCDwSD0Qi0ASBx+KBpgg0Q+CJeKA5Ai0QeCoeaIlAKwSeiQdaI9AGgefigbYIRCHwQjzQDoFoBF6KB2IQiEXglXggDgEVAq/FA+0R6IDAG/FARwTiEXgrHuiEQGcE3okHEhBIROC9eCAJgWQEPogHUhDogsBH8UAqAmkIfBIPpCOQgcBn8UBXBLoh8EU80B2BHgh8FQ/0RKAXAt/EA70R6IPAd/FAXwT6IfBDPNAfgQEI/BQPDERgEAK/xAODERiCAN5yFwkMRWAYAubigeEIjEAgl3hgJAKjEMgtHhiNwBgE8ogHxiIwDoG84oHxCExAQCIemIjAJAQsxAOTEchEwFI8MAWBqQgw4oFpCExHwEo8MAOBmQjkEw/MQmA2AvnFA3MQmItAAfHAPATmI1BQPLAAgYUIFBIPLEJgMQJS8cASBJYiUFg8sAyB5QgUEQ+sQGAlAkXFA6sQWI1AMfHAGgTWIlBcPLAOgfUIlBAPbEAgCwFr8cBGBDYhUFI8sBmBbARKiQe2ILAVgdLigW0IbEegjHhgBwI7ESgrHtiFwG4EyokH9iCwF4Hy4oF9COxHoIJ44D8EDiBgIx44iMAhBCqKBw4jcASBSuKBowgcQ6CyeOA4AicQqCIeOInAKQSqigdOI3AGgWrigbMInEOgunjgPAIXEKghHriIwCUEaooHLiNwBQFb8cBVBK4hUEs8cB2BGwjUFg/cROAWAnbigdsI3EHAXjxwF4F7CNQRD9xH4AECDuKBhwg8QkAmHniMwBME5OKBpwg8Q8BRPPAcgRcIOIkHXiLwCgFn8cBrBN4g4CIeeIvAOwRcxQPvEfiAgJt44CMCnxBwFw98RuALAh7iga8IfEOgrnjgOwI/EKgnHviJwC8E6osHzOzYH+bsD/MG4oFcCORGoKF4IA8CeRHwFA9IELBAQCEesESAQcBLPGCFQD4EvMUD+REogICPeKAgAoUQ8BUPSBEojICfeKAIAkUR8BcPFEOgOAIB4oESCFgjoBQPlESgFAKNxAOlESiDQKB4oCwC5RAIEg+UR6ACAsHiARsEKiIQIh6ohEBlBELFA1UQqIpAmHigGgLVEWgsHqiBQE0EwsUDtgjUQiBCPFAbATsEIsUD9gjUQaCJeMABARkCTcUDcgQcEWgmHnBCwBmB5uIBFwRcEWghHnBDwB2BluIBDwTqItBKPFAPgfoItBYPNECgIQJtxAOeCCgQaCse8ELAG4Eo8YAPAr4ItBMP+CHgj0C0eCAAASUCMeKBRggEIhArHghCIBiBOPFACAKhCKjEA2EINEagvXggHIEIBDqIByIRaIJAR/FAUwSaIRAvHmiOQAsEOokHWiLQCoHOVKAoH2iNQBsEEsRnaItAFAKJ4oF2CEQjkCSOiEEgFoFk8RniEFAhkCIeaI9ABwS6iAc6IhCPQKp4oBMCnRFIEw8kIJCIQLp4IAmBZAQyxAMpCHRBoKt4IBWBNAS6iQfSEchAoLt4oCsC3RDoIR7ojkAPBHqKB3oi0AuBXuKB3gj0QaC3eKAvAv0Q6CMe6I/AAAT6igcGIjCI/ZEXn2+oJvphBa/oNJUiPT01PiYjXaVMVyXisA+LqOT27dNU6ZZRHVXROGbEKiqaZCyjYqPVB2FKotLSeySo8H/R6Sozc/ZfHkvnP4PU0lYRGIxPR+A//JMMZhvOExKdqJIM0V4aSi4x0Mvb/eyvX8aR8NENC5z8ShUVpTnWRX1wAT76gTVCIRmBFWuKjGQkf3GU9qK6B/M0tgf0oR4/gBuvPqJmLJvMF5TcTZVq450QnZgiGcf+wkr9C009PkdAM2ESPeFAbkL14SGTkG+SkqKdcDImVP9CU2fmCGgmjKcnHMRNiOM4JNPg0iQpPj1NMp2/OEN7UTM+jh4/mBufF+Nn2+ELBdn1zEiTzKEuz+Uva6aIoqcYwk2h3soLtNt2ofbSIp2tbN6SHjyU3kJL+c2yjL+4PMcWakKPH0ZvoVW89Gr+4poc/mH0+OF08+u1LW/QXsrSbT6QHjyCbn4z33E2f3FLjub96PEj6ea38x3v4C/uzNG8gh4/it6b9lAbbC91eV/OjVePnmI07X9Aa31Qe+mQrr8rPXgM7X+Ulz7GXzyew19Ojx9L+5/ipU/zF8/k8Lejx4+j/c9Tzheoyxdz+tegpxhP336uwDUsOr2j5Kr20jVySTO4Mj14Ar14N3npW/zF2zn8y9PjJ9Lj7/GD7vMXH+QYX4oeP4le/8f8oj3hLz7NsX7FqPFSfD6sIMa+wB1NAu65ohLiE+PTJS+12/8V7pM0xxaq69dsbRnOPnyEJiX0kLzBwAzcQ3ED3/LxyB4pKsk7ts6t9HGUvNdckEs+aC7IJB/ZC/nJB+nUc3/SXOUi+ay54Cz5orngJPmKcFx8WkpCdI+oJDYszeSat5J8Y68rxH03CvlSFMl3bHbNLy3N2dAPtrbgvkhF8hNXBikbN1H6SH5hhdRfnSIxs2etIyNCgyTm7CVLMpd65fgfktz22tHSKWQJ89hzonntc6ylxJ6spYU9vXaW9jnWjrHXXTsre92lz2fPLWF+e24JC9jnXMKC9twSFrLnllBqzy1hYfucSziVa17jVhRaxdgfRTTLZBeWGh+rsg8LV3r7skuoub4E+yNvhCo9I0VijfnoqGZ1SrG/tnB0dPFR+kZISiOuniHnIpalYtJppBGsIoMVZLBqDBaMwToxWBsGC8Jg
A5: FRisAAN7BsIMZBmIMpCUThd62f3Gqw7v5SDuJbfX7lASR71aznxKOsO0VjOFVn6/sQrgrZTiVoHqfmUu/ooISZBeqxA+JZ1lWqvZtJWVpK09bsua3YKcvlF9+42yp26/7aidR9NhjL32VhyLK7mhOUVU2ph0jmk95up6ZLC/K8jdJ9EaXWmNbvzOommvB2/R04BFb95inmkt5utajFZbqLe7jsUY2mIsv3No2hvPW0wwYDGJt1hgWouFuhYLdfYpzSlI1RqLaI3Fgn1qKe+xTO2hGZrTYwXvsci0Hot1PbbRW4PS2E5r7Mi5NXbxFrsNWOzlLZaY1mIpeYg8DYT668msJGdwDdkm5IFWbXOWtjlHbRTJed7kAizxBZruDpKL9gYeqy9rmdJlptVaTrQeUVqP1buaZhPpWD2hrZ7y20jyjJd6Tkm9MCT1ipdaYVqplUTqJyX1S5+UWR1KyrwOL5WrjlYqdx1OSuYgyVPHgJSkjlZqlWmlVuvejErU4Z8ukq+BVetY0zol6/AP96VwhebLKGWS0rxbGfiQKXL6lKMGSdeY1mitrpGdPiN72qgOZeTANyeXyHgjuSEjJ2qQdJ1pjdbrGvnoM/KljfwoI3++OUdJAG+kNGQUSA2SbjCtUZauUSt9Rq1pozaUUVtcoTl3mkwSxRu1M2QUQw2SbjSt0SZdo1R9Rmm0UTpllME15wKjrrxRN0NGPahB0s2mNcrWNRqhz2gkbTSKMhrNNyeXjOGNxhoyGk8Nkm4xrdFWXaN5+ozm00YLKKOFfHOOkkW80WJDRkupQdJtpjXarmuUrc9oC220lTLahsvq70OVSbbzQjsMCe3ix0h3mNZnp67PSX0+p2if05TPGW1vcslZ3uecIZ8L/BjpLtP67Nb1eaDP5yHt84jyeUx685JJnvA+Tw35POfHSPeY1mevrs93fT4/aJ+flM8vbW9yiZmD1sfcwYBPbgftGOk+0/rs1/Up6kA98dYRKuZACRV3oJ54l2CLPN4BinCJNe9T0pBPaTJC+p9pbQ7o2tjqtalF29SmbexQeClDEZfY80J1DAnJqEHSg6Z1OqTrpNDr5EU7edNOPvz+I/HllfwMKQVQ+9xh0xod0TVqrteoBW3UkjZq5cDfK7TmjdoYMorix0iPmtbomK5Rsl6jFNqoC22U6sDfb6fxRumGjLryY6THTWt0QtdoqF6jYbTRcNpohAP/yDqSNxplyGgMP0Z60rRGp3SNZus1mkMbzaWN5jlQz37m80oLDCktogZJT5vW6Yyu00a9Tptop820U7YD9Rx1C++01ZDTdmqQ9Kxpnc7pOh3T63ScdjpBO53k25NJTvFOpw05naUGSc+b1umCrtNdvU73aKf7tNMDB+r13kPe6ZEhpyfUIOlF0zpd0nX6otfpK+30jXb67kC9Kv/BO/005GQmo16VXzat0xVdJ6lMn1NhGeVUREY5FeXbk0uKybROxWUGnKypQdKrpnW6putUXa9TDdqpJu1ky7cnk9TinWobcrKnBkmvm9bphq5TA71ODWknT9pJgSLELsA70M5L4sU7eRty8qUGSW+a1umWrlMTvU5NaadmtFNzvj2FpAXv1NKQU2tqkPS2aZ3u6Dol6HVKpJ2SaKdk9K6+W2Y7lKTwUl0MSaXRo6R3TWt1T9dqkF6rwbTVENpqKPrDSXVxYnLJMN5quCGrkfQo6X3TWj3QtZqh12ombTWLtpqN/oL8g9QnmpfM4a3mGrKaT4+SPjSt1SNdq/V6rTbQVlm01Ua2yB0gj5Bs4oU2GxLawg2QPjatyxNdl8N6XY7QLkdpl2PqO2XfEJyIU3Kc9zlhyOcUNUj61LROz3Sdbul1uk073aGd7qqvaRLkp/APkdzjne4bcnpIDZI+N63TC12nj3qdPtFOn2mnL/yDZ4TkK+/0zZDTD2qQ9KVpnV7pOhWQ63MqKKecCskpJylbWJLzx0kKy7VSReQGpIrRo6SvTWv1Rteqil6rqrRVNdqqOvojZ12T1OCtahqyqkWPkr41rdU7Xau6eq3q0Vb1aasG6E8md7JDj5KGvJWnISsvepT0vWmtPuhaheu1iqCtImmrJii409JJmvJSzQxJtaAGST+a1umTrlO8XqdOtFNn2imBLSSaE9xJEnmlJENKKfwY6WfTGn3RNeqv12gAbTSQNhqE1n2UYXbeocFhksG80xBDTsPoUdKvprX6pms1Va/VNNpqOm01AwV3Hk/JTF5qliGpOdQg6XfTOv3QdVqj12kt7bSOdlqvvm/mTn4p2cBLZRmS2kSPkv40rdUvXasDeq0O0laHaKvD8FC/Tyw5wisdNaR0XDtEiu8XM6GPeW0dn+t6fW7QPjdpn1ukOYXkNu9zx5DPPe0QaS7T+uTW9Xmn1+c97fOB9vko17y2cw0LahIh+cQrfTak9JUeJc1jWqu8ulZWjvqs8jlSVvkdKasCbGHppWQ7DAqNkBR01FoVcjRgVZgeJZWY1spC16qiXqtKtFVl2qoKW0jUr8O9JFV5p2qGnGrwY6SWpjVidI3c9Bq500YetFFdbXcKST3eqL4ho4b8GKmVaY3y6RqF6jUKo40a00bhXHfO7DaK4I0iDRk15cdI85vWqICuUXu9Rh1oo460Uby2O4WkE2/U2ZBRIj9GWtC0RoV0jfroNepLG/WjjfqjUNqFhfuxG2kArzTQkNJgapBUalqnwrpOk/U6ZdJOU2inqXx7Csk03mm6IaeZ1CBpEdM6FdV1WqnXaRXttJp2WqPu3dsuTBGu8JOs5aXWGZLaQI+SFjOtVXFdq316rfbTVv/RVgfQXwSxOshbHTJkdYQeJS1hWitrXasreq2u0lbXaKvr6v788a4je6O6wVvdNGR1mx4lLWlaq1K6Vq/1Wr2hrd7SVu+o/hSS97zVB0NWn+hR0tKmtSqja2XhpM/K0omyYpwoKysn9XvEAZp3lvM5aa3yOxmwKkiPkpY1rVU5Xavyeq0q0FY2tFVF9Ocd7hWitqrEW1U2ZFWVHiUtb1qrCrpWznqtXGgrV9rKDf0pvJU+ait33srDkFU9epTUxrRWFXWtgvRaBdNWIbRVKFvkiVCE+EjCeKPGhowiyAhpJdPaVNa1idVrE0fbqGib9myRWxERIOnAy3Q0JNOJGyCtYlqXqrouPfW69KJdetMufZzwPVWSvrxJP0MmA9RxaTXTelTX9Zig12Mi7TGJ9piMxiIkmbzHFEMe09RxaQ3TetTU9Vim12M57bGC9ljphJ1f8+7dKl5mtSGZtfwYqa1pjWrpGu3Wa7SHNtpLG+1DdyEao/280X+GjA7yY6S1TWtkp2t0Ua/RJdroMm10Rf3IqGQfGpuxz32u8k7XDDndoEdJ7U1rVUfX6oVeq5e01Sva6jXVn0Lyhrd6a8jqPT1K6mBaK5muVR5nfVZ5nSkriTNlZeGs6S9Iva0snbVWjLMBq3z0KKnctFaOulZl9FqVpa3K0Vblqf4Ukgq8lY0hq0r0KKmTaa2cda3keq0caSsn2soZBT6hofCOlLjwUq6GpNypQVIX0zq56jop9To1op0CaacgZ9w3N8HtQxLMK4UYUgrjx0jdTGvkrmvUTq9RNG0UQxvFct2xe5EkjjdSGTLqwI+RepjWqK6uUTe9Rt1pox60UU+07t9EoVR4hwZJevFOvQ059aVHSeuZ1qq+rtVYvVbjaKvxtNUE9KcI8g4NwMcgJvJWkwxZZdKjpA1Ma9VQ12qxXqsltNVS2moZikDfyFD8JXA5L7XCkNQqapDU07ROCl2nHXqddtJOu2in3Zo19/ENaOHjK9nDS+01JLWfHiX1Mq2Vt67VOb1W52mrC7TVRXjgNWmE5BKvdNmQ0lXtEKmPaX18dX2e6vV5Rvs8p31esEXukFC55CVv88qQzRtugNTPtC7+ui7mLvpccrlQLrldKJc8bJE7gnXJ66J1kbgYcLHkBkgDTOui1HUpqdelFO1SmnYpg75ldl5NIn1DfCVleaFyhoQq0KOkjUxrFahrVUevlQNtJaOt5CjCwkPDIOXISzkZknKhBkmDTOsUrOvkp9fJn3YKoJ2ULvgUeGQAlBrxSoGGlIL5MdIQ0xqF6hq10WvUljaKoo3aofUQ7EX4SGg07xRjyCmOHiUNM61VY12rdL1WGbRVV9qqG9mNINWdl+phSKoXNUgablqnCF2nUXqdRtNOY2insdx+BKVxvNJ4Q0oT+THSSNMaNdE1WqDXaCFttIg2WowimFNawistNaS0nBokbWpap2a6Tlv1Om2jnbbTTjvwMOPNPi7t5H12GfLZww2QNjetSwtdl9N6Xc7QLmdpl3Nskcs7VHKeV7lgSOWSJi9taVqTVromj/SaPKZNntAmT9GZIlzyjDd5bsjkpSYvbW1akza6Jj/1mvyiTcxcKRNztsgVIpfkcuW/RMnVgEleTV7a1rQmUbomxV31mZRwpUysaZOS6Iy9oZTiTUobMimryUvbmdYkWtektl4TO9rEnjapg84C5BIH3kRmyMRRk5fGmNYkVtfEW6+JD23iS5v4waCZItI3XOLPywQYkmmkHSKNM62PivaxxFeUq/9JWrLEUuF2crmzvTwg0i5YoQyxDw4N8o1qofQN8mEN1VmbqHm5vCStXPG59ITk2M5pktbs5YK64yRteMu2rtrPfUaxF634KXMqR2sHSdubVrmDHuUuf6GcSimniSin88oZRFkh6WpYuTuv3NG0yvF6lIf/hfIISnmkiPIoXnm0K//5vTGGncfxzp1M69xZj/Pcv3CeRznPF3FewDsvdOU/D7fIsPMS3jnBtM6Jepw3/4VzNuW8RcR5K++8DXdr5Njy7Yald/LSSaaVTtYjfeIvpE9S0qdEpE/z0md4abnkrGHp87x0immlu+iRvv8X0g8o6Yci0o946ceuZtpvt3li2PkZ75xqWuc0Pc7f/sL5O+X8Q8T5J+/8S+ssk5i5GXTO5aZ1Tjetc4Ye5yJuf+5c1I13LuYmdC6u7V5Sws1M+w051oadS/HOXU3r3E2Pc82/cLalnGuJONfmne20zjKJvWFnB965u2mde+hx9vwLZwXl7CXi7M07+7AXtd+y42tY2p+X7mla6V56pJv9hXRzSrqFiHRLXroVLy2XtDYs3ZaX7m1a6T56pJP+QjqZkk4Rke7CS6fy0jJJmmHpDF66r2ml++mRHvIX0kMp6WEi0sN56RGctPqLfEYalh7NS/fnupSMcctxBomxbuQMEuPcdE8JMZ6t+TNKTHDLcUaJiXxcfUaJSW7cSSomu3Gnksh0404lMcUt56kkprpxp5KY5sadSmK6G3cqiRluOU8lMYBrnlrdmQZXVzJLuIi6Kz6bX3HNWs3ll3iemxn/fTXzDS/xQn6JB5IdAUvMYFkZrCiDZWSwegxWjMEyMVgiBsvDYGkYrAaDlWCwCgxWQDpIKL3BsHTW76Q35pTezEtn89IRki2Gpbfx0oPJfrWdbP0dOXewndodbJfODrU75w61J8cOtTfH/riP7Ff7yX71n2C/OkD2q4NkvzpE9qvDgv1qCGn+iFaIWu2j6C/cTiZzsPcO9fWTaU98cZy6tZ7ASHVIctKN/+DiKfayuUxyGteqB+dcwrP8Eg4l+w2WkMHyMVgyBqvFYJEYLAyD1WCwBAz0GagzsGVgysCSgaF0GJG6IyZ1V5/UfUrqAS/10I3/7OIjjdRjvVJPeanhppUaQaS+iEl91Sf1nZL6wUv9dKM/vvhLo2Xmrk8rl7tWa6RptUYRrcLuIlpF3PVoFXPntYq7a7VKuNOfX7R2V2uV1KtVmtcabVqtMUSrppiWrT6t2pSWHa9l7059KK6OxspBr5WctxprWqtxxEohZuWlz8qHsvLlrfzc6Y9l+mu0AvRqNeK1xptWawLRaiGm1VKfVmtKqw2v1ZbSUkiiNFrt9GrF8FoTTas1iWh1EdNK1aeVTmll8Fpd3bUfSJR000h11yvVk5eabFqpTCI1QkxqpD6p0ZTUGF5qLCeFzzGO00iN1ys1kZeaYlqpqURqvpjUAn1SiyipxbzUEnf6o4xLNVrL9Gqt4LWmmVZrOtHaKqa1TZ/WDkprJ6+1y53+hNxujdYevVr7eK0ZptWaSbTOiGmd1ad1ntK6wGtddKc+zHhJY3VZr9VV3mqWaa1mE6snYlZP9Vk9p6xe8FYv3ekPnr7SaL3Wq/WW15pjWq25RMvcQ0Qrl4cerTwevFZeD62WxEP7eUYLD7WTpYc+JystUDqPNJHPI8crg/we5JVBAQ/dp/oFPehXCoU8crxSkHrovlIo7MG9+Cjiwb1EKOrBvUQo5pHzJUJxD+4lQgkP7iWCtQf3EqGkR86XCPO55q0kpdjrSkSo0tPjkzqk2UdnpCdHqXBS4Oh0laQ02iXXqf9GWob9TQGdELU45ei4pLyBqCZvI0hIF5AdBYsqqaRdyMq6C8lgIRmsn6RajjWrTtasBlmzmmTNbAVrVousWW2yZnbcmjFYM+lC7TLVYUvtuek0ZwOTOIBPnS5T5sH/AZn+u7Z2n5E4IaHnZGIu/K61iF4FBqvAYAF4awbWDFQZaDJQZKDHwIiBDQMTjcVirYUv9ji5q1yr4Add9heaD/iJ96/k+29koP8gvv8lpu1/qbb/Vur+2Rs26b+1un+Zg7r/NuL9R/H9tzPQfwzf/zLT9r9c238Xdf/Oztr+U9X9OztrzgEk3n8G339XA/135/tfYdr+V2r7H4ZbrItc3lzzyQkYDMdtFL9SK4wQVxjFK4z2IJ+aEHEYyzusMq3Daq3DbGwDJwcn7TaYg23A/kItMFdcYD4vsMDANljE97/GtP2v1fafpd6HHBzIySUlG9X7kIPmNrBJvP9svv8t6v7FTy+5je9/nWn7X6/t/whb5ndmb8PaXegoBJy5G/ExcYETvMBJQ3vQad5gg2kNsrQGtzyEp7eR3PbQfTC4k9NDcs+DnBHmPi/zwMPAh4gekRHSjaZ12aR1+Sjm8imHy2eBy1f8hpwP5huv892Qzk9qkHSzaY2ytUYF6ooYFayra1Sobk6jwvgN+ebzInW1RkXrGjAqTg2SbjGt0VatURUxo/+xcqeBTRVbAIDTFq4Ni8xj3xsBQdQWWsraNkubAoVuNGERkRLaAJEu0KRAWURxQwXEXd9TUQFRXJ/6UFlFURRFZBVFcXkouyiLy3Ph3cm9OTOZmTv+mX/JvefcO9/JaZpC5lzOiHpyoivI4jxabyK6Uia6mkpC69WKNoAoSyTKZkQ5nMiVZaOmnrsJySMj5dFZaKNa0yYwlYlMPsbk50xj8Opg5vlYYhonM42ns9BmtaYtYAqJTNczpumcqTrLRk08ryGmWplpJp2F3lJr2gqmG0WmmxjTIs50S5Y57/xWwrlNxllsJqC31UreAclDIsnDjOQRTvIvfCQ27fxRonlMpllBJaFtakXvguhFkeglRvQyJ3olesScdf4qEb0mE62jktB7akXbQfSuSPQeI9rOiT7Iov7bcgcRfSgT7aSS0PtqRR+A6AuR6EtGdJgTfY1XDnPOvyGkb2WkI3QW2qHW9CGYzolM5xnTBc70C14dTDn/lZh+k5l+p7PQR2pNO8HUJFtgapodb2qWzZouzcb7J2MzzltkgwllS0wt6Sz0sVrTLjBdJjJ1Y0zdOdPl+EhswnlPQuolI/WmktAnakW7QTRIJBrMiIZwomwcYc43zyEgpwzkJjloj1rPXvCUiDyljGcU5/HhhcN0cz8RjZaJxtJZaJ9a034wTRGZpjKmaZzpenwkNtt8OiFVyUg1VBI6oFb0KYgWiEQ3MKKFnOgmvHKYbL6IkG6WkW6ls9BBtabPwHS/yPQAY3qQMz2cDftbHiGgf8pAj0IK+lyt5hBonhNpnmc0L3Cal2JL82gvE82/ZZpXIQV9oVbzJWjeFmneYTTbOM172TZqpvl2AnpfBtpBZ6HDak1fgekzkelzxnSIM32JVwcTzQ8T01cy0zd0FvparekbMP0oMv3EmM5ypvM4wpxnfoGIfpaJfiU56Fu1nv+C55IcgSc5J95jz2E9TXNssBuqWQ54mudIPC1IDjqi1vMdeLqKPCmMx8F5uplrw7PMuxNPD5mnJ8lB36v1HAVPf5FnAOMZyHkGw9o82hDiyZJ5ckgOOqbWcxw8hSJPEeMp5jyl+EhsjvkoAiqTgfxUEjqhVnQSRBUiUSUjCnKiqWRxHm0aEYVkoulUEjqlVnQaRHNFonmMaD4nuiG68ti074WEdKOMtIjOQj+oNZ0B0z0i072M6T7O9ABeHUwwf5CYHpKZHqGz0I9qTT+B6RmR6VnGtJYzPR9dXWx++QvE9KLM9DKdhc6qNZ0D0xaR6S3GtJUzvUOtzqNtI6Z3ZabtdBY6r9Z0AUwHRKZPGdNBzvR5jo2aXX6ImL6QmQ7TWehntaZfwHRaZPqBMZ3hTD/h1cHk8rPEdE5mukBnoV/Vmn4DUyOnwNTYGW/SnKwp2Wmj5pbbnWBq4pSYmtFZ6H9qTb+DqZPI1JkxdeFMKc7Y1HIH8Vwm83SPZaA/1Fr+BEuGyNKPsWRylgFOc2b5QEIZJKMMMRPQX2olF0FSIJKMYCQjOUmRMzqxvJg4SmSOUdFwZEtVqkhIjSkmiRQBRjGZU1Q6o/PKg0QxRaaYFg1HiWoVSaCYLVLMYRQNnGIejjA3/cwnlAUyykKSgxqp9TQGzzKR527Gs5zz3IsjzP0+9xHP/TLPgyQHaWo9l4BntcjzNONZw3meddJbfdYS0XMy0Qt0FkpWa7KDaaPItIkxbeZMb1Gr82hbieltmWkbnYWaqDU1BdNekWkfY9rPmT510tthDhLTZzLTIToLNVNrag6mEyLTScZ0ijP9QK3Oo50hph9lprN0FrpUrakFmBJcAlOiK96U5GJNjV3UZizNBaRLXBKSnUpCSK3oHyBqLxJ1YEQdOVFnHGFu7elCQF1lIAfJQS3VelqBp4/I05fxpHOefuba8K6eTOLpL/MMJDmotVpPG/AMFXmGMZ7hnGeEi97QM5KICmWiYjoLtVVragem60SmiYypnDMFXPQGkcnEVCEzBeks1F6tqQOYIiJTPWOaxZnmuKitPA2ENFdGmk8loY5qRZ1AdJdItIQRLeVEd7voPVfLCekeGek+Ogt1VmvqAqanRKaVjGkVZ3raBXt41hDQMzLQWkhBXdVqUkDzpkizntFs4DSbXOZE8s3EskVm2WomIIdayWUg+UQk2c1I9nCSfS5zHvl+Ijkgkxw0E1A3tZLuIDkqkhxjJMc5yUm8aphGfopwTss4Z+gs1EOt6XIw/SUyXWRMNjdrSnTbyCzyJDeQGrklJI1KQj3VinqBqI1bIGrrjhe140QdcIQ5ibwjAXWSgbqQHHSFWk9v8Fwt8qQynjTO0xcvHOaQpxNRhkyUSWehK9WargJTnsjkZUz5nGlYrIEwaTghFchII6kkdLVaUSqIxotE1zKiCZxootlBGFROQJNkoMkkB6Wp9fQBz0yRp47xhDlPPT4Sm0A+i4Bmy0ANVBLqq1aUDqLFItEdjOhOTrTEbc4fX0o0y2Sa5WYCylAr6QeSFSLJE4zkSU6y0m1MH19FIKtlkDVGPMpU6+gPjnUix+uM4w3Osd5tzB7fQBwbZY7NRjwaoNYxEBw7RY6PGccuzrHbbUwe30Mce2WO/UY8GqTWMRgcR0SO7xjH95zjmNuYO36cOE7IHKeMeDRErSMLHL+LHH8wjj85x0W3MXXc5gFHgkfiSPIYU8ez1TpywNHSI3C08sQ7WntYR1u8fmPmeDtCaS+jdIQU5FSrcYGmN6Xx+cuKykeXlmpXMpqrWI2xvlQc5h00IBVPP8KQ2AVYSF8SiNxqJR6QuEQSNyPxUBItF9fXX+L3FGp55CXx4hDjJfFp+TLWMMhHuWpVeaAaI1KNZVTjaNU1RDWeqK714P/wHJZapk2QkSYSklctKR9I1SJSDUOqpUkzCGkmIdVhSOHwMUW+1PT+WljGqiesoWpZw4B1i4h1K8O6jWbdTliLCesOT2w/99Ay7U6xSlviob6LvpR6goar9RWA71GR7zHG9zjtW0F8TxDfk7TvKQvfKg+9u2g1/QyNUCscCcLXRML/MMJ1tPB1InyDCN+khesthBs91I6wTdQTVKjWVwS+j0S+nYzvY9q3i/g+Ib7dtG+PhW+fh95bsJ9+horVCkvIZyWR8DtG+D0tPEqEx4jwOC08YSE85aF3i52mn6FStcJRIPxDJPyTEf5FCy8SoS2XfIbKpYSJuWJho1xqn1Vj6gkqU+vzga91rsDXJjfe1zaX8rXLBV974utA+zpa+Drj65q7rrqQx8ivVjea/KuRSJfK6NJoXR+i60t06bQuw0KXmQs7YfrDQzRGrW0s2LwiWz5jG0rbhhHbcGIroG0jLGyFMZBHK4KHaJxa2zVgm6Dfo83oSKgqFGlI9dVXp+mrHu3PK/H5tev0U02pU1HmRFyLsmC4vioSdugHqwN1Dexnkkl6jB2uw/1zUtxZNF6t7Frzcsla2zFHH38paU+2NlO/4aX+1H79+qblenwFvvKyMq0u+gLhY/EDmsP4VaUGNNOftPALFrsAe3I2fRJNUGu6Lna56K1u12+FDM7Q/Hxvuc/vGZavLY4DJbfBkXeIMNpd+tEkPU5boj9oQi7BkpaZcWiiWk157BVKTsS3eUy/TTODU2xQHo+ntOilR62wfl2exKeKhYSV5BSapFYR4PvsFbPPMqg+e9W0ZDB99pq1Z52sz96I67PJak0VcX32vtlnGXF99kEcyOizHcI++yjaPxkZ2k55n+0y41ClWk0wvs8Om32WAX32VTwl2mdfW78u31r32RGqz6aoVUzl++yc2WfpVJ+dNy3pTJ9dsPb8Iuuz3+L6bJpaUwhemQR8r+Q8o9HS4xrNnkeLklNwZJM8UaM1w5F6XGq61jxP2motIBJdr5Y0Pb7ZuuYZzZYOzZYSz4k2m0PEMVbaLc+y2XqQU6hKraI6drnoENJMjND/+C4pKE7LH1dalqH1x7c2jsCo0oH6sabeYDg0tSbVNyNYwS53MIZH09kzWXAG1cQ58FRSe/N4Bx44asdTRu14wqgdTxe148midjxM1I4HidrbgaMWPt6M0O/RCmaGBmvxDM9wYFZQG5lnYwaGFuLeIRHUQovpWK3EKs4IHhV/Gs1QS5tJvvWt36gDoVXU1tRWhyrC5YGKSEgHBjjgZPxzxsZRK6+MYwbl0UbKVFEQqlNLDgN5ln67Xr7QXH2BjkBNpSOvNowXm5YXmBGKBKrw0+hH0kiotkabrQe35IOjpZijn2styqJsc8X52ry/zzUusMAqEEXUFqgeCrREv2WPguIx+T5/UX6xf0iav1a/uaMsMNtRFIgE60KBqnAUoi3FP7ZUZLQsy/SD7S1T7rYoyHLcBPlzghX1+NU3/ybQ7mFuoN0ruzhbu/tlwWiW2vrNhvqt1G/bU9Bg3lBdsCIS31+rJP21Gr/tCJIo4RqLaj7zt6lG/lqLODRHbXEayFfEcHH45iqtq8UjjR1mpxu9sl7UXhv0gx0lSRstSrJJ2GCb2QbbIr88W8Ct8nA0V20d55EvqOk3dvB1NP7SDgXNn7bdogruwW8pwvC9FrXbJ6zdfrZ2B6wuzFbtoFUgmq+2XgvI1+DE9SqZEawLYKNRgGOieh0nq2XCT1jU66SwXqfYep22ujBbrzNWgegGtfVaSL5ip9+yG10v/OmsLlipv5NGgo7aKY6yYKS+rka7KKqYzWuztbVISPCKa5boFdUsycvUrJH1pdmqadah6Ea1dbuJfJHPi+ezpzlK9V81tZXdtLb684QS4+t7+sNkONGelXXQDyR2K9U6RjO0TnS0AepiUbquwtKl4BuUpsFa0CK15pvBnKbfKUX4nl5Zr78h+gJVwbDWxytolL76wVai6HQLaoaQ2o+tZabFddkWGWAR1wj/VZLiawhHgtVpo2tCkQZf9KNDaG701+Pw2qrKYF2SfoVG3kAkYI9G4HH8zTzhcLB6clUDHrefYEtIbpIYu1fT/wMAAP//AwBQSwECLQAUAAAACACbgclaVW9SS7gwAQAwCgoAGABgAAAAAAAAAAAAAAAAAAAAQXNwZW5UZWNoLkFTV1hMLldvcmtib29rTlU4AE5VQ1gYAAAAQQBzAHAAZQBuAFQAZQBjAGgALgBBAFMAVwBYAEwALgBXAG8AcgBrAGIAbwBvAGsACgAgAAAAAAABABgAiK476w3Z2wGIrjvrDdnbAWPyOOsN2dsBUEsFBgAAAAABAAEApgAAADAxAQAfAEFTV1hMIFN0b3JhZ2UgVmVyc2lvbiA0MC4wLjAuMTA=

Sheet 20250531_220044_OilComponent
A1: PHENOLS | B1: PHENOL1 | C1: PHENOL2 | D1: PHENOL3 | E1: CYC-5A | F1: CYC-5A1 | G1: CYC-6A | H1: CYC-6A1 | I1: CYC-6A2 | J1: CYC-6A3 | K1: ARM-A | L1: ARM-A1 | M1: ARM-A2 | N1: ARM-B | O1: ARM-B1 | P1: ARM-B2 | Q1: TCC | R1: TOC | S1: TRC | T1: TPS | U1: TUC | V1: SAF | W1: MJSP | X1: LHV | Y1: SG | Z1: SLF | AA1: ARM | AB1: MBP | AC1: MFP | AD1: GT10 | AE1: GT90 | AF1: DFP | AG1: DT90 | AH1: ERRSIM | AI1: ERR_0 | AJ1: ERR_1 | AK1: ERR_2 | AL1: ERR_3 | AM1: ERR_4 | AN1: ERR_5 | AO1: ERR_6 | AP1: ERR_7 | AQ1: ERR_8 | AR1: ERR_9 | AS1: ERR_10 | AT1: ERR_11
A2: 2.2 | B2: 0 | C2: 0 | D2: 0 | E2: 1.8 | F2: 0 | G2: 2.4 | H2: 0 | I2: 0 | J2: 0 | K2: 3.5 | L2: 0 | M2: 0 | N2: 1.5 | O2: 0 | P2: 0 | Q2: 6.1109186e+08 | R2: 49299400 | S2: 79696219 | T2: 73515900 | U2: 17281811 | V2: 227.47874 | W2: 1.353722 | X2: 43.783633 | Y2: 782.84833 | Z2: 1.2598471e-16 | AA2: 23.544546 | AB2: 91.85 | AC2: -239.5006 | AD2: 62.893989 | AE2: 92.803696 | AF2: 165.7 | AG2: 236.22725 | AH2: 0 | AI2: 0 | AJ2: 0 | AK2: 0 | AL2: 0 | AM2: 0 | AN2: 0 | AO2: 0 | AP2: 0 | AQ2: 0 | AR2: 0 | AS2: 0 | AT2: 0
A3: 0 | B3: 3.06 | C3: 0 | D3: 0 | E3: 1.8 | F3: 0 | G3: 2.4 | H3: 0 | I3: 0 | J3: 0 | K3: 3.5 | L3: 0 | M3: 0 | N3: 1.5 | O3: 0 | P3: 0 | Q3: 6.1032985e+08 | R3: 49299400 | S3: 79696215 | T3: 73515900 | U3: 17273338 | V3: 218.84361 | W3: 1.4047733 | X3: 44.150003 | Y3: 789.4182 | Z3: 1.0925813e-18 | AA3: 20.496791 | AB3: 91.85 | AC3: -409.30686 | AD3: 62.770888 | AE3: 92.649087 | AF3: 144.29 | AG3: 225.61165 | AH3: 0 | AI3: 0 | AJ3: 0 | AK3: 0 | AL3: 0 | AM3: 0 | AN3: 0 | AO3: 0 | AP3: 0 | AQ3: 0 | AR3: 0 | AS3: 0 | AT3: 0
A4: 0 | B4: 0 | C4: 3 | D4: 0 | E4: 1.8 | F4: 0 | G4: 2.4 | H4: 0 | I4: 0 | J4: 0 | K4: 3.5 | L4: 0 | M4: 0 | N4: 1.5 | O4: 0 | P4: 0 | Q4: 6.1021388e+08 | R4: 49299400 | S4: 79696222 | T4: 73515900 | U4: 17276556 | V4: 226.35625 | W4: 1.3578019 | X4: 43.825054 | Y4: 784.40115 | Z4: 3.4208688e-17 | AA4: 22.567996 | AB4: 91.85 | AC4: -223.83348 | AD4: 62.712003 | AE4: 92.58961 | AF4: 165.7 | AG4: 240.08799 | AH4: 0 | AI4: 0 | AJ4: 0 | AK4: 0 | AL4: 0 | AM4: 0 | AN4: 0 | AO4: 0 | AP4: 0 | AQ4: 0 | AR4: 0 | AS4: 0 | AT4: 0
A5: 0 | B5: 0 | C5: 0 | D5: 2.14 | E5: 1.8 | F5: 0 | G5: 2.4 | H5: 0 | I5: 0 | J5: 0 | K5: 3.5 | L5: 0 | M5: 0 | N5: 1.5 | O5: 0 | P5: 0 | Q5: 6.1117432e+08 | R5: 49299400 | S5: 79696220 | T5: 73515900 | U5: 17282171 | V5: 227.76256 | W5: 1.3522808 | X5: 43.799328 | Y5: 783.02942 | Z5: 9.5818693e-17 | AA5: 23.631204 | AB5: 91.85 | AC5: -236.05295 | AD5: 62.84089 | AE5: 92.754747 | AF5: 165.7 | AG5: 248.14986 | AH5: 0 | AI5: 0 | AJ5: 0 | AK5: 0 | AL5: 0 | AM5: 0 | AN5: 0 | AO5: 0 | AP5: 0 | AQ5: 0 | AR5: 0 | AS5: 0 | AT5: 0
A6: 2.2 | B6: 0 | C6: 0 | D6: 0 | E6: 0 | F6: 2.1 | G6: 2.4 | H6: 0 | I6: 0 | J6: 0 | K6: 3.5 | L6: 0 | M6: 0 | N6: 1.5 | O6: 0 | P6: 0 | Q6: 6.1292992e+08 | R6: 49299400 | S6: 79696218 | T6: 73515900 | U6: 17292551 | V6: 229.94819 | W6: 1.3446104 | X6: 43.782389 | Y6: 782.81258 | Z6: 9.9353966e-17 | AA6: 23.233849 | AB6: 91.85 | AC6: -210.71554 | AD6: 60.201367 | AE6: 85.755318 | AF6: 165.7 | AG6: 236.54225 | AH6: 0 | AI6: 0 | AJ6: 0 | AK6: 0 | AL6: 0 | AM6: 0 | AN6: 0 | AO6: 0 | AP6: 0 | AQ6: 0 | AR6: 0 | AS6: 0 | AT6: 0
A7: 2.2 | B7: 0 | C7: 0 | D7: 0 | E7: 1.8 | F7: 0 | G7: 0 | H7: 2.06 | I7: 0 | J7: 0 | K7: 3.5 | L7: 0 | M7: 0 | N7: 1.5 | O7: 0 | P7: 0 | Q7: 6.1022226e+08 | R7: 49299400 | S7: 79696219 | T7: 73515900 | U7: 17277313 | V7: 221.47288 | W7: 1.3877664 | X7: 43.827521 | Y7: 781.96459 | Z7: 7.4077346e-17 | AA7: 23.640585 | AB7: 100.934 | AC7: -266.75403 | AD7: 66.160863 | AE7: 96.509472 | AF7: 165.7 | AG7: 234.27269 | AH7: 0 | AI7: 0 | AJ7: 0 | AK7: 0 | AL7: 0 | AM7: 0 | AN7: 0 | AO7: 0 | AP7: 0 | AQ7: 0 | AR7: 0 | AS7: 0 | AT7: 0
A8: 2.2 | B8: 0 | C8: 0 | D8: 0 | E8: 1.8 | F8: 0 | G8: 0 | H8: 0 | I8: 1.77 | J8: 0 | K8: 3.5 | L8: 0 | M8: 0 | N8: 1.5 | O8: 0 | P8: 0 | Q8: 6.106117e+08 | R8: 49299400 | S8: 79696219 | T8: 73515900 | U8: 17280254 | V8: 200.83185 | W8: 1.5317142 | X8: 43.989155 | Y8: 785.60619 | Z8: 4.5327332e-18 | AA8: 22.36114 | AB8: 100.934 | AC8: -201.55224 | AD8: 66.359557 | AE8: 97.480562 | AF8: 144.29 | AG8: 224.0432 | AH8: 0 | AI8: 0 | AJ8: 0 | AK8: 0 | AL8: 0 | AM8: 0 | AN8: 0 | AO8: 0 | AP8: 0 | AQ8: 0 | AR8: 0 | AS8: 0 | AT8: 0
A9: 2.2 | B9: 0 | C9: 0 | D9: 0 | E9: 1.8 | F9: 0 | G9: 0 | H9: 0 | I9: 0 | J9: 2.06 | K9: 3.5 | L9: 0 | M9: 0 | N9: 1.5 | O9: 0 | P9: 0 | Q9: 6.1055587e+08 | R9: 49299400 | S9: 79696217 | T9: 73515900 | U9: 17280901 | V9: 189.18952 | W9: 1.6257724 | X9: 44.093695 | Y9: 789.57451 | Z9: 1.9305737e-18 | AA9: 22.397373 | AB9: 100.934 | AC9: -431.52667 | AD9: 67.634517 | AE9: 98.073459 | AF9: 144.29 | AG9: 223.00542 | AH9: 0 | AI9: 0 | AJ9: 0 | AK9: 0 | AL9: 0 | AM9: 0 | AN9: 0 | AO9: 0 | AP9: 0 | AQ9: 0 | AR9: 0 | AS9: 0 | AT9: 0
A10: 2.2 | B10: 0 | C10: 0 | D10: 0 | E10: 1.8 | F10: 0 | G10: 2.4 | H10: 0 | I10: 0 | J10: 0 | K10: 0 | L10: 3.44 | M10: 0 | N10: 1.5 | O10: 0 | P10: 0 | Q10: 6.1136813e+08 | R10: 49299400 | S10: 79696219 | T10: 73515900 | U10: 17284392 | V10: 223.48124 | W10: 1.3787757 | X10: 44.847495 | Y10: 795.87606 | Z10: 1.0528969e-16 | AA10: 7.9858759 | AB10: 91.85 | AC10: -266.61469 | AD10: 62.913751 | AE10: 92.770769 | AF10: 165.7 | AG10: 236.04358 | AH10: 0 | AI10: 0 | AJ10: 0 | AK10: 0 | AL10: 0 | AM10: 0 | AN10: 0.017655162 | AO10: 0 | AP10: 0 | AQ10: 0 | AR10: 0 | AS10: 0 | AT10: 0
A11: 2.2 | B11: 0 | C11: 0 | D11: 0 | E11: 1.8 | F11: 0 | G11: 2.4 | H11: 0 | I11: 0 | J11: 0 | K11: 0 | L11: 0 | M11: 2.69 | N11: 1.5 | O11: 0 | P11: 0 | Q11: 6.1319854e+08 | R11: 49299400 | S11: 79696222 | T11: 73515900 | U11: 17297885 | V11: 221.6161 | W11: 1.3959866 | X11: 44.083419 | Y11: 785.88391 | Z11: 2.5749648e-15 | AA11: 9.2745358 | AB11: 91.85 | AC11: -253.98815 | AD11: 64.194233 | AE11: 92.892523 | AF11: 165.7 | AG11: 229.03933 | AH11: 0 | AI11: 0 | AJ11: 0 | AK11: 0 | AL11: 0 | AM11: 0 | AN11: 0 | AO11: 0 | AP11: 0 | AQ11: 0 | AR11: 0 | AS11: 0 | AT11: 0
A12: 2.2 | B12: 0 | C12: 0 | D12: 0 | E12: 1.8 | F12: 0 | G12: 2.4 | H12: 0 | I12: 0 | J12: 0 | K12: 3.5 | L12: 0 | M12: 0 | N12: 0 | O12: 1.24 | P12: 0 | Q12: 6.1168221e+08 | R12: 49299400 | S12: 79696219 | T12: 73515900 | U12: 17284051 | V12: 224.9303 | W12: 1.3708412 | X12: 43.627156 | Y12: 778.5875 | Z12: 1.1092455e-15 | AA12: 19.328862 | AB12: 91.85 | AC12: -238.8943 | AD12: 62.863346 | AE12: 92.780075 | AF12: 165.7 | AG12: 233.45594 | AH12: 0 | AI12: 0 | AJ12: 0 | AK12: 0 | AL12: 0 | AM12: 0 | AN12: 0 | AO12: 0 | AP12: 0 | AQ12: 0 | AR12: 0 | AS12: 0 | AT12: 0
A13: 2.2 | B13: 0 | C13: 0 | D13: 0 | E13: 1.8 | F13: 0 | G13: 2.4 | H13: 0 | I13: 0 | J13: 0 | K13: 3.5 | L13: 0 | M13: 0 | N13: 0 | O13: 0 | P13: 1.3 | Q13: 6.1161518e+08 | R13: 49299400 | S13: 79696219 | T13: 73515900 | U13: 17283468 | V13: 226.27121 | W13: 1.3625163 | X13: 43.608097 | Y13: 779.54591 | Z13: 1.0407078e-15 | AA13: 19.207163 | AB13: 91.85 | AC13: -238.80564 | AD13: 62.840801 | AE13: 92.759473 | AF13: 165.7 | AG13: 231.17584 | AH13: 0 | AI13: 0 | AJ13: 0 | AK13: 0 | AL13: 0 | AM13: 0 | AN13: 0 | AO13: 0 | AP13: 0 | AQ13: 0 | AR13: 0 | AS13: 0 | AT13: 0
U15: MIN | V15: =MIN(V3:V13) -> 189.18952 | X15: =MIN(X3:X13) -> 43.608097 | Y15: =MIN(Y3:Y13) -> 778.5875 | Z15: =MIN(Z3:Z13) -> 1.0925813e-18 | AA15: =MIN(AA3:AA13) -> 7.9858759 | AB15: =MIN(AB3:AB13) -> 91.85 | AC15: =MIN(AC3:AC13) -> -431.52667 | AD15: =MIN(AD3:AD13) -> 60.201367 | AE15: =MIN(AE3:AE13) -> 85.755318 | ... AG15: =MIN(AG3:AG13) -> 223.00542
U16: MAX | V16: =MAX(V3:V13) -> 229.94819 | X16: =MAX(X3:X13) -> 44.847495 | Y16: =MAX(Y3:Y13) -> 795.87606 | Z16: =MAX(Z3:Z13) -> 2.5749648e-15 | AA16: =MAX(AA3:AA13) -> 23.640585 | AB16: =MAX(AB3:AB13) -> 100.934 | AC16: =MAX(AC3:AC13) -> -201.55224 | AD16: =MAX(AD3:AD13) -> 67.634517 | AE16: =MAX(AE3:AE13) -> 98.073459 | ... AG16: =MAX(AG3:AG13) -> 248.14986
U18: LOWER | V18: =V15-V$2 -> -38.289215 | X18: =X15-X$2 -> -0.1755358 | Y18: =Y15-Y$2 -> -4.260834 | Z18: =Z15-Z$2 -> -1.2489213e-16 | AA18: =AA15-AA$2 -> -15.55867 | AB18: =AB15-AB$2 -> 0 | AC18: =AC15-AC$2 -> -192.02607 | AD18: =AD15-AD$2 -> -2.6926223 | AE18: =AE15-AE$2 -> -7.0483781 | ... AG18: =AG15-AG$2 -> -13.221822
U19: HIGHER | V19: =V16-V$2 -> 2.469459 | X19: =X16-X$2 -> 1.0638621 | Y19: =Y16-Y$2 -> 13.02773 | Z19: =Z16-Z$2 -> 2.4489801e-15 | AA19: =AA16-AA$2 -> 0.096039189 | AB19: =AB16-AB$2 -> 9.084 | AC19: =AC16-AC$2 -> 37.948366 | AD19: =AD16-AD$2 -> 4.7405273 | AE19: =AE16-AE$2 -> 5.2697622 | ... AG19: =AG16-AG$2 -> 11.922619
U21: AVERAGE | V21: =AVERAGE(V2:V13) -> 219.84854 | X21: =AVERAGE(X2:X13) -> 43.951412 | Y21: =AVERAGE(Y2:Y13) -> 784.96236 | Z21: =AVERAGE(Z2:Z13) -> 4.3893392e-16 | AA21: =AVERAGE(AA2:AA13) -> 19.805827 | AB21: =AVERAGE(AB2:AB13) -> 94.121 | AC21: =AVERAGE(AC2:AC13) -> -268.12876 | AD21: =AVERAGE(AD2:AD13) -> 63.69885 | AE21: =AVERAGE(AE2:AE13) -> 93.318233 | ... AG21: =AVERAGE(AG2:AG13) -> 233.13792

Sheet 20250531_223825_Grid
A1: PYROTEMP | B1: GAS.N | C1: GAS.F | D1: GAS.RR | E1: SAF.N | F1: SAF.F | G1: SAF.RR | H1: DSL.N | I1: DSL.F | J1: DSL.RR | K1: TCC | L1: TOC | M1: TRC | N1: TPS | O1: TUC | P1: SAF | Q1: MJSP | R1: LHV | S1: SG | T1: SLF | U1: ARM | V1: MBP | W1: MFP | X1: GT10 | Y1: GT90 | Z1: DFP | AA1: DT90 | AB1: ERRSIM | AC1: ERR_0 | AD1: ERR_1 | AE1: ERR_2 | AF1: ERR_3 | AG1: ERR_4 | AH1: ERR_5 | AI1: ERR_6 | AJ1: ERR_7 | AK1: ERR_8 | AL1: ERR_9 | AM1: ERR_10 | AN1: ERR_11
A2: 930 | B2: 30 | C2: 15 | D2: 2.95 | E2: 20 | F2: 12 | G2: 0.56748 | H2: 20 | I2: 12 | J2: 1.4 | K2: 6.1161518e+08 | L2: 49299400 | M2: 79696219 | N2: 73515900 | O2: 17283468 | P2: 226.27121 | Q2: 1.3625163 | R2: 43.608097 | S2: 779.54591 | T2: 1.0407078e-15 | U2: 19.207163 | V2: 91.85 | W2: -238.80564 | X2: 62.840801 | Y2: 92.759473 | Z2: 165.7 | AA2: 231.17584 | AB2: 0 | AC2: 0 | AD2: 0 | AE2: 0 | AF2: 0 | AG2: 0 | AH2: 5.491046 | AI2: 0 | AJ2: 0 | AK2: 0 | AL2: 0 | AM2: 0 | AN2: 0
A3: 930 | B3: 30 | C3: 15 | D3: 2.95 | E3: 20 | F3: 12 | G3: 0.56748 | H3: 20 | I3: 12 | J3: 1.4 | K3: 6.1161518e+08 | L3: 49299400 | M3: 79696219 | N3: 73515900 | O3: 15885038 | P3: 226.27121 | Q3: 1.3625163 | R3: 43.608097 | S3: 779.54591 | T3: 1.0407078e-15 | U3: 19.207163 | V3: 91.85 | W3: -238.80564 | X3: 62.840801 | Y3: 92.759473 | Z3: 165.7 | AA3: 231.17584 | AB3: 99 | AC3: 0 | AD3: 0 | AE3: 0 | AF3: 0 | AG3: 0 | AH3: 5.491046 | AI3: 0 | AJ3: 0 | AK3: 0 | AL3: 0 | AM3: 0 | AN3: 0
A4: 930 | B4: 30 | C4: 15 | D4: 2.95 | E4: 20 | F4: 12 | G4: 0.56748 | H4: 20 | I4: 12 | J4: 0.7 | K4: 5.8337241e+08 | L4: 50126300 | M4: 79694719 | N4: 71705400 | O4: 15885038 | P4: 226.28026 | Q4: 1.3291829 | R4: 43.608097 | S4: 779.54344 | T4: 1.0405959e-15 | U4: 19.206405 | V4: 91.85 | W4: -238.82056 | X4: 62.841637 | Y4: 92.759895 | Z4: 165.7 | AA4: 232.05796 | AB4: 0 | AC4: 0 | AD4: 0 | AE4: 0 | AF4: 0 | AG4: 0 | AH4: 5.491994 | AI4: 0 | AJ4: 0 | AK4: 0 | AL4: 0 | AM4: 0 | AN4: 0
A5: 910 | B5: 30 | C5: 15 | D5: 2.95 | E5: 20 | F5: 12 | G5: 0.56748 | H5: 20 | I5: 12 | J5: 1.4 | K5: 5.8317356e+08 | L5: 50218400 | M5: 79674146 | N5: 71200300 | O5: 15890480 | P5: 224.98823 | Q5: 1.3479332 | R5: 43.608513 | S5: 779.51119 | T5: 1.0467246e-15 | U5: 19.201057 | V5: 91.85 | W5: -238.6967 | X5: 62.86712 | Y5: 92.770307 | Z5: 165.7 | AA5: 231.1767 | AB5: 0 | AC5: 0 | AD5: 0 | AE5: 0 | AF5: 0 | AG5: 0 | AH5: 5.4986785 | AI5: 0 | AJ5: 0 | AK5: 0 | AL5: 0 | AM5: 0 | AN5: 0
A6: 915 | B6: 30 | C6: 15 | D6: 2.95 | E6: 20 | F6: 12 | G6: 0.56748 | H6: 20 | I6: 12 | J6: 1.4 | K6: 5.8333011e+08 | L6: 50224700 | M6: 79680038 | N6: 71333200 | O6: 15890348 | P6: 225.35302 | Q6: 1.3437429 | R6: 43.608394 | S6: 779.52111 | T6: 1.0450046e-15 | U6: 19.202834 | V6: 91.85 | W6: -238.72859 | X6: 62.859629 | Y6: 92.76722 | Z6: 165.7 | AA6: 231.17645 | AB6: 0 | AC6: 0 | AD6: 0 | AE6: 0 | AF6: 0 | AG6: 0 | AH6: 5.4964569 | AI6: 0 | AJ6: 0 | AK6: 0 | AL6: 0 | AM6: 0 | AN6: 0
A7: 920 | B7: 30 | C7: 15 | D7: 2.95 | E7: 20 | F7: 12 | G7: 0.56748 | H7: 20 | I7: 12 | J7: 1.4 | K7: 5.8329352e+08 | L7: 50345900 | M7: 79686030 | N7: 71468900 | O7: 15892966 | P7: 225.72636 | Q7: 1.3411268 | R7: 43.608273 | S7: 779.53127 | T7: 1.0432256e-15 | U7: 19.204589 | V7: 91.85 | W7: -238.75682 | X7: 62.851832 | Y7: 92.76401 | Z7: 165.7 | AA7: 231.1762 | AB7: 0 | AC7: 0 | AD7: 0 | AE7: 0 | AF7: 0 | AG7: 0 | AH7: 5.4942638 | AI7: 0 | AJ7: 0 | AK7: 0 | AL7: 0 | AM7: 0 | AN7: 0
A8: 925 | B8: 30 | C8: 15 | D8: 2.95 | E8: 20 | F8: 12 | G8: 0.56748 | H8: 20 | I8: 12 | J8: 1.4 | K8: 5.8296965e+08 | L8: 50348700 | M8: 79688627 | N8: 71528500 | O8: 15883165 | P8: 225.88994 | Q8: 1.3380723 | R8: 43.608222 | S8: 779.53549 | T8: 1.0425018e-15 | U8: 19.20536 | V8: 91.85 | W8: -238.77223 | X8: 62.848628 | Y8: 92.762671 | Z8: 165.7 | AA8: 231.1762 | AB8: 0 | AC8: 0 | AD8: 0 | AE8: 0 | AF8: 0 | AG8: 0 | AH8: 5.4932997 | AI8: 0 | AJ8: 0 | AK8: 0 | AL8: 0 | AM8: 0 | AN8: 0
A9: 930 | B9: 30 | C9: 15 | D9: 2.95 | E9: 20 | F9: 12 | G9: 0.56748 | H9: 20 | I9: 12 | J9: 1.4 | K9: 5.8342518e+08 | L9: 50125800 | M9: 79694719 | N9: 71667300 | O9: 15885038 | P9: 226.27121 | Q9: 1.3301279 | R9: 43.608097 | S9: 779.54591 | T9: 1.0407078e-15 | U9: 19.207163 | V9: 91.85 | W9: -238.80564 | X9: 62.840801 | Y9: 92.759473 | Z9: 165.7 | AA9: 231.17584 | AB9: 0 | AC9: 0 | AD9: 0 | AE9: 0 | AF9: 0 | AG9: 0 | AH9: 5.491046 | AI9: 0 | AJ9: 0 | AK9: 0 | AL9: 0 | AM9: 0 | AN9: 0
A10: 935 | B10: 30 | C10: 15 | D10: 2.95 | E10: 20 | F10: 12 | G10: 0.56748 | H10: 20 | I10: 12 | J10: 1.4 | K10: 5.8369341e+08 | L10: 50125800 | M10: 79694709 | N10: 71667300 | O10: 15888926 | P10: 226.80973 | Q10: 1.3277726 | R10: 43.607933 | S10: 779.55907 | T10: 1.0383002e-15 | U10: 19.209976 | V10: 91.85 | W10: -238.85192 | X10: 62.829986 | Y10: 92.755045 | Z10: 165.7 | AA10: 231.17554 | AB10: 100 | AC10: 0 | AD10: 0 | AE10: 0 | AF10: 0 | AG10: 0 | AH10: 5.4875299 | AI10: 0 | AJ10: 0 | AK10: 0 | AL10: 0 | AM10: 0 | AN10: 0
A11: 940 | B11: 30 | C11: 15 | D11: 2.95 | E11: 20 | F11: 12 | G11: 0.56748 | H11: 20 | I11: 12 | J11: 1.4 | K11: 5.8355473e+08 | L11: 50150800 | M11: 79707302 | N11: 71953500 | O11: 15889686 | P11: 227.05774 | Q11: 1.3208296 | R11: 43.607837 | S11: 779.56754 | T11: 1.0370076e-15 | U11: 19.210819 | V11: 91.85 | W11: -238.87539 | X11: 62.825009 | Y11: 92.752925 | Z11: 165.7 | AA11: 231.17554 | AB11: 0 | AC11: 0 | AD11: 0 | AE11: 0 | AF11: 0 | AG11: 0 | AH11: 5.4864767 | AI11: 0 | AJ11: 0 | AK11: 0 | AL11: 0 | AM11: 0 | AN11: 0
A12: 945 | B12: 30 | C12: 15 | D12: 2.95 | E12: 20 | F12: 12 | G12: 0.56748 | H12: 20 | I12: 12 | J12: 1.4 | K12: 5.8161796e+08 | L12: 50239400 | M12: 79713794 | N12: 72101300 | O12: 15892403 | P12: 227.46274 | Q12: 1.3115487 | R12: 43.607701 | S12: 779.57881 | T12: 1.0351314e-15 | U12: 19.212742 | V12: 91.85 | W12: -238.91914 | X12: 62.816919 | Y12: 92.749678 | Z12: 165.7 | AA12: 231.17504 | AB12: 0 | AC12: 0 | AD12: 0 | AE12: 0 | AF12: 0 | AG12: 0 | AH12: 5.4840719 | AI12: 0 | AJ12: 0 | AK12: 0 | AL12: 0 | AM12: 0 | AN12: 0
A13: 950 | B13: 30 | C13: 15 | D13: 2.95 | E13: 20 | F13: 12 | G13: 0.56748 | H13: 20 | I13: 12 | J13: 1.4 | K13: 5.8176236e+08 | L13: 50246500 | M13: 79720385 | N13: 72251900 | O13: 15895414 | P13: 227.87759 | Q13: 1.3068114 | R13: 43.607562 | S13: 779.59033 | T13: 1.0331681e-15 | U13: 19.214579 | V13: 91.85 | W13: -238.95343 | X13: 62.808644 | Y13: 92.746222 | Z13: 165.7 | AA13: 231.17477 | AB13: 0 | AC13: 0 | AD13: 0 | AE13: 0 | AF13: 0 | AG13: 0 | AH13: 5.4817766 | AI13: 0 | AJ13: 0 | AK13: 0 | AL13: 0 | AM13: 0 | AN13: 0
... A114: 930 | B114: 30 | C114: 15 | D114: 2.95 | E114: 20 | F114: 12 | G114: 0.56748 | H114: 20 | I114: 12 | J114: 1.4 | K114: 5.8342528e+08 | L114: 50125800 | M114: 79694719 | N114: 71667300 | O114: 15885042 | P114: 226.27121 | Q114: 1.3301282 | R114: 43.608134 | S114: 779.54574 | T114: 1.0407078e-15 | U114: 19.207163 | V114: 91.85 | W114: -238.8056 | X114: 62.840859 | Y114: 92.759473 | Z114: 165.7 | AA114: 231.17584 | AB114: 0 | AC114: 0 | AD114: 0 | AE114: 0 | AF114: 0 | AG114: 0 | AH114: 5.491046 | AI114: 0 | AJ114: 0 | AK114: 0 | AL114: 0 | AM114: 0 | AN114: 0

Sheet 20250602_153217_ARMB2
A1: PYROTEMP | B1: GAS.N | C1: GAS.F | D1: GAS.RR | E1: SAF.N | F1: SAF.F | G1: SAF.RR | H1: DSL.N | I1: DSL.F | J1: DSL.RR | K1: TCC | L1: TOC | M1: TRC | N1: TPS | O1: TUC | P1: SAF | Q1: MJSP | R1: LHV | S1: SG | T1: SLF | U1: ARM | V1: MBP | W1: MFP | X1: GT10 | Y1: GT90 | Z1: DFP | AA1: DT90 | AB1: ERRSIM | AC1: ERR_0 | AD1: ERR_1 | AE1: ERR_2 | AF1: ERR_3 | AG1: ERR_4 | AH1: ERR_5 | AI1: ERR_6 | AJ1: ERR_7 | AK1: ERR_8 | AL1: ERR_9 | AM1: ERR_10 | AN1: ERR_11 | AO1: OBJ
A2: 930 | B2: 30 | C2: 15 | D2: 2.95 | E2: 20 | F2: 12 | G2: 0.56748 | H2: 20 | I2: 12 | J2: 0.7 | K2: 5.0914037e+08 | L2: 54446000 | M2: 79696319 | N2: 72467800 | O2: 15885037 | P2: 211.10034 | Q2: 1.2604347 | R2: 43.608139 | S2: 779.54344 | T2: 1.0405959e-15 | U2: 19.206405 | V2: 91.85 | W2: -238.82056 | X2: 62.841637 | Y2: 92.759895 | Z2: 165.7 | AA2: 232.05796 | AB2: 0 | AC2: 0 | AD2: 0 | AE2: 0 | AF2: 0 | AG2: 0 | AH2: 0 | AI2: 0 | AJ2: 0 | AK2: 0 | AL2: 0 | AM2: 0 | AN2: 0 | AO2: 1.2604347
A3: 930 | B3: 30 | C3: 18 | D3: 2.95 | E3: 20 | F3: 12 | G3: 0.56748 | H3: 20 | I3: 12 | J3: 1.4 | K3: 5.0914445e+08 | L3: 54446000 | M3: 79696319 | N3: 72467800 | O3: 15885037 | P3: 211.03787 | Q3: 1.2608209 | R3: 43.610077 | S3: 779.51589 | T3: 1.4472486e-13 | U3: 19.210471 | V3: 91.85 | W3: -240.1279 | X3: 62.839121 | Y3: 92.781455 | Z3: 165.7 | AA3: 231.15929 | AB3: 0 | AC3: 0 | AD3: 0 | AE3: 0 | AF3: 0 | AG3: 0 | AH3: 0 | AI3: 0 | AJ3: 0 | AK3: 0 | AL3: 0 | AM3: 0 | AN3: 0 | AO3: 1.2608209
A4: 929.70681 | B4: 28 | C4: 11 | D4: 13.257009 | E4: 22 | F4: 12 | G4: 1.0178085 | H4: 23 | I4: 7 | J4: 0.76814446 | K4: 5.0912712e+08 | L4: 54446000 | M4: 79696319 | N4: 72467800 | O4: 15890355 | P4: 210.72776 | Q4: 1.2626205 | R4: 43.633308 | S4: 780.45328 | T4: 2.0755048e-16 | U4: 19.159813 | V4: 100.934 | W4: -238.48124 | X4: 62.839121 | Y4: 92.400305 | Z4: 180.981 | AA4: 231.77212 | AB4: 0 | AC4: 0 | AD4: 0 | AE4: 0 | AF4: 0 | AG4: 0 | AH4: 0 | AI4: 0 | AJ4: 0 | AK4: 0 | AL4: 0 | AM4: 0 | AN4: 0 | AO4: 1.2626205
A5: 913.60997 | B5: 29 | C5: 14 | D5: 6.3682909 | E5: 11 | F5: 7 | G5: 0.56912727 | H5: 15 | I5: 9 | J5: 1.2187978 | K5: 5.0870496e+08 | L5: 54446000 | M5: 79696340 | N5: 72467800 | O5: 15893065 | P5: 210.69416 | Q5: 1.2614616 | R5: 43.533587 | S5: 779.84217 | T5: 3.7488732e-11 | U5: 19.17889 | V5: 100.934 | W5: -240.96826 | X5: 62.863817 | Y5: 92.515186 | Z5: 144.29 | AA5: 230.52684 | AB5: 0 | AC5: 0 | AD5: 0 | AE5: 0 | AF5: 0 | AG5: 0 | AH5: 0 | AI5: 0 | AJ5: 0 | AK5: 0 | AL5: 0 | AM5: 0 | AN5: 0 | AO5: 1.2614616
A6: 936.28459 | B6: 30 | C6: 15 | D6: 1.3001992 | E6: 20 | F6: 10 | G6: 0.62900786 | H6: 16 | I6: 12 | J6: 0.31449754 | K6: 5.0938467e+08 | L6: 54446000 | M6: 79696317 | N6: 72467800 | O6: 15889363 | P6: 209.74936 | Q6: 1.2693437 | R6: 43.598643 | S6: 780.10771 | T6: 1.5714406e-13 | U6: 19.373141 | V6: 80.72 | W6: -192.44718 | X6: 62.910995 | Y6: 93.763288 | Z6: 177.97 | AA6: 234.84288 | AB6: 0 | AC6: 0 | AD6: 0 | AE6: 0 | AF6: 0 | AG6: 0 | AH6: 0 | AI6: 0 | AJ6: 0 | AK6: 0 | AL6: 0 | AM6: 0 | AN6: 0 | AO6: 1.2693437
A7: 927.35464 | B7: 38 | C7: 17 | D7: 1.4975434 | E7: 11 | F7: 8 | G7: 0.65045696 | H7: 29 | I7: 13 | J7: 1.1992389 | K7: 5.0913621e+08 | L7: 54446000 | M7: 79696323 | N7: 72467800 | O7: 15882487 | P7: 211.33979 | Q7: 1.2589932 | R7: 43.479956 | S7: 780.11858 | T7: 4.5277777e-12 | U7: 19.036863 | V7: 91.85 | W7: -221.93477 | X7: 62.885856 | Y7: 93.388223 | Z7: 121.522 | AA7: 229.43062 | AB7: 0 | AC7: 0 | AD7: 0 | AE7: 0 | AF7: 0 | AG7: 0 | AH7: 0 | AI7: 0 | AJ7: 0 | AK7: 0 | AL7: 0 | AM7: 0 | AN7: 0 | AO7: 1.2589932
A8: 937.13606 | B8: 30 | C8: 16 | D8: 7.2741048 | E8: 11 | F8: 9 | G8: 0.48955232 | H8: 14 | I8: 12 | J8: 1.2804189 | K8: 5.0960928e+08 | L8: 54446000 | M8: 79696307 | N8: 72467800 | O8: 15891052 | P8: 213.87875 | Q8: 1.2455492 | R8: 43.386391 | S8: 780.85565 | T8: 2.1436833e-12 | U8: 18.758924 | V8: 100.934 | W8: -242.21207 | X8: 62.887363 | Y8: 92.482934 | Z8: 100.934 | AA8: 229.06872 | AB8: 0 | AC8: 0 | AD8: 0 | AE8: 0 | AF8: 0 | AG8: 0 | AH8: 0 | AI8: 0 | AJ8: 0 | AK8: 0 | AL8: 0 | AM8: 0 | AN8: 0 | AO8: 1.2455492
A9: 946.40393 | B9: 35 | C9: 19 | D9: 13.873458 | E9: 21 | F9: 9 | G9: 0.84561692 | H9: 19 | I9: 9 | J9: 0.34263791 | K9: 5.0976836e+08 | L9: 54446000 | M9: 79696295 | N9: 72467800 | O9: 15899842 | P9: 211.85266 | Q9: 1.257971 | R9: 43.634921 | S9: 780.20696 | T9: 1.4631512e-13 | U9: 19.238618 | V9: 100.934 | W9: -237.96593 | X9: 62.791274 | Y9: 92.183945 | Z9: 180.981 | AA9: 234.85277 | AB9: 0 | AC9: 0 | AD9: 0 | AE9: 0 | AF9: 0 | AG9: 0 | AH9: 0 | AI9: 0 | AJ9: 0 | AK9: 0 | AL9: 0 | AM9: 0 | AN9: 0 | AO9: 1.257971
A10: 938.97606 | B10: 35 | C10: 10 | D10: 11.22367 | E10: 21 | F10: 8 | G10: 1.0130961 | H10: 19 | I10: 14 | J10: 0.31754123 | K10: 5.094825e+08 | L10: 54446000 | M10: 79696311 | N10: 72467800 | O10: 15895347 | P10: 211.16565 | Q10: 1.2611447 | R10: 43.636833 | S10: 780.38728 | T10: 8.6873786e-13 | U10: 19.245543 | V10: 100.934 | W10: -237.3795 | X10: 62.79814 | Y10: 92.22705 | Z10: 180.981 | AA10: 236.50972 | AB10: 0 | AC10: 0 | AD10: 0 | AE10: 0 | AF10: 0 | AG10: 0 | AH10: 0 | AI10: 0 | AJ10: 0 | AK10: 0 | AL10: 0 | AM10: 0 | AN10: 0 | AO10: 1.2611447
A11: 913.57289 | B11: 29 | C11: 18 | D11: 9.5132499 | E11: 26 | F11: 8 | G11: 0.65913835 | H11: 25 | I11: 11 | J11: 1.2401972 | K11: 5.086296e+08 | L11: 54446000 | M11: 79696340 | N11: 72467800 | O11: 15894689 | P11: 209.8708 | Q11: 1.2661668 | R11: 43.641066 | S11: 779.94208 | T11: 1.860662e-12 | U11: 19.274651 | V11: 100.934 | W11: -238.13844 | X11: 62.859214 | Y11: 92.448509 | Z11: 180.981 | AA11: 231.08111 | AB11: 0 | AC11: 0 | AD11: 0 | AE11: 0 | AF11: 0 | AG11: 0 | AH11: 0 | AI11: 0 | AJ11: 0 | AK11: 0 | AL11: 0 | AM11: 0 | AN11: 0 | AO11: 1.2661668
A12: 922.62289 | B12: 39 | C12: 10 | D12: 6.9349656 | E12: 12 | F12: 8 | G12: 0.99531677 | H12: 29 | I12: 9 | J12: 1.1172475 | K12: 5.0900398e+08 | L12: 54446000 | M12: 79696326 | N12: 72467800 | O12: 15895779 | P12: 210.96269 | Q12: 1.2608182 | R12: 43.576182 | S12: 779.88448 | T12: 1.6306622e-12 | U12: 19.139383 | V12: 100.934 | W12: -238.96426 | X12: 62.84723 | Y12: 92.297486 | Z12: 144.29 | AA12: 230.54622 | AB12: 0 | AC12: 0 | AD12: 0 | AE12: 0 | AF12: 0 | AG12: 0 | AH12: 0 | AI12: 0 | AJ12: 0 | AK12: 0 | AL12: 0 | AM12: 0 | AN12: 0 | AO12: 1.2608182
A13: 946.31511 | B13: 34 | C13: 12 | D13: 2.5897835 | E13: 19 | F13: 7 | G13: 0.90411706 | H13: 27 | I13: 10 | J13: 1.1864197 | K13: 5.0977031e+08 | L13: 54446000 | M13: 79696291 | N13: 72467800 | O13: 15892980 | P13: 211.99153 | Q13: 1.2571532 | R13: 43.632539 | S13: 780.14213 | T13: 9.3568926e-12 | U13: 19.276677 | V13: 100.934 | W13: -234.98236 | X13: 62.820434 | Y13: 92.811857 | Z13: 180.981 | AA13: 230.97029 | AB13: 0 | AC13: 0 | AD13: 0 | AE13: 0 | AF13: 0 | AG13: 0 | AH13: 0 | AI13: 0 | AJ13: 0 | AK13: 0 | AL13: 0 | AM13: 0 | AN13: 0 | AO13: 1.2571532
... A292: 910 | B292: 27 | C292: 14 | D292: 15 | E292: 20 | F292: 7 | G292: 0.3 | H292: 21 | I292: 7 | J292: 1.4 | K292: 5.1044374e+08 | L292: 54439500 | M292: 79674346 | N292: 71401900 | O292: 15896750 | P292: 209.608 | Q292: 1.2959407 | R292: 43.643603 | S292: 780.0761 | T292: 1.2726243e-10 | U292: 19.696266 | V292: 100.934 | W292: -238.69325 | X292: 62.864678 | Y292: 92.427785 | Z292: 177.97 | AA292: 231.31864 | AB292: 0 | AC292: 0 | AD292: 0 | AE292: 0 | AF292: 0 | AG292: 0 | AH292: 0 | AI292: 0 | AJ292: 0 | AK292: 0 | AL292: 0 | AM292: 0 | AN292: 0 | AO292: 1.2959407

Sheet 20250603_135559_BO_SEP
A1: PYROTEMP | B1: GAS.N | C1: GAS.F | D1: GAS.RR | E1: SAF.N | F1: SAF.F | G1: SAF.RR | H1: DSL.N | I1: DSL.F | J1: DSL.RR | K1: TCC | L1: TOC | M1: TRC | N1: TPS | O1: TUC | P1: SAF | Q1: MJSP | R1: LHV | S1: SG | T1: SLF | U1: ARM | V1: MBP | W1: MFP | X1: GT10 | Y1: GT90 | Z1: DFP | AA1: DT90 | AB1: ERRSIM | AC1: ERR_0 | AD1: ERR_1 | AE1: ERR_2 | AF1: ERR_3 | AG1: ERR_4 | AH1: ERR_5 | AI1: ERR_6 | AJ1: ERR_7 | AK1: ERR_8 | AL1: ERR_9 | AM1: ERR_10 | AN1: ERR_11 | AO1: OBJ
A2: 930 | B2: 30 | C2: 18 | D2: 2.95 | E2: 20 | F2: 12 | G2: 0.56748 | H2: 20 | I2: 12 | J2: 1.4 | K2: 5.0816602e+08 | L2: 54419900 | M2: 79688419 | N2: 73518900 | O2: 15884331 | P2: 211.77717 | Q2: 1.2308296 | R2: 43.784978 | S2: 782.81606 | T2: 1.4197116e-13 | U2: 23.54101 | V2: 91.85 | W2: -240.83121 | X2: 62.892317 | Y2: 92.825612 | Z2: 165.7 | AA2: 236.15088 | AB2: 0 | AC2: 0 | AD2: 0 | AE2: 0 | AF2: 0 | AG2: 0 | AH2: 0 | AI2: 0 | AJ2: 0 | AK2: 0 | AL2: 0 | AM2: 0 | AN2: 0 | AO2: 1.2308296
A3: 958.19893 | B3: 30 | C3: 18 | D3: 13.51033 | E3: 26 | F3: 12 | G3: 1.1830322 | H3: 15 | I3: 12 | J3: 1.3838869 | K3: 5.0360135e+08 | L3: 54419900 | M3: 79688505 | N3: 73518900 | O3: 16382713 | P3: 204.42933 | Q3: 1.2599115 | R3: 43.936531 | S3: 783.52019 | T3: 1.0593881e-18 | U3: 24.993105 | V3: 100.934 | W3: -234.45896 | X3: 62.947321 | Y3: 92.412746 | Z3: 180.981 | AA3: 254.31637 | AB3: 100 | AC3: 0 | AD3: 0 | AE3: 0 | AF3: 0 | AG3: 0 | AH3: 0 | AI3: 0 | AJ3: 0 | AK3: 0 | AL3: 0 | AM3: 0 | AN3: 0 | AO3: 101.25991
A4: 919.87192 | B4: 28 | C4: 17 | D4: 3.0957245 | E4: 22 | F4: 13 | G4: 0.80041561 | H4: 21 | I4: 8 | J4: 0.52990854 | K4: 342709000 | L4: 54419900 | M4: 79654400 | N4: 73518900 | O4: 0 | P4: 0 | Q4: 100 | R4: 0 | S4: 0 | T4: 0 | U4: 0 | V4: 0 | W4: 0 | X4: 0 | Y4: 0 | Z4: 0 | AA4: 0 | AB4: 99 | AC4: 100 | AD4: 0 | AE4: 0 | AF4: 0 | AG4: 0 | AH4: 0 | AI4: 0 | AJ4: 0 | AK4: 0 | AL4: 0 | AM4: 0 | AN4: 0 | AO4: 299
A5: 928.08617 | B5: 31 | C5: 19 | D5: 3.918495 | E5: 21 | F5: 11 | G5: 0.46561985 | H5: 13 | I5: 11 | J5: 1.2231087 | K5: 5.0806784e+08 | L5: 54416600 | M5: 79686222 | N5: 73366400 | O5: 15884295 | P5: 212.08872 | Q5: 1.2318127 | R5: 43.766419 | S5: 782.28321 | T5: 6.1531369e-14 | U5: 23.276642 | V5: 91.85 | W5: -240.32629 | X5: 62.906775 | Y5: 92.706408 | Z5: 177.97 | AA5: 237.73255 | AB5: 0 | AC5: 0 | AD5: 0 | AE5: 0 | AF5: 0 | AG5: 0 | AH5: 0 | AI5: 0 | AJ5: 0 | AK5: 0 | AL5: 0 | AM5: 0 | AN5: 0 | AO5: 1.2318127
A6: 946.1991 | B6: 35 | C6: 17 | D6: 11.313189 | E6: 15 | F6: 5 | G6: 0.61634017 | H6: 19 | I6: 7 | J6: 0.43501342 | K6: 5.1010992e+08 | L6: 54504700 | M6: 79710694 | N6: 73765400 | O6: 15896704 | P6: 213.18001 | Q6: 1.225572 | R6: 43.776488 | S6: 782.49102 | T6: 7.8772479e-10 | U6: 23.45922 | V6: 100.934 | W6: -238.75239 | X6: 62.85302 | Y6: 92.26791 | Z6: 177.97 | AA6: 235.41871 | AB6: 0 | AC6: 0 | AD6: 0 | AE6: 0 | AF6: 0 | AG6: 0 | AH6: 0 | AI6: 0 | AJ6: 0 | AK6: 0 | AL6: 0 | AM6: 0 | AN6: 0 | AO6: 1.225572
A7: 957.01083 | B7: 31 | C7: 11 | D7: 7.0621531 | E7: 19 | F7: 7 | G7: 0.81622372 | H7: 18 | I7: 10 | J7: 1.3178786 | K7: 5.0498452e+08 | L7: 54504700 | M7: 79710803 | N7: 73765400 | O7: 16378976 | P7: 205.23243 | Q7: 1.2560785 | R7: 43.856969 | S7: 782.99428 | T7: 2.4844946e-12 | U7: 24.085985 | V7: 100.934 | W7: -235.21767 | X7: 62.957504 | Y7: 92.502035 | Z7: 177.97 | AA7: 241.85796 | AB7: 100 | AC7: 0 | AD7: 0 | AE7: 0 | AF7: 0 | AG7: 0 | AH7: 0 | AI7: 0 | AJ7: 0 | AK7: 0 | AL7: 0 | AM7: 0 | AN7: 0 | AO7: 101.25608
A8: 934.3007 | B8: 37 | C8: 18 | D8: 8.1863403 | E8: 17 | F8: 7 | G8: 0.82554101 | H8: 10 | I8: 8 | J8: 1.2820137 | K8: 5.0906195e+08 | L8: 54459500 | M8: 79697416 | N8: 74467600 | O8: 15889264 | P8: 211.63954 | Q8: 1.215542 | R8: 43.842218 | S8: 782.96919 | T8: 2.7775814e-12 | U8: 23.991803 | V8: 100.934 | W8: -237.59107 | X8: 62.871072 | Y8: 92.300038 | Z8: 177.97 | AA8: 243.20169 | AB8: 0 | AC8: 0 | AD8: 0 | AE8: 0 | AF8: 0 | AG8: 0 | AH8: 0 | AI8: 0 | AJ8: 0 | AK8: 0 | AL8: 0 | AM8: 0 | AN8: 0 | AO8: 1.215542
A9: 939.24902 | B9: 39 | C9: 19 | D9: 15 | E9: 10 | F9: 5 | G9: 0.3 | H9: 29 | I9: 14 | J9: 0.3 | K9: 5.1070648e+08 | L9: 54536600 | M9: 79703909 | N9: 71320200 | O9: 15896200 | P9: 213.86466 | Q9: 1.2746715 | R9: 43.587276 | S9: 782.43683 | T9: 5.5606568e-09 | U9: 22.83036 | V9: 100.934 | W9: -241.63643 | X9: 62.84021 | Y9: 92.103592 | Z9: 144.29 | AA9: 233.40978 | AB9: 0 | AC9: 0 | AD9: 0 | AE9: 0 | AF9: 0 | AG9: 0 | AH9: 0 | AI9: 0 | AJ9: 0 | AK9: 0 | AL9: 0 | AM9: 0 | AN9: 0 | AO9: 1.2746715
A10: 942.58147 | B10: 39 | C10: 19 | D10: 1 | E10: 10 | F10: 5 | G10: 1.2 | H10: 29 | I10: 7 | J10: 1.4 | K10: 5.0863239e+08 | L10: 54483600 | M10: 79703898 | N10: 74074700 | O10: 15889290 | P10: 209.73189 | Q10: 1.2339846 | R10: 43.694556 | S10: 783.32664 | T10: 3.124875e-10 | U10: 23.58813 | V10: 80.72 | W10: -148.24438 | X10: 63.127683 | Y10: 94.926407 | Z10: 144.29 | AA10: 234.99131 | AB10: 0 | AC10: 0 | AD10: 0 | AE10: 0 | AF10: 0 | AG10: 0 | AH10: 0 | AI10: 0 | AJ10: 0 | AK10: 0 | AL10: 0 | AM10: 0 | AN10: 0 | AO10: 1.2339846
A11: 935.72384 | B11: 35 | C11: 19 | D11: 2.1477343 | E11: 26 | F11: 10 | G11: 0.76719923 | H11: 13 | I11: 11 | J11: 0.72898123 | K11: 5.0797469e+08 | L11: 54457500 | M11: 79707923 | N11: 75187100 | O11: 15889738 | P11: 210.64057 | Q11: 1.2026824 | R11: 43.892264 | S11: 783.44007 | T11: 1.1185596e-15 | U11: 24.532578 | V11: 91.85 | W11: -235.63074 | X11: 62.814859 | Y11: 92.896079 | Z11: 180.981 | AA11: 253.76104 | AB11: 0 | AC11: 0 | AD11: 0 | AE11: 0 | AF11: 0 | AG11: 0 | AH11: 0 | AI11: 0 | AJ11: 0 | AK11: 0 | AL11: 0 | AM11: 0 | AN11: 0 | AO11: 1.2026824
A12: 938.0233 | B12: 28 | C12: 18 | D12: 1.1742861 | E12: 11 | F12: 8 | G12: 0.3 | H12: 11 | I12: 9 | J12: 1.3481922 | K12: 5.0753345e+08 | L12: 54394700 | M12: 79696605 | N12: 70905700 | O12: 15887350 | P12: 212.26458 | Q12: 1.2798014 | R12: 43.46454 | S12: 782.49665 | T12: 1.3178688e-10 | U12: 22.571618 | V12: 80.72 | W12: -184.63732 | X12: 63.095769 | Y12: 94.550061 | Z12: 100.934 | AA12: 229.26855 | AB12: 0 | AC12: 0 | AD12: 0 | AE12: 0 | AF12: 0 | AG12: 0 | AH12: 0 | AI12: 0 | AJ12: 0 | AK12: 0 | AL12: 0 | AM12: 0 | AN12: 0 | AO12: 1.2798014
A13: 938.88671 | B13: 39 | C13: 10 | D13: 15 | E13: 29 | F13: 5 | G13: 0.3 | H13: 29 | I13: 14 | J13: 1.4 | K13: 5.1099891e+08 | L13: 54548700 | M13: 79698904 | N13: 72496700 | O13: 15894694 | P13: 213.50386 | Q13: 1.2536806 | R13: 43.717824 | S13: 781.85394 | T13: 3.9991783e-09 | U13: 22.547031 | V13: 100.934 | W13: -238.13191 | X13: 62.878785 | Y13: 92.134697 | Z13: 177.97 | AA13: 233.17558 | AB13: 0 | AC13: 0 | AD13: 0 | AE13: 0 | AF13: 0 | AG13: 0 | AH13: 0 | AI13: 0 | AJ13: 0 | AK13: 0 | AL13: 0 | AM13: 0 | AN13: 0 | AO13: 1.2536806
... A380: 910 | B380: 39 | C380: 10 | D380: 15 | E380: 22 | F380: 5 | G380: 1.2 | H380: 29 | I380: 7 | J380: 1.4 | K380: 5.0748577e+08 | L380: 54426300 | M380: 79694448 | N380: 71787600 | O380: 15896406 | P380: 209.87197 | Q380: 1.2763525 | R380: 43.888926 | S380: 782.85757 | T380: 1.9411896e-10 | U380: 24.381429 | V380: 100.934 | W380: -235.53272 | X380: 62.908048 | Y380: 92.144261 | Z380: 180.981 | AA380: 244.59058 | AB380: 0 | AC380: 0 | AD380: 0 | AE380: 0 | AF380: 0 | AG380: 0 | AH380: 0 | AI380: 0 | AJ380: 0 | AK380: 0 | AL380: 0 | AM380: 0 | AN380: 0 | AO380: 1.2763525

Sheet 20250604_133649_OilComp551
A1: PHENOLS | B1: PHENOL1 | C1: PHENOL2 | D1: PHENOL3 | E1: CYC-5A | F1: CYC-5A1 | G1: CYC-6A | H1: CYC-6A1 | I1: CYC-6A2 | J1: CYC-6A3 | K1: ARM-A | L1: ARM-A1 | M1: ARM-A2 | N1: ARM-B | O1: ARM-B1 | P1: ARM-B2 | Q1: TCC | R1: TOC | S1: TRC | T1: TPS | U1: TUC | V1: SAF | W1: MJSP | X1: LHV | Y1: SG | Z1: SLF | AA1: ARM | AB1: MBP | AC1: MFP | AD1: GT10 | AE1: GT90 | AF1: DFP | AG1: DT90 | AH1: ERRSIM | AI1: ERR_0 | AJ1: ERR_1 | AK1: ERR_2 | AL1: ERR_3 | AM1: ERR_4 | AN1: ERR_5 | AO1: ERR_6 | AP1: ERR_7 | AQ1: ERR_8 | AR1: ERR_9 | AS1: ERR_10 | AT1: ERR_11
A2: 2.2 | B2: 0 | C2: 0 | D2: 0 | E2: 1.8 | F2: 0 | G2: 2.4 | H2: 0 | I2: 0 | J2: 0 | K2: 3.5 | L2: 0 | M2: 0 | N2: 1.5 | O2: 0 | P2: 0 | Q2: 4.2663915e+08 | R2: 179084000 | S2: 80017913 | T2: 78501500 | U2: 15696139 | V2: 231.48805 | W2: 3.1691985 | X2: 43.488964 | Y2: 790.53207 | Z2: 5.543905e-14 | AA2: 24.96693 | AB2: 80.72 | AC2: -198.86909 | AD2: 65.786516 | AE2: 95.642853 | AF2: 192.3 | AG2: 268.41408 | AH2: 99 | AI2: 0 | AJ2: 0 | AK2: 0 | AL2: 0 | AM2: 0 | AN2: 0 | AO2: 0 | AP2: 0 | AQ2: 0 | AR2: 0 | AS2: 0 | AT2: 0
A3: 0 | B3: 3.06 | C3: 0 | D3: 0 | E3: 1.8 | F3: 0 | G3: 2.4 | H3: 0 | I3: 0 | J3: 0 | K3: 3.5 | L3: 0 | M3: 0 | N3: 1.5 | O3: 0 | P3: 0 | Q3: 4.263793e+08 | R3: 179084000 | S3: 80017649 | T3: 78501500 | U3: 15488052 | V3: 225.10415 | W3: 3.2582926 | X3: 44.211736 | Y3: 806.82325 | Z3: 3.4882026e-14 | AA3: 22.42381 | AB3: 91.85 | AC3: -541.56538 | AD3: 69.376126 | AE3: 96.83567 | AF3: 177.97 | AG3: 255.72363 | AH3: 100 | AI3: 0 | AJ3: 0 | AK3: 0 | AL3: 0 | AM3: 0 | AN3: 0 | AO3: 0 | AP3: 0 | AQ3: 0 | AR3: 0 | AS3: 0 | AT3: 0
A4: 0 | B4: 0 | C4: 3 | D4: 0 | E4: 1.8 | F4: 0 | G4: 2.4 | H4: 0 | I4: 0 | J4: 0 | K4: 3.5 | L4: 0 | M4: 0 | N4: 1.5 | O4: 0 | P4: 0 | Q4: 4.2635977e+08 | R4: 179084000 | S4: 80017649 | T4: 78501500 | U4: 15487456 | V4: 234.60298 | W4: 3.1263113 | X4: 43.383087 | Y4: 796.91843 | Z4: 3.410888e-14 | AA4: 24.260375 | AB4: 91.85 | AC4: -224.34226 | AD4: 69.315023 | AE4: 96.547158 | AF4: 192.3 | AG4: 264.71315 | AH4: 100 | AI4: 0 | AJ4: 0 | AK4: 0 | AL4: 0 | AM4: 0 | AN4: 0 | AO4: 0 | AP4: 0 | AQ4: 0 | AR4: 0 | AS4: 0 | AT4: 0
A5: 0 | B5: 0 | C5: 0 | D5: 2.14 | E5: 1.8 | F5: 0 | G5: 2.4 | H5: 0 | I5: 0 | J5: 0 | K5: 3.5 | L5: 0 | M5: 0 | N5: 1.5 | O5: 0 | P5: 0 | Q5: 4.2631833e+08 | R5: 179084000 | S5: 80017649 | T5: 78501500 | U5: 15486619 | V5: 230.66473 | W5: 3.1795663 | X5: 43.519262 | Y5: 790.92032 | Z5: 5.5288059e-14 | AA5: 25.060457 | AB5: 80.72 | AC5: -198.65391 | AD5: 65.838831 | AE5: 95.628354 | AF5: 192.3 | AG5: 269.88745 | AH5: 100 | AI5: 0 | AJ5: 0 | AK5: 0 | AL5: 0 | AM5: 0 | AN5: 0 | AO5: 0.024182609 | AP5: 0 | AQ5: 0 | AR5: 0 | AS5: 0 | AT5: 0
A6: 2.2 | B6: 0 | C6: 0 | D6: 0 | E6: 0 | F6: 2.1 | G6: 2.4 | H6: 0 | I6: 0 | J6: 0 | K6: 3.5 | L6: 0 | M6: 0 | N6: 1.5 | O6: 0 | P6: 0 | Q6: 4.2669319e+08 | R6: 179084000 | S6: 80017907 | T6: 78501500 | U6: 15692079 | V6: 233.13477 | W6: 3.1469706 | X6: 43.578105 | Y6: 789.48318 | Z6: 7.6050046e-14 | AA6: 24.866137 | AB6: 80.72 | AC6: -220.33227 | AD6: 64.615283 | AE6: 89.145153 | AF6: 192.3 | AG6: 263.30491 | AH6: 0 | AI6: 0 | AJ6: 0 | AK6: 0 | AL6: 0 | AM6: 0 | AN6: 0 | AO6: 0 | AP6: 0 | AQ6: 0 | AR6: 0 | AS6: 0 | AT6: 0
A7: 2.2 | B7: 0 | C7: 0 | D7: 0 | E7: 1.8 | F7: 0 | G7: 0 | H7: 2.06 | I7: 0 | J7: 0 | K7: 3.5 | L7: 0 | M7: 0 | N7: 1.5 | O7: 0 | P7: 0 | Q7: 4.2659494e+08 | R7: 179084000 | S7: 80017924 | T7: 78501500 | U7: 15701258 | V7: 229.95734 | W7: 3.1901637 | X7: 43.390366 | Y7: 791.31493 | Z7: 4.1134806e-14 | AA7: 24.949462 | AB7: 91.85 | AC7: -187.21607 | AD7: 69.928237 | AE7: 101.46257 | AF7: 192.3 | AG7: 277.55927 | AH7: 0 | AI7: 0 | AJ7: 0 | AK7: 0 | AL7: 0 | AM7: 0 | AN7: 0 | AO7: 0 | AP7: 0 | AQ7: 0 | AR7: 0 | AS7: 0 | AT7: 0
A8: 2.2 | B8: 0 | C8: 0 | D8: 0 | E8: 1.8 | F8: 0 | G8: 0 | H8: 0 | I8: 1.77 | J8: 0 | K8: 3.5 | L8: 0 | M8: 0 | N8: 1.5 | O8: 0 | P8: 0 | Q8: 4.2657005e+08 | R8: 179084000 | S8: 80017937 | T8: 78501500 | U8: 15707867 | V8: 228.54926 | W8: 3.2097443 | X8: 43.371342 | Y8: 798.69336 | Z8: 9.6951076e-17 | AA8: 24.695877 | AB8: 91.85 | AC8: -141.79483 | AD8: 70.87221 | AE8: 113.60046 | AF8: 192.3 | AG8: 279.40152 | AH8: 0 | AI8: 0 | AJ8: 0 | AK8: 0 | AL8: 0 | AM8: 0 | AN8: 0 | AO8: 0 | AP8: 0 | AQ8: 0.1246015 | AR8: 0 | AS8: 0 | AT8: 0
A9: 2.2 | B9: 0 | C9: 0 | D9: 0 | E9: 1.8 | F9: 0 | G9: 0 | H9: 0 | I9: 0 | J9: 2.06 | K9: 3.5 | L9: 0 | M9: 0 | N9: 1.5 | O9: 0 | P9: 0 | Q9: 4.2659142e+08 | R9: 179084000 | S9: 80017926 | T9: 78501500 | U9: 15706718 | V9: 224.01159 | W9: 3.274827 | X9: 43.55811 | Y9: 806.72522 | Z9: 4.5252309e-17 | AA9: 24.726295 | AB9: 100.934 | AC9: -310.24465 | AD9: 72.232491 | AE9: 113.63753 | AF9: 192.3 | AG9: 277.82808 | AH9: 0 | AI9: 0 | AJ9: 0 | AK9: 0 | AL9: 0 | AM9: 0 | AN9: 0 | AO9: 0 | AP9: 0 | AQ9: 0.3189273 | AR9: 0 | AS9: 0 | AT9: 0
A10: 2.2 | B10: 0 | C10: 0 | D10: 0 | E10: 1.8 | F10: 0 | G10: 2.4 | H10: 0 | I10: 0 | J10: 0 | K10: 0 | L10: 3.44 | M10: 0 | N10: 1.5 | O10: 0 | P10: 0 | Q10: 4.2663606e+08 | R10: 179084000 | S10: 80017917 | T10: 78501500 | U10: 15697929 | V10: 227.95333 | W10: 3.2183319 | X10: 44.489702 | Y10: 803.74824 | Z10: 5.0819743e-14 | AA10: 9.9604121 | AB10: 80.72 | AC10: -226.64265 | AD10: 66.13499 | AE10: 95.694428 | AF10: 192.3 | AG10: 276.62144 | AH10: 0 | AI10: 0 | AJ10: 0 | AK10: 0 | AL10: 0 | AM10: 0 | AN10: 0 | AO10: 0 | AP10: 0 | AQ10: 0 | AR10: 0 | AS10: 0 | AT10: 0
A11: 2.2 | B11: 0 | C11: 0 | D11: 0 | E11: 1.8 | F11: 0 | G11: 2.4 | H11: 0 | I11: 0 | J11: 0 | K11: 0 | L11: 0 | M11: 2.69 | N11: 1.5 | O11: 0 | P11: 0 | Q11: 4.2659891e+08 | R11: 179084000 | S11: 80017947 | T11: 78501500 | U11: 15707423 | V11: 233.14595 | W11: 3.1465451 | X11: 43.942932 | Y11: 801.92103 | Z11: 5.549446e-14 | AA11: 9.8408526 | AB11: 80.72 | AC11: -194.67508 | AD11: 65.275689 | AE11: 94.966751 | AF11: 192.3 | AG11: 280.98481 | AH11: 0 | AI11: 0 | AJ11: 0 | AK11: 0 | AL11: 0 | AM11: 0 | AN11: 0 | AO11: 0 | AP11: 0 | AQ11: 0 | AR11: 0 | AS11: 0 | AT11: 0
A12: 2.2 | B12: 0 | C12: 0 | D12: 0 | E12: 1.8 | F12: 0 | G12: 2.4 | H12: 0 | I12: 0 | J12: 0 | K12: 3.5 | L12: 0 | M12: 0 | N12: 0 | O12: 1.24 | P12: 0 | Q12: 4.2663026e+08 | R12: 179084000 | S12: 80017920 | T12: 78501500 | U12: 15697807 | V12: 235.18064 | W12: 3.119413 | X12: 43.104197 | Y12: 783.29777 | Z12: 6.0246855e-14 | AA12: 18.672227 | AB12: 80.72 | AC12: -193.69927 | AD12: 65.479589 | AE12: 95.423423 | AF12: 203.285 | AG12: 277.86382 | AH12: 0 | AI12: 0 | AJ12: 0 | AK12: 0 | AL12: 0 | AM12: 0 | AN12: 0 | AO12: 0 | AP12: 0 | AQ12: 0 | AR12: 0 | AS12: 0 | AT12: 0
A13: 2.2 | B13: 0 | C13: 0 | D13: 0 | E13: 1.8 | F13: 0 | G13: 2.4 | H13: 0 | I13: 0 | J13: 0 | K13: 3.5 | L13: 0 | M13: 0 | N13: 0 | O13: 0 | P13: 1.3 | Q13: 4.2663303e+08 | R13: 179084000 | S13: 80017919 | T13: 78501500 | U13: 15697523 | V13: 234.99018 | W13: 3.1219493 | X13: 43.115361 | Y13: 785.2418 | Z13: 5.9039835e-14 | AA13: 18.540675 | AB13: 80.72 | AC13: -198.69543 | AD13: 65.639388 | AE13: 95.512195 | AF13: 203.285 | AG13: 277.01153 | AH13: 0 | AI13: 0 | AJ13: 0 | AK13: 0 | AL13: 0 | AM13: 0 | AN13: 0 | AO13: 0 | AP13: 0 | AQ13: 0 | AR13: 0 | AS13: 0 | AT13: 0
A14: FRZPoint(F) | F14: -86

Sheet 20250606_192743
A1: GAS.N | B1: GAS.F | C1: GAS.RR | D1: SAF.N | E1: SAF.F | F1: SAF.RR | G1: DSL.N | H1: DSL.F | I1: DSL.RR | J1: TCC | K1: TOC | L1: TRC | M1: TPS | N1: TUC | O1: SAF | P1: MJSP | Q1: LHV | R1: SG | S1: SLF | T1: ARM | U1: MBP | V1: MFP | W1: GT10 | X1: GT90 | Y1: DFP | Z1: DT90 | AA1: ERRSIM | AB1: ERR_0 | AC1: ERR_1 | AD1: ERR_2 | AE1: ERR_3 | AF1: ERR_4 | AG1: ERR_5 | AH1: ERR_6 | AI1: ERR_7 | AJ1: ERR_8 | AK1: ERR_9 | AL1: ERR_10 | AM1: ERR_11 | AN1: OBJ
A2: 30 | B2: 15 | C2: 3.6 | D2: 20 | E2: 10 | F2: 0.43 | G2: 20 | H2: 10 | I2: 0.72 | J2: 3.2719307e+08 | K2: 165430000 | L2: 79925721 | M2: 77595700 | N2: 15759844 | O2: 230.15657 | P2: 2.6497058 | Q2: 43.94435 | R2: 801.48126 | S2: 4.254062e-13 | T2: 21.871823 | U2: 100.934 | V2: -621.36518 | W2: 69.225905 | X2: 94.879777 | Y2: 165.7 | Z2: 253.70994 | AA2: 0 | AB2: 0 | AC2: 0 | AD2: 0 | AE2: 0 | AF2: 0 | AG2: 0 | AH2: 0 | AI2: 0 | AJ2: 0 | AK2: 0 | AL2: 0 | AM2: 0 | AN2: 2.6497058
A3: 27 | B3: 18 | C3: 1.7678789 | D3: 22 | E3: 6 | F3: 0.33102022 | G3: 20 | H3: 13 | I3: 1.177838 | J3: 3.2682613e+08 | K3: 165409000 | L3: 79924520 | M3: 77562700 | N3: 15759544 | O3: 230.69332 | P3: 2.6426906 | Q3: 43.811558 | R3: 800.72831 | S3: 6.0261362e-09 | T3: 21.81711 | U3: 80.72 | V3: -557.53606 | W3: 69.363553 | X3: 95.395388 | Y3: 177.97 | Z3: 254.38642 | AA3: 0 | AB3: 0 | AC3: 0 | AD3: 0 | AE3: 0 | AF3: 0 | AG3: 0 | AH3: 0 | AI3: 0 | AJ3: 0 | AK3: 0 | AL3: 0 | AM3: 0 | AN3: 2.6426906
A4: 31 | B4: 19 | C4: 4.7924543 | D4: 26 | E4: 11 | F4: 0.72912612 | G4: 18 | H4: 13 | I4: 1.0968123 | J4: 3.2794143e+08 | K4: 165467000 | L4: 79924720 | M4: 78123200 | N4: 15759577 | O4: 227.44523 | P4: 2.6740064 | Q4: 44.172465 | R4: 804.08929 | S4: 4.1883156e-14 | T4: 22.311907 | U4: 100.934 | V4: -654.28534 | W4: 69.221021 | X4: 94.856881 | Y4: 177.97 | Z4: 253.23889 | AA4: 0 | AB4: 0 | AC4: 0 | AD4: 0 | AE4: 0 | AF4: 0 | AG4: 0 | AH4: 0 | AI4: 0 | AJ4: 0 | AK4: 0 | AL4: 0 | AM4: 0 | AN4: 2.6740064
A5: 37 | B5: 13 | C5: 2.9990757 | D5: 16 | E5: 8 | F5: 1.1242949 | G5: 19 | H5: 13 | I5: 0.63301208 | J5: 3.2740168e+08 | K5: 165449000 | L5: 79925621 | M5: 78265500 | N5: 15759793 | O5: 226.75965 | P5: 2.6773545 | Q5: 44.212356 | R5: 804.67355 | S5: 3.1673569e-13 | T5: 22.406491 | U5: 100.934 | V5: -664.59764 | W5: 69.229189 | X5: 94.88984 | Y5: 165.7 | Z5: 253.07691 | AA5: 0 | AB5: 0 | AC5: 0 | AD5: 0 | AE5: 0 | AF5: 0 | AG5: 0 | AH5: 0 | AI5: 0 | AJ5: 0 | AK5: 0 | AL5: 0 | AM5: 0 | AN5: 2.6773545
A6: 33 | B6: 12 | C6: 7.5886839 | D6: 25 | E6: 13 | F6: 0.86855123 | G6: 19 | H6: 13 | I6: 0.96057899 | J6: 3.2844582e+08 | K6: 165490000 | L6: 79924720 | M6: 78279000 | N6: 15759587 | O6: 226.61065 | P6: 2.6827785 | Q6: 44.234029 | R6: 804.9044 | S6: 6.6895234e-19 | T6: 22.455516 | U6: 100.934 | V6: -667.44288 | W6: 69.220962 | X6: 94.854627 | Y6: 177.97 | Z6: 252.83139 | AA6: 0 | AB6: 0 | AC6: 0 | AD6: 0 | AE6: 0 | AF6: 0 | AG6: 0 | AH6: 0 | AI6: 0 | AJ6: 0 | AK6: 0 | AL6: 0 | AM6: 0 | AN6: 2.6827785
A7: 28 | B7: 11 | C7: 8.7349075 | D7: 26 | E7: 13 | F7: 0.75414595 | G7: 16 | H7: 12 | I7: 1.0533796 | J7: 3.2852348e+08 | K7: 165472000 | L7: 79925321 | M7: 78203600 | N7: 15759677 | O7: 227.05824 | P7: 2.6788382 | Q7: 44.195915 | R7: 804.54588 | S7: 2.2241191e-18 | T7: 22.387462 | U7: 100.934 | V7: -659.44323 | W7: 69.222907 | X7: 94.866074 | Y7: 177.97 | Z7: 253.54835 | AA7: 0 | AB7: 0 | AC7: 0 | AD7: 0 | AE7: 0 | AF7: 0 | AG7: 0 | AH7: 0 | AI7: 0 | AJ7: 0 | AK7: 0 | AL7: 0 | AM7: 0 | AN7: 2.6788382
A8: 27 | B8: 10 | C8: 1 | D8: 10 | E8: 5 | F8: 0.3 | G8: 29 | H8: 14 | I8: 1.4 | J8: 3.2660222e+08 | K8: 165407000 | L8: 79924420 | M8: 77882800 | N8: 15759505 | O8: 229.31465 | P8: 2.6517155 | Q8: 43.712631 | R8: 802.43618 | S8: 5.6007505e-08 | T8: 21.475174 | U8: 91.85 | V8: -481.55194 | W8: 69.595135 | X8: 97.136021 | Y8: 144.29 | Z8: 254.35258 | AA8: 0 | AB8: 0 | AC8: 0 | AD8: 0 | AE8: 0 | AF8: 0 | AG8: 0 | AH8: 0 | AI8: 0 | AJ8: 0 | AK8: 0 | AL8: 0 | AM8: 0 | AN8: 2.6517155
A9: 27 | B9: 10 | C9: 1 | D9: 29 | E9: 5 | F9: 0.3 | G9: 29 | H9: 14 | I9: 0.3 | J9: 3.269585e+08 | K9: 165460000 | L9: 79941739 | M9: 77874000 | N9: 15763899 | O9: 229.46809 | P9: 2.6521853 | Q9: 43.746099 | R9: 801.57007 | S9: 5.1936086e-08 | T9: 21.592612 | U9: 91.85 | V9: -464.4962 | W9: 69.595135 | X9: 97.136021 | Y9: 177.97 | Z9: 253.35742 | AA9: 0 | AB9: 0 | AC9: 0 | AD9: 0 | AE9: 0 | AF9: 0 | AG9: 0 | AH9: 0 | AI9: 0 | AJ9: 0 | AK9: 0 | AL9: 0 | AM9: 0 | AN9: 2.6521853
A10: 27 | B10: 19 | C10: 15 | D10: 17 | E10: 5 | F10: 0.3 | G10: 29 | H10: 14 | I10: 1.4 | J10: 3.2963322e+08 | K10: 165552000 | L10: 79924420 | M10: 77227900 | N10: 15759505 | O10: 231.924 | P10: 2.6459783 | Q10: 43.803307 | R10: 800.20558 | S10: 6.0692803e-08 | T10: 21.710402 | U10: 100.934 | V10: -600.9855 | W10: 69.221072 | X10: 94.855333 | Y10: 170.55 | Z10: 254.40036 | AA10: 0 | AB10: 0 | AC10: 0 | AD10: 0 | AE10: 0 | AF10: 0 | AG10: 0 | AH10: 0 | AI10: 0 | AJ10: 0 | AK10: 0 | AL10: 0 | AM10: 0 | AN10: 2.6459783
A11: 27 | B11: 10 | C11: 15 | D11: 28 | E11: 5 | F11: 0.3 | G11: 16 | H11: 14 | I11: 1.4 | J11: 3.2957894e+08 | K11: 165553000 | L11: 79925221 | M11: 77296600 | N11: 15759554 | O11: 232.01111 | P11: 2.6435379 | Q11: 43.80864 | R11: 799.98209 | S11: 6.0048714e-08 | T11: 21.743423 | U11: 100.934 | V11: -593.8197 | W11: 69.222165 | X11: 94.861836 | Y11: 177.97 | Z11: 257.6454 | AA11: 0 | AB11: 0 | AC11: 0 | AD11: 0 | AE11: 0 | AF11: 0 | AG11: 0 | AH11: 0 | AI11: 0 | AJ11: 0 | AK11: 0 | AL11: 0 | AM11: 0 | AN11: 2.6435379
A12: 27 | B12: 19 | C12: 1 | D12: 29 | E12: 5 | F12: 0.3 | G12: 29 | H12: 7 | I12: 1.4 | J12: 3.2710228e+08 | K12: 165445000 | L12: 79925922 | M12: 77972400 | N12: 15759893 | O12: 229.14952 | P12: 2.6541139 | Q12: 43.728042 | R12: 801.96634 | S12: 5.2369184e-08 | T12: 21.945651 | U12: 68.71 | V12: -467.6238 | W12: 69.729894 | X12: 98.485041 | Y12: 177.97 | Z12: 254.31605 | AA12: 0 | AB12: 0 | AC12: 0 | AD12: 0 | AE12: 0 | AF12: 0 | AG12: 0 | AH12: 0 | AI12: 0 | AJ12: 0 | AK12: 0 | AL12: 0 | AM12: 0 | AN12: 2.6541139
A13: 27 | B13: 15 | C13: 1 | D13: 10 | E13: 5 | F13: 0.3 | G13: 10 | H13: 8 | I13: 1.4 | J13: 3.2624859e+08 | K13: 165397000 | L13: 79931127 | M13: 77949600 | N13: 15761034 | O13: 229.24818 | P13: 2.6499584 | Q13: 43.70181 | R13: 802.68287 | S13: 5.6179858e-08 | T13: 21.732839 | U13: 80.72 | V13: -485.69164 | W13: 69.627533 | X13: 97.05051 | Y13: 144.29 | Z13: 257.33687 | AA13: 0 | AB13: 0 | AC13: 0 | AD13: 0 | AE13: 0 | AF13: 0 | AG13: 0 | AH13: 0 | AI13: 0 | AJ13: 0 | AK13: 0 | AL13: 0 | AM13: 0 | AN13: 2.6499584
... A307: 27 | B307: 16 | C307: 12.231894 | D307: 16 | E307: 14 | F307: 0.32090888 | G307: 10 | H307: 7 | I307: 1.1036092 | J307: 3.2688626e+08 | K307: 165447000 | L307: 79944842 | M307: 77259600 | N307: 15764507 | O307: 231.33842 | P307: 2.6420066 | Q307: 43.744246 | R307: 802.39139 | S307: 1.3578649e-10 | T307: 21.40549 | U307: 100.934 | V307: -602.6366 | W307: 69.278186 | X307: 95.065285 | Y307: 121.522 | Z307: 255.4133 | AA307: 99 | AB307: 0 | AC307: 0 | AD307: 0 | AE307: 0 | AF307: 0 | AG307: 0 | AH307: 0 | AI307: 0 | AJ307: 0 | AK307: 0 | AL307: 0 | AM307: 0 | AN307: 101.64201

Sheet 20250606_192743_D1
A1: GAS.N | B1: GAS.F | C1: GAS.RR | D1: SAF.N | E1: SAF.F | F1: SAF.RR | G1: DSL.N | H1: DSL.F | I1: DSL.RR | J1: TCC | K1: TOC | L1: TRC | M1: TPS | N1: TUC | O1: SAF | P1: MJSP | Q1: LHV | R1: SG | S1: SLF | T1: ARM | U1: MBP | V1: MFP | W1: GT10 | X1: GT90 | Y1: DFP | Z1: DT90 | AA1: ERRSIM | AB1: ERR_0 | AC1: ERR_1 | AD1: ERR_2 | AE1: ERR_3 | AF1: ERR_4 | AG1: ERR_5 | AH1: ERR_6 | AI1: ERR_7 | AJ1: ERR_8 | AK1: ERR_9 | AL1: ERR_10 | AM1: ERR_11 | AN1: OBJ
A2: 30 | B2: 15 | C2: 3.6 | D2: 20 | E2: 10 | F2: 0.43 | G2: 20 | H2: 10 | I2: 0.72 | J2: 3.2719307e+08 | K2: 165430000 | L2: 79925721 | M2: 77595700 | N2: 15759844 | O2: 230.15657 | P2: 2.6497058 | Q2: 43.94435 | R2: 801.48126 | S2: 4.254062e-13 | T2: 21.871823 | U2: 100.934 | V2: -621.36518 | W2: 69.225905 | X2: 94.879777 | Y2: 165.7 | Z2: 253.70994 | AA2: 0 | AB2: 0 | AC2: 0 | AD2: 0 | AE2: 0 | AF2: 0 | AG2: 0 | AH2: 0 | AI2: 0 | AJ2: 0 | AK2: 0 | AL2: 0 | AM2: 0 | AN2: 2.6497058
A3: 27 | B3: 18 | C3: 1.7678789 | D3: 22 | E3: 6 | F3: 0.33102022 | G3: 20 | H3: 13 | I3: 1.177838 | J3: 3.2682613e+08 | K3: 165409000 | L3: 79924520 | M3: 77562700 | N3: 15759544 | O3: 230.69332 | P3: 2.6426906 | Q3: 43.811558 | R3: 800.72831 | S3: 6.0261362e-09 | T3: 21.81711 | U3: 80.72 | V3: -557.53606 | W3: 69.363553 | X3: 95.395388 | Y3: 177.97 | Z3: 254.38642 | AA3: 0 | AB3: 0 | AC3: 0 | AD3: 0 | AE3: 0 | AF3: 0 | AG3: 0 | AH3: 0 | AI3: 0 | AJ3: 0 | AK3: 0 | AL3: 0 | AM3: 0 | AN3: 2.6426906
A4: 31 | B4: 19 | C4: 4.7924543 | D4: 26 | E4: 11 | F4: 0.72912612 | G4: 18 | H4: 13 | I4: 1.0968123 | J4: 3.2794143e+08 | K4: 165467000 | L4: 79924720 | M4: 78123200 | N4: 15759577 | O4: 227.44523 | P4: 2.6740064 | Q4: 44.172465 | R4: 804.08929 | S4: 4.1883156e-14 | T4: 22.311907 | U4: 100.934 | V4: -654.28534 | W4: 69.221021 | X4: 94.856881 | Y4: 177.97 | Z4: 253.23889 | AA4: 0 | AB4: 0 | AC4: 0 | AD4: 0 | AE4: 0 | AF4: 0 | AG4: 0 | AH4: 0 | AI4: 0 | AJ4: 0 | AK4: 0 | AL4: 0 | AM4: 0 | AN4: 2.6740064
A5: 37 | B5: 13 | C5: 2.9990757 | D5: 16 | E5: 8 | F5: 1.1242949 | G5: 19 | H5: 13 | I5: 0.63301208 | J5: 3.2740168e+08 | K5: 165449000 | L5: 79925621 | M5: 78265500 | N5: 15759793 | O5: 226.75965 | P5: 2.6773545 | Q5: 44.212356 | R5: 804.67355 | S5: 3.1673569e-13 | T5: 22.406491 | U5: 100.934 | V5: -664.59764 | W5: 69.229189 | X5: 94.88984 | Y5: 165.7 | Z5: 253.07691 | AA5: 0 | AB5: 0 | AC5: 0 | AD5: 0 | AE5: 0 | AF5: 0 | AG5: 0 | AH5: 0 | AI5: 0 | AJ5: 0 | AK5: 0 | AL5: 0 | AM5: 0 | AN5: 2.6773545
A6: 33 | B6: 12 | C6: 7.5886839 | D6: 25 | E6: 13 | F6: 0.86855123 | G6: 19 | H6: 13 | I6: 0.96057899 | J6: 3.2844582e+08 | K6: 165490000 | L6: 79924720 | M6: 78279000 | N6: 15759587 | O6: 226.61065 | P6: 2.6827785 | Q6: 44.234029 | R6: 804.9044 | S6: 6.6895234e-19 | T6: 22.455516 | U6: 100.934 | V6: -667.44288 | W6: 69.220962 | X6: 94.854627 | Y6: 177.97 | Z6: 252.83139 | AA6: 0 | AB6: 0 | AC6: 0 | AD6: 0 | AE6: 0 | AF6: 0 | AG6: 0 | AH6: 0 | AI6: 0 | AJ6: 0 | AK6: 0 | AL6: 0 | AM6: 0 | AN6: 2.6827785
A7: 28 | B7: 11 | C7: 8.7349075 | D7: 26 | E7: 13 | F7: 0.75414595 | G7: 16 | H7: 12 | I7: 1.0533796 | J7: 3.2852348e+08 | K7: 165472000 | L7: 79925321 | M7: 78203600 | N7: 15759677 | O7: 227.05824 | P7: 2.6788382 | Q7: 44.195915 | R7: 804.54588 | S7: 2.2241191e-18 | T7: 22.387462 | U7: 100.934 | V7: -659.44323 | W7: 69.222907 | X7: 94.866074 | Y7: 177.97 | Z7: 253.54835 | AA7: 0 | AB7: 0 | AC7: 0 | AD7: 0 | AE7: 0 | AF7: 0 | AG7: 0 | AH7: 0 | AI7: 0 | AJ7: 0 | AK7: 0 | AL7: 0 | AM7: 0 | AN7: 2.6788382
A8: 27 | B8: 10 | C8: 1 | D8: 10 | E8: 5 | F8: 0.3 | G8: 29 | H8: 14 | I8: 1.4 | J8: 3.2660222e+08 | K8: 165407000 | L8: 79924420 | M8: 77882800 | N8: 15759505 | O8: 229.31465 | P8: 2.6517155 | Q8: 43.712631 | R8: 802.43618 | S8: 5.6007505e-08 | T8: 21.475174 | U8: 91.85 | V8: -481.55194 | W8: 69.595135 | X8: 97.136021 | Y8: 144.29 | Z8: 254.35258 | AA8: 0 | AB8: 0 | AC8: 0 | AD8: 0 | AE8: 0 | AF8: 0 | AG8: 0 | AH8: 0 | AI8: 0 | AJ8: 0 | AK8: 0 | AL8: 0 | AM8: 0 | AN8: 2.6517155
A9: 27 | B9: 10 | C9: 1 | D9: 29 | E9: 5 | F9: 0.3 | G9: 29 | H9: 14 | I9: 0.3 | J9: 3.269585e+08 | K9: 165460000 | L9: 79941739 | M9: 77874000 | N9: 15763899 | O9: 229.46809 | P9: 2.6521853 | Q9: 43.746099 | R9: 801.57007 | S9: 5.1936086e-08 | T9: 21.592612 | U9: 91.85 | V9: -464.4962 | W9: 69.595135 | X9: 97.136021 | Y9: 177.97 | Z9: 253.35742 | AA9: 0 | AB9: 0 | AC9: 0 | AD9: 0 | AE9: 0 | AF9: 0 | AG9: 0 | AH9: 0 | AI9: 0 | AJ9: 0 | AK9: 0 | AL9: 0 | AM9: 0 | AN9: 2.6521853
A10: 27 | B10: 19 | C10: 15 | D10: 17 | E10: 5 | F10: 0.3 | G10: 29 | H10: 14 | I10: 1.4 | J10: 3.2963322e+08 | K10: 165552000 | L10: 79924420 | M10: 77227900 | N10: 15759505 | O10: 231.924 | P10: 2.6459783 | Q10: 43.803307 | R10: 800.20558 | S10: 6.0692803e-08 | T10: 21.710402 | U10: 100.934 | V10: -600.9855 | W10: 69.221072 | X10: 94.855333 | Y10: 170.55 | Z10: 254.40036 | AA10: 0 | AB10: 0 | AC10: 0 | AD10: 0 | AE10: 0 | AF10: 0 | AG10: 0 | AH10: 0 | AI10: 0 | AJ10: 0 | AK10: 0 | AL10: 0 | AM10: 0 | AN10: 2.6459783
A11: 27 | B11: 10 | C11: 15 | D11: 28 | E11: 5 | F11: 0.3 | G11: 16 | H11: 14 | I11: 1.4 | J11: 3.2957894e+08 | K11: 165553000 | L11: 79925221 | M11: 77296600 | N11: 15759554 | O11: 232.01111 | P11: 2.6435379 | Q11: 43.80864 | R11: 799.98209 | S11: 6.0048714e-08 | T11: 21.743423 | U11: 100.934 | V11: -593.8197 | W11: 69.222165 | X11: 94.861836 | Y11: 177.97 | Z11: 257.6454 | AA11: 0 | AB11: 0 | AC11: 0 | AD11: 0 | AE11: 0 | AF11: 0 | AG11: 0 | AH11: 0 | AI11: 0 | AJ11: 0 | AK11: 0 | AL11: 0 | AM11: 0 | AN11: 2.6435379
A12: 27 | B12: 19 | C12: 1 | D12: 29 | E12: 5 | F12: 0.3 | G12: 29 | H12: 7 | I12: 1.4 | J12: 3.2710228e+08 | K12: 165445000 | L12: 79925922 | M12: 77972400 | N12: 15759893 | O12: 229.14952 | P12: 2.6541139 | Q12: 43.728042 | R12: 801.96634 | S12: 5.2369184e-08 | T12: 21.945651 | U12: 68.71 | V12: -467.6238 | W12: 69.729894 | X12: 98.485041 | Y12: 177.97 | Z12: 254.31605 | AA12: 0 | AB12: 0 | AC12: 0 | AD12: 0 | AE12: 0 | AF12: 0 | AG12: 0 | AH12: 0 | AI12: 0 | AJ12: 0 | AK12: 0 | AL12: 0 | AM12: 0 | AN12: 2.6541139
A13: 27 | B13: 15 | C13: 1 | D13: 10 | E13: 5 | F13: 0.3 | G13: 10 | H13: 8 | I13: 1.4 | J13: 3.2624859e+08 | K13: 165397000 | L13: 79931127 | M13: 77949600 | N13: 15761034 | O13: 229.24818 | P13: 2.6499584 | Q13: 43.70181 | R13: 802.68287 | S13: 5.6179858e-08 | T13: 21.732839 | U13: 80.72 | V13: -485.69164 | W13: 69.627533 | X13: 97.05051 | Y13: 144.29 | Z13: 257.33687 | AA13: 0 | AB13: 0 | AC13: 0 | AD13: 0 | AE13: 0 | AF13: 0 | AG13: 0 | AH13: 0 | AI13: 0 | AJ13: 0 | AK13: 0 | AL13: 0 | AM13: 0 | AN13: 2.6499584
... A193: 39 | B193: 16 | C193: 1.7034156 | D193: 10 | E193: 8 | F193: 0.37501906 | G193: 12 | H193: 7 | I193: 0.32709718 | J193: 3.2688626e+08 | K193: 165447000 | L193: 79944842 | M193: 77259600 | N193: 15764507 | O193: 231.33842 | P193: 2.6420066 | Q193: 43.744246 | R193: 802.39139 | S193: 1.3578649e-10 | T193: 21.40549 | U193: 100.934 | V193: -602.6366 | W193: 69.278186 | X193: 95.065285 | Y193: 121.522 | Z193: 255.4133 | AA193: 0 | AB193: 0 | AC193: 0 | AD193: 0 | AE193: 0 | AF193: 0 | AG193: 0 | AH193: 0 | AI193: 0 | AJ193: 0 | AK193: 0 | AL193: 0 | AM193: 0 | AN193: 2.6420066

Sheet 20250607_065115_D2
A1: GAS.N | B1: GAS.F | C1: GAS.RR | D1: SAF.N | E1: SAF.F | F1: SAF.RR | G1: DSL.N | H1: DSL.F | I1: DSL.RR | J1: TCC | K1: TOC | L1: TRC | M1: TPS | N1: TUC | O1: SAF | P1: MJSP | Q1: LHV | R1: SG | S1: SLF | T1: ARM | U1: MBP | V1: MFP | W1: GT10 | X1: GT90 | Y1: DFP | Z1: DT90 | AA1: ERRSIM | AB1: ERR_0 | AC1: ERR_1 | AD1: ERR_2 | AE1: ERR_3 | AF1: ERR_4 | AG1: ERR_5 | AH1: ERR_6 | AI1: ERR_7 | AJ1: ERR_8 | AK1: ERR_9 | AL1: ERR_10 | AM1: ERR_11 | AN1: OBJ
A2: 30 | B2: 15 | C2: 3.6 | D2: 20 | E2: 10 | F2: 0.43 | G2: 20 | H2: 10 | I2: 0.72 | J2: 3.2719307e+08 | K2: 165430000 | L2: 79925721 | M2: 77595700 | N2: 15759844 | O2: 230.15657 | P2: 2.6497059 | Q2: 43.94435 | R2: 801.48126 | S2: 4.254062e-13 | T2: 21.871823 | U2: 100.934 | V2: -621.36518 | W2: 69.225905 | X2: 94.879777 | Y2: 165.7 | Z2: 253.70994 | AA2: 99 | AB2: 0 | AC2: 0 | AD2: 0 | AE2: 0 | AF2: 0 | AG2: 0 | AH2: 0 | AI2: 0 | AJ2: 0 | AK2: 0 | AL2: 0 | AM2: 0 | AN2: 101.64971
A3: 30 | B3: 15 | C3: 2.95 | D3: 20 | E3: 12 | F3: 0.56748 | G3: 20 | H3: 12 | I3: 0.7 | J3: 3.2718649e+08 | K3: 165431000 | L3: 79925221 | M3: 77910200 | N3: 15759715 | O3: 228.43843 | P3: 2.6635573 | Q3: 44.063535 | R3: 803.38194 | S3: 4.9130103e-16 | T3: 22.166252 | U3: 100.934 | V3: -641.81686 | W3: 69.23129 | X3: 94.901946 | Y3: 144.29 | Z3: 253.48249 | AA3: 0 | AB3: 0 | AC3: 0 | AD3: 0 | AE3: 0 | AF3: 0 | AG3: 0 | AH3: 0 | AI3: 0 | AJ3: 0 | AK3: 0 | AL3: 0 | AM3: 0 | AN3: 2.6635573
A4: 39 | B4: 15 | C4: 1.0496851 | D4: 23 | E4: 5 | F4: 1.1698878 | G4: 20 | H4: 13 | I4: 0.81048352 | J4: 3.2744807e+08 | K4: 165464000 | L4: 79924821 | M4: 78634300 | N4: 15759610 | O4: 225.69969 | P4: 2.683148 | Q4: 44.072001 | R4: 804.97077 | S4: 1.5300227e-09 | T4: 22.296238 | U4: 100.934 | V4: -529.50945 | W4: 69.558116 | X4: 96.543135 | Y4: 177.97 | Z4: 253.19433 | AA4: 0 | AB4: 0 | AC4: 0 | AD4: 0 | AE4: 0 | AF4: 0 | AG4: 0 | AH4: 0 | AI4: 0 | AJ4: 0 | AK4: 0 | AL4: 0 | AM4: 0 | AN4: 2.683148
A5: 28 | B5: 13 | C5: 7.4397189 | D5: 28 | E5: 14 | F5: 1.1353704 | G5: 14 | H5: 12 | I5: 0.98587471 | J5: 3.2843021e+08 | K5: 165477000 | L5: 79929225 | M5: 78503000 | N5: 15760473 | O5: 226.10048 | P5: 2.6841579 | Q5: 44.285311 | R5: 805.11452 | S5: 5.1533314e-21 | T5: 22.541294 | U5: 100.934 | V5: -673.59788 | W5: 69.222303 | X5: 94.863157 | Y5: 177.97 | Z5: 257.10104 | AA5: 0 | AB5: 0 | AC5: 0 | AD5: 0 | AE5: 0 | AF5: 0 | AG5: 0 | AH5: 0 | AI5: 0 | AJ5: 0 | AK5: 0 | AL5: 0 | AM5: 0 | AN5: 2.6841579
A6: 30 | B6: 18 | C6: 6.8666576 | D6: 17 | E6: 7 | F6: 0.91487739 | G6: 27 | H6: 12 | I6: 1.3744138 | J6: 3.2844034e+08 | K6: 165473000 | L6: 79924520 | M6: 78100600 | N6: 15759544 | O6: 227.54907 | P6: 2.6748294 | Q6: 44.16133 | R6: 803.8898 | S6: 1.1124214e-11 | T6: 22.260382 | U6: 100.934 | V6: -656.74191 | W6: 69.220314 | X6: 94.851719 | Y6: 177.97 | Z6: 252.92985 | AA6: 0 | AB6: 0 | AC6: 0 | AD6: 0 | AE6: 0 | AF6: 0 | AG6: 0 | AH6: 0 | AI6: 0 | AJ6: 0 | AK6: 0 | AL6: 0 | AM6: 0 | AN6: 2.6748294
A7: 36 | B7: 17 | C7: 11.949058 | D7: 15 | E7: 12 | F7: 0.77195017 | G7: 29 | H7: 7 | I7: 0.31857253 | J7: 3.2951545e+08 | K7: 165569000 | L7: 79942239 | M7: 77945900 | N7: 15764037 | O7: 227.61777 | P7: 2.6820904 | Q7: 44.097856 | R7: 805.18057 | S7: 1.1322593e-16 | T7: 22.327549 | U7: 100.934 | V7: -664.20669 | W7: 69.218784 | X7: 94.832719 | Y7: 121.522 | Z7: 251.87025 | AA7: 0 | AB7: 0 | AC7: 0 | AD7: 0 | AE7: 0 | AF7: 0 | AG7: 0 | AH7: 0 | AI7: 0 | AJ7: 0 | AK7: 0 | AL7: 0 | AM7: 0 | AN7: 2.6820904
A8: 34 | B8: 18 | C8: 12.014773 | D8: 24 | E8: 14 | F8: 1.144653 | G8: 13 | H8: 7 | I8: 1.0104683 | J8: 3.2948802e+08 | K8: 165537000 | L8: 79928024 | M8: 78386800 | N8: 15760399 | O8: 226.08831 | P8: 2.6909189 | Q8: 44.281141 | R8: 805.22583 | S8: 5.2145772e-21 | T8: 22.58454 | U8: 100.934 | V8: -676.76866 | W8: 69.218874 | X8: 94.834333 | Y8: 177.97 | Z8: 252.47931 | AA8: 0 | AB8: 0 | AC8: 0 | AD8: 0 | AE8: 0 | AF8: 0 | AG8: 0 | AH8: 0 | AI8: 0 | AJ8: 0 | AK8: 0 | AL8: 0 | AM8: 0 | AN8: 2.6909189
A9: 29 | B9: 19 | C9: 14.991857 | D9: 10 | E9: 5 | F9: 0.32992158 | G9: 13 | H9: 9 | I9: 0.8878511 | J9: 3.2912531e+08 | K9: 165521000 | L9: 79927423 | M9: 77275000 | N9: 15760196 | O9: 231.62022 | P9: 2.6464715 | Q9: 43.801929 | R9: 800.94033 | S9: 4.8262115e-08 | T9: 21.655975 | U9: 100.934 | V9: -613.48395 | W9: 69.21973 | X9: 94.845931 | Y9: 144.29 | Z9: 255.26467 | AA9: 0 | AB9: 0 | AC9: 0 | AD9: 0 | AE9: 0 | AF9: 0 | AG9: 0 | AH9: 0 | AI9: 0 | AJ9: 0 | AK9: 0 | AL9: 0 | AM9: 0 | AN9: 2.6464715
A10: 27 | B10: 10 | C10: 1 | D10: 10 | E10: 5 | F10: 0.3 | G10: 10 | H10: 8 | I10: 0.3 | J10: 3.2603272e+08 | K10: 165445000 | L10: 79977978 | M10: 78109500 | N10: 15772318 | O10: 229.31465 | P10: 2.6463971 | Q10: 43.712631 | R10: 802.43618 | S10: 5.6007505e-08 | T10: 21.475174 | U10: 91.85 | V10: -481.55194 | W10: 69.595135 | X10: 97.136021 | Y10: 144.29 | Z10: 275.57108 | AA10: 0 | AB10: 0 | AC10: 0 | AD10: 0 | AE10: 0 | AF10: 0 | AG10: 0 | AH10: 0 | AI10: 0 | AJ10: 0 | AK10: 0 | AL10: 0 | AM10: 0 | AN10: 2.6463971
A11: 27 | B11: 10 | C11: 15 | D11: 10 | E11: 5 | F11: 1.0133014 | G11: 16 | H11: 14 | I11: 1.0803282 | J11: 3.2947527e+08 | K11: 165522000 | L11: 79926122 | M11: 77909500 | N11: 15759937 | O11: 228.41512 | P11: 2.6724036 | Q11: 44.067979 | R11: 803.38376 | S11: 2.6343909e-09 | T11: 22.119188 | U11: 100.934 | V11: -650.03412 | W11: 69.222165 | X11: 94.861836 | Y11: 144.29 | Z11: 253.19138 | AA11: 0 | AB11: 0 | AC11: 0 | AD11: 0 | AE11: 0 | AF11: 0 | AG11: 0 | AH11: 0 | AI11: 0 | AJ11: 0 | AK11: 0 | AL11: 0 | AM11: 0 | AN11: 2.6724036
A12: 27 | B12: 19 | C12: 1 | D12: 12 | E12: 10 | F12: 0.3 | G12: 14 | H12: 12 | I12: 0.3 | J12: 3.262259e+08 | K12: 165443000 | L12: 79975976 | M12: 77954100 | N12: 15771831 | O12: 229.57211 | P12: 2.6469501 | Q12: 43.615033 | R12: 803.75953 | S12: 1.1715604e-09 | T12: 21.425635 | U12: 68.71 | V12: -491.77019 | W12: 69.729894 | X12: 98.485041 | Y12: 100.934 | Z12: 275.2714 | AA12: 0 | AB12: 0 | AC12: 0 | AD12: 0 | AE12: 0 | AF12: 0 | AG12: 0 | AH12: 0 | AI12: 0 | AJ12: 0 | AK12: 0 | AL12: 0 | AM12: 0 | AN12: 2.6469501
A13: 27 | B13: 19 | C13: 1 | D13: 10 | E13: 5 | F13: 0.3 | G13: 10 | H13: 7 | I13: 0.3 | J13: 3.2606976e+08 | K13: 165428000 | L13: 79962261 | M13: 78071300 | N13: 15768613 | O13: 228.9969 | P13: 2.6505877 | Q13: 43.694359 | R13: 802.83574 | S13: 5.6413498e-08 | T13: 21.8264 | U13: 68.71 | V13: -484.82801 | W13: 69.729894 | X13: 98.485041 | Y13: 144.29 | Z13: 261.4383 | AA13: 0 | AB13: 0 | AC13: 0 | AD13: 0 | AE13: 0 | AF13: 0 | AG13: 0 | AH13: 0 | AI13: 0 | AJ13: 0 | AK13: 0 | AL13: 0 | AM13: 0 | AN13: 2.6505877
... A340: 35 | B340: 13 | C340: 10.321383 | D340: 27 | E340: 13 | F340: 0.96193427 | G340: 25 | H340: 11 | I340: 0.58046547 | J340: 3.2719362e+08 | K340: 165430000 | L340: 79925722 | M340: 77595700 | N340: 15759990 | O340: 226.40897 | P340: 2.6935663 | Q340: 44.258124 | R340: 804.96592 | S340: 2.9284908e-19 | T340: 22.467633 | U340: 100.934 | V340: -670.33698 | W340: 69.219516 | X340: 94.843829 | Y340: 177.97 | Z340: 252.45787 | AA340: 0 | AB340: 0 | AC340: 0 | AD340: 0 | AE340: 0 | AF340: 0 | AG340: 0 | AH340: 0 | AI340: 0 | AJ340: 0 | AK340: 0 | AL340: 0 | AM340: 0 | AN340: 2.6935663

Sheet 20250607_173844_D3
A1: GAS.N | B1: GAS.F | C1: GAS.RR | D1: SAF.N | E1: SAF.F | F1: SAF.RR | G1: DSL.N | H1: DSL.F | I1: DSL.RR | J1: TCC | K1: TOC | L1: TRC | M1: TPS | N1: TUC | O1: SAF | P1: MJSP | Q1: LHV | R1: SG | S1: SLF | T1: ARM | U1: MBP | V1: MFP | W1: GT10 | X1: GT90 | Y1: DFP | Z1: DT90 | AA1: ERRSIM | AB1: ERR_0 | AC1: ERR_1 | AD1: ERR_2 | AE1: ERR_3 | AF1: ERR_4 | AG1: ERR_5 | AH1: ERR_6 | AI1: ERR_7 | AJ1: ERR_8 | AK1: ERR_9 | AL1: ERR_10 | AM1: ERR_11 | AN1: OBJ
A2: 30 | B2: 15 | C2: 3.6 | D2: 20 | E2: 10 | F2: 0.43 | G2: 20 | H2: 10 | I2: 0.72 | J2: 3.2719307e+08 | K2: 165430000 | L2: 79925721 | M2: 77595700 | N2: 15759844 | O2: 230.15657 | P2: 2.6497059 | Q2: 43.94435 | R2: 801.48126 | S2: 4.254062e-13 | T2: 21.871823 | U2: 100.934 | V2: -621.36518 | W2: 69.225905 | X2: 94.879777 | Y2: 165.7 | Z2: 253.70994 | AA2: 99 | AB2: 0 | AC2: 0 | AD2: 0 | AE2: 0 | AF2: 0 | AG2: 0 | AH2: 0 | AI2: 0 | AJ2: 0 | AK2: 0 | AL2: 0 | AM2: 0 | AN2: 101.64971
A3: 30 | B3: 15 | C3: 2.95 | D3: 20 | E3: 12 | F3: 0.56748 | G3: 20 | H3: 12 | I3: 0.7 | J3: 3.2719249e+08 | K3: 165430000 | L3: 79925721 | M3: 77595700 | N3: 15759715 | O3: 228.43843 | P3: 2.6696332 | Q3: 44.063535 | R3: 803.38194 | S3: 4.9130103e-16 | T3: 22.166252 | U3: 100.934 | V3: -641.81686 | W3: 69.23129 | X3: 94.901946 | Y3: 144.29 | Z3: 253.48249 | AA3: 0 | AB3: 0 | AC3: 0 | AD3: 0 | AE3: 0 | AF3: 0 | AG3: 0 | AH3: 0 | AI3: 0 | AJ3: 0 | AK3: 0 | AL3: 0 | AM3: 0 | AN3: 2.6696332
A4: 31 | B4: 11 | C4: 12.767639 | D4: 23 | E4: 8 | F4: 0.68829861 | G4: 27 | H4: 13 | I4: 0.32396573 | J4: 3.2720359e+08 | K4: 165430000 | L4: 79925738 | M4: 77595700 | N4: 15763594 | O4: 228.22839 | P4: 2.672123 | Q4: 44.11484 | R4: 803.22166 | S4: 2.40668e-12 | T4: 22.176526 | U4: 100.934 | V4: -643.7502 | W4: 69.220449 | X4: 94.851567 | Y4: 177.97 | Z4: 252.23349 | AA4: 0 | AB4: 0 | AC4: 0 | AD4: 0 | AE4: 0 | AF4: 0 | AG4: 0 | AH4: 0 | AI4: 0 | AJ4: 0 | AK4: 0 | AL4: 0 | AM4: 0 | AN4: 2.672123
A5: 34 | B5: 19 | C5: 10.735737 | D5: 27 | E5: 9 | F5: 0.89696805 | G5: 27 | H5: 13 | I5: 1.2275239 | J5: 3.2719231e+08 | K5: 165430000 | L5: 79925720 | M5: 77595700 | N5: 15759532 | O5: 227.15272 | P5: 2.6847431 | Q5: 44.206569 | R5: 804.17274 | S5: 4.2004862e-14 | T5: 22.30896 | U5: 100.934 | V5: -658.79099 | W5: 69.218906 | X5: 94.834601 | Y5: 177.97 | Z5: 252.8058 | AA5: 0 | AB5: 0 | AC5: 0 | AD5: 0 | AE5: 0 | AF5: 0 | AG5: 0 | AH5: 0 | AI5: 0 | AJ5: 0 | AK5: 0 | AL5: 0 | AM5: 0 | AN5: 2.6847431
A6: 35 | B6: 13 | C6: 9.0190933 | D6: 20 | E6: 7 | F6: 0.9940642 | G6: 17 | H6: 12 | I6: 0.53469112 | J6: 3.2719174e+08 | K6: 165430000 | L6: 79925725 | M6: 77595700 | N6: 15760528 | O6: 227.37985 | P6: 2.6820596 | Q6: 44.184333 | R6: 803.93203 | S6: 8.1434397e-12 | T6: 22.26939 | U6: 100.934 | V6: -657.16484 | W6: 69.219731 | X6: 94.845859 | Y6: 177.97 | Z6: 253.80945 | AA6: 0 | AB6: 0 | AC6: 0 | AD6: 0 | AE6: 0 | AF6: 0 | AG6: 0 | AH6: 0 | AI6: 0 | AJ6: 0 | AK6: 0 | AL6: 0 | AM6: 0 | AN6: 2.6820596
A7: 38 | B7: 14 | C7: 10.708852 | D7: 27 | E7: 11 | F7: 0.44794873 | G7: 15 | H7: 12 | I7: 0.8883322 | J7: 3.2718743e+08 | K7: 165430000 | L7: 79925722 | M7: 77595700 | N7: 15759889 | O7: 230.05233 | P7: 2.6508898 | Q7: 43.9721 | R7: 801.45795 | S7: 3.464067e-14 | T7: 21.926732 | U7: 100.934 | V7: -620.24539 | W7: 69.219071 | X7: 94.83846 | Y7: 177.97 | Z7: 256.01805 | AA7: 0 | AB7: 0 | AC7: 0 | AD7: 0 | AE7: 0 | AF7: 0 | AG7: 0 | AH7: 0 | AI7: 0 | AJ7: 0 | AK7: 0 | AL7: 0 | AM7: 0 | AN7: 2.6508898
A8: 30 | B8: 16 | C8: 13.740455 | D8: 17 | E8: 9 | F8: 1.1366645 | G8: 25 | H8: 14 | I8: 0.83519442 | J8: 3.2719237e+08 | K8: 165430000 | L8: 79925720 | M8: 77595700 | N8: 15759558 | O8: 226.57462 | P8: 2.6915933 | Q8: 44.234483 | R8: 804.87998 | S8: 1.6450595e-14 | T8: 22.456791 | U8: 100.934 | V8: -671.43151 | W8: 69.219445 | X8: 94.843805 | Y8: 165.7 | Z8: 252.62199 | AA8: 0 | AB8: 0 | AC8: 0 | AD8: 0 | AE8: 0 | AF8: 0 | AG8: 0 | AH8: 0 | AI8: 0 | AJ8: 0 | AK8: 0 | AL8: 0 | AM8: 0 | AN8: 2.6915933
A9: 36 | B9: 19 | C9: 1.2472296 | D9: 12 | E9: 5 | F9: 0.95390337 | G9: 27 | H9: 9 | I9: 1.1398447 | J9: 3.2719283e+08 | K9: 165430000 | L9: 79925721 | M9: 77595700 | N9: 15759724 | O9: 226.82014 | P9: 2.6886812 | Q9: 44.02941 | R9: 804.35026 | S9: 2.6044979e-09 | T9: 22.274984 | U9: 91.85 | V9: -568.51198 | W9: 69.452052 | X9: 96.069193 | Y9: 144.29 | Z9: 253.17228 | AA9: 0 | AB9: 0 | AC9: 0 | AD9: 0 | AE9: 0 | AF9: 0 | AG9: 0 | AH9: 0 | AI9: 0 | AJ9: 0 | AK9: 0 | AL9: 0 | AM9: 0 | AN9: 2.6886812
A10: 29 | B10: 19 | C10: 13.297894 | D10: 12 | E10: 5 | F10: 0.58990344 | G10: 10 | H10: 7 | I10: 0.84675088 | J10: 3.2719165e+08 | K10: 165430000 | L10: 79925730 | M10: 77595700 | N10: 15761729 | O10: 229.71813 | P10: 2.6547589 | Q10: 43.97407 | R10: 802.08194 | S10: 8.9449186e-09 | T10: 21.941107 | U10: 100.934 | V10: -632.35041 | W10: 69.219842 | X10: 94.846948 | Y10: 144.29 | Z10: 255.93431 | AA10: 0 | AB10: 0 | AC10: 0 | AD10: 0 | AE10: 0 | AF10: 0 | AG10: 0 | AH10: 0 | AI10: 0 | AJ10: 0 | AK10: 0 | AL10: 0 | AM10: 0 | AN10: 2.6547589
A11: 39 | B11: 10 | C11: 15 | D11: 29 | E11: 14 | F11: 0.3 | G11: 29 | H11: 7 | I11: 1.4 | J11: 3.2719329e+08 | K11: 165430000 | L11: 79925722 | M11: 77595700 | N11: 15759893 | O11: 232.02811 | P11: 2.628334 | Q11: 43.80951 | R11: 799.96345 | S11: 6.007757e-08 | T11: 21.744364 | U11: 100.934 | V11: -594.13048 | W11: 69.220163 | X11: 94.847149 | Y11: 177.97 | Z11: 254.34269 | AA11: 0 | AB11: 0 | AC11: 0 | AD11: 0 | AE11: 0 | AF11: 0 | AG11: 0 | AH11: 0 | AI11: 0 | AJ11: 0 | AK11: 0 | AL11: 0 | AM11: 0 | AN11: 2.628334
A12: 27 | B12: 10 | C12: 1 | D12: 29 | E12: 14 | F12: 0.3 | G12: 10 | H12: 7 | I12: 0.3 | J12: 3.2719884e+08 | K12: 165430000 | L12: 79925762 | M12: 77595700 | N12: 15768817 | O12: 229.2972 | P12: 2.6596536 | Q12: 43.75922 | R12: 801.42149 | S12: 3.6233038e-14 | T12: 21.478922 | U12: 91.85 | V12: -471.70286 | W12: 69.595135 | X12: 97.136021 | Y12: 170.55 | Z12: 261.58617 | AA12: 0 | AB12: 0 | AC12: 0 | AD12: 0 | AE12: 0 | AF12: 0 | AG12: 0 | AH12: 0 | AI12: 0 | AJ12: 0 | AK12: 0 | AL12: 0 | AM12: 0 | AN12: 2.6596536
A13: 39 | B13: 10 | C13: 15 | D13: 29 | E13: 5 | F13: 0.3 | G13: 10 | H13: 7 | I13: 0.3 | J13: 3.2719886e+08 | K13: 165430000 | L13: 79925762 | M13: 77595700 | N13: 15768719 | O13: 232.02811 | P13: 2.6283503 | Q13: 43.80951 | R13: 799.96345 | S13: 6.007757e-08 | T13: 21.744364 | U13: 100.934 | V13: -594.13048 | W13: 69.220163 | X13: 94.847149 | Y13: 177.97 | Z13: 261.66171 | AA13: 0 | AB13: 0 | AC13: 0 | AD13: 0 | AE13: 0 | AF13: 0 | AG13: 0 | AH13: 0 | AI13: 0 | AJ13: 0 | AK13: 0 | AL13: 0 | AM13: 0 | AN13: 2.6283503
... A308: 27 | B308: 10 | C308: 1 | D308: 19 | E308: 5 | F308: 1.2 | G308: 20 | H308: 14 | I308: 1.4 | J308: 3.2719197e+08 | K308: 165430000 | L308: 79925720 | M308: 77595700 | N308: 15759522 | O308: 225.40942 | P308: 2.7055056 | Q308: 44.07853 | R308: 804.98925 | S308: 1.4369662e-09 | T308: 22.023362 | U308: 91.85 | V308: -518.75046 | W308: 69.595135 | X308: 97.136021 | Y308: 177.97 | Z308: 253.14049 | AA308: 0 | AB308: 0 | AC308: 0 | AD308: 0 | AE308: 0 | AF308: 0 | AG308: 0 | AH308: 0 | AI308: 0 | AJ308: 0 | AK308: 0 | AL308: 0 | AM308: 0 | AN308: 2.7055056

Sheet 20250608_211122_TSOL2
A1: PHENOLS | B1: PHENOL1 | C1: PHENOL2 | D1: PHENOL3 | E1: CYC-5A | F1: CYC-5A1 | G1: CYC-6A | H1: CYC-6A1 | I1: CYC-6A2 | J1: CYC-6A3 | K1: ARM-A | L1: ARM-A1 | M1: ARM-A2 | N1: ARM-B | O1: ARM-B1 | P1: ARM-B2 | Q1: TCC | R1: TOC | S1: TRC | T1: TPS | U1: TUC | V1: SAF | W1: MJSP | X1: LHV | Y1: SG | Z1: SLF | AA1: ARM | AB1: MBP | AC1: MFP | AD1: GT10 | AE1: GT90 | AF1: DFP | AG1: DT90 | AH1: ERRSIM | AI1: ERR_0 | AJ1: ERR_1 | AK1: ERR_2 | AL1: ERR_3 | AM1: ERR_4 | AN1: ERR_5 | AO1: ERR_6 | AP1: ERR_7 | AQ1: ERR_8 | AR1: ERR_9 | AS1: ERR_10 | AT1: ERR_11
A2: 2.2 | B2: 0 | C2: 0 | D2: 0 | E2: 1.8 | F2: 0 | G2: 2.4 | H2: 0 | I2: 0 | J2: 0 | K2: 3.5 | L2: 0 | M2: 0 | N2: 1.5 | O2: 0 | P2: 0 | Q2: 4.2736174e+08 | R2: 179051000 | S2: 79966127 | T2: 77196800 | U2: 15761600 | V2: 233.88238 | W2: 3.162854 | X2: 43.435542 | Y2: 786.17593 | Z2: 4.1393856e-12 | AA2: 24.225895 | AB2: 100.934 | AC2: -51.369138 | AD2: 65.71182 | AE2: 94.099567 | AF2: 177.97 | AG2: 265.57843 | AH2: 0 | AI2: 0 | AJ2: 0 | AK2: 0 | AL2: 0 | AM2: 0 | AN2: 0 | AO2: 0 | AP2: 0 | AQ2: 0 | AR2: 0 | AS2: 0 | AT2: 0
A3: 0 | B3: 3.06 | C3: 0 | D3: 0 | E3: 1.8 | F3: 0 | G3: 2.4 | H3: 0 | I3: 0 | J3: 0 | K3: 3.5 | L3: 0 | M3: 0 | N3: 1.5 | O3: 0 | P3: 0 | Q3: 4.2716524e+08 | R3: 179010000 | S3: 79925721 | T3: 77595500 | U3: 15759840 | V3: 230.1514 | W3: 3.205114 | X3: 43.944395 | Y3: 801.47763 | Z3: 4.2499805e-13 | AA3: 21.871605 | AB3: 100.934 | AC3: -1.2403163 | AD3: 69.225417 | AE3: 94.879482 | AF3: 165.7 | AG3: 253.66075 | AH3: 0 | AI3: 0 | AJ3: 0 | AK3: 0 | AL3: 9.6899209 | AM3: 0 | AN3: 0 | AO3: 0 | AP3: 0 | AQ3: 0 | AR3: 0 | AS3: 0 | AT3: 0
A4: 0 | B4: 0 | C4: 3 | D4: 0 | E4: 1.8 | F4: 0 | G4: 2.4 | H4: 0 | I4: 0 | J4: 0 | K4: 3.5 | L4: 0 | M4: 0 | N4: 1.5 | O4: 0 | P4: 0 | Q4: 4.2754386e+08 | R4: 179046000 | S4: 79960330 | T4: 75965600 | U4: 15763006 | V4: 235.59803 | W4: 3.1633216 | X4: 43.426742 | Y4: 794.9734 | Z4: 2.707062e-12 | AA4: 23.343695 | AB4: 100.934 | AC4: 51.689729 | AD4: 69.167764 | AE4: 94.810027 | AF4: 177.97 | AG4: 260.44183 | AH4: 0 | AI4: 0 | AJ4: 0 | AK4: 0 | AL4: 22.922432 | AM4: 0 | AN4: 0 | AO4: 0 | AP4: 0 | AQ4: 0 | AR4: 0 | AS4: 0 | AT4: 0
A5: 0 | B5: 0 | C5: 0 | D5: 2.14 | E5: 1.8 | F5: 0 | G5: 2.4 | H5: 0 | I5: 0 | J5: 0 | K5: 3.5 | L5: 0 | M5: 0 | N5: 1.5 | O5: 0 | P5: 0 | Q5: 4.273857e+08 | R5: 179057000 | S5: 79972128 | T5: 77231100 | U5: 15761869 | V5: 233.53512 | W5: 3.1670919 | X5: 43.436304 | Y5: 785.23548 | Z5: 5.1557089e-12 | AA5: 23.764076 | AB5: 100.934 | AC5: -51.300818 | AD5: 65.765694 | AE5: 94.099302 | AF5: 177.97 | AG5: 262.58632 | AH5: 0 | AI5: 0 | AJ5: 0 | AK5: 0 | AL5: 0 | AM5: 0 | AN5: 0 | AO5: 0 | AP5: 0 | AQ5: 0 | AR5: 0 | AS5: 0 | AT5: 0
A6: 2.2 | B6: 0 | C6: 0 | D6: 0 | E6: 0 | F6: 2.1 | G6: 2.4 | H6: 0 | I6: 0 | J6: 0 | K6: 3.5 | L6: 0 | M6: 0 | N6: 1.5 | O6: 0 | P6: 0 | Q6: 4.2745794e+08 | R6: 179053000 | S6: 79953725 | T6: 76087400 | U6: 15758545 | V6: 234.82317 | W6: 3.1713533 | X6: 43.476356 | Y6: 785.49212 | Z6: 2.914361e-12 | AA6: 23.781165 | AB6: 91.85 | AC6: -52.542917 | AD6: 64.648477 | AE6: 86.776644 | AF6: 177.97 | AG6: 260.52021 | AH6: 0 | AI6: 0 | AJ6: 0 | AK6: 0 | AL6: 0 | AM6: 0 | AN6: 0 | AO6: 0 | AP6: 0 | AQ6: 0 | AR6: 0 | AS6: 0 | AT6: 0
A7: 2.2 | B7: 0 | C7: 0 | D7: 0 | E7: 1.8 | F7: 0 | G7: 0 | H7: 2.06 | I7: 0 | J7: 0 | K7: 3.5 | L7: 0 | M7: 0 | N7: 1.5 | O7: 0 | P7: 0 | Q7: 4.2716071e+08 | R7: 179052000 | S7: 79981030 | T7: 78035500 | U7: 15764842 | V7: 232.83053 | W7: 3.1606743 | X7: 43.380719 | Y7: 787.02452 | Z7: 6.0708771e-12 | AA7: 24.720813 | AB7: 100.934 | AC7: -50.133857 | AD7: 69.797303 | AE7: 96.904744 | AF7: 177.97 | AG7: 276.27467 | AH7: 0 | AI7: 0 | AJ7: 0 | AK7: 0 | AL7: 0 | AM7: 0 | AN7: 0 | AO7: 0 | AP7: 0 | AQ7: 0 | AR7: 0 | AS7: 0 | AT7: 0
A8: 2.2 | B8: 0 | C8: 0 | D8: 0 | E8: 1.8 | F8: 0 | G8: 0 | H8: 0 | I8: 1.77 | J8: 0 | K8: 3.5 | L8: 0 | M8: 0 | N8: 1.5 | O8: 0 | P8: 0 | Q8: 4.2716648e+08 | R8: 179073000 | S8: 79998137 | T8: 78213200 | U8: 15770141 | V8: 229.19846 | W8: 3.2077601 | X8: 43.290077 | Y8: 797.91732 | Z8: 8.9420932e-12 | AA8: 25.441083 | AB8: 100.934 | AC8: -48.501145 | AD8: 70.977381 | AE8: 101.87174 | AF8: 177.97 | AG8: 277.43201 | AH8: 0 | AI8: 0 | AJ8: 0 | AK8: 0 | AL8: 0 | AM8: 0 | AN8: 0 | AO8: 0.17643326 | AP8: 0 | AQ8: 0.13962584 | AR8: 0 | AS8: 0 | AT8: 0
A9: 2.2 | B9: 0 | C9: 0 | D9: 0 | E9: 1.8 | F9: 0 | G9: 0 | H9: 0 | I9: 0 | J9: 2.06 | K9: 3.5 | L9: 0 | M9: 0 | N9: 1.5 | O9: 0 | P9: 0 | Q9: 4.2722633e+08 | R9: 179058000 | S9: 79981631 | T9: 79029300 | U9: 15769880 | V9: 224.81045 | W9: 3.2542328 | X9: 43.418597 | Y9: 804.53957 | Z9: 6.7101389e-12 | AA9: 25.509521 | AB9: 100.934 | AC9: -48.345858 | AD9: 72.394248 | AE9: 102.96474 | AF9: 177.97 | AG9: 276.42391 | AH9: 0 | AI9: 0 | AJ9: 0 | AK9: 0 | AL9: 0 | AM9: 0 | AN9: 0 | AO9: 0.20380831 | AP9: 0 | AQ9: 0.34203547 | AR9: 0 | AS9: 0 | AT9: 0
A10: 2.2 | B10: 0 | C10: 0 | D10: 0 | E10: 1.8 | F10: 0 | G10: 2.4 | H10: 0 | I10: 0 | J10: 0 | K10: 0 | L10: 3.44 | M10: 0 | N10: 1.5 | O10: 0 | P10: 0 | Q10: 4.2746554e+08 | R10: 179057000 | S10: 79969028 | T10: 76928200 | U10: 15762677 | V10: 230.32018 | W10: 3.2173407 | X10: 44.442564 | Y10: 799.04391 | Z10: 4.0291696e-12 | AA10: 9.2842492 | AB10: 100.934 | AC10: -50.118286 | AD10: 66.059273 | AE10: 94.186468 | AF10: 177.97 | AG10: 267.58516 | AH10: 0 | AI10: 0 | AJ10: 0 | AK10: 0 | AL10: 0 | AM10: 0 | AN10: 0 | AO10: 0 | AP10: 0 | AQ10: 0 | AR10: 0 | AS10: 0 | AT10: 0
A11: 2.2 | B11: 0 | C11: 0 | D11: 0 | E11: 1.8 | F11: 0 | G11: 2.4 | H11: 0 | I11: 0 | J11: 0 | K11: 0 | L11: 0 | M11: 2.69 | N11: 1.5 | O11: 0 | P11: 0 | Q11: 4.2758972e+08 | R11: 179136000 | S11: 80025649 | T11: 74751600 | U11: 15770518 | V11: 236.57942 | W11: 3.1746623 | X11: 43.726094 | Y11: 794.53021 | Z11: 1.9239546e-11 | AA11: 10.597976 | AB11: 100.934 | AC11: -27.682032 | AD11: 65.260756 | AE11: 93.679267 | AF11: 177.97 | AG11: 278.60948 | AH11: 0 | AI11: 0 | AJ11: 0 | AK11: 0 | AL11: 3.0794919 | AM11: 0 | AN11: 0 | AO11: 0 | AP11: 0 | AQ11: 0 | AR11: 0 | AS11: 0 | AT11: 0
A12: 2.2 | B12: 0 | C12: 0 | D12: 0 | E12: 1.8 | F12: 0 | G12: 2.4 | H12: 0 | I12: 0 | J12: 0 | K12: 3.5 | L12: 0 | M12: 0 | N12: 0 | O12: 1.24 | P12: 0 | Q12: 4.2739186e+08 | R12: 179061000 | S12: 79976029 | T12: 76809500 | U12: 15761993 | V12: 235.27903 | W12: 3.15162 | X12: 43.200858 | Y12: 782.31301 | Z12: 1.400908e-11 | AA12: 19.608319 | AB12: 100.934 | AC12: -46.66187 | AD12: 65.420629 | AE12: 93.959173 | AF12: 177.97 | AG12: 276.41337 | AH12: 0 | AI12: 0 | AJ12: 0 | AK12: 0 | AL12: 0 | AM12: 0 | AN12: 0 | AO12: 0 | AP12: 0 | AQ12: 0 | AR12: 0 | AS12: 0 | AT12: 0
A13: 2.2 | B13: 0 | C13: 0 | D13: 0 | E13: 1.8 | F13: 0 | G13: 2.4 | H13: 0 | I13: 0 | J13: 0 | K13: 3.5 | L13: 0 | M13: 0 | N13: 0 | O13: 0 | P13: 1.3 | Q13: 4.2740178e+08 | R13: 179060000 | S13: 79975129 | T13: 76753700 | U13: 15761956 | V13: 234.93579 | W13: 3.1572828 | X13: 43.224384 | Y13: 784.68278 | Z13: 1.0631202e-11 | AA13: 19.498454 | AB13: 100.934 | AC13: -47.218649 | AD13: 65.57399 | AE13: 94.016049 | AF13: 177.97 | AG13: 275.76418 | AH13: 0 | AI13: 0 | AJ13: 0 | AK13: 0 | AL13: 0 | AM13: 0 | AN13: 0 | AO13: 0 | AP13: 0 | AQ13: 0 | AR13: 0 | AS13: 0 | AT13: 0

Sheet 20250608_211122_CUT
A1: PHENOLS | B1: PHENOL1 | C1: CYC-5A | D1: CYC-5A1 | E1: CYC-6A | F1: CYC-6A1 | G1: CYC-6A2 | H1: CYC-6A3 | I1: ARM-A | J1: ARM-A1 | K1: ARM-B | L1: ARM-B1 | M1: ARM-B2 | N1: TCC | O1: TOC | P1: TRC | Q1: TPS | R1: TUC | S1: SAF | T1: MJSP | U1: LHV | V1: SG | W1: SLF | X1: ARM | Y1: MBP | Z1: MFP | AA1: GT10 | AB1: GT90 | AC1: DFP | AD1: DT90 | AE1: ERRSIM | AF1: ERR_0 | AG1: ERR_1 | AH1: ERR_2 | AI1: ERR_3 | AJ1: ERR_4 | AK1: ERR_5 | AL1: ERR_6 | AM1: ERR_7 | AN1: ERR_8 | AO1: ERR_9 | AP1: ERR_10 | AQ1: ERR_11
A2: 2.2 | B2: 0 | C2: 1.8 | D2: 0 | E2: 2.4 | F2: 0 | G2: 0 | H2: 0 | I2: 3.5 | J2: 0 | K2: 1.5 | L2: 0 | M2: 0 | N2: 4.2736174e+08 | O2: 179051000 | P2: 79966127 | Q2: 77196800 | R2: 15761600 | S2: 233.88238 | T2: 3.162854 | U2: 43.435542 | V2: 786.17593 | W2: 4.1393856e-12 | X2: 24.225895 | Y2: 100.934 | Z2: -51.369138 | AA2: 65.71182 | AB2: 94.099567 | AC2: 177.97 | AD2: 265.57843 | AE2: 0 | AF2: 0 | AG2: 0 | AH2: 0 | AI2: 0 | AJ2: 0 | AK2: 0 | AL2: 0 | AM2: 0 | AN2: 0 | AO2: 0 | AP2: 0 | AQ2: 0
A3: 0 | B3: 2.14 | C3: 1.8 | D3: 0 | E3: 2.4 | F3: 0 | G3: 0 | H3: 0 | I3: 3.5 | J3: 0 | K3: 1.5 | L3: 0 | M3: 0 | N3: 4.273857e+08 | O3: 179057000 | P3: 79972128 | Q3: 77231100 | R3: 15761869 | S3: 233.53512 | T3: 3.1670919 | U3: 43.436304 | V3: 785.23548 | W3: 5.1557089e-12 | X3: 23.764076 | Y3: 100.934 | Z3: -51.300818 | AA3: 65.765694 | AB3: 94.099302 | AC3: 177.97 | AD3: 262.58632 | AE3: 0 | AF3: 0 | AG3: 0 | AH3: 0 | AI3: 0 | AJ3: 0 | AK3: 0 | AL3: 0 | AM3: 0 | AN3: 0 | AO3: 0 | AP3: 0 | AQ3: 0
A4: 2.2 | B4: 0 | C4: 0 | D4: 2.1 | E4: 2.4 | F4: 0 | G4: 0 | H4: 0 | I4: 3.5 | J4: 0 | K4: 1.5 | L4: 0 | M4: 0 | N4: 4.2745794e+08 | O4: 179053000 | P4: 79953725 | Q4: 76087400 | R4: 15758545 | S4: 234.82317 | T4: 3.1713533 | U4: 43.476356 | V4: 785.49212 | W4: 2.914361e-12 | X4: 23.781165 | Y4: 91.85 | Z4: -52.542917 | AA4: 64.648477 | AB4: 86.776644 | AC4: 177.97 | AD4: 260.52021 | AE4: 0 | AF4: 0 | AG4: 0 | AH4: 0 | AI4: 0 | AJ4: 0 | AK4: 0 | AL4: 0 | AM4: 0 | AN4: 0 | AO4: 0 | AP4: 0 | AQ4: 0
A5: 2.2 | B5: 0 | C5: 1.8 | D5: 0 | E5: 0 | F5: 2.06 | G5: 0 | H5: 0 | I5: 3.5 | J5: 0 | K5: 1.5 | L5: 0 | M5: 0 | N5: 4.2716071e+08 | O5: 179052000 | P5: 79981030 | Q5: 78035500 | R5: 15764842 | S5: 232.83053 | T5: 3.1606743 | U5: 43.380719 | V5: 787.02452 | W5: 6.0708771e-12 | X5: 24.720813 | Y5: 100.934 | Z5: -50.133857 | AA5: 69.797303 | AB5: 96.904744 | AC5: 177.97 | AD5: 276.27467 | AE5: 0 | AF5: 0 | AG5: 0 | AH5: 0 | AI5: 0 | AJ5: 0 | AK5: 0 | AL5: 0 | AM5: 0 | AN5: 0 | AO5: 0 | AP5: 0 | AQ5: 0
A6: 2.2 | B6: 0 | C6: 1.8 | D6: 0 | E6: 0 | F6: 0 | G6: 1.77 | H6: 0 | I6: 3.5 | J6: 0 | K6: 1.5 | L6: 0 | M6: 0 | N6: 4.2716648e+08 | O6: 179073000 | P6: 79998137 | Q6: 78213200 | R6: 15770141 | S6: 229.19846 | T6: 3.2077601 | U6: 43.290077 | V6: 797.91732 | W6: 8.9420932e-12 | X6: 25.441083 | Y6: 100.934 | Z6: -48.501145 | AA6: 70.977381 | AB6: 101.87174 | AC6: 177.97 | AD6: 277.43201 | AE6: 0 | AF6: 0 | AG6: 0 | AH6: 0 | AI6: 0 | AJ6: 0 | AK6: 0 | AL6: 0.17643326 | AM6: 0 | AN6: 0.13962584 | AO6: 0 | AP6: 0 | AQ6: 0
A7: 2.2 | B7: 0 | C7: 1.8 | D7: 0 | E7: 0 | F7: 0 | G7: 0 | H7: 2.06 | I7: 3.5 | J7: 0 | K7: 1.5 | L7: 0 | M7: 0 | N7: 4.2722633e+08 | O7: 179058000 | P7: 79981631 | Q7: 79029300 | R7: 15769880 | S7: 224.81045 | T7: 3.2542328 | U7: 43.418597 | V7: 804.53957 | W7: 6.7101389e-12 | X7: 25.509521 | Y7: 100.934 | Z7: -48.345858 | AA7: 72.394248 | AB7: 102.96474 | AC7: 177.97 | AD7: 276.42391 | AE7: 0 | AF7: 0 | AG7: 0 | AH7: 0 | AI7: 0 | AJ7: 0 | AK7: 0 | AL7: 0.20380831 | AM7: 0 | AN7: 0.34203547 | AO7: 0 | AP7: 0 | AQ7: 0
A8: 2.2 | B8: 0 | C8: 1.8 | D8: 0 | E8: 2.4 | F8: 0 | G8: 0 | H8: 0 | I8: 0 | J8: 3.44 | K8: 1.5 | L8: 0 | M8: 0 | N8: 4.2746554e+08 | O8: 179057000 | P8: 79969028 | Q8: 76928200 | R8: 15762677 | S8: 230.32018 | T8: 3.2173407 | U8: 44.442564 | V8: 799.04391 | W8: 4.0291696e-12 | X8: 9.2842492 | Y8: 100.934 | Z8: -50.118286 | AA8: 66.059273 | AB8: 94.186468 | AC8: 177.97 | AD8: 267.58516 | AE8: 0 | AF8: 0 | AG8: 0 | AH8: 0 | AI8: 0 | AJ8: 0 | AK8: 0 | AL8: 0 | AM8: 0 | AN8: 0 | AO8: 0 | AP8: 0 | AQ8: 0
A9: 2.2 | B9: 0 | C9: 1.8 | D9: 0 | E9: 2.4 | F9: 0 | G9: 0 | H9: 0 | I9: 3.5 | J9: 0 | K9: 0 | L9: 1.24 | M9: 0 | N9: 4.2739186e+08 | O9: 179061000 | P9: 79976029 | Q9: 76809500 | R9: 15761993 | S9: 235.27903 | T9: 3.15162 | U9: 43.200858 | V9: 782.31301 | W9: 1.400908e-11 | X9: 19.608319 | Y9: 100.934 | Z9: -46.66187 | AA9: 65.420629 | AB9: 93.959173 | AC9: 177.97 | AD9: 276.41337 | AE9: 0 | AF9: 0 | AG9: 0 | AH9: 0 | AI9: 0 | AJ9: 0 | AK9: 0 | AL9: 0 | AM9: 0 | AN9: 0 | AO9: 0 | AP9: 0 | AQ9: 0
A10: 2.2 | B10: 0 | C10: 1.8 | D10: 0 | E10: 2.4 | F10: 0 | G10: 0 | H10: 0 | I10: 3.5 | J10: 0 | K10: 0 | L10: 0 | M10: 1.3 | N10: 4.2740178e+08 | O10: 179060000 | P10: 79975129 | Q10: 76753700 | R10: 15761956 | S10: 234.93579 | T10: 3.1572828 | U10: 43.224384 | V10: 784.68278 | W10: 1.0631202e-11 | X10: 19.498454 | Y10: 100.934 | Z10: -47.218649 | AA10: 65.57399 | AB10: 94.016049 | AC10: 177.97 | AD10: 275.76418 | AE10: 0 | AF10: 0 | AG10: 0 | AH10: 0 | AI10: 0 | AJ10: 0 | AK10: 0 | AL10: 0 | AM10: 0 | AN10: 0 | AO10: 0 | AP10: 0 | AQ10: 0

Sheet 20250608_223227_retune
A1: PHENOLS | B1: PHENOL1 | C1: PHENOL2 | D1: PHENOL3 | E1: CYC-5A | F1: CYC-5A1 | G1: CYC-6A | H1: CYC-6A1 | I1: CYC-6A2 | J1: CYC-6A3 | K1: ARM-A | L1: ARM-A1 | M1: ARM-A2 | N1: ARM-B | O1: ARM-B1 | P1: ARM-B2 | Q1: TCC | R1: TOC | S1: TRC | T1: TPS | U1: TUC | V1: SAF | W1: MJSP | X1: LHV | Y1: SG | Z1: SLF | AA1: ARM | AB1: MBP | AC1: MFP | AD1: GT10 | AE1: GT90 | AF1: DFP | AG1: DT90 | AH1: ERRSIM | AI1: ERR_0 | AJ1: ERR_1 | AK1: ERR_2 | AL1: ERR_3 | AM1: ERR_4 | AN1: ERR_5 | AO1: ERR_6 | AP1: ERR_7 | AQ1: ERR_8 | AR1: ERR_9 | AS1: ERR_10 | AT1: ERR_11
A2: 2.2 | B2: 0 | C2: 0 | D2: 0 | E2: 1.8 | F2: 0 | G2: 2.4 | H2: 0 | I2: 0 | J2: 0 | K2: 3.5 | L2: 0 | M2: 0 | N2: 1.5 | O2: 0 | P2: 0 | Q2: 4.2829091e+08 | R2: 179086000 | S2: 79956622 | T2: 86319300 | U2: 15779118 | V2: 160.95128 | W2: 4.3507035 | X2: 43.94671 | Y2: 769.64653 | Z2: 1.5332802e-30 | AA2: 21.904526 | AB2: 100.934 | AC2: -61.013861 | AD2: 65.71182 | AE2: 94.099567 | AF2: 100.934 | AG2: 222.43627 | AH2: 99 | AI2: 0 | AJ2: 0.069077032 | AK2: 0 | AL2: 0 | AM2: 0 | AN2: 0 | AO2: 0 | AP2: 0 | AQ2: 0 | AR2: 0 | AS2: 0 | AT2: 0
A3: 0 | B3: 3.06 | C3: 0 | D3: 0 | E3: 1.8 | F3: 0 | G3: 2.4 | H3: 0 | I3: 0 | J3: 0 | K3: 3.5 | L3: 0 | M3: 0 | N3: 1.5 | O3: 0 | P3: 0 | Q3: 4.2793194e+08 | R3: 179048000 | S3: 79918718 | T3: 85380500 | U3: 15778156 | V3: 166.48471 | W3: 4.2285207 | X3: 44.036015 | Y3: 772.05755 | Z3: 1.5008032e-30 | AA3: 21.740764 | AB3: 100.934 | AC3: -61.592126 | AD3: 69.225417 | AE3: 94.879482 | AF3: 121.522 | AG3: 214.05455 | AH3: 0 | AI3: 0 | AJ3: 0.037967135 | AK3: 0 | AL3: 0 | AM3: 0 | AN3: 0 | AO3: 0 | AP3: 0 | AQ3: 0 | AR3: 0 | AS3: 0 | AT3: 0
A4: 0 | B4: 0 | C4: 3 | D4: 0 | E4: 1.8 | F4: 0 | G4: 2.4 | H4: 0 | I4: 0 | J4: 0 | K4: 3.5 | L4: 0 | M4: 0 | N4: 1.5 | O4: 0 | P4: 0 | Q4: 4.2816642e+08 | R4: 179083000 | S4: 79953027 | T4: 85371300 | U4: 15780433 | V4: 165.11086 | W4: 4.265851 | X4: 43.971282 | Y4: 770.46372 | Z4: 9.6690338e-30 | AA4: 22.551552 | AB4: 100.934 | AC4: -60.822426 | AD4: 69.167764 | AE4: 94.810027 | AF4: 121.522 | AG4: 227.35214 | AH4: 0 | AI4: 0 | AJ4: 0.058532697 | AK4: 0 | AL4: 0 | AM4: 0 | AN4: 0 | AO4: 0 | AP4: 0 | AQ4: 0 | AR4: 0 | AS4: 0 | AT4: 0
A5: 2.2 | B5: 0 | C5: 0 | D5: 0 | E5: 1.8 | F5: 0 | G5: 2.4 | H5: 0 | I5: 0 | J5: 0 | K5: 0 | L5: 0 | M5: 2.69 | N5: 1.5 | O5: 0 | P5: 0 | Q5: 4.2856068e+08 | R5: 179136000 | S5: 80000227 | T5: 84445800 | U5: 15783835 | V5: 166.71751 | W5: 4.2522554 | X5: 44.678389 | Y5: 757.67786 | Z5: 1.0396548e-26 | AA5: 7.0038076 | AB5: 91.85 | AC5: -75.259442 | AD5: 65.260756 | AE5: 93.679267 | AF5: 100.934 | AG5: 223.45106 | AH5: 0 | AI5: 0 | AJ5: 0.22351143 | AK5: 0 | AL5: 0 | AM5: 0 | AN5: 1.2452405 | AO5: 0 | AP5: 0 | AQ5: 0 | AR5: 0 | AS5: 0 | AT5: 0
A6: 0 | B6: 3.06 | C6: 0 | D6: 0 | E6: 1.8 | F6: 0 | G6: 2.4 | H6: 0 | I6: 0 | J6: 0 | K6: 3.5 | L6: 0 | M6: 0 | N6: 1.5 | O6: 0 | P6: 0 | Q6: 4.2793094e+08 | R6: 179048000 | S6: 79918718 | T6: 85380500 | U6: 15778156 | V6: 166.48471 | W6: 4.2285166 | X6: 44.036015 | Y6: 772.05755 | Z6: 1.5008032e-30 | AA6: 21.740764 | AB6: 100.934 | AC6: -61.592126 | AD6: 69.225417 | AE6: 94.879482 | AF6: 121.522 | AG6: 214.05455 | AH6: 0 | AI6: 0 | AJ6: 0.037967135 | AK6: 0 | AL6: 0 | AM6: 0 | AN6: 0 | AO6: 0 | AP6: 0 | AQ6: 0 | AR6: 0 | AS6: 0 | AT6: 0
A7: 0 | B7: 0 | C7: 3 | D7: 0 | E7: 1.8 | F7: 0 | G7: 2.4 | H7: 0 | I7: 0 | J7: 0 | K7: 3.5 | L7: 0 | M7: 0 | N7: 1.5 | O7: 0 | P7: 0 | Q7: 4.2816642e+08 | R7: 179083000 | S7: 79953027 | T7: 85371300 | U7: 15780433 | V7: 165.11086 | W7: 4.265851 | X7: 43.971282 | Y7: 770.46372 | Z7: 9.6690338e-30 | AA7: 22.551552 | AB7: 100.934 | AC7: -60.822426 | AD7: 69.167764 | AE7: 94.810027 | AF7: 121.522 | AG7: 227.35214 | AH7: 0 | AI7: 0 | AJ7: 0.058532697 | AK7: 0 | AL7: 0 | AM7: 0 | AN7: 0 | AO7: 0 | AP7: 0 | AQ7: 0 | AR7: 0 | AS7: 0 | AT7: 0
A8: 0 | B8: 0 | C8: 0 | D8: 2.14 | E8: 1.8 | F8: 0 | G8: 2.4 | H8: 0 | I8: 0 | J8: 0 | K8: 3.5 | L8: 0 | M8: 0 | N8: 1.5 | O8: 0 | P8: 0 | Q8: 4.2830304e+08 | R8: 179092000 | S8: 79962923 | T8: 86363500 | U8: 15778756 | V8: 160.56986 | W8: 4.3600394 | X8: 43.945353 | Y8: 769.63521 | Z8: 1.3775234e-30 | AA8: 21.892272 | AB8: 100.934 | AC8: -60.985549 | AD8: 65.765694 | AE8: 94.099302 | AF8: 100.934 | AG8: 229.43028 | AH8: 0 | AI8: 0 | AJ8: 0.069223045 | AK8: 0 | AL8: 0 | AM8: 0 | AN8: 0 | AO8: 0 | AP8: 0 | AQ8: 0 | AR8: 0 | AS8: 0 | AT8: 0
A9: 2.2 | B9: 0 | C9: 0 | D9: 0 | E9: 0 | F9: 2.1 | G9: 2.4 | H9: 0 | I9: 0 | J9: 0 | K9: 3.5 | L9: 0 | M9: 0 | N9: 1.5 | O9: 0 | P9: 0 | Q9: 4.2839275e+08 | R9: 179089000 | S9: 79945421 | T9: 85272300 | U9: 15776437 | V9: 161.4609 | W9: 4.3661066 | X9: 43.934304 | Y9: 769.62106 | Z9: 9.7904225e-31 | AA9: 21.416805 | AB9: 91.85 | AC9: -61.628346 | AD9: 64.648477 | AE9: 86.776644 | AF9: 100.934 | AG9: 221.52398 | AH9: 0 | AI9: 0 | AJ9: 0.069405729 | AK9: 0 | AL9: 0 | AM9: 0 | AN9: 0 | AO9: 0 | AP9: 0 | AQ9: 0 | AR9: 0 | AS9: 0 | AT9: 0
A10: 2.2 | B10: 0 | C10: 0 | D10: 0 | E10: 1.8 | F10: 0 | G10: 0 | H10: 2.06 | I10: 0 | J10: 0 | K10: 3.5 | L10: 0 | M10: 0 | N10: 1.5 | O10: 0 | P10: 0 | Q10: 4.2792254e+08 | R10: 179082000 | S10: 79969422 | T10: 87098400 | U10: 15781721 | V10: 160.31868 | W10: 4.3447484 | X10: 43.949359 | Y10: 769.92541 | Z10: 2.6279502e-30 | AA10: 22.502013 | AB10: 100.934 | AC10: -60.331184 | AD10: 69.797303 | AE10: 96.904744 | AF10: 100.934 | AG10: 222.74902 | AH10: 0 | AI10: 0 | AJ10: 0.065478632 | AK10: 0 | AL10: 0 | AM10: 0 | AN10: 0 | AO10: 0 | AP10: 0 | AQ10: 0 | AR10: 0 | AS10: 0 | AT10: 0
A11: 2.2 | B11: 0 | C11: 0 | D11: 0 | E11: 1.8 | F11: 0 | G11: 0 | H11: 0 | I11: 1.77 | J11: 0 | K11: 3.5 | L11: 0 | M11: 0 | N11: 1.5 | O11: 0 | P11: 0 | Q11: 4.2814987e+08 | R11: 179101000 | S11: 79980423 | T11: 87220100 | U11: 15785408 | V11: 157.19017 | W11: 4.4293186 | X11: 43.904244 | Y11: 784.28209 | Z11: 4.1127297e-30 | AA11: 23.504358 | AB11: 100.934 | AC11: -60.665184 | AD11: 70.977381 | AE11: 101.87174 | AF11: 121.522 | AG11: 222.92225 | AH11: 0 | AI11: 0 | AJ11: 0 | AK11: 0 | AL11: 0 | AM11: 0 | AN11: 0 | AO11: 0 | AP11: 0 | AQ11: 0.13962584 | AR11: 0 | AS11: 0 | AT11: 0
A12: 2.2 | B12: 0 | C12: 0 | D12: 0 | E12: 1.8 | F12: 0 | G12: 0 | H12: 0 | I12: 0 | J12: 2.06 | K12: 3.5 | L12: 0 | M12: 0 | N12: 1.5 | O12: 0 | P12: 0 | Q12: 4.2815435e+08 | R12: 179091000 | S12: 79969522 | T12: 87890700 | U12: 15786611 | V12: 153.62363 | W12: 4.5126129 | X12: 44.033222 | Y12: 792.12921 | Z12: 1.3942364e-30 | AA12: 23.760568 | AB12: 100.934 | AC12: -62.428909 | AD12: 72.394248 | AE12: 102.96474 | AF12: 121.522 | AG12: 222.82484 | AH12: 0 | AI12: 0 | AJ12: 0 | AK12: 0 | AL12: 0 | AM12: 0 | AN12: 0 | AO12: 0 | AP12: 0 | AQ12: 0.34203547 | AR12: 0 | AS12: 0 | AT12: 0
A13: 2.2 | B13: 0 | C13: 0 | D13: 0 | E13: 1.8 | F13: 0 | G13: 2.4 | H13: 0 | I13: 0 | J13: 0 | K13: 0 | L13: 3.44 | M13: 0 | N13: 1.5 | O13: 0 | P13: 0 | Q13: 4.2826173e+08 | R13: 179091000 | S13: 79959022 | T13: 85977000 | U13: 15779996 | V13: 158.31265 | W13: 4.4327765 | X13: 45.343439 | Y13: 785.04802 | Z13: 9.1749436e-31 | AA13: 1.64655 | AB13: 100.934 | AC13: -69.973956 | AD13: 66.059273 | AE13: 94.186468 | AF13: 100.934 | AG13: 222.65206 | AH13: 0 | AI13: 0 | AJ13: 0 | AK13: 0 | AL13: 0 | AM13: 0 | AN13: 7.9418125 | AO13: 0 | AP13: 0 | AQ13: 0 | AR13: 0 | AS13: 0 | AT13: 0
... A16: 2.2 | B16: 0 | C16: 0 | D16: 0 | E16: 1.8 | F16: 0 | G16: 2.4 | H16: 0 | I16: 0 | J16: 0 | K16: 3.5 | L16: 0 | M16: 0 | N16: 0 | O16: 0 | P16: 1.3 | Q16: 4.2832764e+08 | R16: 179094000 | S16: 79964722 | T16: 86375300 | U16: 15779199 | V16: 159.57284 | W16: 4.3871145 | X16: 43.940151 | Y16: 769.71314 | Z16: 1.047945e-30 | AA16: 21.861195 | AB16: 100.934 | AC16: -60.97097 | AD16: 65.57399 | AE16: 94.016049 | AF16: 100.934 | AG16: 223.1063 | AH16: 0 | AI16: 0 | AJ16: 0.068217574 | AK16: 0 | AL16: 0 | AM16: 0 | AN16: 0 | AO16: 0 | AP16: 0 | AQ16: 0 | AR16: 0 | AS16: 0 | AT16: 0

Sheet InteractiveSheet
A1: Name | B1: Value | C1: Units | D1: Status | E1: Variable Name | F1: Object ID1 | G1: Object ID2 | H1: Container | I1: Container Type | M1: Name | N1: Value | O1: Units | P1: Status | Q1: Variable Name | R1: Object ID1 | S1: Object ID2 | T1: Container | U1: Container Type
A2: Settings.economics_active | B2: 1 | E2: economics_active | F2: Settings | L2: LHV | M2: 326SAF.STRM_UPP | Q2: STRM_UPP | R2: LHVMS-15 | S2: MIXED | T2: 326SAF | U2: MATERIAL
A3: Settings.auto_evaluate | B3: 0 | E3: auto_evaluate | F3: Settings | L3: SG | M3: 326SAF.STRM_UPP | Q3: STRM_UPP | R3: SG-R | S3: MIXED | T3: 326SAF | U3: MATERIAL
L4: SLF | M4: 326SAF.STRM_UPP | Q4: STRM_UPP | R4: MASSFRS | S4: MIXED | T4: 326SAF | U4: MATERIAL
L5: ARM | N5: =SUM(B22:B30)*100 -> 0 | O5: vol%
A6: Name | B6: Value | C6: Units | D6: Status | E6: Variable Name | F6: Object ID1 | G6: Object ID2 | H6: Container | I6: Container Type | J6: initial | K6: opt | L6: Flash Point (Minimum Boiling Point) | N6: =(FrzPt!L84-32)*5/9 -> -17.777778 | O6: C
A7: PYROIN.EXPR2 | B7: 937.1966 | D7: Specified | E7: EXPR2 | H7: PYROIN | I7: DESIGN-SPEC | J7: 930 | L7: Freezing Point (Maximum Freezing Point) | N7: =(B90-32)*5/9 -> -17.777778 | O7: C
A8: T-310.NSTAGE | B8: 30 | D8: Specified | E8: NSTAGE | H8: T-310 | I8: RADFRAC | J8: 30 | K8: 30 | L8: Gas T10 | N8: =DiesFlash!P2 -> 0 | O8: C
A9: T-310.FEED_STAGE | B9: 19 | D9: Specified | E9: FEED_STAGE | F9: 310-1 | H9: T-310 | I9: RADFRAC | J9: 15 | K9: 19 | L9: Gas T90 | N9: =DiesFlash!P3 -> 0 | O9: C
A10: T-310.BASIS_RR | B10: 11.35 | D10: Specified | E10: BASIS_RR | H10: T-310 | I10: RADFRAC | J10: 3.6 | K10: 11.35 | L10: Dies Flash | N10: =(DiesFlash!L84-32)*5/9 -> -17.777778 | O10: C
A11: T-320.NSTAGE | B11: 15 | D11: Specified | E11: NSTAGE | H11: T-320 | I11: RADFRAC | J11: 20 | K11: 15 | L11: Dies T90 | N11: =DiesFlash!P4 -> 0 | O11: C
A12: T-320.FEED_STAGE | B12: 13 | D12: Specified | E12: FEED_STAGE | F12: 322 | H12: T-320 | I12: RADFRAC | J12: 10 | K12: 13
A13: T-320.BASIS_RR | B13: 0.3 | D13: Specified | E13: BASIS_RR | H13: T-320 | I13: RADFRAC | J13: 0.43 | K13: 0.3
A14: T-330.NSTAGE | B14: 12 | D14: Specified | E14: NSTAGE | H14: T-330 | I14: RADFRAC | J14: 20 | K14: 12
A15: T-330.FEED_STAGE | B15: 8 | D15: Specified | E15: FEED_STAGE | F15: 330 | H15: T-330 | I15: RADFRAC | J15: 10 | K15: 8
A16: T-330.BASIS_RR | B16: 0.66 | D16: Specified | E16: BASIS_RR | H16: T-330 | I16: RADFRAC | J16: 0.72 | K16: 0.66
A21: Name | B21: Value | C21: Units | D21: Status | E21: Variable Name | F21: Object ID1 | G21: Object ID2 | H21: Container | I21: Container Type
A22: 326SAF.STRM_UPP | E22: STRM_UPP | F22: VLSTDFR | G22: MIXED | H22: 326SAF | I22: MATERIAL
A23: 326SAF.STRM_UPP | E23: STRM_UPP | F23: VLSTDFR | G23: MIXED | H23: 326SAF | I23: MATERIAL | M23: Costing Result
A24: 326SAF.STRM_UPP | E24: STRM_UPP | F24: VLSTDFR | G24: MIXED | H24: 326SAF | I24: MATERIAL | M24: Total Capital Cost [USD] | N24: USD | O24: =Cost!D4 -> 428267000
A25: 326SAF.STRM_UPP | E25: STRM_UPP | F25: VLSTDFR | G25: MIXED | H25: 326SAF | I25: MATERIAL | M25: Total Operating Cost [USD/Year] | N25: USD/Year | O25: =Cost!D5 -> 179230000
A26: 326SAF.STRM_UPP | E26: STRM_UPP | F26: VLSTDFR | G26: MIXED | H26: 326SAF | I26: MATERIAL | M26: Total Raw Materials Cost [USD/Year] | N26: USD/Year | O26: =Cost!D6 -> 79990200
A27: 326SAF.STRM_UPP | E27: STRM_UPP | F27: VLSTDFR | G27: MIXED | H27: 326SAF | I27: MATERIAL | M27: Total Product Sales [USD/Year] | N27: USD/Year | O27: =Cost!D7 -> 77023300
A28: 326SAF.STRM_UPP | E28: STRM_UPP | F28: VLSTDFR | G28: MIXED | H28: 326SAF | I28: MATERIAL | M28: Total Utilities Cost [USD/Year] | N28: USD/Year | O28: =Cost!D8 -> 0
A29: 326SAF.STRM_UPP | E29: STRM_UPP | F29: VLSTDFR | G29: MIXED | H29: 326SAF | I29: MATERIAL | M29: Main Product | N29: cuft/hr | O29: =B83 -> 0
A30: 326SAF.STRM_UPP | E30: STRM_UPP | F30: VLSTDFR | G30: MIXED | H30: 326SAF | I30: MATERIAL
A34: Name | B34: Value | C34: Units | D34: Status | E34: Variable Name | F34: Object ID1 | G34: Object ID2 | H34: Container | I34: Container Type
A35: Utility-Sum.TOTUTCOST | D35: Not calculated | E35: TOTUTCOST | H35: UTIL-SUMMARY | I35: DATA
A36: 326SAF.VOLFLMX | E36: VOLFLMX | F36: MIXED | H36: 326SAF | I36: MATERIAL
A37: 510.MASSFLMX | E37: MASSFLMX | F37: MIXED | H37: 510 | I37: MATERIAL
A38: 200.VLSTDMX | E38: VLSTDMX | F38: MIXED | H38: 200 | I38: MATERIAL
A39: 404.VOLFLMX | E39: VOLFLMX | F39: MIXED | H39: 404 | I39: MATERIAL
A40: 622X.MASSFLMX | E40: MASSFLMX | F40: MIXED | H40: 622X | I40: MATERIAL
A41: 255.VOLFLMX | E41: VOLFLMX | F41: MIXED | H41: 255 | I41: MATERIAL
A42: 210.VOLFLMX | E42: VOLFLMX | F42: MIXED | H42: 210 | I42: MATERIAL
A43: 272.VOLFLMX | E43: VOLFLMX | F43: MIXED | H43: 272 | I43: MATERIAL
A45: Pyrolysis
A46: Name | B46: Value | C46: Units | D46: Status | E46: Variable Name | F46: Object ID1 | G46: Object ID2 | H46: Container | I46: Container Type
A47: R-110.COEF1 | B47: 0.041453235 | D47: Specified | E47: COEF1 | F47: 1 | G47: ACIDS | H47: R-110 | I47: RSTOIC | J47: 0.041453235
A48: R-110.COEF1 | B48: 0.040554755 | D48: Specified | E48: COEF1 | F48: 1 | G48: ALCOHOLS | H48: R-110 | I48: RSTOIC | J48: 0.040554755
A49: R-110.COEF1 | B49: 0.071700882 | D49: Specified | E49: COEF1 | F49: 1 | G49: KETONES | H49: R-110 | I49: RSTOIC | J49: 0.071700882
A50: R-110.COEF1 | B50: 0.029348836 | D50: Specified | E50: COEF1 | F50: 1 | G50: ALDEHYDE | H50: R-110 | I50: RSTOIC | J50: 0.029348836
A51: R-110.COEF1 | B51: 0.019435118 | D51: Specified | E51: COEF1 | F51: 1 | G51: GUAIACOL | H51: R-110 | I51: RSTOIC | J51: 0.019435118
A52: R-110.COEF1 | B52: 0.023586365 | D52: Specified | E52: COEF1 | F52: 1 | G52: SUGLMW | H52: R-110 | I52: RSTOIC | J52: 0.023586365
A53: R-110.COEF1 | B53: 0.063366911 | D53: Specified | E53: COEF1 | F53: 1 | G53: SUGHMW | H53: R-110 | I53: RSTOIC | J53: 0.063366911
A54: R-110.COEF1 | B54: 0.02920146 | D54: Specified | E54: COEF1 | F54: 1 | G54: LIGLMW-A | H54: R-110 | I54: RSTOIC | J54: 0.02920146
A55: R-110.COEF1 | B55: 0.008419469 | D55: Specified | E55: COEF1 | F55: 1 | G55: LIGLMW-B | H55: R-110 | I55: RSTOIC | J55: 0.008419469
A56: R-110.COEF1 | B56: 0.006378986 | D56: Specified | E56: COEF1 | F56: 1 | G56: EXTRACT | H56: R-110 | I56: RSTOIC | J56: 0.006378986
A57: R-110.COEF1 | B57: 0.014863687 | D57: Specified | E57: COEF1 | F57: 1 | G57: LIGHMW-A | H57: R-110 | I57: RSTOIC | J57: 0.014863687
A58: R-110.COEF1 | B58: 0.003137103 | D58: Specified | E58: COEF1 | F58: 1 | G58: LIGHMW-B | H58: R-110 | I58: RSTOIC | J58: 0.003137103
... A60: R-110.COEF1 | B60: 8.69609e-05 | D60: Specified | E60: COEF1 | F60: 1 | G60: S-COMP | H60: R-110 | I60: RSTOIC | J60: 8.69609e-05
A62: Hydrotreated Product
A63: Name | B63: Value | C63: Units | D63: Status | E63: Variable Name | F63: Object ID1 | G63: Object ID2 | H63: Container | I63: Container Type
A64: R-225.2HT-MAIN.MOLE_YIELD | B64: 2.2 | D64: Specified | E64: MOLE_YIELD | F64: PHENOLS | G64: MIXED | H64: R-225.2HT-MAIN | I64: RYIELD | J64: 2.2
A65: R-225.2HT-MAIN.MOLE_YIELD | B65: 0 | D65: Specified | E65: MOLE_YIELD | F65: PHENOL1 | G65: MIXED | H65: R-225.2HT-MAIN | I65: RYIELD | J65: 3.06
A66: R-225.2HT-MAIN.MOLE_YIELD | B66: 0 | D66: Specified | E66: MOLE_YIELD | F66: PHENOL2 | G66: MIXED | H66: R-225.2HT-MAIN | I66: RYIELD | J66: 3
A67: R-225.2HT-MAIN.MOLE_YIELD | B67: 0 | D67: Specified | E67: MOLE_YIELD | F67: PHENOL3 | G67: MIXED | H67: R-225.2HT-MAIN | I67: RYIELD | J67: 2.14
A68: R-225.2HT-MAIN.MOLE_YIELD | B68: 1.8 | D68: Specified | E68: MOLE_YIELD | F68: CYC5-A | G68: MIXED | H68: R-225.2HT-MAIN | I68: RYIELD | J68: 1.8
A69: R-225.2HT-MAIN.MOLE_YIELD | B69: 0 | D69: Specified | E69: MOLE_YIELD | F69: CYC5-A1 | G69: MIXED | H69: R-225.2HT-MAIN | I69: RYIELD | J69: 2.1
A70: R-225.2HT-MAIN.MOLE_YIELD | B70: 2.4 | D70: Specified | E70: MOLE_YIELD | F70: CYC6-A | G70: MIXED | H70: R-225.2HT-MAIN | I70: RYIELD | J70: 2.4
A71: R-225.2HT-MAIN.MOLE_YIELD | B71: 0 | D71: Specified | E71: MOLE_YIELD | F71: CYC6-A1 | G71: MIXED | H71: R-225.2HT-MAIN | I71: RYIELD | J71: 2.06
A72: R-225.2HT-MAIN.MOLE_YIELD | B72: 0 | D72: Specified | E72: MOLE_YIELD | F72: CYC6-A2 | G72: MIXED | H72: R-225.2HT-MAIN | I72: RYIELD | J72: 1.77
